Workbook

Sheet Cotizacion
D1: Calle Aquiles Serdán S/N
D2: C. P. 42820, Michimaloya Centro, Tula de Allende Hgo.
D3: Oficina +52 (773) 7240055
D4: www.immee.com.mx
D5: immee_013@hotmail.com
B8: Apoyando el consumo inteligente de energía eléctrica
A10: Ing. Lemuel Cruz Nieto | C10: Tula de Allende Hgo, a 11 de febrero de 2025
A11: Supervisor de proyectos
A12: TRACSA ENERGIA
A14: Presente | E14: COT. IMM-042-2025
A16: Atendiendo a su amable solicitud, le presentamos a su consideración el presupuesto por el servicio de "SUMINISTRO E INSTALACIÓN DE CIRCUITOS DE FUERZA PARA GENERADOR DE 2500 kW en parque Industrial AMEXHE Apaseo el Alto Guanajuato" en base al siguiente alcance.
A18: No. | B18: CONCEPTO | C18: UNIDIDAD | D18: CANTIDAD | E18: P.U | F18: IMPORTE
A19: 1 | B19: CHAROLA & SOPORTERIA - CHAROLA TIPO NEMA 8C
A20: 1.1 | B20: Suministro e instalación de charola tipo escalera perfil Z para servicio pesado de 30". Marca Croos line | C20: PZA | D20: 6 | E20: ='M0 (1)'!H97/6 -> 7744.8082 | F20: =D20*E20 -> 46468.849
A21: 1.2 | B21: Suministro e instalación de tapa para charola tipo escalera de 30". | C21: JGO | D21: 6 | E21: ='M0 (2)'!H97/6 -> 2203.3584 | F21: =D21*E21 -> 13220.15
A22: 1.3 | B22: Suministro e instalación de curva vertical exterior de 90° para charola tipo escalera de 30", en servicio pesado radio 12. | C22: PZA | D22: 4 | E22: ='M0 (3)'!H98 -> 2328.0623 | F22: =D22*E22 -> 9312.2492
A23: 1.4 | B23: Suministro e instalación de tapa para curva vertical exterior de 90° para charola tipo escalera para servicio pesado de 30", radio 12 | C23: PZA | D23: 4 | E23: ='M0 (4)'!H98 -> 1748.9644 | F23: =D23*E23 -> 6995.8575
A24: 1.5 | B24: Suministro e instalación de curva horizontal de 90° para charola tipo escalera para servicio pesado de 30", radio 12. Marca soportes eléctricos. | C24: PZA | D24: 2 | E24: =E22 -> 2328.0623 | F24: =D24*E24 -> 4656.1246
A25: 1.6 | B25: Suministro e instalación de tapa para curva horizontal de 90° para charola tipo escalera de 30", radio 12. Marca soportes eléctricos. | C25: PZA | D25: 2 | E25: =E23 -> 1748.9644 | F25: =D25*E25 -> 3497.9288
A26: 1.7 | B26: Suministro e instalación de soporte elaborado en sitio a base de unicanal solido galvanizado de 4x4, tornilleria galvanizada para su correcta instalación, varilla roscada galvanizada de 3 metros de largo X 1/2", mordaza sujeta barra. | C26: PZA | D26: 6 | E26: ='M0 (5)'!H98 -> 3810.5221 | F26: =D26*E26 -> 22863.133
A27: 1.8 | B27: Suministro e instalación de conector de charola para servicio pesado de 30" a caja. | C27: PZA | D27: 2 | E27: ='M0 (6)'!H98 -> 2358.6105 | F27: =D27*E27 -> 4717.2209
A28: 2 | B28: TORNILLERIA & ZAPATAS
A29: 2.1 | B29: Suministro e instalación de zapata ponchable para cable de cobre cañon largo calibre 500 KCM, con 2 ojillos de 1/2". | C29: PZA | D29: 80 | E29: ='M0 (7)'!H98 -> 1611.3597 | F29: =D29*E29 -> 128908.77
A30: 2.2 | B30: Suministro e instalación de manga termocontractil para nivel de aislamiento de 600 V, en calibre 500 KCM. | C30: PZA | D30: 4 | E30: ='M0 (8)'!H98 -> 3568.2161 | F30: =D30*E30 -> 14272.865
A31: 2.3 | B31: Suministro e instalación de tornillo tropicalizado de 1/2" con 2" de largo, incluye tuerca, roldana plana y de presion | C31: PZA | D31: 40 | E31: =12*1.8 -> 21.6 | F31: =D31*E31 -> 864
A32: 2.4 | B32: Suministro e instalación de tornillo tropicalizado de 1/2" con 4" de largo, incluye tuerca, roldana plana y de presion | C32: PZA | D32: 40 | E32: =16*1.8 -> 28.8 | F32: =D32*E32 -> 1152
A33: 3 | B33: CORTAFUEGO
A34: 3.1 | B34: Suministro e instalación de sistema corta fuego con lana mineral y compuesto SF-ONE. | C34: PZA | D34: 2 | E34: ='M0 (9)'!H98 -> 29218.802 | F34: =D34*E34 -> 58437.604
A35: 4 | B35: ACCESORIOS
A36: 4.1 | B36: Suministro e instalación de materiales consumibles.- Cintillos para exterior- Cintas de aislar para identificación de terminales- Discos de corte | C36: LOTE | D36: 1 | E36: 5480 | F36: =D36*E36 -> 5480
A37: 4.2 | B37: Suministro de materiales e instalacion de cuellos de lona flexibles en gargantas primarias de generador electrico | C37: PZA | D37: 1 | E37: 5860 | F37: =D37*E37 -> 5860
A38: 4.3 | B38: Suministro e instalación de cable de cobre THW calibre 12 AWG en color verde con zapatas ponchables en charolas de generador | C38: SERV | D38: 1 | E38: 2600 | F38: =D38*E38 -> 2600
A39: 4.4 | B39: Suministro e instalación de tapones para unicanal de 4x4 y varilla roscada | C39: SERV | D39: 1 | E39: 1600 | F39: =D39*E39 -> 1600
A40: 4.5 | B40: Suministro e instalación de tapones para esparrago | C40: SERV | D40: 1 | E40: 1240 | F40: =D40*E40 -> 1240
A41: 5 | B41: SERVICIOS & MANO DE OBRA
A42: 5.1 | B42: Servicio de prueba de resistencia de aislamiento a cable de baja tensión tipo THW LS calibre 500 KCM . El concepto incluye: - Desconexión en caso de ser necesario - Conexión de terminales - Repriete en conexiónes con torque requerido - Prueba de resistencia de aislamiento con inyección de corriente directa con equipo calibrado ante la EMA | C42: PBA | D42: 38 | E42: 650 | F42: =D42*E42 -> 24700
A43: 5.2 | B43: Servicio de mano de obra por los siguientes conceptos. - Instalación de materiales de partida anterior - Instalación de cable de cobre 500 mts THW LS calibre 500 MCM. (En charola de 30 " 12 puntas por fase (3 fases +2 cables de tierra). De acuerdo a medidas del cliente. | C43: SERV | D43: 1 | E43: ='M0 (10)'!H97 -> 42106.909 | F43: =D43*E43 -> 42106.909
A44: 6 | B44: PLATAFORMA ARTICULADA
A45: 6.1 | B45: Renta de plataforma articulada para trabajos en altura | C45: SERV | D45: 1 | E45: ='MAT (11)'!H124 -> 24196.249 | F45: =D45*E45 -> 24196.249
A46: 7 | B46: SEGURIDAD
A47: 7.1 | B47: Servicio de supervición EHS por el suministro e instalación de los trabajos anteriores fuerza y control | C47: SERV | D47: 1 | E47: ='M0 (12)'!H97 -> 39483.773 | F47: =D47*E47 -> 39483.773
E48: SUBTOTAL: | F48: =SUM(F20:F47) -> 462633.69 | G48: ='Semana completa M0'!H97 -> 278663.16
B49: CONDICIONES TÉCNICO-COMERCIALES:
B50: 1.- Plazo de ejecución: 1 semana a 2 semanas depues de recibir el adelanto y orden de compra
B51: 2.- Condiciones economicas: 50% para compra de materiales y el resto contra entrega de trabajo.
B52: 3.- Al importe se le aplicará el impuesto IVA al facturar.
B53: 4.- Vigencia de la cotización: 15 dias del calendario.
B54: 5.- Precios en moneda nacional.
A57: Atentamente:
A63: Ing. José Esteban Garcia Monrroy.
A64: Gerencia Técnica.

Sheet Hoja1

Sheet Semana completa MAT
A1: I M M E E S. A. D E C. V.
A2: A N A L I S I S D E P R E C I O U N I T A R I O
A3: COTIZACION:
A4: FECHA:
A5: PARTIDA 1
A6: REV-06-feb-2021
A7: MATERIALES.
A8: DESCRIPCION | E8: UNIDAD | F8: CANT. | G8: P.U. | H8: IMPORTE | J8: MATERIALES
A9: charola tipo escalera perfil Z para servicio pesado de 30" | E9: Pza | F9: 6 | G9: 2540.01 | H9: =G9*F9 -> 15240.06
A10: tapa para charola tipo escalera de 30". | E10: Pza | F10: 6 | G10: 1001 | H10: =G10*F10 -> 6006
A11: curva vertical exterior de 90° para charola tipo escalera de 30 | E11: Pza | F11: 4 | G11: 450.5 | H11: =G11*F11 -> 1802
A12: tapa para curva vertical exterior de 90° para charola tipo escalera para servicio pesado de 30" | E12: Pza | F12: 4 | G12: 136.52 | H12: =G12*F12 -> 546.08
A13: curva horizontal de 90° para charola tipo escalera para servicio pesado de 30" | E13: Pza | F13: 2 | G13: 620.97 | H13: =G13*F13 -> 1241.94
A14: base de unicanal solido galvanizado de 4x4 | E14: Pza | F14: 6 | G14: 382.32 | H14: =G14*F14 -> 2293.92
A15: tornilleria galvanizada | E15: Pza | F15: 6 | G15: 200 | H15: =G15*F15 -> 1200
A16: varilla roscada galvanizada de 3 metros de largo X 1/2" | E16: Pza | F16: 6 | G16: 70 | H16: =G16*F16 -> 420
A17: conector de charola para servicio pesado de 30 | E17: Pza | F17: 2 | G17: 467.05 | H17: =G17*F17 -> 934.1
A18: zapata ponchable para cable de cobre cañon largo calibre 500 KCM, con 2 ojillos de 1/2 | E18: Pza | F18: 80 | G18: 495.41 | H18: =G18*F18 -> 39632.8
A19: manga termocontractil para nivel de aislamiento de 600 V, en calibre 500 KCM. | E19: Pza | F19: 4 | G19: 212.43 | H19: =G19*F19 -> 849.72
A20: tornillo tropicalizado de 1/2" con 2" de largo | E20: Pza | F20: 40 | G20: 15 | H20: =G20*F20 -> 600
... A24: cuellos de lona flexibles en gargantas primarias de generador electrico | E24: Pza | F24: 1 | G24: 160.08 | H24: =G24*F24 -> 160.08
A25: cable de cobre THW calibre 12 AWG | E25: mt | F25: 1 | G25: 12.63 | H25: =G25*F25 -> 12.63 | L25: NOTA: CONSIDERAR LA JORNADA DE 8.0 HORAS, AUNQUE EN IMMEE SE TRABAJE JORNADA LARGA CONVENIDA, Y DOMINGO DESCANSO
A26: tapones para unicanal de 4x4 y varilla roscada | E26: Pza | F26: 1 | G26: 27.6 | H26: =G26*F26 -> 27.6
A27: tapones para esparrago | E27: Pza | F27: 1 | G27: 70.34 | H27: =G27*F27 -> 70.34
A28: cable de cobre 500 mts THW LS calibre 500 MCM | E28: CARRETE | F28: 1 | G28: 897.84 | H28: =G28*F28 -> 897.84
A29: Renta de una plataforma de elevacion | E29: Pza | F29: 1 | G29: 48000 | H29: =G29*F29 -> 48000 | I29: =H29*1.455 -> 69840
G30: SUBT 1 | H30: =SUM(H9:H29) -> 122431.61
A32: MANO DE OBRA SIN INDIRECTOS | O32: HORARIOS DE TRABAJO | V32: HORAS RESULTANTES | Y32: PERSONAL PEOPUESTO
A33: PERSONAL. | E33: UNIDAD | F33: CANT. | G33: HORA NORMAL | H33: IMPORTE | I33: CANT. | J33: Hr. Extra | K33: IMPORTE | L33: CANT. | M33: Dom, ó Fest.TRIPLE | N33: IMPORTE | O33: L | P33: M | Q33: MI | R33: J | S33: V | T33: S | U33: D | V33: N | W33: D | X33: T
A34: SUPERVISOR DE SEGURIDAD CERTIFICADO | E34: hr | G34: 390.39 | H34: =F34*G34 -> 0 | J34: 358.81 | K34: =I34*J34 -> 0 | M34: 538.27 | N34: =L34*M34 -> 0 | V34: =+O34+P34+Q34+R34+S34+T34+U34-W34-X34 -> 0
A35: SUPERVISOR DE SEGURIDAD | E35: hr | G35: 243.45 | H35: =F35*G35 -> 0 | J35: 211.59 | K35: =I35*J35 -> 0 | M35: 317.39 | N35: =L35*M35 -> 0 | V35: =+O35+P35+Q35+R35+S35+T35+U35-W35-X35 -> 0 | Y35: OSWALDO Z-GABRIEL
A36: SUPERVISOR ELECTRICO | E36: hr | G36: 390.39 | H36: =F36*G36 -> 0 | J36: 358.81 | K36: =I36*J36 -> 0 | M36: 538.22 | N36: =L36*M36 -> 0 | V36: =+O36+P36+Q36+R36+S36+T36+U36-W36-X36 -> 0 | Y36: ADRIAN
A37: TECNICO DE PRUEBAS ELECTRICAS | E37: hr | G37: 231.67 | H37: =F37*G37 -> 0 | J37: 197.63 | K37: =I37*J37 -> 0 | M37: 296.45 | N37: =L37*M37 -> 0 | V37: =+O37+P37+Q37+R37+S37+T37+U37-W37-X37 -> 0 | Y37: HECTOR
A38: CABO OBRA ELECTRICA | E38: hr | G38: 310.62 | H38: =F38*G38 -> 0 | J38: 291.24 | K38: =I38*J38 -> 0 | M38: 436.87 | N38: =L38*M38 -> 0 | V38: =+O38+P38+Q38+R38+S38+T38+U38-W38-X38 -> 0
A39: LINIERO | E39: hr | G39: 310.62 | H39: =F39*G39 -> 0 | J39: 291.24 | K39: =I39*J39 -> 0 | M39: 436.87 | N39: =L39*M39 -> 0 | V39: =+O39+P39+Q39+R39+S39+T39+U39-W39-X39 -> 0 | Y39: JOSE J
A40: ESPECIALISTA DE MANTTO ELECTRICO | E40: hr | H40: =F40*G40 -> 0 | J40: 0 | K40: =I40*J40 -> 0 | M40: 0 | N40: =L40*M40 -> 0 | V40: =+O40+P40+Q40+R40+S40+T40+U40-W40-X40 -> 0
A41: TECNICO EN INSTRUMENTACION | E41: hr | G41: 199.6 | H41: =F41*G41 -> 0 | J41: 159.6 | K41: =I41*J41 -> 0 | M41: 239.4 | N41: =L41*M41 -> 0 | V41: =+O41+P41+Q41+R41+S41+T41+U41-W41-X41 -> 0
A42: OFICIAL ELECTRICO/ELECTROMECANICO | E42: hr | G42: 199.6 | H42: =F42*G42 -> 0 | J42: 159.6 | K42: =I42*J42 -> 0 | M42: 239.4 | N42: =L42*M42 -> 0 | V42: =+O42+P42+Q42+R42+S42+T42+U42-W42-X42 -> 0
A43: ASISTENTE DE DISEÑO | E43: hr | G43: 199.6 | H43: =F43*G43 -> 0 | J43: 159.6 | K43: =I43*J43 -> 0 | M43: 239.4 | N43: =L43*M43 -> 0 | V43: =+O43+P43+Q43+R43+S43+T43+U43-W43-X43 -> 0
A44: ELECTRICISTA -B | E44: hr | G44: 211.15 | H44: =F44*G44 -> 0 | J44: 173.29 | K44: =I44*J44 -> 0 | M44: 259.94 | N44: =L44*M44 -> 0 | V44: =+O44+P44+Q44+R44+S44+T44+U44-W44-X44 -> 0 | Y44: GERMAN
A45: ELECTRICISTA -A | E45: hr | G45: 199.6 | H45: =F45*G45 -> 0 | J45: 159.6 | K45: =I45*J45 -> 0 | M45: 239.4 | N45: =L45*M45 -> 0 | V45: =+O45+P45+Q45+R45+S45+T45+U45-W45-X45 -> 0 | Y45: OSCAR-OSWALDO JIM
A46: AUXILIAR TECNICO | E46: hr | G46: 187.81 | H46: =F46*G46 -> 0 | J46: 145.62 | K46: =I46*J46 -> 0 | M46: 218.43 | N46: =L46*M46 -> 0 | V46: =+O46+P46+Q46+R46+S46+T46+U46-W46-X46 -> 0
A47: AYTE ELECTRICO - B | E47: hr | H47: =F47*G47 -> 0 | J47: 0 | K47: =I47*J47 -> 0 | N47: =L47*M47 -> 0 | V47: =+O47+P47+Q47+R47+S47+T47+U47-W47-X47 -> 0
A48: AYTE DE ELECTR. -A | E48: hr | G48: 187.81 | H48: =F48*G48 -> 0 | J48: 145.62 | K48: =I48*J48 -> 0 | M48: 218.43 | N48: =L48*M48 -> 0 | V48: =+O48+P48+Q48+R48+S48+T48+U48-W48-X48 -> 0 | Y48: URIEL-GUILLERMO-ENRIQUE
A49: AYTE GENERAL | E49: hr | G49: 94.81 | H49: =F49*G49 -> 0 | J49: 145.62 | K49: =I49*J49 -> 0 | M49: 218.43 | N49: =L49*M49 -> 0 | V49: =+O49+P49+Q49+R49+S49+T49+U49-W49-X49 -> 0
A50: PROFESIONISTA | E50: hr | G50: 243.45 | H50: =F50*G50 -> 0 | J50: 211.59 | K50: =I50*J50 -> 0 | M50: 317.39 | N50: =L50*M50 -> 0 | V50: 0 | Y50: O.ZARCO-GABRIEL
A51: COORDINADOR DE OPERACIONES | E51: hr | G51: 339.75 | H51: =F51*G51 -> 0 | J51: 325.79 | K51: =I51*J51 -> 0 | M51: 488.68 | N51: =L51*M51 -> 0 | V51: =+O51+P51+Q51+R51+S51+T51+U51-W51-X51 -> 0
A52: INGENIERIA Y SOPORTE TEC. | E52: hr | G52: 339.75 | H52: =F52*G52 -> 0 | J52: 325.79 | K52: =I52*J52 -> 0 | M52: 488.68 | N52: =L52*M52 -> 0 | V52: =+O52+P52+Q52+R52+S52+T52+U52-W52-X52 -> 0
A53: INGENIERO DE SUBESTACIONES | E53: hr | G53: 339.75 | H53: =F53*G53 -> 0 | J53: 325.79 | K53: =I53*J53 -> 0 | M53: 488.68 | N53: =L53*M53 -> 0 | V53: =+O53+P53+Q53+R53+S53+T53+U53-W53-X53 -> 0
A54: INGENIERO DE PRUEBAS ELECTRICAS | E54: hr | G54: 339.75 | H54: =F54*G54 -> 0 | J54: 325.79 | K54: =I54*J54 -> 0 | M54: 488.68 | N54: =L54*M54 -> 0 | V54: =+O54+P54+Q54+R54+S54+T54+U54-W54-X54 -> 0
A55: ING. ESPECIALISTA EN PROTECCIONES | E55: hr | G55: 1004.49 | H55: =F55*G55 -> 0 | J55: 1164.98 | K55: =I55*J55 -> 0 | M55: 1747.46 | N55: =L55*M55 -> 0 | V55: =+O55+P55+Q55+R55+S55+T55+U55-W55-X55 -> 0
A56: SUPERINTENDENTE | E56: hr | H56: =F56*G56 -> 0 | J56: =G56*1.5 -> 0 | K56: =I56*J56 -> 0 | M56: =G56*2.25 -> 0 | N56: =L56*M56 -> 0 | V56: =+O56+P56+Q56+R56+S56+T56+U56-W56-X56 -> 0
F57: =V57 -> 0 | G57: SUBT 2 | H57: =SUM(H34:H56) -> 0 | J57: SUBT. | K57: =SUM(K34:K56) -> 0 | M57: SUBT. | N57: =SUM(N34:N56) -> 0
G58: SUMA M.O. | H58: =H57+K57+N57 -> 0
A59: HERRAMIENTA MENOR | G59: 1 a 10% | H59: =+H58*0.06 -> 0
H60: =+H58+H59 -> 0
A61: VEHICULOS
A62: DESCRIPCION | E62: UNIDAD | F62: CANT. | G62: P.U. | H62: IMPORTE | J62: HR IDA | K62: HR RETORNO | L62: HR SITIO | M62: SUMA
A63: camioneta EXPRES VAN CARGO sin operador sin combustible | E63: HR | F63: 0 | G63: 170 | H63: =F63*G63 -> 0 | M63: =J63+K63+L63 -> 0
A64: camioneta RANGER sin operador sin combustible | E64: HR | F64: 8 | G64: 180 | H64: =F64*G64 -> 1440 | M64: =J64+K64+L64 -> 0
A65: camioneta TORNADO Tornado sin operador sin combustible | E65: HR | F65: 0 | G65: 80 | H65: =F65*G65 -> 0 | M65: =J65+K65+L65 -> 0
A66: camioneta WV TRANSPORTER pasajeros | E66: HR | F66: 0 | G66: 150 | H66: =F66*G66 -> 0 | M66: =J66+K66+L66 -> 0
E67: HR | F67: 0 | H67: =F67*G67 -> 0 | M67: =J67+K67+L67 -> 0
E68: pza | F68: 0 | H68: =F68*G68 -> 0 | M68: =J68+K68+L68 -> 0
A69: Km. Recorrido (incluye conbustible y depresiación de Vehiculo | E69: KM | F69: 0 | G69: 2.5 | H69: =F69*G69 -> 0 | M69: =J69+K69+L69 -> 0
G70: SUBT 4 | H70: =SUM(H63:H69) -> 1440
A71: COMBUSTIBLE
A72: DESCRIPCION | E72: UNIDAD | F72: CANT. | G72: P.U. | H72: IMPORTE | J72: KM IDA | K72: KM RETORNO | L72: KM SITIO | M72: SUMA
A73: GASOLINA MAGNA | E73: LT | F73: 80 | G73: 23 | H73: =F73*G73 -> 1840 | M73: =J73+K73+L73 -> 0
A74: DIESEL | E74: LT | F74: 0 | G74: 24 | H74: =F74*G74 -> 0 | M74: =J74+K74+L74 -> 0
G75: SUBT 5 | H75: =SUM(H73:H74) -> 1840
A76: CASETAS
A77: DESCRIPCION | E77: UNIDAD | F77: CANT. | G77: P.U. | H77: IMPORTE
A78: Camion | E78: CASETA | F78: 0 | G78: 65 | H78: =F78*G78 -> 0
A79: camioneta pick up | E79: CASETA | F79: 2 | G79: 250 | H79: =F79*G79 -> 500
G80: SUBT 6 | H80: =SUM(H78:H79) -> 500
A81: VIATICOS
A82: ALIMENTOS
A83: DESCRIPCION | E83: UNIDAD | F83: CANT. | G83: P.U. | H83: IMPORTE
A84: CONSUMO DE ALIMENTOS | E84: Pza | F84: 20 | G84: 600 | H84: =F84*G84 -> 12000
H85: =SUM(H84) -> 12000
A86: HOSPEDAJE
A87: DESCRIPCION | E87: UNIDAD | F87: CANT. | G87: P.U. | H87: IMPORTE
A88: HOTEL | E88: NOCHES | F88: 8 | G88: 900 | H88: =F88*G88 -> 7200
G89: SUBT 8 | H89: =SUM(H88) -> 7200
G90: SUMA: | H90: =H70+H75+H80+H85+H89+H59+H58+H30 -> 145411.61
A91: EQUIPO DE PRUEBA
A92: DESCRIPCION | E92: UNIDAD | F92: CANT. | G92: P.U. | H92: IMPORTE | I92: TR | K92: S.E
A93: Megger | E93: jr | G93: 2200 | H93: =(F93*G93) -> 0
A94: TTR | E94: jr | G94: 2000 | H94: =(F94*G94) -> 0
A95: Factor de Potencia de 2.5 KV | E95: jr | G95: 7000 | H95: =(F95*G95) -> 0
A96: Factor de Potencia de 10.5 KV | E96: jr | G96: 15200 | H96: =(F96*G96) -> 0
A97: Ducter | E97: jr | G97: 2200 | H97: =(F97*G97) -> 0
A98: resistencia óhmica | E98: jr | G98: 2000 | H98: =(F98*G98) -> 0
A99: hipot de 80 KV vcd | E99: jr | G99: 2500 | H99: =(F99*G99) -> 0
A100: Rigidez dieléctrica al aceite 60 kv | E100: jr | G100: 1600 | H100: =(F100*G100) -> 0
A101: Terrómetro | E101: jr | G101: 1100 | H101: =(F101*G101) -> 0
A102: Analizador de tiempos de interruptor | E102: jr | G102: 2700 | H102: =(F102*G102) -> 0
A103: Fuente de corriente para calibrador de relevadores | E103: jr | G103: 2500 | H103: =(F103*G103) -> 0
A104: Probador de relevador de Protecciones | E104: jr | G104: 13373 | H104: =(F104*G104) -> 0
...

Sheet Semana completa M0
A1: I M M E E S. A. D E C. V.
A2: A N A L I S I S D E P R E C I O U N I T A R I O
A3: COTIZACION:
A4: FECHA:
A5: PARTIDA 1
A6: REV-06-feb-2021
A7: MATERIALES.
A8: DESCRIPCION | E8: UNIDAD | F8: CANT. | G8: P.U. | H8: IMPORTE | J8: MANO DE OBRA
A9: Consumible | E9: Pza | H9: =G9*F9 -> 0
E10: Pza | H10: =G10*F10 -> 0
E11: Pza | H11: =G11*F11 -> 0
E12: Pza | H12: =G12*F12 -> 0
E13: Pza | H13: =G13*F13 -> 0
E14: Pza | H14: =G14*F14 -> 0
E15: Pza | H15: =G15*F15 -> 0
E16: Pza | H16: =G16*F16 -> 0 | I16: =H16*1.455 -> 0
G17: SUBT 1 | H17: =SUM(H9:H16) -> 0
A19: MANO DE OBRA SIN INDIRECTOS | O19: HORARIOS DE TRABAJO | V19: HORAS RESULTANTES | Y19: PERSONAL PEOPUESTO
A20: PERSONAL. | E20: UNIDAD | F20: CANT. | G20: HORA NORMAL | H20: IMPORTE | I20: CANT. | J20: Hr. Extra | K20: IMPORTE | L20: CANT. | M20: Dom, ó Fest.TRIPLE | N20: IMPORTE | O20: L | P20: M | Q20: MI | R20: J | S20: V | T20: S | U20: D | V20: N | W20: D | X20: T
A21: SUPERVISOR DE SEGURIDAD CERTIFICADO | E21: hr | G21: 390.39 | H21: =F21*G21 -> 0 | J21: 358.81 | K21: =I21*J21 -> 0 | M21: 538.27 | N21: =L21*M21 -> 0 | V21: =+O21+P21+Q21+R21+S21+T21+U21-W21-X21 -> 0
A22: SUPERVISOR DE SEGURIDAD | E22: hr | G22: 317.98 | H22: =F22*G22 -> 0 | J22: 326.25 | K22: =I22*J22 -> 0 | M22: 489.37 | N22: =L22*M22 -> 0 | V22: =+O22+P22+Q22+R22+S22+T22+U22-W22-X22 -> 0 | Y22: OSWALDO Z-GABRIEL
A23: SUPERVISOR ELECTRICO | E23: hr | F23: =9.5*5 -> 47.5 | G23: 390.39 | H23: =F23*G23 -> 18543.525 | I23: 6 | J23: 358.81 | K23: =I23*J23 -> 2152.86 | M23: 538.22 | N23: =L23*M23 -> 0 | V23: =+O23+P23+Q23+R23+S23+T23+U23-W23-X23 -> 0 | Y23: ADRIAN
A24: TECNICO DE PRUEBAS ELECTRICAS | E24: hr | G24: 317.98 | H24: =F24*G24 -> 0 | J24: 244.27 | K24: =I24*J24 -> 0 | M24: 489.37 | N24: =L24*M24 -> 0 | V24: =+O24+P24+Q24+R24+S24+T24+U24-W24-X24 -> 0 | Y24: HECTOR
A25: CABO OBRA ELECTRICA | E25: hr | G25: 310.62 | H25: =F25*G25 -> 0 | J25: 335 | K25: =I25*J25 -> 0 | M25: 436.87 | N25: =L25*M25 -> 0 | V25: =+O25+P25+Q25+R25+S25+T25+U25-W25-X25 -> 0
A26: LINIERO | E26: hr | F26: =9.5*5 -> 47.5 | G26: 209.25 | H26: =F26*G26 -> 9939.375 | I26: 6 | J26: 221.7 | K26: =I26*J26 -> 1330.2 | M26: 437.63 | N26: =L26*M26 -> 0 | V26: =+O26+P26+Q26+R26+S26+T26+U26-W26-X26 -> 0 | Y26: JOSE J
A27: ESPECIALISTA DE MANTTO ELECTRICO | E27: hr | G27: 237.68 | H27: =F27*G27 -> 0 | J27: 277.97 | K27: =I27*J27 -> 0 | M27: 538.84 | N27: =L27*M27 -> 0 | V27: =+O27+P27+Q27+R27+S27+T27+U27-W27-X27 -> 0
A28: TECNICO EN INSTRUMENTACION | E28: hr | G28: 368.59 | H28: =F28*G28 -> 0 | J28: 221.7 | K28: =I28*J28 -> 0 | M28: 538.84 | N28: =L28*M28 -> 0 | V28: =+O28+P28+Q28+R28+S28+T28+U28-W28-X28 -> 0
A29: OFICIAL ELECTRICO/ELECTROMECANICO | E29: hr | F29: =9.5*5 -> 47.5 | G29: 143 | H29: =F29*G29 -> 6792.5 | I29: 6 | J29: 165 | K29: =I29*J29 -> 990 | M29: 277.56 | N29: =L29*M29 -> 0 | V29: =+O29+P29+Q29+R29+S29+T29+U29-W29-X29 -> 0
A30: ASISTENTE DE DISEÑO | E30: hr | G30: 190.25 | H30: =F30*G30 -> 0 | J30: 221.7 | K30: =I30*J30 -> 0 | M30: 297.41 | N30: =L30*M30 -> 0 | V30: =+O30+P30+Q30+R30+S30+T30+U30-W30-X30 -> 0
A31: ELECTRICISTA -B | E31: hr | F31: =9.5*5 -> 47.5 | G31: 119.54 | H31: =F31*G31 -> 5678.15 | I31: 6 | J31: 137.92 | K31: =I31*J31 -> 827.52 | M31: 0 | N31: =L31*M31 -> 0 | V31: =+O31+P31+Q31+R31+S31+T31+U31-W31-X31 -> 0 | Y31: GERMAN
A32: ELECTRICISTA -A | E32: hr | G32: 119.54 | H32: =F32*G32 -> 0 | J32: 137.92 | K32: =I32*J32 -> 0 | M32: 240.95 | N32: =L32*M32 -> 0 | V32: =+O32+P32+Q32+R32+S32+T32+U32-W32-X32 -> 0 | Y32: OSCAR-OSWALDO JIM
A33: AUXILIAR TECNICO | E33: hr | G33: 106.45 | H33: =F33*G33 -> 0 | J33: 137.92 | K33: =I33*J33 -> 0 | M33: 260.95 | N33: =L33*M33 -> 0 | V33: =+O33+P33+Q33+R33+S33+T33+U33-W33-X33 -> 0
A34: AYTE ELECTRICO - B | E34: hr | G34: 106.45 | H34: =F34*G34 -> 0 | J34: 122.4 | K34: =I34*J34 -> 0 | N34: =L34*M34 -> 0 | V34: =+O34+P34+Q34+R34+S34+T34+U34-W34-X34 -> 0
A35: AYTE DE ELECTR. -A | E35: hr | G35: 106.54 | H35: =F35*G35 -> 0 | J35: 122.4 | K35: =I35*J35 -> 0 | M35: 198.17 | N35: =L35*M35 -> 0 | V35: =+O35+P35+Q35+R35+S35+T35+U35-W35-X35 -> 0 | Y35: URIEL-GUILLERMO-ENRIQUE
A36: AYTE GENERAL | E36: hr | G36: 100.42 | H36: =F36*G36 -> 0 | J36: 122.4 | K36: =I36*J36 -> 0 | M36: 0 | N36: =L36*M36 -> 0 | V36: =+O36+P36+Q36+R36+S36+T36+U36-W36-X36 -> 0
A37: PROFESIONISTA | E37: hr | G37: 209.25 | H37: =F37*G37 -> 0 | J37: 406 | K37: =I37*J37 -> 0 | M37: 564.86 | N37: =L37*M37 -> 0 | V37: 0 | Y37: O.ZARCO-GABRIEL
A38: COORDINADOR DE OPERACIONES | E38: hr | G38: 0 | H38: =F38*G38 -> 0 | J38: 0 | K38: =I38*J38 -> 0 | M38: 0 | N38: =L38*M38 -> 0 | V38: =+O38+P38+Q38+R38+S38+T38+U38-W38-X38 -> 0
A39: INGENIERIA Y SOPORTE TEC. | E39: hr | G39: 339.75 | H39: =F39*G39 -> 0 | J39: 325.79 | K39: =I39*J39 -> 0 | M39: 488.68 | N39: =L39*M39 -> 0 | V39: =+O39+P39+Q39+R39+S39+T39+U39-W39-X39 -> 0
A40: INGENIERO DE SUBESTACIONES | E40: hr | G40: 339.75 | H40: =F40*G40 -> 0 | J40: 325.79 | K40: =I40*J40 -> 0 | M40: 488.68 | N40: =L40*M40 -> 0 | V40: =+O40+P40+Q40+R40+S40+T40+U40-W40-X40 -> 0
A41: INGENIERO DE PRUEBAS ELECTRICAS | E41: hr | G41: 339.75 | H41: =F41*G41 -> 0 | J41: 325.79 | K41: =I41*J41 -> 0 | M41: 488.68 | N41: =L41*M41 -> 0 | V41: =+O41+P41+Q41+R41+S41+T41+U41-W41-X41 -> 0
A42: ING. ESPECIALISTA EN PROTECCIONES | E42: hr | G42: 650 | H42: =F42*G42 -> 0 | J42: =G42*1.5 -> 975 | K42: =I42*J42 -> 0 | M42: 1747.46 | N42: =L42*M42 -> 0 | V42: =+O42+P42+Q42+R42+S42+T42+U42-W42-X42 -> 0
A43: SUPERINTENDENTE | E43: hr | H43: =F43*G43 -> 0 | J43: =G43*1.5 -> 0 | K43: =I43*J43 -> 0 | M43: =G43*2.25 -> 0 | N43: =L43*M43 -> 0 | V43: =+O43+P43+Q43+R43+S43+T43+U43-W43-X43 -> 0
F44: =V44 -> 0 | G44: SUBT 2 | H44: =SUM(H21:H43) -> 40953.55 | J44: SUBT. | K44: =SUM(K21:K43) -> 5300.58 | M44: SUBT. | N44: =SUM(N21:N43) -> 0
G45: SUMA M.O. | H45: =H44+K44+N44 -> 46254.13
A46: HERRAMIENTA MENOR | G46: 1 a 10% | H46: =+H45*0.06 -> 2775.2478
A49: VEHICULOS
A50: DESCRIPCION | E50: UNIDAD | F50: CANT. | G50: P.U. | H50: IMPORTE | J50: HR IDA | K50: HR RETORNO | L50: HR SITIO | M50: SUMA
A51: camioneta EXPRES VAN CARGO sin operador sin combustible | E51: HR | F51: 0 | G51: 150 | H51: =F51*G51 -> 0 | M51: =J51+K51+L51 -> 0
A52: camioneta RANGER sin operador sin combustible | E52: HR | F52: 0 | G52: 150 | H52: =F52*G52 -> 0 | M52: =J52+K52+L52 -> 0
A53: camioneta TORNADO Tornado sin operador sin combustible | E53: HR | F53: 0 | G53: 60 | H53: =F53*G53 -> 0 | M53: =J53+K53+L53 -> 0
A54: camioneta WV TRANSPORTER pasajeros | E54: HR | F54: 0 | G54: 120 | H54: =F54*G54 -> 0 | M54: =J54+K54+L54 -> 0
E55: HR | F55: 0 | H55: =F55*G55 -> 0 | M55: =J55+K55+L55 -> 0
E56: pza | F56: 0 | H56: =F56*G56 -> 0 | M56: =J56+K56+L56 -> 0
A57: Km. Recorrido (incluye conbustible y depresiación de Vehiculo | E57: KM | F57: 0 | G57: 2.5 | H57: =F57*G57 -> 0 | M57: =J57+K57+L57 -> 0
G58: SUBT 4 | H58: =SUM(H51:H57) -> 0
G59: SUMA: | H59: =H58+H45+H17 -> 46254.13
A60: EQUIPO DE PRUEBA
A61: DESCRIPCION | E61: UNIDAD | F61: CANT. | G61: P.U. | H61: IMPORTE | I61: TR | K61: S.E
A62: Megger | E62: jr | F62: 0.3 | G62: 2200 | H62: =(F62*G62) -> 660
A63: TTR | E63: jr | G63: 2000 | H63: =(F63*G63) -> 0
A64: Factor de Potencia de 2.5 KV | E64: jr | G64: 7000 | H64: =(F64*G64) -> 0
A65: Factor de Potencia de 10.5 KV | E65: jr | G65: 15200 | H65: =(F65*G65) -> 0
A66: Ducter | E66: jr | G66: 2200 | H66: =(F66*G66) -> 0
A67: resistencia óhmica | E67: jr | G67: 2000 | H67: =(F67*G67) -> 0
A68: hipot de 80 KV vcd | E68: jr | G68: 2500 | H68: =(F68*G68) -> 0
A69: Rigidez dieléctrica al aceite 60 kv | E69: jr | G69: 1600 | H69: =(F69*G69) -> 0
A70: Terrómetro | E70: jr | G70: 1100 | H70: =(F70*G70) -> 0
A71: Analizador de tiempos de interruptor | E71: jr | G71: 2700 | H71: =(F71*G71) -> 0
A72: Fuente de corriente para calibrador de relevadores | E72: jr | G72: 2500 | H72: =(F72*G72) -> 0
A73: Probador de relevador de Protecciones | E73: jr | G73: 13373 | H73: =(F73*G73) -> 0
A74: Fuente trifasica de voltaje | E74: jr | G74: 800 | H74: =(F74*G74) -> 0
... A82: Test Kit maleta de prueba G.E. | E82: jr | G82: 5800 | H82: =(F82*G82) -> 0
E83: jr | H83: =(F83*G83) -> 0
A84: Camara termografica | E84: jr | G84: 15000 | H84: =(F84*G84) -> 0
A85: Generador de Luz con combustible | E85: jr | F85: 1 | G85: 383.5 | H85: =(F85*G85) -> 383.5
G86: SUBT 9 | H86: =SUM(H62:H85) -> 1043.5
E88: 0 | H88: =+E88 -> 0 | I88: IMPUESTO | J88: INDIRECTO DISPONIBLE
F89: COSTO DIRECTO | H89: =H59+H86 -> 47297.63
F90: Indirectos | G90: 0.25 | H90: =H89*G90 -> 11824.407 | I90: =+M96 -> -6528.9217 | J90: =H90-M96 -> 18353.329 | N90: REV-06-feb-2021
F91: Subtotal 1 | H91: =H89+H90 -> 59122.037
F92: Financ. | G92: 0.06 | H92: =H91*G92 -> 3547.3222 | K92: BASE IMPUESTO | L92: SIN UTILIDAD
F93: Subtotal 2 | H93: =H91+H92 -> 62669.36 | J93: COMPRAS | K93: =+H17 -> 0
F94: Utilidad | G94: 0.2 | H94: =H93*G94 -> 12533.872 | J94: M.O | K94: =H44 -> 40953.55
F95: Importe | H95: =H93+H94 -> 75203.232 | J95: GASTOS FACTURADOS | K95: =H59-H46 -> 43478.882 | M95: IMP. 30%
F96: Materiales | H96: ='Semana completa MAT'!H124 -> 203459.92 | I96: FACTOR | J96: SUMA | K96: =SUM(K93:K95) -> 84432.432 | L96: =H95-H94 -> 62669.36 | M96: =+(L96-K96)*0.3 -> -6528.9217
B97: utilidad | F97: Total | H97: =H95+H96 -> 278663.16 | J97: =H95/H89 -> 1.59
B98: ime | C98: comisión | D98: total
B99: 0.275 | C99: 0.05 | D99: =B99+C99 -> 0.325

Sheet MAT (1)
A1: I M M E E S. A. D E C. V.
A2: A N A L I S I S D E P R E C I O U N I T A R I O
A3: COTIZACION:
A4: FECHA:
A5: PARTIDA 1
A6: REV-06-feb-2021
A7: MATERIALES.
A8: DESCRIPCION | E8: UNIDAD | F8: CANT. | G8: P.U. | H8: IMPORTE | J8: MATERIALES
A9: charola tipo escalera perfil Z para servicio pesado de 30" | E9: Pza | F9: 6 | G9: 2540.01 | H9: =G9*F9 -> 15240.06
A10: tapa para charola tipo escalera de 30". | E10: Pza | G10: 1001 | H10: =G10*F10 -> 0
A11: curva vertical exterior de 90° para charola tipo escalera de 30 | E11: Pza | G11: 450.5 | H11: =G11*F11 -> 0
A12: tapa para curva vertical exterior de 90° para charola tipo escalera para servicio pesado de 30" | E12: Pza | G12: 136.52 | H12: =G12*F12 -> 0
A13: curva horizontal de 90° para charola tipo escalera para servicio pesado de 30" | E13: Pza | G13: 620.97 | H13: =G13*F13 -> 0
A14: base de unicanal solido galvanizado de 4x4 | E14: Pza | G14: 382.32 | H14: =G14*F14 -> 0
A15: tornilleria galvanizada | E15: Pza | G15: 200 | H15: =G15*F15 -> 0
A16: varilla roscada galvanizada de 3 metros de largo X 1/2" | E16: Pza | G16: 70 | H16: =G16*F16 -> 0
A17: conector de charola para servicio pesado de 30 | E17: Pza | G17: 467.05 | H17: =G17*F17 -> 0
A18: zapata ponchable para cable de cobre cañon largo calibre 500 KCM, con 2 ojillos de 1/2 | E18: Pza | G18: 495.41 | H18: =G18*F18 -> 0
A19: manga termocontractil para nivel de aislamiento de 600 V, en calibre 500 KCM. | E19: Pza | G19: 212.43 | H19: =G19*F19 -> 0
A20: sistema corta fuego con lana mineral y compuesto SF-ONE. | E20: Pza | G20: 698.25 | H20: =G20*F20 -> 0
A21: cuellos de lona flexibles en gargantas primarias de generador electrico | E21: Pza | G21: 160.08 | H21: =G21*F21 -> 0
A22: cable de cobre THW calibre 12 AWG | E22: mt | G22: 12.63 | H22: =G22*F22 -> 0 | L22: NOTA: CONSIDERAR LA JORNADA DE 8.0 HORAS, AUNQUE EN IMMEE SE TRABAJE JORNADA LARGA CONVENIDA, Y DOMINGO DESCANSO
A23: tapones para unicanal de 4x4 y varilla roscada | E23: Pza | G23: 27.6 | H23: =G23*F23 -> 0
A24: tapones para esparrago | E24: Pza | G24: 70.34 | H24: =G24*F24 -> 0
A25: cable de cobre 500 mts THW LS calibre 500 MCM | E25: CARRETE | G25: 897.84 | H25: =G25*F25 -> 0
A26: Renta de una plataforma de elevacion | E26: Pza | F26: 0 | G26: 25000 | H26: =G26*F26 -> 0 | I26: =H26*1.455 -> 0
G27: SUBT 1 | H27: =SUM(H9:H26) -> 15240.06
A29: MANO DE OBRA SIN INDIRECTOS | O29: HORARIOS DE TRABAJO | V29: HORAS RESULTANTES | Y29: PERSONAL PEOPUESTO
A30: PERSONAL. | E30: UNIDAD | F30: CANT. | G30: HORA NORMAL | H30: IMPORTE | I30: CANT. | J30: Hr. Extra | K30: IMPORTE | L30: CANT. | M30: Dom, ó Fest.TRIPLE | N30: IMPORTE | O30: L | P30: M | Q30: MI | R30: J | S30: V | T30: S | U30: D | V30: N | W30: D | X30: T
A31: SUPERVISOR DE SEGURIDAD CERTIFICADO | E31: hr | G31: 390.39 | H31: =F31*G31 -> 0 | J31: 358.81 | K31: =I31*J31 -> 0 | M31: 538.27 | N31: =L31*M31 -> 0 | V31: =+O31+P31+Q31+R31+S31+T31+U31-W31-X31 -> 0
A32: SUPERVISOR DE SEGURIDAD | E32: hr | G32: 243.45 | H32: =F32*G32 -> 0 | J32: 211.59 | K32: =I32*J32 -> 0 | M32: 317.39 | N32: =L32*M32 -> 0 | V32: =+O32+P32+Q32+R32+S32+T32+U32-W32-X32 -> 0 | Y32: OSWALDO Z-GABRIEL
A33: SUPERVISOR ELECTRICO | E33: hr | G33: 390.39 | H33: =F33*G33 -> 0 | J33: 358.81 | K33: =I33*J33 -> 0 | M33: 538.22 | N33: =L33*M33 -> 0 | V33: =+O33+P33+Q33+R33+S33+T33+U33-W33-X33 -> 0 | Y33: ADRIAN
A34: TECNICO DE PRUEBAS ELECTRICAS | E34: hr | G34: 231.67 | H34: =F34*G34 -> 0 | J34: 197.63 | K34: =I34*J34 -> 0 | M34: 296.45 | N34: =L34*M34 -> 0 | V34: =+O34+P34+Q34+R34+S34+T34+U34-W34-X34 -> 0 | Y34: HECTOR
A35: CABO OBRA ELECTRICA | E35: hr | G35: 310.62 | H35: =F35*G35 -> 0 | J35: 291.24 | K35: =I35*J35 -> 0 | M35: 436.87 | N35: =L35*M35 -> 0 | V35: =+O35+P35+Q35+R35+S35+T35+U35-W35-X35 -> 0
A36: LINIERO | E36: hr | G36: 310.62 | H36: =F36*G36 -> 0 | J36: 291.24 | K36: =I36*J36 -> 0 | M36: 436.87 | N36: =L36*M36 -> 0 | V36: =+O36+P36+Q36+R36+S36+T36+U36-W36-X36 -> 0 | Y36: JOSE J
A37: ESPECIALISTA DE MANTTO ELECTRICO | E37: hr | H37: =F37*G37 -> 0 | J37: 0 | K37: =I37*J37 -> 0 | M37: 0 | N37: =L37*M37 -> 0 | V37: =+O37+P37+Q37+R37+S37+T37+U37-W37-X37 -> 0
A38: TECNICO EN INSTRUMENTACION | E38: hr | G38: 199.6 | H38: =F38*G38 -> 0 | J38: 159.6 | K38: =I38*J38 -> 0 | M38: 239.4 | N38: =L38*M38 -> 0 | V38: =+O38+P38+Q38+R38+S38+T38+U38-W38-X38 -> 0
A39: OFICIAL ELECTRICO/ELECTROMECANICO | E39: hr | G39: 199.6 | H39: =F39*G39 -> 0 | J39: 159.6 | K39: =I39*J39 -> 0 | M39: 239.4 | N39: =L39*M39 -> 0 | V39: =+O39+P39+Q39+R39+S39+T39+U39-W39-X39 -> 0
A40: ASISTENTE DE DISEÑO | E40: hr | G40: 199.6 | H40: =F40*G40 -> 0 | J40: 159.6 | K40: =I40*J40 -> 0 | M40: 239.4 | N40: =L40*M40 -> 0 | V40: =+O40+P40+Q40+R40+S40+T40+U40-W40-X40 -> 0
A41: ELECTRICISTA -B | E41: hr | G41: 211.15 | H41: =F41*G41 -> 0 | J41: 173.29 | K41: =I41*J41 -> 0 | M41: 259.94 | N41: =L41*M41 -> 0 | V41: =+O41+P41+Q41+R41+S41+T41+U41-W41-X41 -> 0 | Y41: GERMAN
A42: ELECTRICISTA -A | E42: hr | G42: 199.6 | H42: =F42*G42 -> 0 | J42: 159.6 | K42: =I42*J42 -> 0 | M42: 239.4 | N42: =L42*M42 -> 0 | V42: =+O42+P42+Q42+R42+S42+T42+U42-W42-X42 -> 0 | Y42: OSCAR-OSWALDO JIM
A43: AUXILIAR TECNICO | E43: hr | G43: 187.81 | H43: =F43*G43 -> 0 | J43: 145.62 | K43: =I43*J43 -> 0 | M43: 218.43 | N43: =L43*M43 -> 0 | V43: =+O43+P43+Q43+R43+S43+T43+U43-W43-X43 -> 0
A44: AYTE ELECTRICO - B | E44: hr | H44: =F44*G44 -> 0 | J44: 0 | K44: =I44*J44 -> 0 | N44: =L44*M44 -> 0 | V44: =+O44+P44+Q44+R44+S44+T44+U44-W44-X44 -> 0
A45: AYTE DE ELECTR. -A | E45: hr | G45: 187.81 | H45: =F45*G45 -> 0 | J45: 145.62 | K45: =I45*J45 -> 0 | M45: 218.43 | N45: =L45*M45 -> 0 | V45: =+O45+P45+Q45+R45+S45+T45+U45-W45-X45 -> 0 | Y45: URIEL-GUILLERMO-ENRIQUE
A46: AYTE GENERAL | E46: hr | G46: 94.81 | H46: =F46*G46 -> 0 | J46: 145.62 | K46: =I46*J46 -> 0 | M46: 218.43 | N46: =L46*M46 -> 0 | V46: =+O46+P46+Q46+R46+S46+T46+U46-W46-X46 -> 0
A47: PROFESIONISTA | E47: hr | G47: 243.45 | H47: =F47*G47 -> 0 | J47: 211.59 | K47: =I47*J47 -> 0 | M47: 317.39 | N47: =L47*M47 -> 0 | V47: 0 | Y47: O.ZARCO-GABRIEL
A48: COORDINADOR DE OPERACIONES | E48: hr | G48: 339.75 | H48: =F48*G48 -> 0 | J48: 325.79 | K48: =I48*J48 -> 0 | M48: 488.68 | N48: =L48*M48 -> 0 | V48: =+O48+P48+Q48+R48+S48+T48+U48-W48-X48 -> 0
A49: INGENIERIA Y SOPORTE TEC. | E49: hr | G49: 339.75 | H49: =F49*G49 -> 0 | J49: 325.79 | K49: =I49*J49 -> 0 | M49: 488.68 | N49: =L49*M49 -> 0 | V49: =+O49+P49+Q49+R49+S49+T49+U49-W49-X49 -> 0
A50: INGENIERO DE SUBESTACIONES | E50: hr | G50: 339.75 | H50: =F50*G50 -> 0 | J50: 325.79 | K50: =I50*J50 -> 0 | M50: 488.68 | N50: =L50*M50 -> 0 | V50: =+O50+P50+Q50+R50+S50+T50+U50-W50-X50 -> 0
A51: INGENIERO DE PRUEBAS ELECTRICAS | E51: hr | G51: 339.75 | H51: =F51*G51 -> 0 | J51: 325.79 | K51: =I51*J51 -> 0 | M51: 488.68 | N51: =L51*M51 -> 0 | V51: =+O51+P51+Q51+R51+S51+T51+U51-W51-X51 -> 0
A52: ING. ESPECIALISTA EN PROTECCIONES | E52: hr | G52: 1004.49 | H52: =F52*G52 -> 0 | J52: 1164.98 | K52: =I52*J52 -> 0 | M52: 1747.46 | N52: =L52*M52 -> 0 | V52: =+O52+P52+Q52+R52+S52+T52+U52-W52-X52 -> 0
A53: SUPERINTENDENTE | E53: hr | H53: =F53*G53 -> 0 | J53: =G53*1.5 -> 0 | K53: =I53*J53 -> 0 | M53: =G53*2.25 -> 0 | N53: =L53*M53 -> 0 | V53: =+O53+P53+Q53+R53+S53+T53+U53-W53-X53 -> 0
F54: =V54 -> 0 | G54: SUBT 2 | H54: =SUM(H31:H53) -> 0 | J54: SUBT. | K54: =SUM(K31:K53) -> 0 | M54: SUBT. | N54: =SUM(N31:N53) -> 0
G55: SUMA M.O. | H55: =H54+K54+N54 -> 0
A56: HERRAMIENTA MENOR | G56: 1 a 10% | H56: =+H55*0.06 -> 0
H57: =+H55+H56 -> 0
A58: VEHICULOS
A59: DESCRIPCION | E59: UNIDAD | F59: CANT. | G59: P.U. | H59: IMPORTE | J59: HR IDA | K59: HR RETORNO | L59: HR SITIO | M59: SUMA
A60: camioneta EXPRES VAN CARGO sin operador sin combustible | E60: HR | F60: 1 | G60: 170 | H60: =F60*G60 -> 170 | M60: =J60+K60+L60 -> 0
A61: camioneta RANGER sin operador sin combustible | E61: HR | F61: 0 | G61: 180 | H61: =F61*G61 -> 0 | M61: =J61+K61+L61 -> 0
A62: camioneta TORNADO Tornado sin operador sin combustible | E62: HR | F62: 0 | G62: 80 | H62: =F62*G62 -> 0 | M62: =J62+K62+L62 -> 0
A63: camioneta WV TRANSPORTER pasajeros | E63: HR | F63: 0 | G63: 150 | H63: =F63*G63 -> 0 | M63: =J63+K63+L63 -> 0
E64: HR | F64: 0 | H64: =F64*G64 -> 0 | M64: =J64+K64+L64 -> 0
E65: pza | F65: 0 | H65: =F65*G65 -> 0 | M65: =J65+K65+L65 -> 0
A66: Km. Recorrido (incluye conbustible y depresiación de Vehiculo | E66: KM | F66: 0 | G66: 2.5 | H66: =F66*G66 -> 0 | M66: =J66+K66+L66 -> 0
G67: SUBT 4 | H67: =SUM(H60:H66) -> 170
A68: COMBUSTIBLE
A69: DESCRIPCION | E69: UNIDAD | F69: CANT. | G69: P.U. | H69: IMPORTE | J69: KM IDA | K69: KM RETORNO | L69: KM SITIO | M69: SUMA
A70: GASOLINA MAGNA | E70: LT | F70: 60 | G70: 23 | H70: =F70*G70 -> 1380 | M70: =J70+K70+L70 -> 0
A71: DIESEL | E71: LT | F71: 0 | G71: 24 | H71: =F71*G71 -> 0 | M71: =J71+K71+L71 -> 0
G72: SUBT 5 | H72: =SUM(H70:H71) -> 1380
A73: CASETAS
A74: DESCRIPCION | E74: UNIDAD | F74: CANT. | G74: P.U. | H74: IMPORTE
A75: Camion | E75: CASETA | F75: 4 | G75: 120 | H75: =F75*G75 -> 480
A76: camioneta pick up | E76: CASETA | F76: 0 | G76: 250 | H76: =F76*G76 -> 0
G77: SUBT 6 | H77: =SUM(H75:H76) -> 480
A78: VIATICOS
A79: ALIMENTOS
A80: DESCRIPCION | E80: UNIDAD | F80: CANT. | G80: P.U. | H80: IMPORTE
A81: CONSUMO DE ALIMENTOS | E81: Pza | F81: 5 | G81: 650 | H81: =F81*G81 -> 3250
H82: =SUM(H81) -> 3250
A83: HOSPEDAJE
A84: DESCRIPCION | E84: UNIDAD | F84: CANT. | G84: P.U. | H84: IMPORTE
A85: HOTEL | E85: NOCHES | F85: 2 | G85: 1100 | H85: =F85*G85 -> 2200
G86: SUBT 8 | H86: =SUM(H85) -> 2200
G87: SUMA: | H87: =H67+H72+H77+H82+H86+H56+H55+H27 -> 22720.06
A88: EQUIPO DE PRUEBA
A89: DESCRIPCION | E89: UNIDAD | F89: CANT. | G89: P.U. | H89: IMPORTE | I89: TR | K89: S.E
A90: Megger | E90: jr | G90: 2200 | H90: =(F90*G90) -> 0
A91: TTR | E91: jr | G91: 2000 | H91: =(F91*G91) -> 0
A92: Factor de Potencia de 2.5 KV | E92: jr | G92: 7000 | H92: =(F92*G92) -> 0
A93: Factor de Potencia de 10.5 KV | E93: jr | G93: 15200 | H93: =(F93*G93) -> 0
A94: Ducter | E94: jr | G94: 2200 | H94: =(F94*G94) -> 0
A95: resistencia óhmica | E95: jr | G95: 2000 | H95: =(F95*G95) -> 0
A96: hipot de 80 KV vcd | E96: jr | G96: 2500 | H96: =(F96*G96) -> 0
A97: Rigidez dieléctrica al aceite 60 kv | E97: jr | G97: 1600 | H97: =(F97*G97) -> 0
A98: Terrómetro | E98: jr | G98: 1100 | H98: =(F98*G98) -> 0
A99: Analizador de tiempos de interruptor | E99: jr | G99: 2700 | H99: =(F99*G99) -> 0
A100: Fuente de corriente para calibrador de relevadores | E100: jr | G100: 2500 | H100: =(F100*G100) -> 0
A101: Probador de relevador de Protecciones | E101: jr | G101: 13373 | H101: =(F101*G101) -> 0
...

Sheet M0 (1)
A1: I M M E E S. A. D E C. V.
A2: A N A L I S I S D E P R E C I O U N I T A R I O
A3: COTIZACION:
A4: FECHA:
A5: PARTIDA 1
A6: REV-06-feb-2021
A7: MATERIALES.
A8: DESCRIPCION | E8: UNIDAD | F8: CANT. | G8: P.U. | H8: IMPORTE | J8: MANO DE OBRA
A9: Consumible | E9: Pza | H9: =G9*F9 -> 0
E10: Pza | H10: =G10*F10 -> 0
E11: Pza | H11: =G11*F11 -> 0
E12: Pza | H12: =G12*F12 -> 0
E13: Pza | H13: =G13*F13 -> 0
E14: Pza | H14: =G14*F14 -> 0
E15: Pza | H15: =G15*F15 -> 0
E16: Pza | H16: =G16*F16 -> 0 | I16: =H16*1.455 -> 0
G17: SUBT 1 | H17: =SUM(H9:H16) -> 0
A19: MANO DE OBRA SIN INDIRECTOS | O19: HORARIOS DE TRABAJO | V19: HORAS RESULTANTES | Y19: PERSONAL PEOPUESTO
A20: PERSONAL. | E20: UNIDAD | F20: CANT. | G20: HORA NORMAL | H20: IMPORTE | I20: CANT. | J20: Hr. Extra | K20: IMPORTE | L20: CANT. | M20: Dom, ó Fest.TRIPLE | N20: IMPORTE | O20: L | P20: M | Q20: MI | R20: J | S20: V | T20: S | U20: D | V20: N | W20: D | X20: T
A21: SUPERVISOR DE SEGURIDAD CERTIFICADO | E21: hr | G21: 390.39 | H21: =F21*G21 -> 0 | J21: 358.81 | K21: =I21*J21 -> 0 | M21: 538.27 | N21: =L21*M21 -> 0 | V21: =+O21+P21+Q21+R21+S21+T21+U21-W21-X21 -> 0
A22: SUPERVISOR DE SEGURIDAD | E22: hr | F22: 8 | G22: 317.98 | H22: =F22*G22 -> 2543.84 | I22: 2 | J22: 326.25 | K22: =I22*J22 -> 652.5 | M22: 489.37 | N22: =L22*M22 -> 0 | V22: =+O22+P22+Q22+R22+S22+T22+U22-W22-X22 -> 0 | Y22: OSWALDO Z-GABRIEL
A23: SUPERVISOR ELECTRICO | E23: hr | F23: 8 | G23: 237.68 | H23: =F23*G23 -> 1901.44 | I23: 2 | J23: 358.81 | K23: =I23*J23 -> 717.62 | M23: 538.22 | N23: =L23*M23 -> 0 | V23: =+O23+P23+Q23+R23+S23+T23+U23-W23-X23 -> 0 | Y23: ADRIAN
A24: TECNICO DE PRUEBAS ELECTRICAS | E24: hr | G24: 317.98 | H24: =F24*G24 -> 0 | J24: 244.27 | K24: =I24*J24 -> 0 | M24: 489.37 | N24: =L24*M24 -> 0 | V24: =+O24+P24+Q24+R24+S24+T24+U24-W24-X24 -> 0 | Y24: HECTOR
A25: CABO OBRA ELECTRICA | E25: hr | G25: 310.62 | H25: =F25*G25 -> 0 | J25: 335 | K25: =I25*J25 -> 0 | M25: 436.87 | N25: =L25*M25 -> 0 | V25: =+O25+P25+Q25+R25+S25+T25+U25-W25-X25 -> 0
A26: LINIERO | E26: hr | G26: 209.25 | H26: =F26*G26 -> 0 | J26: 221.7 | K26: =I26*J26 -> 0 | M26: 437.63 | N26: =L26*M26 -> 0 | V26: =+O26+P26+Q26+R26+S26+T26+U26-W26-X26 -> 0 | Y26: JOSE J
A27: ESPECIALISTA DE MANTTO ELECTRICO | E27: hr | G27: 237.68 | H27: =F27*G27 -> 0 | J27: 277.97 | K27: =I27*J27 -> 0 | M27: 538.84 | N27: =L27*M27 -> 0 | V27: =+O27+P27+Q27+R27+S27+T27+U27-W27-X27 -> 0
A28: TECNICO EN INSTRUMENTACION | E28: hr | G28: 368.59 | H28: =F28*G28 -> 0 | J28: 221.7 | K28: =I28*J28 -> 0 | M28: 538.84 | N28: =L28*M28 -> 0 | V28: =+O28+P28+Q28+R28+S28+T28+U28-W28-X28 -> 0
A29: OFICIAL ELECTRICO/ELECTROMECANICO | E29: hr | F29: 8 | G29: 190.22 | H29: =F29*G29 -> 1521.76 | I29: 2 | J29: 221.7 | K29: =I29*J29 -> 443.4 | M29: 277.56 | N29: =L29*M29 -> 0 | V29: =+O29+P29+Q29+R29+S29+T29+U29-W29-X29 -> 0
A30: ASISTENTE DE DISEÑO | E30: hr | G30: 190.25 | H30: =F30*G30 -> 0 | J30: 221.7 | K30: =I30*J30 -> 0 | M30: 297.41 | N30: =L30*M30 -> 0 | V30: =+O30+P30+Q30+R30+S30+T30+U30-W30-X30 -> 0
A31: ELECTRICISTA -B | E31: hr | G31: 119.54 | H31: =F31*G31 -> 0 | J31: 137.92 | K31: =I31*J31 -> 0 | M31: 0 | N31: =L31*M31 -> 0 | V31: =+O31+P31+Q31+R31+S31+T31+U31-W31-X31 -> 0 | Y31: GERMAN
A32: ELECTRICISTA -A | E32: hr | G32: 119.54 | H32: =F32*G32 -> 0 | J32: 137.92 | K32: =I32*J32 -> 0 | M32: 240.95 | N32: =L32*M32 -> 0 | V32: =+O32+P32+Q32+R32+S32+T32+U32-W32-X32 -> 0 | Y32: OSCAR-OSWALDO JIM
A33: AUXILIAR TECNICO | E33: hr | G33: 106.45 | H33: =F33*G33 -> 0 | J33: 137.92 | K33: =I33*J33 -> 0 | M33: 260.95 | N33: =L33*M33 -> 0 | V33: =+O33+P33+Q33+R33+S33+T33+U33-W33-X33 -> 0
A34: AYTE ELECTRICO - B | E34: hr | F34: 8 | G34: 106.45 | H34: =F34*G34 -> 851.6 | I34: 2 | J34: 122.4 | K34: =I34*J34 -> 244.8 | N34: =L34*M34 -> 0 | V34: =+O34+P34+Q34+R34+S34+T34+U34-W34-X34 -> 0
A35: AYTE DE ELECTR. -A | E35: hr | G35: 106.54 | H35: =F35*G35 -> 0 | J35: 122.4 | K35: =I35*J35 -> 0 | M35: 198.17 | N35: =L35*M35 -> 0 | V35: =+O35+P35+Q35+R35+S35+T35+U35-W35-X35 -> 0 | Y35: URIEL-GUILLERMO-ENRIQUE
A36: AYTE GENERAL | E36: hr | G36: 100.42 | H36: =F36*G36 -> 0 | J36: 122.4 | K36: =I36*J36 -> 0 | M36: 0 | N36: =L36*M36 -> 0 | V36: =+O36+P36+Q36+R36+S36+T36+U36-W36-X36 -> 0
A37: PROFESIONISTA | E37: hr | G37: 209.25 | H37: =F37*G37 -> 0 | J37: 406 | K37: =I37*J37 -> 0 | M37: 564.86 | N37: =L37*M37 -> 0 | V37: 0 | Y37: O.ZARCO-GABRIEL
A38: COORDINADOR DE OPERACIONES | E38: hr | G38: 0 | H38: =F38*G38 -> 0 | J38: 0 | K38: =I38*J38 -> 0 | M38: 0 | N38: =L38*M38 -> 0 | V38: =+O38+P38+Q38+R38+S38+T38+U38-W38-X38 -> 0
A39: INGENIERIA Y SOPORTE TEC. | E39: hr | G39: 339.75 | H39: =F39*G39 -> 0 | J39: 325.79 | K39: =I39*J39 -> 0 | M39: 488.68 | N39: =L39*M39 -> 0 | V39: =+O39+P39+Q39+R39+S39+T39+U39-W39-X39 -> 0
A40: INGENIERO DE SUBESTACIONES | E40: hr | G40: 339.75 | H40: =F40*G40 -> 0 | J40: 325.79 | K40: =I40*J40 -> 0 | M40: 488.68 | N40: =L40*M40 -> 0 | V40: =+O40+P40+Q40+R40+S40+T40+U40-W40-X40 -> 0
A41: INGENIERO DE PRUEBAS ELECTRICAS | E41: hr | G41: 339.75 | H41: =F41*G41 -> 0 | J41: 325.79 | K41: =I41*J41 -> 0 | M41: 488.68 | N41: =L41*M41 -> 0 | V41: =+O41+P41+Q41+R41+S41+T41+U41-W41-X41 -> 0
A42: ING. ESPECIALISTA EN PROTECCIONES | E42: hr | G42: 650 | H42: =F42*G42 -> 0 | J42: =G42*1.5 -> 975 | K42: =I42*J42 -> 0 | M42: 1747.46 | N42: =L42*M42 -> 0 | V42: =+O42+P42+Q42+R42+S42+T42+U42-W42-X42 -> 0
A43: SUPERINTENDENTE | E43: hr | H43: =F43*G43 -> 0 | J43: =G43*1.5 -> 0 | K43: =I43*J43 -> 0 | M43: =G43*2.25 -> 0 | N43: =L43*M43 -> 0 | V43: =+O43+P43+Q43+R43+S43+T43+U43-W43-X43 -> 0
F44: =V44 -> 0 | G44: SUBT 2 | H44: =SUM(H21:H43) -> 6818.64 | J44: SUBT. | K44: =SUM(K21:K43) -> 2058.32 | M44: SUBT. | N44: =SUM(N21:N43) -> 0
G45: SUMA M.O. | H45: =H44+K44+N44 -> 8876.96
A46: HERRAMIENTA MENOR | G46: 1 a 10% | H46: =+H45*0.06 -> 532.6176
A49: VEHICULOS
A50: DESCRIPCION | E50: UNIDAD | F50: CANT. | G50: P.U. | H50: IMPORTE | J50: HR IDA | K50: HR RETORNO | L50: HR SITIO | M50: SUMA
A51: camioneta EXPRES VAN CARGO sin operador sin combustible | E51: HR | F51: 0 | G51: 150 | H51: =F51*G51 -> 0 | M51: =J51+K51+L51 -> 0
A52: camioneta RANGER sin operador sin combustible | E52: HR | F52: 0 | G52: 150 | H52: =F52*G52 -> 0 | M52: =J52+K52+L52 -> 0
A53: camioneta TORNADO Tornado sin operador sin combustible | E53: HR | F53: 0 | G53: 60 | H53: =F53*G53 -> 0 | M53: =J53+K53+L53 -> 0
A54: camioneta WV TRANSPORTER pasajeros | E54: HR | F54: 0 | G54: 120 | H54: =F54*G54 -> 0 | M54: =J54+K54+L54 -> 0
E55: HR | F55: 0 | H55: =F55*G55 -> 0 | M55: =J55+K55+L55 -> 0
E56: pza | F56: 0 | H56: =F56*G56 -> 0 | M56: =J56+K56+L56 -> 0
A57: Km. Recorrido (incluye conbustible y depresiación de Vehiculo | E57: KM | F57: 0 | G57: 2.5 | H57: =F57*G57 -> 0 | M57: =J57+K57+L57 -> 0
G58: SUBT 4 | H58: =SUM(H51:H57) -> 0
G59: SUMA: | H59: =H58+H45+H17 -> 8876.96
A60: EQUIPO DE PRUEBA
A61: DESCRIPCION | E61: UNIDAD | F61: CANT. | G61: P.U. | H61: IMPORTE | I61: TR | K61: S.E
A62: Megger | E62: jr | G62: 2200 | H62: =(F62*G62) -> 0
A63: TTR | E63: jr | G63: 2000 | H63: =(F63*G63) -> 0
A64: Factor de Potencia de 2.5 KV | E64: jr | G64: 7000 | H64: =(F64*G64) -> 0
A65: Factor de Potencia de 10.5 KV | E65: jr | G65: 15200 | H65: =(F65*G65) -> 0
A66: Ducter | E66: jr | G66: 2200 | H66: =(F66*G66) -> 0
A67: resistencia óhmica | E67: jr | G67: 2000 | H67: =(F67*G67) -> 0
A68: hipot de 80 KV vcd | E68: jr | G68: 2500 | H68: =(F68*G68) -> 0
A69: Rigidez dieléctrica al aceite 60 kv | E69: jr | G69: 1600 | H69: =(F69*G69) -> 0
A70: Terrómetro | E70: jr | G70: 1100 | H70: =(F70*G70) -> 0
A71: Analizador de tiempos de interruptor | E71: jr | G71: 2700 | H71: =(F71*G71) -> 0
A72: Fuente de corriente para calibrador de relevadores | E72: jr | G72: 2500 | H72: =(F72*G72) -> 0
A73: Probador de relevador de Protecciones | E73: jr | G73: 13373 | H73: =(F73*G73) -> 0
... A82: Test Kit maleta de prueba G.E. | E82: jr | G82: 5800 | H82: =(F82*G82) -> 0
E83: jr | H83: =(F83*G83) -> 0
A84: Camara termografica | E84: jr | G84: 15000 | H84: =(F84*G84) -> 0
A85: Generador de Luz con combustible | E85: jr | G85: 383.5 | H85: =(F85*G85) -> 0
G86: SUBT 9 | H86: =SUM(H62:H85) -> 0
E88: 0 | H88: =+E88 -> 0 | I88: IMPUESTO | J88: INDIRECTO DISPONIBLE
F89: COSTO DIRECTO | H89: =H59+H86 -> 8876.96
F90: Indirectos | G90: 0.3 | H90: =H89*G90 -> 2663.088 | I90: =+M96 -> -879.15946 | J90: =H90-M96 -> 3542.2475 | N90: REV-06-feb-2021
F91: Subtotal 1 | H91: =H89+H90 -> 11540.048
F92: Financ. | G92: 0.06 | H92: =H91*G92 -> 692.40288 | K92: BASE IMPUESTO | L92: SIN UTILIDAD
F93: Subtotal 2 | H93: =H91+H92 -> 12232.451 | J93: COMPRAS | K93: =+H17 -> 0
F94: Utilidad | G94: 0.2 | H94: =H93*G94 -> 2446.4902 | J94: M.O | K94: =H44 -> 6818.64
F95: Importe | H95: =H93+H94 -> 14678.941 | J95: GASTOS FACTURADOS | K95: =H59-H46 -> 8344.3424 | M95: IMP. 30%
F96: Materiales | H96: ='MAT (1)'!H121 -> 31789.908 | I96: FACTOR | J96: SUMA | K96: =SUM(K93:K95) -> 15162.982 | L96: =H95-H94 -> 12232.451 | M96: =+(L96-K96)*0.3 -> -879.15946
B97: utilidad | F97: Total | H97: =H95+H96 -> 46468.849 | J97: =H95/H89 -> 1.6536
B98: ime | C98: comisión | D98: total | H98: =H97/6 -> 7744.8082
B99: 0.275 | C99: 0.05 | D99: =B99+C99 -> 0.325

Sheet MAT (2)
A1: I M M E E S. A. D E C. V.
A2: A N A L I S I S D E P R E C I O U N I T A R I O
A3: COTIZACION:
A4: FECHA:
A5: PARTIDA 1
A6: REV-06-feb-2021
A7: MATERIALES.
A8: DESCRIPCION | E8: UNIDAD | F8: CANT. | G8: P.U. | H8: IMPORTE | J8: MATERIALES
A9: charola tipo escalera perfil Z para servicio pesado de 30" | E9: Pza | G9: 2540.01 | H9: =G9*F9 -> 0
A10: tapa para charola tipo escalera de 30". | E10: Pza | F10: 6 | G10: 1001 | H10: =G10*F10 -> 6006
A11: curva vertical exterior de 90° para charola tipo escalera de 30 | E11: Pza | G11: 450.5 | H11: =G11*F11 -> 0
A12: tapa para curva vertical exterior de 90° para charola tipo escalera para servicio pesado de 30" | E12: Pza | G12: 136.52 | H12: =G12*F12 -> 0
A13: curva horizontal de 90° para charola tipo escalera para servicio pesado de 30" | E13: Pza | G13: 620.97 | H13: =G13*F13 -> 0
A14: base de unicanal solido galvanizado de 4x4 | E14: Pza | G14: 382.32 | H14: =G14*F14 -> 0
A15: tornilleria galvanizada | E15: Pza | G15: 200 | H15: =G15*F15 -> 0
A16: varilla roscada galvanizada de 3 metros de largo X 1/2" | E16: Pza | G16: 70 | H16: =G16*F16 -> 0
A17: conector de charola para servicio pesado de 30 | E17: Pza | G17: 467.05 | H17: =G17*F17 -> 0
A18: zapata ponchable para cable de cobre cañon largo calibre 500 KCM, con 2 ojillos de 1/2 | E18: Pza | G18: 495.41 | H18: =G18*F18 -> 0
A19: manga termocontractil para nivel de aislamiento de 600 V, en calibre 500 KCM. | E19: Pza | G19: 212.43 | H19: =G19*F19 -> 0
A20: sistema corta fuego con lana mineral y compuesto SF-ONE. | E20: Pza | G20: 698.25 | H20: =G20*F20 -> 0
A21: cuellos de lona flexibles en gargantas primarias de generador electrico | E21: Pza | G21: 160.08 | H21: =G21*F21 -> 0
A22: cable de cobre THW calibre 12 AWG | E22: mt | G22: 12.63 | H22: =G22*F22 -> 0 | L22: NOTA: CONSIDERAR LA JORNADA DE 8.0 HORAS, AUNQUE EN IMMEE SE TRABAJE JORNADA LARGA CONVENIDA, Y DOMINGO DESCANSO
A23: tapones para unicanal de 4x4 y varilla roscada | E23: Pza | G23: 27.6 | H23: =G23*F23 -> 0
A24: tapones para esparrago | E24: Pza | G24: 70.34 | H24: =G24*F24 -> 0
A25: Renta de una plataforma de elevacion | E25: Pza | F25: 0 | G25: 25000 | H25: =G25*F25 -> 0
A26: CONSUMIBLES | E26: Pza | F26: 1 | G26: 200 | H26: =G26*F26 -> 200
G27: SUBT 1 | H27: =SUM(H9:H26) -> 6206
A29: MANO DE OBRA SIN INDIRECTOS | O29: HORARIOS DE TRABAJO | V29: HORAS RESULTANTES | Y29: PERSONAL PEOPUESTO
A30: PERSONAL. | E30: UNIDAD | F30: CANT. | G30: HORA NORMAL | H30: IMPORTE | I30: CANT. | J30: Hr. Extra | K30: IMPORTE | L30: CANT. | M30: Dom, ó Fest.TRIPLE | N30: IMPORTE | O30: L | P30: M | Q30: MI | R30: J | S30: V | T30: S | U30: D | V30: N | W30: D | X30: T
A31: SUPERVISOR DE SEGURIDAD CERTIFICADO | E31: hr | G31: 390.39 | H31: =F31*G31 -> 0 | J31: 358.81 | K31: =I31*J31 -> 0 | M31: 538.27 | N31: =L31*M31 -> 0 | V31: =+O31+P31+Q31+R31+S31+T31+U31-W31-X31 -> 0
A32: SUPERVISOR DE SEGURIDAD | E32: hr | G32: 243.45 | H32: =F32*G32 -> 0 | J32: 211.59 | K32: =I32*J32 -> 0 | M32: 317.39 | N32: =L32*M32 -> 0 | V32: =+O32+P32+Q32+R32+S32+T32+U32-W32-X32 -> 0 | Y32: OSWALDO Z-GABRIEL
A33: SUPERVISOR ELECTRICO | E33: hr | G33: 390.39 | H33: =F33*G33 -> 0 | J33: 358.81 | K33: =I33*J33 -> 0 | M33: 538.22 | N33: =L33*M33 -> 0 | V33: =+O33+P33+Q33+R33+S33+T33+U33-W33-X33 -> 0 | Y33: ADRIAN
A34: TECNICO DE PRUEBAS ELECTRICAS | E34: hr | G34: 231.67 | H34: =F34*G34 -> 0 | J34: 197.63 | K34: =I34*J34 -> 0 | M34: 296.45 | N34: =L34*M34 -> 0 | V34: =+O34+P34+Q34+R34+S34+T34+U34-W34-X34 -> 0 | Y34: HECTOR
A35: CABO OBRA ELECTRICA | E35: hr | G35: 310.62 | H35: =F35*G35 -> 0 | J35: 291.24 | K35: =I35*J35 -> 0 | M35: 436.87 | N35: =L35*M35 -> 0 | V35: =+O35+P35+Q35+R35+S35+T35+U35-W35-X35 -> 0
A36: LINIERO | E36: hr | G36: 310.62 | H36: =F36*G36 -> 0 | J36: 291.24 | K36: =I36*J36 -> 0 | M36: 436.87 | N36: =L36*M36 -> 0 | V36: =+O36+P36+Q36+R36+S36+T36+U36-W36-X36 -> 0 | Y36: JOSE J
A37: ESPECIALISTA DE MANTTO ELECTRICO | E37: hr | H37: =F37*G37 -> 0 | J37: 0 | K37: =I37*J37 -> 0 | M37: 0 | N37: =L37*M37 -> 0 | V37: =+O37+P37+Q37+R37+S37+T37+U37-W37-X37 -> 0
A38: TECNICO EN INSTRUMENTACION | E38: hr | G38: 199.6 | H38: =F38*G38 -> 0 | J38: 159.6 | K38: =I38*J38 -> 0 | M38: 239.4 | N38: =L38*M38 -> 0 | V38: =+O38+P38+Q38+R38+S38+T38+U38-W38-X38 -> 0
A39: OFICIAL ELECTRICO/ELECTROMECANICO | E39: hr | G39: 199.6 | H39: =F39*G39 -> 0 | J39: 159.6 | K39: =I39*J39 -> 0 | M39: 239.4 | N39: =L39*M39 -> 0 | V39: =+O39+P39+Q39+R39+S39+T39+U39-W39-X39 -> 0
A40: ASISTENTE DE DISEÑO | E40: hr | G40: 199.6 | H40: =F40*G40 -> 0 | J40: 159.6 | K40: =I40*J40 -> 0 | M40: 239.4 | N40: =L40*M40 -> 0 | V40: =+O40+P40+Q40+R40+S40+T40+U40-W40-X40 -> 0
A41: ELECTRICISTA -B | E41: hr | G41: 211.15 | H41: =F41*G41 -> 0 | J41: 173.29 | K41: =I41*J41 -> 0 | M41: 259.94 | N41: =L41*M41 -> 0 | V41: =+O41+P41+Q41+R41+S41+T41+U41-W41-X41 -> 0 | Y41: GERMAN
A42: ELECTRICISTA -A | E42: hr | G42: 199.6 | H42: =F42*G42 -> 0 | J42: 159.6 | K42: =I42*J42 -> 0 | M42: 239.4 | N42: =L42*M42 -> 0 | V42: =+O42+P42+Q42+R42+S42+T42+U42-W42-X42 -> 0 | Y42: OSCAR-OSWALDO JIM
A43: AUXILIAR TECNICO | E43: hr | G43: 187.81 | H43: =F43*G43 -> 0 | J43: 145.62 | K43: =I43*J43 -> 0 | M43: 218.43 | N43: =L43*M43 -> 0 | V43: =+O43+P43+Q43+R43+S43+T43+U43-W43-X43 -> 0
A44: AYTE ELECTRICO - B | E44: hr | H44: =F44*G44 -> 0 | J44: 0 | K44: =I44*J44 -> 0 | N44: =L44*M44 -> 0 | V44: =+O44+P44+Q44+R44+S44+T44+U44-W44-X44 -> 0
A45: AYTE DE ELECTR. -A | E45: hr | G45: 187.81 | H45: =F45*G45 -> 0 | J45: 145.62 | K45: =I45*J45 -> 0 | M45: 218.43 | N45: =L45*M45 -> 0 | V45: =+O45+P45+Q45+R45+S45+T45+U45-W45-X45 -> 0 | Y45: URIEL-GUILLERMO-ENRIQUE
A46: AYTE GENERAL | E46: hr | G46: 94.81 | H46: =F46*G46 -> 0 | J46: 145.62 | K46: =I46*J46 -> 0 | M46: 218.43 | N46: =L46*M46 -> 0 | V46: =+O46+P46+Q46+R46+S46+T46+U46-W46-X46 -> 0
A47: PROFESIONISTA | E47: hr | G47: 243.45 | H47: =F47*G47 -> 0 | J47: 211.59 | K47: =I47*J47 -> 0 | M47: 317.39 | N47: =L47*M47 -> 0 | V47: 0 | Y47: O.ZARCO-GABRIEL
A48: COORDINADOR DE OPERACIONES | E48: hr | G48: 339.75 | H48: =F48*G48 -> 0 | J48: 325.79 | K48: =I48*J48 -> 0 | M48: 488.68 | N48: =L48*M48 -> 0 | V48: =+O48+P48+Q48+R48+S48+T48+U48-W48-X48 -> 0
A49: INGENIERIA Y SOPORTE TEC. | E49: hr | G49: 339.75 | H49: =F49*G49 -> 0 | J49: 325.79 | K49: =I49*J49 -> 0 | M49: 488.68 | N49: =L49*M49 -> 0 | V49: =+O49+P49+Q49+R49+S49+T49+U49-W49-X49 -> 0
A50: INGENIERO DE SUBESTACIONES | E50: hr | G50: 339.75 | H50: =F50*G50 -> 0 | J50: 325.79 | K50: =I50*J50 -> 0 | M50: 488.68 | N50: =L50*M50 -> 0 | V50: =+O50+P50+Q50+R50+S50+T50+U50-W50-X50 -> 0
A51: INGENIERO DE PRUEBAS ELECTRICAS | E51: hr | G51: 339.75 | H51: =F51*G51 -> 0 | J51: 325.79 | K51: =I51*J51 -> 0 | M51: 488.68 | N51: =L51*M51 -> 0 | V51: =+O51+P51+Q51+R51+S51+T51+U51-W51-X51 -> 0
A52: ING. ESPECIALISTA EN PROTECCIONES | E52: hr | G52: 1004.49 | H52: =F52*G52 -> 0 | J52: 1164.98 | K52: =I52*J52 -> 0 | M52: 1747.46 | N52: =L52*M52 -> 0 | V52: =+O52+P52+Q52+R52+S52+T52+U52-W52-X52 -> 0
A53: SUPERINTENDENTE | E53: hr | H53: =F53*G53 -> 0 | J53: =G53*1.5 -> 0 | K53: =I53*J53 -> 0 | M53: =G53*2.25 -> 0 | N53: =L53*M53 -> 0 | V53: =+O53+P53+Q53+R53+S53+T53+U53-W53-X53 -> 0
F54: =V54 -> 0 | G54: SUBT 2 | H54: =SUM(H31:H53) -> 0 | J54: SUBT. | K54: =SUM(K31:K53) -> 0 | M54: SUBT. | N54: =SUM(N31:N53) -> 0
G55: SUMA M.O. | H55: =H54+K54+N54 -> 0
A56: HERRAMIENTA MENOR | G56: 1 a 10% | H56: =+H55*0.06 -> 0
H57: =+H55+H56 -> 0
A58: VEHICULOS
A59: DESCRIPCION | E59: UNIDAD | F59: CANT. | G59: P.U. | H59: IMPORTE | J59: HR IDA | K59: HR RETORNO | L59: HR SITIO | M59: SUMA
A60: camioneta EXPRES VAN CARGO sin operador sin combustible | E60: HR | F60: 1 | G60: 170 | H60: =F60*G60 -> 170 | M60: =J60+K60+L60 -> 0
A61: camioneta RANGER sin operador sin combustible | E61: HR | F61: 0 | G61: 180 | H61: =F61*G61 -> 0 | M61: =J61+K61+L61 -> 0
A62: camioneta TORNADO Tornado sin operador sin combustible | E62: HR | F62: 0 | G62: 80 | H62: =F62*G62 -> 0 | M62: =J62+K62+L62 -> 0
A63: camioneta WV TRANSPORTER pasajeros | E63: HR | F63: 0 | G63: 150 | H63: =F63*G63 -> 0 | M63: =J63+K63+L63 -> 0
E64: HR | F64: 0 | H64: =F64*G64 -> 0 | M64: =J64+K64+L64 -> 0
E65: pza | F65: 0 | H65: =F65*G65 -> 0 | M65: =J65+K65+L65 -> 0
A66: Km. Recorrido (incluye conbustible y depresiación de Vehiculo | E66: KM | F66: 0 | G66: 2.5 | H66: =F66*G66 -> 0 | M66: =J66+K66+L66 -> 0
G67: SUBT 4 | H67: =SUM(H60:H66) -> 170
A68: COMBUSTIBLE
A69: DESCRIPCION | E69: UNIDAD | F69: CANT. | G69: P.U. | H69: IMPORTE | J69: KM IDA | K69: KM RETORNO | L69: KM SITIO | M69: SUMA
A70: GASOLINA MAGNA | E70: LT | F70: 10 | G70: 23 | H70: =F70*G70 -> 230 | M70: =J70+K70+L70 -> 0
A71: DIESEL | E71: LT | F71: 0 | G71: 24 | H71: =F71*G71 -> 0 | M71: =J71+K71+L71 -> 0
G72: SUBT 5 | H72: =SUM(H70:H71) -> 230
A73: CASETAS
A74: DESCRIPCION | E74: UNIDAD | F74: CANT. | G74: P.U. | H74: IMPORTE
A75: Camion | E75: CASETA | F75: 1 | G75: 65 | H75: =F75*G75 -> 65
A76: camioneta pick up | E76: CASETA | F76: 0 | G76: 250 | H76: =F76*G76 -> 0
G77: SUBT 6 | H77: =SUM(H75:H76) -> 65
A78: VIATICOS
A79: ALIMENTOS
A80: DESCRIPCION | E80: UNIDAD | F80: CANT. | G80: P.U. | H80: IMPORTE
A81: CONSUMO DE ALIMENTOS | E81: Pza | F81: 1 | G81: 650 | H81: =F81*G81 -> 650
H82: =SUM(H81) -> 650
A83: HOSPEDAJE
A84: DESCRIPCION | E84: UNIDAD | F84: CANT. | G84: P.U. | H84: IMPORTE
A85: HOTEL | E85: NOCHES | F85: 0.5 | G85: 1100 | H85: =F85*G85 -> 550
G86: SUBT 8 | H86: =SUM(H85) -> 550
G87: SUMA: | H87: =H67+H72+H77+H82+H86+H56+H55+H27 -> 7871
A88: EQUIPO DE PRUEBA
A89: DESCRIPCION | E89: UNIDAD | F89: CANT. | G89: P.U. | H89: IMPORTE | I89: TR | K89: S.E
A90: Megger | E90: jr | G90: 2200 | H90: =(F90*G90) -> 0
A91: TTR | E91: jr | G91: 2000 | H91: =(F91*G91) -> 0
A92: Factor de Potencia de 2.5 KV | E92: jr | G92: 7000 | H92: =(F92*G92) -> 0
A93: Factor de Potencia de 10.5 KV | E93: jr | G93: 15200 | H93: =(F93*G93) -> 0
A94: Ducter | E94: jr | G94: 2200 | H94: =(F94*G94) -> 0
A95: resistencia óhmica | E95: jr | G95: 2000 | H95: =(F95*G95) -> 0
A96: hipot de 80 KV vcd | E96: jr | G96: 2500 | H96: =(F96*G96) -> 0
A97: Rigidez dieléctrica al aceite 60 kv | E97: jr | G97: 1600 | H97: =(F97*G97) -> 0
A98: Terrómetro | E98: jr | G98: 1100 | H98: =(F98*G98) -> 0
A99: Analizador de tiempos de interruptor | E99: jr | G99: 2700 | H99: =(F99*G99) -> 0
A100: Fuente de corriente para calibrador de relevadores | E100: jr | G100: 2500 | H100: =(F100*G100) -> 0
A101: Probador de relevador de Protecciones | E101: jr | G101: 13373 | H101: =(F101*G101) -> 0
...

Sheet M0 (2)
A1: I M M E E S. A. D E C. V.
A2: A N A L I S I S D E P R E C I O U N I T A R I O
A3: COTIZACION:
A4: FECHA:
A5: PARTIDA 1
A6: REV-06-feb-2021
A7: MATERIALES.
A8: DESCRIPCION | E8: UNIDAD | F8: CANT. | G8: P.U. | H8: IMPORTE | J8: MANO DE OBRA
A9: Consumible | E9: Pza | H9: =G9*F9 -> 0
E10: Pza | H10: =G10*F10 -> 0
E11: Pza | H11: =G11*F11 -> 0
E12: Pza | H12: =G12*F12 -> 0
E13: Pza | H13: =G13*F13 -> 0
E14: Pza | H14: =G14*F14 -> 0
E15: Pza | H15: =G15*F15 -> 0
E16: Pza | H16: =G16*F16 -> 0 | I16: =H16*1.455 -> 0
G17: SUBT 1 | H17: =SUM(H9:H16) -> 0
A19: MANO DE OBRA SIN INDIRECTOS | O19: HORARIOS DE TRABAJO | V19: HORAS RESULTANTES | Y19: PERSONAL PEOPUESTO
A20: PERSONAL. | E20: UNIDAD | F20: CANT. | G20: HORA NORMAL | H20: IMPORTE | I20: CANT. | J20: Hr. Extra | K20: IMPORTE | L20: CANT. | M20: Dom, ó Fest.TRIPLE | N20: IMPORTE | O20: L | P20: M | Q20: MI | R20: J | S20: V | T20: S | U20: D | V20: N | W20: D | X20: T
A21: SUPERVISOR DE SEGURIDAD CERTIFICADO | E21: hr | G21: 390.39 | H21: =F21*G21 -> 0 | J21: 358.81 | K21: =I21*J21 -> 0 | M21: 538.27 | N21: =L21*M21 -> 0 | V21: =+O21+P21+Q21+R21+S21+T21+U21-W21-X21 -> 0
A22: SUPERVISOR DE SEGURIDAD | E22: hr | F22: 1 | G22: 317.98 | H22: =F22*G22 -> 317.98 | J22: 326.25 | K22: =I22*J22 -> 0 | M22: 489.37 | N22: =L22*M22 -> 0 | V22: =+O22+P22+Q22+R22+S22+T22+U22-W22-X22 -> 0 | Y22: OSWALDO Z-GABRIEL
A23: SUPERVISOR ELECTRICO | E23: hr | F23: 1 | G23: 237.68 | H23: =F23*G23 -> 237.68 | J23: 358.81 | K23: =I23*J23 -> 0 | M23: 538.22 | N23: =L23*M23 -> 0 | V23: =+O23+P23+Q23+R23+S23+T23+U23-W23-X23 -> 0 | Y23: ADRIAN
A24: TECNICO DE PRUEBAS ELECTRICAS | E24: hr | G24: 317.98 | H24: =F24*G24 -> 0 | J24: 244.27 | K24: =I24*J24 -> 0 | M24: 489.37 | N24: =L24*M24 -> 0 | V24: =+O24+P24+Q24+R24+S24+T24+U24-W24-X24 -> 0 | Y24: HECTOR
A25: CABO OBRA ELECTRICA | E25: hr | G25: 310.62 | H25: =F25*G25 -> 0 | J25: 335 | K25: =I25*J25 -> 0 | M25: 436.87 | N25: =L25*M25 -> 0 | V25: =+O25+P25+Q25+R25+S25+T25+U25-W25-X25 -> 0
A26: LINIERO | E26: hr | G26: 209.25 | H26: =F26*G26 -> 0 | J26: 221.7 | K26: =I26*J26 -> 0 | M26: 437.63 | N26: =L26*M26 -> 0 | V26: =+O26+P26+Q26+R26+S26+T26+U26-W26-X26 -> 0 | Y26: JOSE J
A27: ESPECIALISTA DE MANTTO ELECTRICO | E27: hr | G27: 237.68 | H27: =F27*G27 -> 0 | J27: 277.97 | K27: =I27*J27 -> 0 | M27: 538.84 | N27: =L27*M27 -> 0 | V27: =+O27+P27+Q27+R27+S27+T27+U27-W27-X27 -> 0
A28: TECNICO EN INSTRUMENTACION | E28: hr | G28: 368.59 | H28: =F28*G28 -> 0 | J28: 221.7 | K28: =I28*J28 -> 0 | M28: 538.84 | N28: =L28*M28 -> 0 | V28: =+O28+P28+Q28+R28+S28+T28+U28-W28-X28 -> 0
A29: OFICIAL ELECTRICO/ELECTROMECANICO | E29: hr | F29: 2 | G29: 190.22 | H29: =F29*G29 -> 380.44 | J29: 165 | K29: =I29*J29 -> 0 | M29: 277.56 | N29: =L29*M29 -> 0 | V29: =+O29+P29+Q29+R29+S29+T29+U29-W29-X29 -> 0
A30: ASISTENTE DE DISEÑO | E30: hr | G30: 190.25 | H30: =F30*G30 -> 0 | J30: 221.7 | K30: =I30*J30 -> 0 | M30: 297.41 | N30: =L30*M30 -> 0 | V30: =+O30+P30+Q30+R30+S30+T30+U30-W30-X30 -> 0
A31: ELECTRICISTA -B | E31: hr | G31: 119.54 | H31: =F31*G31 -> 0 | J31: 137.92 | K31: =I31*J31 -> 0 | M31: 0 | N31: =L31*M31 -> 0 | V31: =+O31+P31+Q31+R31+S31+T31+U31-W31-X31 -> 0 | Y31: GERMAN
A32: ELECTRICISTA -A | E32: hr | F32: 2 | G32: 119.54 | H32: =F32*G32 -> 239.08 | J32: 137.92 | K32: =I32*J32 -> 0 | M32: 240.95 | N32: =L32*M32 -> 0 | V32: =+O32+P32+Q32+R32+S32+T32+U32-W32-X32 -> 0 | Y32: OSCAR-OSWALDO JIM
A33: AUXILIAR TECNICO | E33: hr | G33: 106.45 | H33: =F33*G33 -> 0 | J33: 137.92 | K33: =I33*J33 -> 0 | M33: 260.95 | N33: =L33*M33 -> 0 | V33: =+O33+P33+Q33+R33+S33+T33+U33-W33-X33 -> 0
A34: AYTE ELECTRICO - B | E34: hr | F34: 2 | G34: 106.45 | H34: =F34*G34 -> 212.9 | J34: 122.4 | K34: =I34*J34 -> 0 | N34: =L34*M34 -> 0 | V34: =+O34+P34+Q34+R34+S34+T34+U34-W34-X34 -> 0
A35: AYTE DE ELECTR. -A | E35: hr | G35: 106.54 | H35: =F35*G35 -> 0 | J35: 122.4 | K35: =I35*J35 -> 0 | M35: 198.17 | N35: =L35*M35 -> 0 | V35: =+O35+P35+Q35+R35+S35+T35+U35-W35-X35 -> 0 | Y35: URIEL-GUILLERMO-ENRIQUE
A36: AYTE GENERAL | E36: hr | G36: 100.42 | H36: =F36*G36 -> 0 | J36: 122.4 | K36: =I36*J36 -> 0 | M36: 0 | N36: =L36*M36 -> 0 | V36: =+O36+P36+Q36+R36+S36+T36+U36-W36-X36 -> 0
A37: PROFESIONISTA | E37: hr | G37: 209.25 | H37: =F37*G37 -> 0 | J37: 406 | K37: =I37*J37 -> 0 | M37: 564.86 | N37: =L37*M37 -> 0 | V37: 0 | Y37: O.ZARCO-GABRIEL
A38: COORDINADOR DE OPERACIONES | E38: hr | G38: 0 | H38: =F38*G38 -> 0 | J38: 0 | K38: =I38*J38 -> 0 | M38: 0 | N38: =L38*M38 -> 0 | V38: =+O38+P38+Q38+R38+S38+T38+U38-W38-X38 -> 0
A39: INGENIERIA Y SOPORTE TEC. | E39: hr | G39: 339.75 | H39: =F39*G39 -> 0 | J39: 325.79 | K39: =I39*J39 -> 0 | M39: 488.68 | N39: =L39*M39 -> 0 | V39: =+O39+P39+Q39+R39+S39+T39+U39-W39-X39 -> 0
A40: INGENIERO DE SUBESTACIONES | E40: hr | G40: 339.75 | H40: =F40*G40 -> 0 | J40: 325.79 | K40: =I40*J40 -> 0 | M40: 488.68 | N40: =L40*M40 -> 0 | V40: =+O40+P40+Q40+R40+S40+T40+U40-W40-X40 -> 0
A41: INGENIERO DE PRUEBAS ELECTRICAS | E41: hr | G41: 339.75 | H41: =F41*G41 -> 0 | J41: 325.79 | K41: =I41*J41 -> 0 | M41: 488.68 | N41: =L41*M41 -> 0 | V41: =+O41+P41+Q41+R41+S41+T41+U41-W41-X41 -> 0
A42: ING. ESPECIALISTA EN PROTECCIONES | E42: hr | G42: 650 | H42: =F42*G42 -> 0 | J42: =G42*1.5 -> 975 | K42: =I42*J42 -> 0 | M42: 1747.46 | N42: =L42*M42 -> 0 | V42: =+O42+P42+Q42+R42+S42+T42+U42-W42-X42 -> 0
A43: SUPERINTENDENTE | E43: hr | H43: =F43*G43 -> 0 | J43: =G43*1.5 -> 0 | K43: =I43*J43 -> 0 | M43: =G43*2.25 -> 0 | N43: =L43*M43 -> 0 | V43: =+O43+P43+Q43+R43+S43+T43+U43-W43-X43 -> 0
F44: =V44 -> 0 | G44: SUBT 2 | H44: =SUM(H21:H43) -> 1388.08 | J44: SUBT. | K44: =SUM(K21:K43) -> 0 | M44: SUBT. | N44: =SUM(N21:N43) -> 0
G45: SUMA M.O. | H45: =H44+K44+N44 -> 1388.08
A46: HERRAMIENTA MENOR | G46: 1 a 10% | H46: =+H45*0.06 -> 83.2848
A49: VEHICULOS
A50: DESCRIPCION | E50: UNIDAD | F50: CANT. | G50: P.U. | H50: IMPORTE | J50: HR IDA | K50: HR RETORNO | L50: HR SITIO | M50: SUMA
A51: camioneta EXPRES VAN CARGO sin operador sin combustible | E51: HR | F51: 0 | G51: 150 | H51: =F51*G51 -> 0 | M51: =J51+K51+L51 -> 0
A52: camioneta RANGER sin operador sin combustible | E52: HR | F52: 0 | G52: 150 | H52: =F52*G52 -> 0 | M52: =J52+K52+L52 -> 0
A53: camioneta TORNADO Tornado sin operador sin combustible | E53: HR | F53: 0 | G53: 60 | H53: =F53*G53 -> 0 | M53: =J53+K53+L53 -> 0
A54: camioneta WV TRANSPORTER pasajeros | E54: HR | F54: 0 | G54: 120 | H54: =F54*G54 -> 0 | M54: =J54+K54+L54 -> 0
E55: HR | F55: 0 | H55: =F55*G55 -> 0 | M55: =J55+K55+L55 -> 0
E56: pza | F56: 0 | H56: =F56*G56 -> 0 | M56: =J56+K56+L56 -> 0
A57: Km. Recorrido (incluye conbustible y depresiación de Vehiculo | E57: KM | F57: 0 | G57: 2.5 | H57: =F57*G57 -> 0 | M57: =J57+K57+L57 -> 0
G58: SUBT 4 | H58: =SUM(H51:H57) -> 0
G59: SUMA: | H59: =H58+H45+H17 -> 1388.08
A60: EQUIPO DE PRUEBA
A61: DESCRIPCION | E61: UNIDAD | F61: CANT. | G61: P.U. | H61: IMPORTE | I61: TR | K61: S.E
A62: Megger | E62: jr | G62: 2200 | H62: =(F62*G62) -> 0
A63: TTR | E63: jr | G63: 2000 | H63: =(F63*G63) -> 0
A64: Factor de Potencia de 2.5 KV | E64: jr | G64: 7000 | H64: =(F64*G64) -> 0
A65: Factor de Potencia de 10.5 KV | E65: jr | G65: 15200 | H65: =(F65*G65) -> 0
A66: Ducter | E66: jr | G66: 2200 | H66: =(F66*G66) -> 0
A67: resistencia óhmica | E67: jr | G67: 2000 | H67: =(F67*G67) -> 0
A68: hipot de 80 KV vcd | E68: jr | G68: 2500 | H68: =(F68*G68) -> 0
A69: Rigidez dieléctrica al aceite 60 kv | E69: jr | G69: 1600 | H69: =(F69*G69) -> 0
A70: Terrómetro | E70: jr | G70: 1100 | H70: =(F70*G70) -> 0
A71: Analizador de tiempos de interruptor | E71: jr | G71: 2700 | H71: =(F71*G71) -> 0
A72: Fuente de corriente para calibrador de relevadores | E72: jr | G72: 2500 | H72: =(F72*G72) -> 0
A73: Probador de relevador de Protecciones | E73: jr | G73: 13373 | H73: =(F73*G73) -> 0
... A82: Test Kit maleta de prueba G.E. | E82: jr | G82: 5800 | H82: =(F82*G82) -> 0
E83: jr | H83: =(F83*G83) -> 0
A84: Camara termografica | E84: jr | G84: 15000 | H84: =(F84*G84) -> 0
A85: Generador de Luz con combustible | E85: jr | G85: 383.5 | H85: =(F85*G85) -> 0
G86: SUBT 9 | H86: =SUM(H62:H85) -> 0
E88: 0 | H88: =+E88 -> 0 | I88: IMPUESTO | J88: INDIRECTO DISPONIBLE
F89: COSTO DIRECTO | H89: =H59+H86 -> 1388.08
F90: Indirectos | G90: 0.25 | H90: =H89*G90 -> 347.02 | I90: =+M96 -> -256.10076 | J90: =H90-M96 -> 603.12076 | N90: REV-06-feb-2021
F91: Subtotal 1 | H91: =H89+H90 -> 1735.1
F92: Financ. | G92: 0.06 | H92: =H91*G92 -> 104.106 | K92: BASE IMPUESTO | L92: SIN UTILIDAD
F93: Subtotal 2 | H93: =H91+H92 -> 1839.206 | J93: COMPRAS | K93: =+H17 -> 0
F94: Utilidad | G94: 0.2 | H94: =H93*G94 -> 367.8412 | J94: M.O | K94: =H44 -> 1388.08
F95: Importe | H95: =H93+H94 -> 2207.0472 | J95: GASTOS FACTURADOS | K95: =H59-H46 -> 1304.7952 | M95: IMP. 30%
F96: Materiales | H96: ='MAT (2)'!H121 -> 11013.103 | I96: FACTOR | J96: SUMA | K96: =SUM(K93:K95) -> 2692.8752 | L96: =H95-H94 -> 1839.206 | M96: =+(L96-K96)*0.3 -> -256.10076
B97: utilidad | F97: Total | H97: =H95+H96 -> 13220.15 | J97: =H95/H89 -> 1.59
B98: ime | C98: comisión | D98: total
B99: 0.275 | C99: 0.05 | D99: =B99+C99 -> 0.325

Sheet MAT (3)
A1: I M M E E S. A. D E C. V.
A2: A N A L I S I S D E P R E C I O U N I T A R I O
A3: COTIZACION:
A4: FECHA:
A5: PARTIDA 1
A6: REV-06-feb-2021
A7: MATERIALES.
A8: DESCRIPCION | E8: UNIDAD | F8: CANT. | G8: P.U. | H8: IMPORTE | J8: MATERIALES
A9: charola tipo escalera perfil Z para servicio pesado de 30" | E9: Pza | G9: 2540.01 | H9: =G9*F9 -> 0
A10: tapa para charola tipo escalera de 30". | E10: Pza | G10: 1001 | H10: =G10*F10 -> 0
A11: curva vertical exterior de 90° para charola tipo escalera de 30 | E11: Pza | F11: 4 | G11: 450.5 | H11: =G11*F11 -> 1802
A12: tapa para curva vertical exterior de 90° para charola tipo escalera para servicio pesado de 30" | E12: Pza | G12: 136.52 | H12: =G12*F12 -> 0
A13: curva horizontal de 90° para charola tipo escalera para servicio pesado de 30" | E13: Pza | G13: 620.97 | H13: =G13*F13 -> 0
A14: base de unicanal solido galvanizado de 4x4 | E14: Pza | G14: 382.32 | H14: =G14*F14 -> 0
A15: tornilleria galvanizada | E15: Pza | G15: 200 | H15: =G15*F15 -> 0
A16: varilla roscada galvanizada de 3 metros de largo X 1/2" | E16: Pza | G16: 70 | H16: =G16*F16 -> 0
A17: conector de charola para servicio pesado de 30 | E17: Pza | G17: 467.05 | H17: =G17*F17 -> 0
A18: zapata ponchable para cable de cobre cañon largo calibre 500 KCM, con 2 ojillos de 1/2 | E18: Pza | G18: 495.41 | H18: =G18*F18 -> 0
A19: manga termocontractil para nivel de aislamiento de 600 V, en calibre 500 KCM. | E19: Pza | G19: 212.43 | H19: =G19*F19 -> 0
A20: tornillo tropicalizado de 1/2" con 2" de largo | E20: Pza | G20: 15 | H20: =G20*F20 -> 0
A21: tornillo tropicalizado de 1/2" con 4" de largo | E21: Pza | G21: 15 | H21: =G21*F21 -> 0
A22: sistema corta fuego con lana mineral y compuesto SF-ONE. | E22: Pza | G22: 698.25 | H22: =G22*F22 -> 0
A23: Materiales consumibles | E23: PZA | G23: 500 | H23: =G23*F23 -> 0
A24: cuellos de lona flexibles en gargantas primarias de generador electrico | E24: Pza | G24: 160.08 | H24: =G24*F24 -> 0
A25: cable de cobre THW calibre 12 AWG | E25: mt | G25: 12.63 | H25: =G25*F25 -> 0 | L25: NOTA: CONSIDERAR LA JORNADA DE 8.0 HORAS, AUNQUE EN IMMEE SE TRABAJE JORNADA LARGA CONVENIDA, Y DOMINGO DESCANSO
A26: tapones para unicanal de 4x4 y varilla roscada | E26: Pza | G26: 27.6 | H26: =G26*F26 -> 0
A27: tapones para esparrago | E27: Pza | G27: 70.34 | H27: =G27*F27 -> 0
A28: consumibles | E28: 1 | F28: 1 | G28: 300 | H28: =G28*F28 -> 300
A29: Renta de una plataforma de elevacion | E29: Pza | G29: 25000 | H29: =G29*F29 -> 0 | I29: =H29*1.455 -> 0
G30: SUBT 1 | H30: =SUM(H9:H29) -> 2102
A32: MANO DE OBRA SIN INDIRECTOS | O32: HORARIOS DE TRABAJO | V32: HORAS RESULTANTES | Y32: PERSONAL PEOPUESTO
A33: PERSONAL. | E33: UNIDAD | F33: CANT. | G33: HORA NORMAL | H33: IMPORTE | I33: CANT. | J33: Hr. Extra | K33: IMPORTE | L33: CANT. | M33: Dom, ó Fest.TRIPLE | N33: IMPORTE | O33: L | P33: M | Q33: MI | R33: J | S33: V | T33: S | U33: D | V33: N | W33: D | X33: T
A34: SUPERVISOR DE SEGURIDAD CERTIFICADO | E34: hr | G34: 390.39 | H34: =F34*G34 -> 0 | J34: 358.81 | K34: =I34*J34 -> 0 | M34: 538.27 | N34: =L34*M34 -> 0 | V34: =+O34+P34+Q34+R34+S34+T34+U34-W34-X34 -> 0
A35: SUPERVISOR DE SEGURIDAD | E35: hr | G35: 243.45 | H35: =F35*G35 -> 0 | J35: 211.59 | K35: =I35*J35 -> 0 | M35: 317.39 | N35: =L35*M35 -> 0 | V35: =+O35+P35+Q35+R35+S35+T35+U35-W35-X35 -> 0 | Y35: OSWALDO Z-GABRIEL
A36: SUPERVISOR ELECTRICO | E36: hr | G36: 390.39 | H36: =F36*G36 -> 0 | J36: 358.81 | K36: =I36*J36 -> 0 | M36: 538.22 | N36: =L36*M36 -> 0 | V36: =+O36+P36+Q36+R36+S36+T36+U36-W36-X36 -> 0 | Y36: ADRIAN
A37: TECNICO DE PRUEBAS ELECTRICAS | E37: hr | G37: 231.67 | H37: =F37*G37 -> 0 | J37: 197.63 | K37: =I37*J37 -> 0 | M37: 296.45 | N37: =L37*M37 -> 0 | V37: =+O37+P37+Q37+R37+S37+T37+U37-W37-X37 -> 0 | Y37: HECTOR
A38: CABO OBRA ELECTRICA | E38: hr | G38: 310.62 | H38: =F38*G38 -> 0 | J38: 291.24 | K38: =I38*J38 -> 0 | M38: 436.87 | N38: =L38*M38 -> 0 | V38: =+O38+P38+Q38+R38+S38+T38+U38-W38-X38 -> 0
A39: LINIERO | E39: hr | G39: 310.62 | H39: =F39*G39 -> 0 | J39: 291.24 | K39: =I39*J39 -> 0 | M39: 436.87 | N39: =L39*M39 -> 0 | V39: =+O39+P39+Q39+R39+S39+T39+U39-W39-X39 -> 0 | Y39: JOSE J
A40: ESPECIALISTA DE MANTTO ELECTRICO | E40: hr | H40: =F40*G40 -> 0 | J40: 0 | K40: =I40*J40 -> 0 | M40: 0 | N40: =L40*M40 -> 0 | V40: =+O40+P40+Q40+R40+S40+T40+U40-W40-X40 -> 0
A41: TECNICO EN INSTRUMENTACION | E41: hr | G41: 199.6 | H41: =F41*G41 -> 0 | J41: 159.6 | K41: =I41*J41 -> 0 | M41: 239.4 | N41: =L41*M41 -> 0 | V41: =+O41+P41+Q41+R41+S41+T41+U41-W41-X41 -> 0
A42: OFICIAL ELECTRICO/ELECTROMECANICO | E42: hr | G42: 199.6 | H42: =F42*G42 -> 0 | J42: 159.6 | K42: =I42*J42 -> 0 | M42: 239.4 | N42: =L42*M42 -> 0 | V42: =+O42+P42+Q42+R42+S42+T42+U42-W42-X42 -> 0
A43: ASISTENTE DE DISEÑO | E43: hr | G43: 199.6 | H43: =F43*G43 -> 0 | J43: 159.6 | K43: =I43*J43 -> 0 | M43: 239.4 | N43: =L43*M43 -> 0 | V43: =+O43+P43+Q43+R43+S43+T43+U43-W43-X43 -> 0
A44: ELECTRICISTA -B | E44: hr | G44: 211.15 | H44: =F44*G44 -> 0 | J44: 173.29 | K44: =I44*J44 -> 0 | M44: 259.94 | N44: =L44*M44 -> 0 | V44: =+O44+P44+Q44+R44+S44+T44+U44-W44-X44 -> 0 | Y44: GERMAN
A45: ELECTRICISTA -A | E45: hr | G45: 199.6 | H45: =F45*G45 -> 0 | J45: 159.6 | K45: =I45*J45 -> 0 | M45: 239.4 | N45: =L45*M45 -> 0 | V45: =+O45+P45+Q45+R45+S45+T45+U45-W45-X45 -> 0 | Y45: OSCAR-OSWALDO JIM
A46: AUXILIAR TECNICO | E46: hr | G46: 187.81 | H46: =F46*G46 -> 0 | J46: 145.62 | K46: =I46*J46 -> 0 | M46: 218.43 | N46: =L46*M46 -> 0 | V46: =+O46+P46+Q46+R46+S46+T46+U46-W46-X46 -> 0
A47: AYTE ELECTRICO - B | E47: hr | H47: =F47*G47 -> 0 | J47: 0 | K47: =I47*J47 -> 0 | N47: =L47*M47 -> 0 | V47: =+O47+P47+Q47+R47+S47+T47+U47-W47-X47 -> 0
A48: AYTE DE ELECTR. -A | E48: hr | G48: 187.81 | H48: =F48*G48 -> 0 | J48: 145.62 | K48: =I48*J48 -> 0 | M48: 218.43 | N48: =L48*M48 -> 0 | V48: =+O48+P48+Q48+R48+S48+T48+U48-W48-X48 -> 0 | Y48: URIEL-GUILLERMO-ENRIQUE
A49: AYTE GENERAL | E49: hr | G49: 94.81 | H49: =F49*G49 -> 0 | J49: 145.62 | K49: =I49*J49 -> 0 | M49: 218.43 | N49: =L49*M49 -> 0 | V49: =+O49+P49+Q49+R49+S49+T49+U49-W49-X49 -> 0
A50: PROFESIONISTA | E50: hr | G50: 243.45 | H50: =F50*G50 -> 0 | J50: 211.59 | K50: =I50*J50 -> 0 | M50: 317.39 | N50: =L50*M50 -> 0 | V50: 0 | Y50: O.ZARCO-GABRIEL
A51: COORDINADOR DE OPERACIONES | E51: hr | G51: 339.75 | H51: =F51*G51 -> 0 | J51: 325.79 | K51: =I51*J51 -> 0 | M51: 488.68 | N51: =L51*M51 -> 0 | V51: =+O51+P51+Q51+R51+S51+T51+U51-W51-X51 -> 0
A52: INGENIERIA Y SOPORTE TEC. | E52: hr | G52: 339.75 | H52: =F52*G52 -> 0 | J52: 325.79 | K52: =I52*J52 -> 0 | M52: 488.68 | N52: =L52*M52 -> 0 | V52: =+O52+P52+Q52+R52+S52+T52+U52-W52-X52 -> 0
A53: INGENIERO DE SUBESTACIONES | E53: hr | G53: 339.75 | H53: =F53*G53 -> 0 | J53: 325.79 | K53: =I53*J53 -> 0 | M53: 488.68 | N53: =L53*M53 -> 0 | V53: =+O53+P53+Q53+R53+S53+T53+U53-W53-X53 -> 0
A54: INGENIERO DE PRUEBAS ELECTRICAS | E54: hr | G54: 339.75 | H54: =F54*G54 -> 0 | J54: 325.79 | K54: =I54*J54 -> 0 | M54: 488.68 | N54: =L54*M54 -> 0 | V54: =+O54+P54+Q54+R54+S54+T54+U54-W54-X54 -> 0
A55: ING. ESPECIALISTA EN PROTECCIONES | E55: hr | G55: 1004.49 | H55: =F55*G55 -> 0 | J55: 1164.98 | K55: =I55*J55 -> 0 | M55: 1747.46 | N55: =L55*M55 -> 0 | V55: =+O55+P55+Q55+R55+S55+T55+U55-W55-X55 -> 0
A56: SUPERINTENDENTE | E56: hr | H56: =F56*G56 -> 0 | J56: =G56*1.5 -> 0 | K56: =I56*J56 -> 0 | M56: =G56*2.25 -> 0 | N56: =L56*M56 -> 0 | V56: =+O56+P56+Q56+R56+S56+T56+U56-W56-X56 -> 0
F57: =V57 -> 0 | G57: SUBT 2 | H57: =SUM(H34:H56) -> 0 | J57: SUBT. | K57: =SUM(K34:K56) -> 0 | M57: SUBT. | N57: =SUM(N34:N56) -> 0
G58: SUMA M.O. | H58: =H57+K57+N57 -> 0
A59: HERRAMIENTA MENOR | G59: 1 a 10% | H59: =+H58*0.06 -> 0
H60: =+H58+H59 -> 0
A61: VEHICULOS
A62: DESCRIPCION | E62: UNIDAD | F62: CANT. | G62: P.U. | H62: IMPORTE | J62: HR IDA | K62: HR RETORNO | L62: HR SITIO | M62: SUMA
A63: camioneta EXPRES VAN CARGO sin operador sin combustible | E63: HR | F63: 0 | G63: 170 | H63: =F63*G63 -> 0 | M63: =J63+K63+L63 -> 0
A64: camioneta RANGER sin operador sin combustible | E64: HR | F64: 2 | G64: 180 | H64: =F64*G64 -> 360 | M64: =J64+K64+L64 -> 0
A65: camioneta TORNADO Tornado sin operador sin combustible | E65: HR | F65: 0 | G65: 80 | H65: =F65*G65 -> 0 | M65: =J65+K65+L65 -> 0
A66: camioneta WV TRANSPORTER pasajeros | E66: HR | F66: 0 | G66: 150 | H66: =F66*G66 -> 0 | M66: =J66+K66+L66 -> 0
E67: HR | F67: 0 | H67: =F67*G67 -> 0 | M67: =J67+K67+L67 -> 0
E68: pza | F68: 0 | H68: =F68*G68 -> 0 | M68: =J68+K68+L68 -> 0
A69: Km. Recorrido (incluye conbustible y depresiación de Vehiculo | E69: KM | F69: 0 | G69: 2.5 | H69: =F69*G69 -> 0 | M69: =J69+K69+L69 -> 0
G70: SUBT 4 | H70: =SUM(H63:H69) -> 360
A71: COMBUSTIBLE
A72: DESCRIPCION | E72: UNIDAD | F72: CANT. | G72: P.U. | H72: IMPORTE | J72: KM IDA | K72: KM RETORNO | L72: KM SITIO | M72: SUMA
A73: GASOLINA MAGNA | E73: LT | F73: 10 | G73: 23 | H73: =F73*G73 -> 230 | M73: =J73+K73+L73 -> 0
A74: DIESEL | E74: LT | F74: 0 | G74: 24 | H74: =F74*G74 -> 0 | M74: =J74+K74+L74 -> 0
G75: SUBT 5 | H75: =SUM(H73:H74) -> 230
A76: CASETAS
A77: DESCRIPCION | E77: UNIDAD | F77: CANT. | G77: P.U. | H77: IMPORTE
A78: Camion | E78: CASETA | F78: 1 | G78: 65 | H78: =F78*G78 -> 65
A79: camioneta pick up | E79: CASETA | F79: 0 | G79: 250 | H79: =F79*G79 -> 0
G80: SUBT 6 | H80: =SUM(H78:H79) -> 65
A81: VIATICOS
A82: ALIMENTOS
A83: DESCRIPCION | E83: UNIDAD | F83: CANT. | G83: P.U. | H83: IMPORTE
A84: CONSUMO DE ALIMENTOS | E84: Pza | F84: 1 | G84: 650 | H84: =F84*G84 -> 650
H85: =SUM(H84) -> 650
A86: HOSPEDAJE
A87: DESCRIPCION | E87: UNIDAD | F87: CANT. | G87: P.U. | H87: IMPORTE
A88: HOTEL | E88: NOCHES | F88: 0.5 | G88: 1100 | H88: =F88*G88 -> 550
G89: SUBT 8 | H89: =SUM(H88) -> 550
G90: SUMA: | H90: =H70+H75+H80+H85+H89+H59+H58+H30 -> 3957
A91: EQUIPO DE PRUEBA
A92: DESCRIPCION | E92: UNIDAD | F92: CANT. | G92: P.U. | H92: IMPORTE | I92: TR | K92: S.E
A93: Megger | E93: jr | G93: 2200 | H93: =(F93*G93) -> 0
A94: TTR | E94: jr | G94: 2000 | H94: =(F94*G94) -> 0
A95: Factor de Potencia de 2.5 KV | E95: jr | G95: 7000 | H95: =(F95*G95) -> 0
A96: Factor de Potencia de 10.5 KV | E96: jr | G96: 15200 | H96: =(F96*G96) -> 0
A97: Ducter | E97: jr | G97: 2200 | H97: =(F97*G97) -> 0
A98: resistencia óhmica | E98: jr | G98: 2000 | H98: =(F98*G98) -> 0
A99: hipot de 80 KV vcd | E99: jr | G99: 2500 | H99: =(F99*G99) -> 0
A100: Rigidez dieléctrica al aceite 60 kv | E100: jr | G100: 1600 | H100: =(F100*G100) -> 0
A101: Terrómetro | E101: jr | G101: 1100 | H101: =(F101*G101) -> 0
...

Sheet M0  (3)
A1: I M M E E S. A. D E C. V.
A2: A N A L I S I S D E P R E C I O U N I T A R I O
A3: COTIZACION:
A4: FECHA:
A5: PARTIDA 1
A6: REV-06-feb-2021
A7: MATERIALES.
A8: DESCRIPCION | E8: UNIDAD | F8: CANT. | G8: P.U. | H8: IMPORTE | J8: MANO DE OBRA
A9: Consumible | E9: Pza | H9: =G9*F9 -> 0
E10: Pza | H10: =G10*F10 -> 0
E11: Pza | H11: =G11*F11 -> 0
E12: Pza | H12: =G12*F12 -> 0
E13: Pza | H13: =G13*F13 -> 0
E14: Pza | H14: =G14*F14 -> 0
E15: Pza | H15: =G15*F15 -> 0
E16: Pza | H16: =G16*F16 -> 0 | I16: =H16*1.455 -> 0
G17: SUBT 1 | H17: =SUM(H9:H16) -> 0
A19: MANO DE OBRA SIN INDIRECTOS | O19: HORARIOS DE TRABAJO | V19: HORAS RESULTANTES | Y19: PERSONAL PEOPUESTO
A20: PERSONAL. | E20: UNIDAD | F20: CANT. | G20: HORA NORMAL | H20: IMPORTE | I20: CANT. | J20: Hr. Extra | K20: IMPORTE | L20: CANT. | M20: Dom, ó Fest.TRIPLE | N20: IMPORTE | O20: L | P20: M | Q20: MI | R20: J | S20: V | T20: S | U20: D | V20: N | W20: D | X20: T
A21: SUPERVISOR DE SEGURIDAD CERTIFICADO | E21: hr | G21: 390.39 | H21: =F21*G21 -> 0 | J21: 358.81 | K21: =I21*J21 -> 0 | M21: 538.27 | N21: =L21*M21 -> 0 | V21: =+O21+P21+Q21+R21+S21+T21+U21-W21-X21 -> 0
A22: SUPERVISOR DE SEGURIDAD | E22: hr | F22: 4 | G22: 317.98 | H22: =F22*G22 -> 1271.92 | J22: 326.25 | K22: =I22*J22 -> 0 | M22: 489.37 | N22: =L22*M22 -> 0 | V22: =+O22+P22+Q22+R22+S22+T22+U22-W22-X22 -> 0 | Y22: OSWALDO Z-GABRIEL
A23: SUPERVISOR ELECTRICO | E23: hr | F23: 3 | G23: 237.68 | H23: =F23*G23 -> 713.04 | J23: 358.81 | K23: =I23*J23 -> 0 | M23: 538.22 | N23: =L23*M23 -> 0 | V23: =+O23+P23+Q23+R23+S23+T23+U23-W23-X23 -> 0 | Y23: ADRIAN
A24: TECNICO DE PRUEBAS ELECTRICAS | E24: hr | G24: 317.98 | H24: =F24*G24 -> 0 | J24: 244.27 | K24: =I24*J24 -> 0 | M24: 489.37 | N24: =L24*M24 -> 0 | V24: =+O24+P24+Q24+R24+S24+T24+U24-W24-X24 -> 0 | Y24: HECTOR
A25: CABO OBRA ELECTRICA | E25: hr | G25: 310.62 | H25: =F25*G25 -> 0 | J25: 335 | K25: =I25*J25 -> 0 | M25: 436.87 | N25: =L25*M25 -> 0 | V25: =+O25+P25+Q25+R25+S25+T25+U25-W25-X25 -> 0
A26: LINIERO | E26: hr | F26: 6 | G26: 209.25 | H26: =F26*G26 -> 1255.5 | J26: 221.7 | K26: =I26*J26 -> 0 | M26: 437.63 | N26: =L26*M26 -> 0 | V26: =+O26+P26+Q26+R26+S26+T26+U26-W26-X26 -> 0 | Y26: JOSE J
A27: ESPECIALISTA DE MANTTO ELECTRICO | E27: hr | G27: 237.68 | H27: =F27*G27 -> 0 | J27: 277.97 | K27: =I27*J27 -> 0 | M27: 538.84 | N27: =L27*M27 -> 0 | V27: =+O27+P27+Q27+R27+S27+T27+U27-W27-X27 -> 0
A28: TECNICO EN INSTRUMENTACION | E28: hr | G28: 368.59 | H28: =F28*G28 -> 0 | J28: 221.7 | K28: =I28*J28 -> 0 | M28: 538.84 | N28: =L28*M28 -> 0 | V28: =+O28+P28+Q28+R28+S28+T28+U28-W28-X28 -> 0
A29: OFICIAL ELECTRICO/ELECTROMECANICO | E29: hr | F29: 6 | G29: 190.22 | H29: =F29*G29 -> 1141.32 | J29: 165 | K29: =I29*J29 -> 0 | M29: 277.56 | N29: =L29*M29 -> 0 | V29: =+O29+P29+Q29+R29+S29+T29+U29-W29-X29 -> 0
A30: ASISTENTE DE DISEÑO | E30: hr | G30: 190.25 | H30: =F30*G30 -> 0 | J30: 221.7 | K30: =I30*J30 -> 0 | M30: 297.41 | N30: =L30*M30 -> 0 | V30: =+O30+P30+Q30+R30+S30+T30+U30-W30-X30 -> 0
A31: ELECTRICISTA -B | E31: hr | F31: 6 | G31: 119.54 | H31: =F31*G31 -> 717.24 | J31: 137.92 | K31: =I31*J31 -> 0 | M31: 0 | N31: =L31*M31 -> 0 | V31: =+O31+P31+Q31+R31+S31+T31+U31-W31-X31 -> 0 | Y31: GERMAN
A32: ELECTRICISTA -A | E32: hr | G32: 119.54 | H32: =F32*G32 -> 0 | J32: 137.92 | K32: =I32*J32 -> 0 | M32: 240.95 | N32: =L32*M32 -> 0 | V32: =+O32+P32+Q32+R32+S32+T32+U32-W32-X32 -> 0 | Y32: OSCAR-OSWALDO JIM
A33: AUXILIAR TECNICO | E33: hr | G33: 106.45 | H33: =F33*G33 -> 0 | J33: 137.92 | K33: =I33*J33 -> 0 | M33: 260.95 | N33: =L33*M33 -> 0 | V33: =+O33+P33+Q33+R33+S33+T33+U33-W33-X33 -> 0
A34: AYTE ELECTRICO - B | E34: hr | G34: 106.45 | H34: =F34*G34 -> 0 | J34: 122.4 | K34: =I34*J34 -> 0 | N34: =L34*M34 -> 0 | V34: =+O34+P34+Q34+R34+S34+T34+U34-W34-X34 -> 0
A35: AYTE DE ELECTR. -A | E35: hr | G35: 106.54 | H35: =F35*G35 -> 0 | J35: 122.4 | K35: =I35*J35 -> 0 | M35: 198.17 | N35: =L35*M35 -> 0 | V35: =+O35+P35+Q35+R35+S35+T35+U35-W35-X35 -> 0 | Y35: URIEL-GUILLERMO-ENRIQUE
A36: AYTE GENERAL | E36: hr | G36: 100.42 | H36: =F36*G36 -> 0 | J36: 122.4 | K36: =I36*J36 -> 0 | M36: 0 | N36: =L36*M36 -> 0 | V36: =+O36+P36+Q36+R36+S36+T36+U36-W36-X36 -> 0
A37: PROFESIONISTA | E37: hr | G37: 209.25 | H37: =F37*G37 -> 0 | J37: 406 | K37: =I37*J37 -> 0 | M37: 564.86 | N37: =L37*M37 -> 0 | V37: 0 | Y37: O.ZARCO-GABRIEL
A38: COORDINADOR DE OPERACIONES | E38: hr | G38: 0 | H38: =F38*G38 -> 0 | J38: 0 | K38: =I38*J38 -> 0 | M38: 0 | N38: =L38*M38 -> 0 | V38: =+O38+P38+Q38+R38+S38+T38+U38-W38-X38 -> 0
A39: INGENIERIA Y SOPORTE TEC. | E39: hr | G39: 339.75 | H39: =F39*G39 -> 0 | J39: 325.79 | K39: =I39*J39 -> 0 | M39: 488.68 | N39: =L39*M39 -> 0 | V39: =+O39+P39+Q39+R39+S39+T39+U39-W39-X39 -> 0
A40: INGENIERO DE SUBESTACIONES | E40: hr | G40: 339.75 | H40: =F40*G40 -> 0 | J40: 325.79 | K40: =I40*J40 -> 0 | M40: 488.68 | N40: =L40*M40 -> 0 | V40: =+O40+P40+Q40+R40+S40+T40+U40-W40-X40 -> 0
A41: INGENIERO DE PRUEBAS ELECTRICAS | E41: hr | G41: 339.75 | H41: =F41*G41 -> 0 | J41: 325.79 | K41: =I41*J41 -> 0 | M41: 488.68 | N41: =L41*M41 -> 0 | V41: =+O41+P41+Q41+R41+S41+T41+U41-W41-X41 -> 0
A42: ING. ESPECIALISTA EN PROTECCIONES | E42: hr | G42: 650 | H42: =F42*G42 -> 0 | J42: =G42*1.5 -> 975 | K42: =I42*J42 -> 0 | M42: 1747.46 | N42: =L42*M42 -> 0 | V42: =+O42+P42+Q42+R42+S42+T42+U42-W42-X42 -> 0
A43: SUPERINTENDENTE | E43: hr | H43: =F43*G43 -> 0 | J43: =G43*1.5 -> 0 | K43: =I43*J43 -> 0 | M43: =G43*2.25 -> 0 | N43: =L43*M43 -> 0 | V43: =+O43+P43+Q43+R43+S43+T43+U43-W43-X43 -> 0
F44: =V44 -> 0 | G44: SUBT 2 | H44: =SUM(H21:H43) -> 5099.02 | J44: SUBT. | K44: =SUM(K21:K43) -> 0 | M44: SUBT. | N44: =SUM(N21:N43) -> 0
G45: SUMA M.O. | H45: =H44+K44+N44 -> 5099.02
A46: HERRAMIENTA MENOR | G46: 1 a 10% | H46: =+H45*0.06 -> 305.9412
A49: VEHICULOS
A50: DESCRIPCION | E50: UNIDAD | F50: CANT. | G50: P.U. | H50: IMPORTE | J50: HR IDA | K50: HR RETORNO | L50: HR SITIO | M50: SUMA
A51: camioneta EXPRES VAN CARGO sin operador sin combustible | E51: HR | F51: 0 | G51: 150 | H51: =F51*G51 -> 0 | M51: =J51+K51+L51 -> 0
A52: camioneta RANGER sin operador sin combustible | E52: HR | F52: 0 | G52: 150 | H52: =F52*G52 -> 0 | M52: =J52+K52+L52 -> 0
A53: camioneta TORNADO Tornado sin operador sin combustible | E53: HR | F53: 0 | G53: 60 | H53: =F53*G53 -> 0 | M53: =J53+K53+L53 -> 0
A54: camioneta WV TRANSPORTER pasajeros | E54: HR | F54: 0 | G54: 120 | H54: =F54*G54 -> 0 | M54: =J54+K54+L54 -> 0
E55: HR | F55: 0 | H55: =F55*G55 -> 0 | M55: =J55+K55+L55 -> 0
E56: pza | F56: 0 | H56: =F56*G56 -> 0 | M56: =J56+K56+L56 -> 0
A57: Km. Recorrido (incluye conbustible y depresiación de Vehiculo | E57: KM | F57: 0 | G57: 2.5 | H57: =F57*G57 -> 0 | M57: =J57+K57+L57 -> 0
G58: SUBT 4 | H58: =SUM(H51:H57) -> 0
G59: SUMA: | H59: =H58+H45+H17 -> 5099.02
A60: EQUIPO DE PRUEBA
A61: DESCRIPCION | E61: UNIDAD | F61: CANT. | G61: P.U. | H61: IMPORTE | I61: TR | K61: S.E
A62: Megger | E62: jr | G62: 2200 | H62: =(F62*G62) -> 0
A63: TTR | E63: jr | G63: 2000 | H63: =(F63*G63) -> 0
A64: Factor de Potencia de 2.5 KV | E64: jr | G64: 7000 | H64: =(F64*G64) -> 0
A65: Factor de Potencia de 10.5 KV | E65: jr | G65: 15200 | H65: =(F65*G65) -> 0
A66: Ducter | E66: jr | G66: 2200 | H66: =(F66*G66) -> 0
A67: resistencia óhmica | E67: jr | G67: 2000 | H67: =(F67*G67) -> 0
A68: hipot de 80 KV vcd | E68: jr | G68: 2500 | H68: =(F68*G68) -> 0
A69: Rigidez dieléctrica al aceite 60 kv | E69: jr | G69: 1600 | H69: =(F69*G69) -> 0
A70: Terrómetro | E70: jr | G70: 1100 | H70: =(F70*G70) -> 0
A71: Analizador de tiempos de interruptor | E71: jr | G71: 2700 | H71: =(F71*G71) -> 0
A72: Fuente de corriente para calibrador de relevadores | E72: jr | G72: 2500 | H72: =(F72*G72) -> 0
A73: Probador de relevador de Protecciones | E73: jr | G73: 13373 | H73: =(F73*G73) -> 0
... A82: Test Kit maleta de prueba G.E. | E82: jr | G82: 5800 | H82: =(F82*G82) -> 0
E83: jr | H83: =(F83*G83) -> 0
A84: Camara termografica | E84: jr | G84: 15000 | H84: =(F84*G84) -> 0
A85: Generador de Luz con combustible | E85: jr | G85: 383.5 | H85: =(F85*G85) -> 0
G86: SUBT 9 | H86: =SUM(H62:H85) -> 0
E88: 0 | H88: =+E88 -> 0 | I88: IMPUESTO | J88: INDIRECTO DISPONIBLE
F89: COSTO DIRECTO | H89: =H59+H86 -> 5099.02
F90: Indirectos | G90: 0.3 | H90: =H89*G90 -> 1529.706 | I90: =+M96 -> -859.69477 | J90: =H90-M96 -> 2389.4008 | N90: REV-06-feb-2021
F91: Subtotal 1 | H91: =H89+H90 -> 6628.726
F92: Financ. | G92: 0.06 | H92: =H91*G92 -> 397.72356 | K92: BASE IMPUESTO | L92: SIN UTILIDAD
F93: Subtotal 2 | H93: =H91+H92 -> 7026.4496 | J93: COMPRAS | K93: =+H17 -> 0
F94: Utilidad | G94: 0.2 | H94: =H93*G94 -> 1405.2899 | J94: M.O | K94: =H44 -> 5099.02
F95: Importe | H95: =H93+H94 -> 8431.7395 | J95: GASTOS FACTURADOS | K95: =H59-H46 -> 4793.0788 | M95: IMP. 30%
F96: Materiales | H96: ='MAT (3)'!H124 -> 5536.6344 | I96: FACTOR | J96: SUMA | K96: =SUM(K93:K95) -> 9892.0988 | L96: =H95-H94 -> 7026.4496 | M96: =+(L96-K96)*0.3 -> -859.69477
B97: utilidad | F97: Total | H97: =H95+H96 -> 13968.374 | J97: =H95/H89 -> 1.6536
B98: ime | C98: comisión | D98: total | H98: =H97/6 -> 2328.0623
B99: 0.275 | C99: 0.05 | D99: =B99+C99 -> 0.325

Sheet MAT (4)
A1: I M M E E S. A. D E C. V.
A2: A N A L I S I S D E P R E C I O U N I T A R I O
A3: COTIZACION:
A4: FECHA:
A5: PARTIDA 1
A6: REV-06-feb-2021
A7: MATERIALES.
A8: DESCRIPCION | E8: UNIDAD | F8: CANT. | G8: P.U. | H8: IMPORTE | J8: MATERIALES
A9: charola tipo escalera perfil Z para servicio pesado de 30" | E9: Pza | G9: 2540.01 | H9: =G9*F9 -> 0
A10: tapa para charola tipo escalera de 30". | E10: Pza | G10: 1001 | H10: =G10*F10 -> 0
A11: curva vertical exterior de 90° para charola tipo escalera de 30 | E11: Pza | G11: 450.5 | H11: =G11*F11 -> 0
A12: tapa para curva vertical exterior de 90° para charola tipo escalera para servicio pesado de 30" | E12: Pza | F12: 4 | G12: 136.52 | H12: =G12*F12 -> 546.08
A13: curva horizontal de 90° para charola tipo escalera para servicio pesado de 30" | E13: Pza | G13: 620.97 | H13: =G13*F13 -> 0
A14: base de unicanal solido galvanizado de 4x4 | E14: Pza | G14: 382.32 | H14: =G14*F14 -> 0
A15: tornilleria galvanizada | E15: Pza | G15: 200 | H15: =G15*F15 -> 0
A16: varilla roscada galvanizada de 3 metros de largo X 1/2" | E16: Pza | G16: 70 | H16: =G16*F16 -> 0
A17: conector de charola para servicio pesado de 30 | E17: Pza | G17: 467.05 | H17: =G17*F17 -> 0
A18: zapata ponchable para cable de cobre cañon largo calibre 500 KCM, con 2 ojillos de 1/2 | E18: Pza | G18: 495.41 | H18: =G18*F18 -> 0
A19: manga termocontractil para nivel de aislamiento de 600 V, en calibre 500 KCM. | E19: Pza | G19: 212.43 | H19: =G19*F19 -> 0
A20: tornillo tropicalizado de 1/2" con 2" de largo | E20: Pza | G20: 15 | H20: =G20*F20 -> 0
A21: tornillo tropicalizado de 1/2" con 4" de largo | E21: Pza | G21: 15 | H21: =G21*F21 -> 0
A22: sistema corta fuego con lana mineral y compuesto SF-ONE. | E22: Pza | G22: 698.25 | H22: =G22*F22 -> 0
A23: Materiales consumibles | E23: PZA | G23: 500 | H23: =G23*F23 -> 0
A24: cuellos de lona flexibles en gargantas primarias de generador electrico | E24: Pza | G24: 160.08 | H24: =G24*F24 -> 0
A25: cable de cobre THW calibre 12 AWG | E25: mt | G25: 12.63 | H25: =G25*F25 -> 0 | L25: NOTA: CONSIDERAR LA JORNADA DE 8.0 HORAS, AUNQUE EN IMMEE SE TRABAJE JORNADA LARGA CONVENIDA, Y DOMINGO DESCANSO
A26: tapones para unicanal de 4x4 y varilla roscada | E26: Pza | G26: 27.6 | H26: =G26*F26 -> 0
A27: tapones para esparrago | E27: Pza | G27: 70.34 | H27: =G27*F27 -> 0
A28: CONSUMIBLES | E28: 1 | F28: 1 | G28: 100 | H28: =G28*F28 -> 100
A29: Renta de una plataforma de elevacion | E29: Pza | G29: 48000 | H29: =G29*F29 -> 0 | I29: =H29*1.455 -> 0
G30: SUBT 1 | H30: =SUM(H9:H29) -> 646.08
A32: MANO DE OBRA SIN INDIRECTOS | O32: HORARIOS DE TRABAJO | V32: HORAS RESULTANTES | Y32: PERSONAL PEOPUESTO
A33: PERSONAL. | E33: UNIDAD | F33: CANT. | G33: HORA NORMAL | H33: IMPORTE | I33: CANT. | J33: Hr. Extra | K33: IMPORTE | L33: CANT. | M33: Dom, ó Fest.TRIPLE | N33: IMPORTE | O33: L | P33: M | Q33: MI | R33: J | S33: V | T33: S | U33: D | V33: N | W33: D | X33: T
A34: SUPERVISOR DE SEGURIDAD CERTIFICADO | E34: hr | G34: 390.39 | H34: =F34*G34 -> 0 | J34: 358.81 | K34: =I34*J34 -> 0 | M34: 538.27 | N34: =L34*M34 -> 0 | V34: =+O34+P34+Q34+R34+S34+T34+U34-W34-X34 -> 0
A35: SUPERVISOR DE SEGURIDAD | E35: hr | G35: 243.45 | H35: =F35*G35 -> 0 | J35: 211.59 | K35: =I35*J35 -> 0 | M35: 317.39 | N35: =L35*M35 -> 0 | V35: =+O35+P35+Q35+R35+S35+T35+U35-W35-X35 -> 0 | Y35: OSWALDO Z-GABRIEL
A36: SUPERVISOR ELECTRICO | E36: hr | G36: 390.39 | H36: =F36*G36 -> 0 | J36: 358.81 | K36: =I36*J36 -> 0 | M36: 538.22 | N36: =L36*M36 -> 0 | V36: =+O36+P36+Q36+R36+S36+T36+U36-W36-X36 -> 0 | Y36: ADRIAN
A37: TECNICO DE PRUEBAS ELECTRICAS | E37: hr | G37: 231.67 | H37: =F37*G37 -> 0 | J37: 197.63 | K37: =I37*J37 -> 0 | M37: 296.45 | N37: =L37*M37 -> 0 | V37: =+O37+P37+Q37+R37+S37+T37+U37-W37-X37 -> 0 | Y37: HECTOR
A38: CABO OBRA ELECTRICA | E38: hr | G38: 310.62 | H38: =F38*G38 -> 0 | J38: 291.24 | K38: =I38*J38 -> 0 | M38: 436.87 | N38: =L38*M38 -> 0 | V38: =+O38+P38+Q38+R38+S38+T38+U38-W38-X38 -> 0
A39: LINIERO | E39: hr | G39: 310.62 | H39: =F39*G39 -> 0 | J39: 291.24 | K39: =I39*J39 -> 0 | M39: 436.87 | N39: =L39*M39 -> 0 | V39: =+O39+P39+Q39+R39+S39+T39+U39-W39-X39 -> 0 | Y39: JOSE J
A40: ESPECIALISTA DE MANTTO ELECTRICO | E40: hr | H40: =F40*G40 -> 0 | J40: 0 | K40: =I40*J40 -> 0 | M40: 0 | N40: =L40*M40 -> 0 | V40: =+O40+P40+Q40+R40+S40+T40+U40-W40-X40 -> 0
A41: TECNICO EN INSTRUMENTACION | E41: hr | G41: 199.6 | H41: =F41*G41 -> 0 | J41: 159.6 | K41: =I41*J41 -> 0 | M41: 239.4 | N41: =L41*M41 -> 0 | V41: =+O41+P41+Q41+R41+S41+T41+U41-W41-X41 -> 0
A42: OFICIAL ELECTRICO/ELECTROMECANICO | E42: hr | G42: 199.6 | H42: =F42*G42 -> 0 | J42: 159.6 | K42: =I42*J42 -> 0 | M42: 239.4 | N42: =L42*M42 -> 0 | V42: =+O42+P42+Q42+R42+S42+T42+U42-W42-X42 -> 0
A43: ASISTENTE DE DISEÑO | E43: hr | G43: 199.6 | H43: =F43*G43 -> 0 | J43: 159.6 | K43: =I43*J43 -> 0 | M43: 239.4 | N43: =L43*M43 -> 0 | V43: =+O43+P43+Q43+R43+S43+T43+U43-W43-X43 -> 0
A44: ELECTRICISTA -B | E44: hr | G44: 211.15 | H44: =F44*G44 -> 0 | J44: 173.29 | K44: =I44*J44 -> 0 | M44: 259.94 | N44: =L44*M44 -> 0 | V44: =+O44+P44+Q44+R44+S44+T44+U44-W44-X44 -> 0 | Y44: GERMAN
A45: ELECTRICISTA -A | E45: hr | G45: 199.6 | H45: =F45*G45 -> 0 | J45: 159.6 | K45: =I45*J45 -> 0 | M45: 239.4 | N45: =L45*M45 -> 0 | V45: =+O45+P45+Q45+R45+S45+T45+U45-W45-X45 -> 0 | Y45: OSCAR-OSWALDO JIM
A46: AUXILIAR TECNICO | E46: hr | G46: 187.81 | H46: =F46*G46 -> 0 | J46: 145.62 | K46: =I46*J46 -> 0 | M46: 218.43 | N46: =L46*M46 -> 0 | V46: =+O46+P46+Q46+R46+S46+T46+U46-W46-X46 -> 0
A47: AYTE ELECTRICO - B | E47: hr | H47: =F47*G47 -> 0 | J47: 0 | K47: =I47*J47 -> 0 | N47: =L47*M47 -> 0 | V47: =+O47+P47+Q47+R47+S47+T47+U47-W47-X47 -> 0
A48: AYTE DE ELECTR. -A | E48: hr | G48: 187.81 | H48: =F48*G48 -> 0 | J48: 145.62 | K48: =I48*J48 -> 0 | M48: 218.43 | N48: =L48*M48 -> 0 | V48: =+O48+P48+Q48+R48+S48+T48+U48-W48-X48 -> 0 | Y48: URIEL-GUILLERMO-ENRIQUE
A49: AYTE GENERAL | E49: hr | G49: 94.81 | H49: =F49*G49 -> 0 | J49: 145.62 | K49: =I49*J49 -> 0 | M49: 218.43 | N49: =L49*M49 -> 0 | V49: =+O49+P49+Q49+R49+S49+T49+U49-W49-X49 -> 0
A50: PROFESIONISTA | E50: hr | G50: 243.45 | H50: =F50*G50 -> 0 | J50: 211.59 | K50: =I50*J50 -> 0 | M50: 317.39 | N50: =L50*M50 -> 0 | V50: 0 | Y50: O.ZARCO-GABRIEL
A51: COORDINADOR DE OPERACIONES | E51: hr | G51: 339.75 | H51: =F51*G51 -> 0 | J51: 325.79 | K51: =I51*J51 -> 0 | M51: 488.68 | N51: =L51*M51 -> 0 | V51: =+O51+P51+Q51+R51+S51+T51+U51-W51-X51 -> 0
A52: INGENIERIA Y SOPORTE TEC. | E52: hr | G52: 339.75 | H52: =F52*G52 -> 0 | J52: 325.79 | K52: =I52*J52 -> 0 | M52: 488.68 | N52: =L52*M52 -> 0 | V52: =+O52+P52+Q52+R52+S52+T52+U52-W52-X52 -> 0
A53: INGENIERO DE SUBESTACIONES | E53: hr | G53: 339.75 | H53: =F53*G53 -> 0 | J53: 325.79 | K53: =I53*J53 -> 0 | M53: 488.68 | N53: =L53*M53 -> 0 | V53: =+O53+P53+Q53+R53+S53+T53+U53-W53-X53 -> 0
A54: INGENIERO DE PRUEBAS ELECTRICAS | E54: hr | G54: 339.75 | H54: =F54*G54 -> 0 | J54: 325.79 | K54: =I54*J54 -> 0 | M54: 488.68 | N54: =L54*M54 -> 0 | V54: =+O54+P54+Q54+R54+S54+T54+U54-W54-X54 -> 0
A55: ING. ESPECIALISTA EN PROTECCIONES | E55: hr | G55: 1004.49 | H55: =F55*G55 -> 0 | J55: 1164.98 | K55: =I55*J55 -> 0 | M55: 1747.46 | N55: =L55*M55 -> 0 | V55: =+O55+P55+Q55+R55+S55+T55+U55-W55-X55 -> 0
A56: SUPERINTENDENTE | E56: hr | H56: =F56*G56 -> 0 | J56: =G56*1.5 -> 0 | K56: =I56*J56 -> 0 | M56: =G56*2.25 -> 0 | N56: =L56*M56 -> 0 | V56: =+O56+P56+Q56+R56+S56+T56+U56-W56-X56 -> 0
F57: =V57 -> 0 | G57: SUBT 2 | H57: =SUM(H34:H56) -> 0 | J57: SUBT. | K57: =SUM(K34:K56) -> 0 | M57: SUBT. | N57: =SUM(N34:N56) -> 0
G58: SUMA M.O. | H58: =H57+K57+N57 -> 0
A59: HERRAMIENTA MENOR | G59: 1 a 10% | H59: =+H58*0.06 -> 0
H60: =+H58+H59 -> 0
A61: VEHICULOS
A62: DESCRIPCION | E62: UNIDAD | F62: CANT. | G62: P.U. | H62: IMPORTE | J62: HR IDA | K62: HR RETORNO | L62: HR SITIO | M62: SUMA
A63: camioneta EXPRES VAN CARGO sin operador sin combustible | E63: HR | F63: 0 | G63: 170 | H63: =F63*G63 -> 0 | M63: =J63+K63+L63 -> 0
A64: camioneta RANGER sin operador sin combustible | E64: HR | F64: 0.5 | G64: 180 | H64: =F64*G64 -> 90 | M64: =J64+K64+L64 -> 0
A65: camioneta TORNADO Tornado sin operador sin combustible | E65: HR | F65: 0 | G65: 80 | H65: =F65*G65 -> 0 | M65: =J65+K65+L65 -> 0
A66: camioneta WV TRANSPORTER pasajeros | E66: HR | F66: 0 | G66: 150 | H66: =F66*G66 -> 0 | M66: =J66+K66+L66 -> 0
E67: HR | F67: 0 | H67: =F67*G67 -> 0 | M67: =J67+K67+L67 -> 0
E68: pza | F68: 0 | H68: =F68*G68 -> 0 | M68: =J68+K68+L68 -> 0
A69: Km. Recorrido (incluye conbustible y depresiación de Vehiculo | E69: KM | F69: 0 | G69: 2.5 | H69: =F69*G69 -> 0 | M69: =J69+K69+L69 -> 0
G70: SUBT 4 | H70: =SUM(H63:H69) -> 90
A71: COMBUSTIBLE
A72: DESCRIPCION | E72: UNIDAD | F72: CANT. | G72: P.U. | H72: IMPORTE | J72: KM IDA | K72: KM RETORNO | L72: KM SITIO | M72: SUMA
A73: GASOLINA MAGNA | E73: LT | F73: 5 | G73: 23 | H73: =F73*G73 -> 115 | M73: =J73+K73+L73 -> 0
A74: DIESEL | E74: LT | F74: 0 | G74: 24 | H74: =F74*G74 -> 0 | M74: =J74+K74+L74 -> 0
G75: SUBT 5 | H75: =SUM(H73:H74) -> 115
A76: CASETAS
A77: DESCRIPCION | E77: UNIDAD | F77: CANT. | G77: P.U. | H77: IMPORTE
A78: Camion | E78: CASETA | F78: 1 | G78: 65 | H78: =F78*G78 -> 65
A79: camioneta pick up | E79: CASETA | G79: 250 | H79: =F79*G79 -> 0
G80: SUBT 6 | H80: =SUM(H78:H79) -> 65
A81: VIATICOS
A82: ALIMENTOS
A83: DESCRIPCION | E83: UNIDAD | F83: CANT. | G83: P.U. | H83: IMPORTE
A84: CONSUMO DE ALIMENTOS | E84: Pza | F84: 3 | G84: 600 | H84: =F84*G84 -> 1800
H85: =SUM(H84) -> 1800
A86: HOSPEDAJE
A87: DESCRIPCION | E87: UNIDAD | F87: CANT. | G87: P.U. | H87: IMPORTE
A88: HOTEL | E88: NOCHES | F88: 0.2 | G88: 1100 | H88: =F88*G88 -> 220
G89: SUBT 8 | H89: =SUM(H88) -> 220
G90: SUMA: | H90: =H70+H75+H80+H85+H89+H59+H58+H30 -> 2936.08
A91: EQUIPO DE PRUEBA
A92: DESCRIPCION | E92: UNIDAD | F92: CANT. | G92: P.U. | H92: IMPORTE | I92: TR | K92: S.E
A93: Megger | E93: jr | G93: 2200 | H93: =(F93*G93) -> 0
A94: TTR | E94: jr | G94: 2000 | H94: =(F94*G94) -> 0
A95: Factor de Potencia de 2.5 KV | E95: jr | G95: 7000 | H95: =(F95*G95) -> 0
A96: Factor de Potencia de 10.5 KV | E96: jr | G96: 15200 | H96: =(F96*G96) -> 0
A97: Ducter | E97: jr | G97: 2200 | H97: =(F97*G97) -> 0
A98: resistencia óhmica | E98: jr | G98: 2000 | H98: =(F98*G98) -> 0
A99: hipot de 80 KV vcd | E99: jr | G99: 2500 | H99: =(F99*G99) -> 0
A100: Rigidez dieléctrica al aceite 60 kv | E100: jr | G100: 1600 | H100: =(F100*G100) -> 0
A101: Terrómetro | E101: jr | G101: 1100 | H101: =(F101*G101) -> 0
...

Sheet M0  (4)
A1: I M M E E S. A. D E C. V.
A2: A N A L I S I S D E P R E C I O U N I T A R I O
A3: COTIZACION:
A4: FECHA:
A5: PARTIDA 1
A6: REV-06-feb-2021
A7: MATERIALES.
A8: DESCRIPCION | E8: UNIDAD | F8: CANT. | G8: P.U. | H8: IMPORTE | J8: MANO DE OBRA
A9: Consumible | E9: Pza | H9: =G9*F9 -> 0
E10: Pza | H10: =G10*F10 -> 0
E11: Pza | H11: =G11*F11 -> 0
E12: Pza | H12: =G12*F12 -> 0
E13: Pza | H13: =G13*F13 -> 0
E14: Pza | H14: =G14*F14 -> 0
E15: Pza | H15: =G15*F15 -> 0
E16: Pza | H16: =G16*F16 -> 0 | I16: =H16*1.455 -> 0
G17: SUBT 1 | H17: =SUM(H9:H16) -> 0
A19: MANO DE OBRA SIN INDIRECTOS | O19: HORARIOS DE TRABAJO | V19: HORAS RESULTANTES | Y19: PERSONAL PEOPUESTO
A20: PERSONAL. | E20: UNIDAD | F20: CANT. | G20: HORA NORMAL | H20: IMPORTE | I20: CANT. | J20: Hr. Extra | K20: IMPORTE | L20: CANT. | M20: Dom, ó Fest.TRIPLE | N20: IMPORTE | O20: L | P20: M | Q20: MI | R20: J | S20: V | T20: S | U20: D | V20: N | W20: D | X20: T
A21: SUPERVISOR DE SEGURIDAD CERTIFICADO | E21: hr | G21: 390.39 | H21: =F21*G21 -> 0 | J21: 358.81 | K21: =I21*J21 -> 0 | M21: 538.27 | N21: =L21*M21 -> 0 | V21: =+O21+P21+Q21+R21+S21+T21+U21-W21-X21 -> 0
A22: SUPERVISOR DE SEGURIDAD | E22: hr | G22: 317.98 | H22: =F22*G22 -> 0 | J22: 326.25 | K22: =I22*J22 -> 0 | M22: 489.37 | N22: =L22*M22 -> 0 | V22: =+O22+P22+Q22+R22+S22+T22+U22-W22-X22 -> 0 | Y22: OSWALDO Z-GABRIEL
A23: SUPERVISOR ELECTRICO | E23: hr | F23: 1 | G23: 237.68 | H23: =F23*G23 -> 237.68 | I23: 0 | J23: 358.81 | K23: =I23*J23 -> 0 | M23: 538.22 | N23: =L23*M23 -> 0 | V23: =+O23+P23+Q23+R23+S23+T23+U23-W23-X23 -> 0 | Y23: ADRIAN
A24: TECNICO DE PRUEBAS ELECTRICAS | E24: hr | G24: 317.98 | H24: =F24*G24 -> 0 | J24: 244.27 | K24: =I24*J24 -> 0 | M24: 489.37 | N24: =L24*M24 -> 0 | V24: =+O24+P24+Q24+R24+S24+T24+U24-W24-X24 -> 0 | Y24: HECTOR
A25: CABO OBRA ELECTRICA | E25: hr | G25: 310.62 | H25: =F25*G25 -> 0 | J25: 335 | K25: =I25*J25 -> 0 | M25: 436.87 | N25: =L25*M25 -> 0 | V25: =+O25+P25+Q25+R25+S25+T25+U25-W25-X25 -> 0
A26: LINIERO | E26: hr | F26: 2 | G26: 209.25 | H26: =F26*G26 -> 418.5 | I26: 0 | J26: 221.7 | K26: =I26*J26 -> 0 | M26: 437.63 | N26: =L26*M26 -> 0 | V26: =+O26+P26+Q26+R26+S26+T26+U26-W26-X26 -> 0 | Y26: JOSE J
A27: ESPECIALISTA DE MANTTO ELECTRICO | E27: hr | G27: 237.68 | H27: =F27*G27 -> 0 | J27: 277.97 | K27: =I27*J27 -> 0 | M27: 538.84 | N27: =L27*M27 -> 0 | V27: =+O27+P27+Q27+R27+S27+T27+U27-W27-X27 -> 0
A28: TECNICO EN INSTRUMENTACION | E28: hr | G28: 368.59 | H28: =F28*G28 -> 0 | J28: 221.7 | K28: =I28*J28 -> 0 | M28: 538.84 | N28: =L28*M28 -> 0 | V28: =+O28+P28+Q28+R28+S28+T28+U28-W28-X28 -> 0
A29: OFICIAL ELECTRICO/ELECTROMECANICO | E29: hr | F29: 2 | G29: 190.22 | H29: =F29*G29 -> 380.44 | I29: 0 | J29: 165 | K29: =I29*J29 -> 0 | M29: 277.56 | N29: =L29*M29 -> 0 | V29: =+O29+P29+Q29+R29+S29+T29+U29-W29-X29 -> 0
A30: ASISTENTE DE DISEÑO | E30: hr | G30: 190.25 | H30: =F30*G30 -> 0 | J30: 221.7 | K30: =I30*J30 -> 0 | M30: 297.41 | N30: =L30*M30 -> 0 | V30: =+O30+P30+Q30+R30+S30+T30+U30-W30-X30 -> 0
A31: ELECTRICISTA -B | E31: hr | F31: 1 | G31: 119.54 | H31: =F31*G31 -> 119.54 | I31: 0 | J31: 137.92 | K31: =I31*J31 -> 0 | M31: 0 | N31: =L31*M31 -> 0 | V31: =+O31+P31+Q31+R31+S31+T31+U31-W31-X31 -> 0 | Y31: GERMAN
A32: ELECTRICISTA -A | E32: hr | G32: 119.54 | H32: =F32*G32 -> 0 | J32: 137.92 | K32: =I32*J32 -> 0 | M32: 240.95 | N32: =L32*M32 -> 0 | V32: =+O32+P32+Q32+R32+S32+T32+U32-W32-X32 -> 0 | Y32: OSCAR-OSWALDO JIM
A33: AUXILIAR TECNICO | E33: hr | G33: 106.45 | H33: =F33*G33 -> 0 | J33: 137.92 | K33: =I33*J33 -> 0 | M33: 260.95 | N33: =L33*M33 -> 0 | V33: =+O33+P33+Q33+R33+S33+T33+U33-W33-X33 -> 0
A34: AYTE ELECTRICO - B | E34: hr | G34: 106.45 | H34: =F34*G34 -> 0 | J34: 122.4 | K34: =I34*J34 -> 0 | N34: =L34*M34 -> 0 | V34: =+O34+P34+Q34+R34+S34+T34+U34-W34-X34 -> 0
A35: AYTE DE ELECTR. -A | E35: hr | G35: 106.54 | H35: =F35*G35 -> 0 | J35: 122.4 | K35: =I35*J35 -> 0 | M35: 198.17 | N35: =L35*M35 -> 0 | V35: =+O35+P35+Q35+R35+S35+T35+U35-W35-X35 -> 0 | Y35: URIEL-GUILLERMO-ENRIQUE
A36: AYTE GENERAL | E36: hr | G36: 100.42 | H36: =F36*G36 -> 0 | J36: 122.4 | K36: =I36*J36 -> 0 | M36: 0 | N36: =L36*M36 -> 0 | V36: =+O36+P36+Q36+R36+S36+T36+U36-W36-X36 -> 0
A37: PROFESIONISTA | E37: hr | G37: 209.25 | H37: =F37*G37 -> 0 | J37: 406 | K37: =I37*J37 -> 0 | M37: 564.86 | N37: =L37*M37 -> 0 | V37: 0 | Y37: O.ZARCO-GABRIEL
A38: COORDINADOR DE OPERACIONES | E38: hr | G38: 0 | H38: =F38*G38 -> 0 | J38: 0 | K38: =I38*J38 -> 0 | M38: 0 | N38: =L38*M38 -> 0 | V38: =+O38+P38+Q38+R38+S38+T38+U38-W38-X38 -> 0
A39: INGENIERIA Y SOPORTE TEC. | E39: hr | G39: 339.75 | H39: =F39*G39 -> 0 | J39: 325.79 | K39: =I39*J39 -> 0 | M39: 488.68 | N39: =L39*M39 -> 0 | V39: =+O39+P39+Q39+R39+S39+T39+U39-W39-X39 -> 0
A40: INGENIERO DE SUBESTACIONES | E40: hr | G40: 339.75 | H40: =F40*G40 -> 0 | J40: 325.79 | K40: =I40*J40 -> 0 | M40: 488.68 | N40: =L40*M40 -> 0 | V40: =+O40+P40+Q40+R40+S40+T40+U40-W40-X40 -> 0
A41: INGENIERO DE PRUEBAS ELECTRICAS | E41: hr | G41: 339.75 | H41: =F41*G41 -> 0 | J41: 325.79 | K41: =I41*J41 -> 0 | M41: 488.68 | N41: =L41*M41 -> 0 | V41: =+O41+P41+Q41+R41+S41+T41+U41-W41-X41 -> 0
A42: ING. ESPECIALISTA EN PROTECCIONES | E42: hr | G42: 650 | H42: =F42*G42 -> 0 | J42: =G42*1.5 -> 975 | K42: =I42*J42 -> 0 | M42: 1747.46 | N42: =L42*M42 -> 0 | V42: =+O42+P42+Q42+R42+S42+T42+U42-W42-X42 -> 0
A43: SUPERINTENDENTE | E43: hr | H43: =F43*G43 -> 0 | J43: =G43*1.5 -> 0 | K43: =I43*J43 -> 0 | M43: =G43*2.25 -> 0 | N43: =L43*M43 -> 0 | V43: =+O43+P43+Q43+R43+S43+T43+U43-W43-X43 -> 0
F44: =V44 -> 0 | G44: SUBT 2 | H44: =SUM(H21:H43) -> 1156.16 | J44: SUBT. | K44: =SUM(K21:K43) -> 0 | M44: SUBT. | N44: =SUM(N21:N43) -> 0
G45: SUMA M.O. | H45: =H44+K44+N44 -> 1156.16
A46: HERRAMIENTA MENOR | G46: 1 a 10% | H46: =+H45*0.06 -> 69.3696
A49: VEHICULOS
A50: DESCRIPCION | E50: UNIDAD | F50: CANT. | G50: P.U. | H50: IMPORTE | J50: HR IDA | K50: HR RETORNO | L50: HR SITIO | M50: SUMA
A51: camioneta EXPRES VAN CARGO sin operador sin combustible | E51: HR | F51: 0 | G51: 150 | H51: =F51*G51 -> 0 | M51: =J51+K51+L51 -> 0
A52: camioneta RANGER sin operador sin combustible | E52: HR | F52: 0 | G52: 150 | H52: =F52*G52 -> 0 | M52: =J52+K52+L52 -> 0
A53: camioneta TORNADO Tornado sin operador sin combustible | E53: HR | F53: 0 | G53: 60 | H53: =F53*G53 -> 0 | M53: =J53+K53+L53 -> 0
A54: camioneta WV TRANSPORTER pasajeros | E54: HR | F54: 0 | G54: 120 | H54: =F54*G54 -> 0 | M54: =J54+K54+L54 -> 0
E55: HR | F55: 0 | H55: =F55*G55 -> 0 | M55: =J55+K55+L55 -> 0
E56: pza | F56: 0 | H56: =F56*G56 -> 0 | M56: =J56+K56+L56 -> 0
A57: Km. Recorrido (incluye conbustible y depresiación de Vehiculo | E57: KM | F57: 0 | G57: 2.5 | H57: =F57*G57 -> 0 | M57: =J57+K57+L57 -> 0
G58: SUBT 4 | H58: =SUM(H51:H57) -> 0
G59: SUMA: | H59: =H58+H45+H17 -> 1156.16
A60: EQUIPO DE PRUEBA
A61: DESCRIPCION | E61: UNIDAD | F61: CANT. | G61: P.U. | H61: IMPORTE | I61: TR | K61: S.E
A62: Megger | E62: jr | F62: 0.3 | G62: 2200 | H62: =(F62*G62) -> 660
A63: TTR | E63: jr | G63: 2000 | H63: =(F63*G63) -> 0
A64: Factor de Potencia de 2.5 KV | E64: jr | G64: 7000 | H64: =(F64*G64) -> 0
A65: Factor de Potencia de 10.5 KV | E65: jr | G65: 15200 | H65: =(F65*G65) -> 0
A66: Ducter | E66: jr | G66: 2200 | H66: =(F66*G66) -> 0
A67: resistencia óhmica | E67: jr | G67: 2000 | H67: =(F67*G67) -> 0
A68: hipot de 80 KV vcd | E68: jr | G68: 2500 | H68: =(F68*G68) -> 0
A69: Rigidez dieléctrica al aceite 60 kv | E69: jr | G69: 1600 | H69: =(F69*G69) -> 0
A70: Terrómetro | E70: jr | G70: 1100 | H70: =(F70*G70) -> 0
A71: Analizador de tiempos de interruptor | E71: jr | G71: 2700 | H71: =(F71*G71) -> 0
A72: Fuente de corriente para calibrador de relevadores | E72: jr | G72: 2500 | H72: =(F72*G72) -> 0
A73: Probador de relevador de Protecciones | E73: jr | G73: 13373 | H73: =(F73*G73) -> 0
A74: Fuente trifasica de voltaje | E74: jr | G74: 800 | H74: =(F74*G74) -> 0
... A82: Test Kit maleta de prueba G.E. | E82: jr | G82: 5800 | H82: =(F82*G82) -> 0
E83: jr | H83: =(F83*G83) -> 0
A84: Camara termografica | E84: jr | G84: 15000 | H84: =(F84*G84) -> 0
A85: Generador de Luz con combustible | E85: jr | G85: 383.5 | H85: =(F85*G85) -> 0
G86: SUBT 9 | H86: =SUM(H62:H85) -> 660
E88: 0 | H88: =+E88 -> 0 | I88: IMPUESTO | J88: INDIRECTO DISPONIBLE
F89: COSTO DIRECTO | H89: =H59+H86 -> 1816.16
F90: Indirectos | G90: 0.25 | H90: =H89*G90 -> 454.04 | I90: =+M96 -> 49.03848 | J90: =H90-M96 -> 405.00152 | N90: REV-06-feb-2021
F91: Subtotal 1 | H91: =H89+H90 -> 2270.2
F92: Financ. | G92: 0.06 | H92: =H91*G92 -> 136.212 | K92: BASE IMPUESTO | L92: SIN UTILIDAD
F93: Subtotal 2 | H93: =H91+H92 -> 2406.412 | J93: COMPRAS | K93: =+H17 -> 0
F94: Utilidad | G94: 0.2 | H94: =H93*G94 -> 481.2824 | J94: M.O | K94: =H44 -> 1156.16
F95: Importe | H95: =H93+H94 -> 2887.6944 | J95: GASTOS FACTURADOS | K95: =H59-H46 -> 1086.7904 | M95: IMP. 30%
F96: Materiales | H96: ='MAT (4)'!H124 -> 4108.1631 | I96: FACTOR | J96: SUMA | K96: =SUM(K93:K95) -> 2242.9504 | L96: =H95-H94 -> 2406.412 | M96: =+(L96-K96)*0.3 -> 49.03848
B97: utilidad | F97: Total | H97: =H95+H96 -> 6995.8575 | J97: =H95/H89 -> 1.59
B98: ime | C98: comisión | D98: total | H98: =H97/4 -> 1748.9644
B99: 0.275 | C99: 0.05 | D99: =B99+C99 -> 0.325

Sheet MAT (5)
A1: I M M E E S. A. D E C. V.
A2: A N A L I S I S D E P R E C I O U N I T A R I O
A3: COTIZACION:
A4: FECHA:
A5: PARTIDA 1
A6: REV-06-feb-2021
A7: MATERIALES.
A8: DESCRIPCION | E8: UNIDAD | F8: CANT. | G8: P.U. | H8: IMPORTE | J8: MATERIALES
A9: charola tipo escalera perfil Z para servicio pesado de 30" | E9: Pza | G9: 2540.01 | H9: =G9*F9 -> 0
A10: tapa para charola tipo escalera de 30". | E10: Pza | G10: 1001 | H10: =G10*F10 -> 0
A11: curva vertical exterior de 90° para charola tipo escalera de 30 | E11: Pza | G11: 450.5 | H11: =G11*F11 -> 0
A12: tapa para curva vertical exterior de 90° para charola tipo escalera para servicio pesado de 30" | E12: Pza | G12: 136.52 | H12: =G12*F12 -> 0
A13: curva horizontal de 90° para charola tipo escalera para servicio pesado de 30" | E13: Pza | G13: 620.97 | H13: =G13*F13 -> 0
A14: base de unicanal solido galvanizado de 4x4 | E14: Pza | F14: 3 | G14: 382.32 | H14: =G14*F14 -> 1146.96
A15: tornilleria galvanizada | E15: Pza | F15: 3 | G15: 200 | H15: =G15*F15 -> 600
A16: varilla roscada galvanizada de 3 metros de largo X 1/2" | E16: Pza | F16: 6 | G16: 70 | H16: =G16*F16 -> 420
A17: conector de charola para servicio pesado de 30 | E17: Pza | F17: 6 | G17: 467.05 | H17: =G17*F17 -> 2802.3
A18: zapata ponchable para cable de cobre cañon largo calibre 500 KCM, con 2 ojillos de 1/2 | E18: Pza | G18: 495.41 | H18: =G18*F18 -> 0
A19: manga termocontractil para nivel de aislamiento de 600 V, en calibre 500 KCM. | E19: Pza | G19: 212.43 | H19: =G19*F19 -> 0
A20: tornillo tropicalizado de 1/2" con 2" de largo | E20: Pza | G20: 15 | H20: =G20*F20 -> 0
A21: tornillo tropicalizado de 1/2" con 4" de largo | E21: Pza | G21: 15 | H21: =G21*F21 -> 0
A22: sistema corta fuego con lana mineral y compuesto SF-ONE. | E22: Pza | G22: 698.25 | H22: =G22*F22 -> 0
A23: Materiales consumibles | E23: PZA | G23: 500 | H23: =G23*F23 -> 0
A24: cuellos de lona flexibles en gargantas primarias de generador electrico | E24: Pza | G24: 160.08 | H24: =G24*F24 -> 0
A25: cable de cobre THW calibre 12 AWG | E25: mt | G25: 12.63 | H25: =G25*F25 -> 0 | L25: NOTA: CONSIDERAR LA JORNADA DE 8.0 HORAS, AUNQUE EN IMMEE SE TRABAJE JORNADA LARGA CONVENIDA, Y DOMINGO DESCANSO
A26: tapones para unicanal de 4x4 y varilla roscada | E26: Pza | G26: 27.6 | H26: =G26*F26 -> 0
A27: tapones para esparrago | E27: Pza | G27: 70.34 | H27: =G27*F27 -> 0
A28: consumibles | E28: 1 | G28: 100 | H28: =G28*F28 -> 0
A29: Renta de una plataforma de elevacion | E29: Pza | G29: 25000 | H29: =G29*F29 -> 0 | I29: =H29*1.455 -> 0
G30: SUBT 1 | H30: =SUM(H9:H29) -> 4969.26
A32: MANO DE OBRA SIN INDIRECTOS | O32: HORARIOS DE TRABAJO | V32: HORAS RESULTANTES | Y32: PERSONAL PEOPUESTO
A33: PERSONAL. | E33: UNIDAD | F33: CANT. | G33: HORA NORMAL | H33: IMPORTE | I33: CANT. | J33: Hr. Extra | K33: IMPORTE | L33: CANT. | M33: Dom, ó Fest.TRIPLE | N33: IMPORTE | O33: L | P33: M | Q33: MI | R33: J | S33: V | T33: S | U33: D | V33: N | W33: D | X33: T
A34: SUPERVISOR DE SEGURIDAD CERTIFICADO | E34: hr | G34: 390.39 | H34: =F34*G34 -> 0 | J34: 358.81 | K34: =I34*J34 -> 0 | M34: 538.27 | N34: =L34*M34 -> 0 | V34: =+O34+P34+Q34+R34+S34+T34+U34-W34-X34 -> 0
A35: SUPERVISOR DE SEGURIDAD | E35: hr | G35: 243.45 | H35: =F35*G35 -> 0 | J35: 211.59 | K35: =I35*J35 -> 0 | M35: 317.39 | N35: =L35*M35 -> 0 | V35: =+O35+P35+Q35+R35+S35+T35+U35-W35-X35 -> 0 | Y35: OSWALDO Z-GABRIEL
A36: SUPERVISOR ELECTRICO | E36: hr | G36: 390.39 | H36: =F36*G36 -> 0 | J36: 358.81 | K36: =I36*J36 -> 0 | M36: 538.22 | N36: =L36*M36 -> 0 | V36: =+O36+P36+Q36+R36+S36+T36+U36-W36-X36 -> 0 | Y36: ADRIAN
A37: TECNICO DE PRUEBAS ELECTRICAS | E37: hr | G37: 231.67 | H37: =F37*G37 -> 0 | J37: 197.63 | K37: =I37*J37 -> 0 | M37: 296.45 | N37: =L37*M37 -> 0 | V37: =+O37+P37+Q37+R37+S37+T37+U37-W37-X37 -> 0 | Y37: HECTOR
A38: CABO OBRA ELECTRICA | E38: hr | G38: 310.62 | H38: =F38*G38 -> 0 | J38: 291.24 | K38: =I38*J38 -> 0 | M38: 436.87 | N38: =L38*M38 -> 0 | V38: =+O38+P38+Q38+R38+S38+T38+U38-W38-X38 -> 0
A39: LINIERO | E39: hr | G39: 310.62 | H39: =F39*G39 -> 0 | J39: 291.24 | K39: =I39*J39 -> 0 | M39: 436.87 | N39: =L39*M39 -> 0 | V39: =+O39+P39+Q39+R39+S39+T39+U39-W39-X39 -> 0 | Y39: JOSE J
A40: ESPECIALISTA DE MANTTO ELECTRICO | E40: hr | H40: =F40*G40 -> 0 | J40: 0 | K40: =I40*J40 -> 0 | M40: 0 | N40: =L40*M40 -> 0 | V40: =+O40+P40+Q40+R40+S40+T40+U40-W40-X40 -> 0
A41: TECNICO EN INSTRUMENTACION | E41: hr | G41: 199.6 | H41: =F41*G41 -> 0 | J41: 159.6 | K41: =I41*J41 -> 0 | M41: 239.4 | N41: =L41*M41 -> 0 | V41: =+O41+P41+Q41+R41+S41+T41+U41-W41-X41 -> 0
A42: OFICIAL ELECTRICO/ELECTROMECANICO | E42: hr | G42: 199.6 | H42: =F42*G42 -> 0 | J42: 159.6 | K42: =I42*J42 -> 0 | M42: 239.4 | N42: =L42*M42 -> 0 | V42: =+O42+P42+Q42+R42+S42+T42+U42-W42-X42 -> 0
A43: ASISTENTE DE DISEÑO | E43: hr | G43: 199.6 | H43: =F43*G43 -> 0 | J43: 159.6 | K43: =I43*J43 -> 0 | M43: 239.4 | N43: =L43*M43 -> 0 | V43: =+O43+P43+Q43+R43+S43+T43+U43-W43-X43 -> 0
A44: ELECTRICISTA -B | E44: hr | G44: 211.15 | H44: =F44*G44 -> 0 | J44: 173.29 | K44: =I44*J44 -> 0 | M44: 259.94 | N44: =L44*M44 -> 0 | V44: =+O44+P44+Q44+R44+S44+T44+U44-W44-X44 -> 0 | Y44: GERMAN
A45: ELECTRICISTA -A | E45: hr | G45: 199.6 | H45: =F45*G45 -> 0 | J45: 159.6 | K45: =I45*J45 -> 0 | M45: 239.4 | N45: =L45*M45 -> 0 | V45: =+O45+P45+Q45+R45+S45+T45+U45-W45-X45 -> 0 | Y45: OSCAR-OSWALDO JIM
A46: AUXILIAR TECNICO | E46: hr | G46: 187.81 | H46: =F46*G46 -> 0 | J46: 145.62 | K46: =I46*J46 -> 0 | M46: 218.43 | N46: =L46*M46 -> 0 | V46: =+O46+P46+Q46+R46+S46+T46+U46-W46-X46 -> 0
A47: AYTE ELECTRICO - B | E47: hr | H47: =F47*G47 -> 0 | J47: 0 | K47: =I47*J47 -> 0 | N47: =L47*M47 -> 0 | V47: =+O47+P47+Q47+R47+S47+T47+U47-W47-X47 -> 0
A48: AYTE DE ELECTR. -A | E48: hr | G48: 187.81 | H48: =F48*G48 -> 0 | J48: 145.62 | K48: =I48*J48 -> 0 | M48: 218.43 | N48: =L48*M48 -> 0 | V48: =+O48+P48+Q48+R48+S48+T48+U48-W48-X48 -> 0 | Y48: URIEL-GUILLERMO-ENRIQUE
A49: AYTE GENERAL | E49: hr | G49: 94.81 | H49: =F49*G49 -> 0 | J49: 145.62 | K49: =I49*J49 -> 0 | M49: 218.43 | N49: =L49*M49 -> 0 | V49: =+O49+P49+Q49+R49+S49+T49+U49-W49-X49 -> 0
A50: PROFESIONISTA | E50: hr | G50: 243.45 | H50: =F50*G50 -> 0 | J50: 211.59 | K50: =I50*J50 -> 0 | M50: 317.39 | N50: =L50*M50 -> 0 | V50: 0 | Y50: O.ZARCO-GABRIEL
A51: COORDINADOR DE OPERACIONES | E51: hr | G51: 339.75 | H51: =F51*G51 -> 0 | J51: 325.79 | K51: =I51*J51 -> 0 | M51: 488.68 | N51: =L51*M51 -> 0 | V51: =+O51+P51+Q51+R51+S51+T51+U51-W51-X51 -> 0
A52: INGENIERIA Y SOPORTE TEC. | E52: hr | G52: 339.75 | H52: =F52*G52 -> 0 | J52: 325.79 | K52: =I52*J52 -> 0 | M52: 488.68 | N52: =L52*M52 -> 0 | V52: =+O52+P52+Q52+R52+S52+T52+U52-W52-X52 -> 0
A53: INGENIERO DE SUBESTACIONES | E53: hr | G53: 339.75 | H53: =F53*G53 -> 0 | J53: 325.79 | K53: =I53*J53 -> 0 | M53: 488.68 | N53: =L53*M53 -> 0 | V53: =+O53+P53+Q53+R53+S53+T53+U53-W53-X53 -> 0
A54: INGENIERO DE PRUEBAS ELECTRICAS | E54: hr | G54: 339.75 | H54: =F54*G54 -> 0 | J54: 325.79 | K54: =I54*J54 -> 0 | M54: 488.68 | N54: =L54*M54 -> 0 | V54: =+O54+P54+Q54+R54+S54+T54+U54-W54-X54 -> 0
A55: ING. ESPECIALISTA EN PROTECCIONES | E55: hr | G55: 1004.49 | H55: =F55*G55 -> 0 | J55: 1164.98 | K55: =I55*J55 -> 0 | M55: 1747.46 | N55: =L55*M55 -> 0 | V55: =+O55+P55+Q55+R55+S55+T55+U55-W55-X55 -> 0
A56: SUPERINTENDENTE | E56: hr | H56: =F56*G56 -> 0 | J56: =G56*1.5 -> 0 | K56: =I56*J56 -> 0 | M56: =G56*2.25 -> 0 | N56: =L56*M56 -> 0 | V56: =+O56+P56+Q56+R56+S56+T56+U56-W56-X56 -> 0
F57: =V57 -> 0 | G57: SUBT 2 | H57: =SUM(H34:H56) -> 0 | J57: SUBT. | K57: =SUM(K34:K56) -> 0 | M57: SUBT. | N57: =SUM(N34:N56) -> 0
G58: SUMA M.O. | H58: =H57+K57+N57 -> 0
A59: HERRAMIENTA MENOR | G59: 1 a 10% | H59: =+H58*0.06 -> 0
H60: =+H58+H59 -> 0
A61: VEHICULOS
A62: DESCRIPCION | E62: UNIDAD | F62: CANT. | G62: P.U. | H62: IMPORTE | J62: HR IDA | K62: HR RETORNO | L62: HR SITIO | M62: SUMA
A63: camioneta EXPRES VAN CARGO sin operador sin combustible | E63: HR | F63: 0 | G63: 170 | H63: =F63*G63 -> 0 | M63: =J63+K63+L63 -> 0
A64: camioneta RANGER sin operador sin combustible | E64: HR | F64: 2 | G64: 180 | H64: =F64*G64 -> 360 | M64: =J64+K64+L64 -> 0
A65: camioneta TORNADO Tornado sin operador sin combustible | E65: HR | F65: 0 | G65: 80 | H65: =F65*G65 -> 0 | M65: =J65+K65+L65 -> 0
A66: camioneta WV TRANSPORTER pasajeros | E66: HR | F66: 0 | G66: 150 | H66: =F66*G66 -> 0 | M66: =J66+K66+L66 -> 0
E67: HR | F67: 0 | H67: =F67*G67 -> 0 | M67: =J67+K67+L67 -> 0
E68: pza | F68: 0 | H68: =F68*G68 -> 0 | M68: =J68+K68+L68 -> 0
A69: Km. Recorrido (incluye conbustible y depresiación de Vehiculo | E69: KM | F69: 0 | G69: 2.5 | H69: =F69*G69 -> 0 | M69: =J69+K69+L69 -> 0
G70: SUBT 4 | H70: =SUM(H63:H69) -> 360
A71: COMBUSTIBLE
A72: DESCRIPCION | E72: UNIDAD | F72: CANT. | G72: P.U. | H72: IMPORTE | J72: KM IDA | K72: KM RETORNO | L72: KM SITIO | M72: SUMA
A73: GASOLINA MAGNA | E73: LT | F73: 10 | G73: 23 | H73: =F73*G73 -> 230 | M73: =J73+K73+L73 -> 0
A74: DIESEL | E74: LT | F74: 0 | G74: 24 | H74: =F74*G74 -> 0 | M74: =J74+K74+L74 -> 0
G75: SUBT 5 | H75: =SUM(H73:H74) -> 230
A76: CASETAS
A77: DESCRIPCION | E77: UNIDAD | F77: CANT. | G77: P.U. | H77: IMPORTE
A78: Camion | E78: CASETA | F78: 2 | G78: 65 | H78: =F78*G78 -> 130
A79: camioneta pick up | E79: CASETA | G79: 250 | H79: =F79*G79 -> 0
G80: SUBT 6 | H80: =SUM(H78:H79) -> 130
A81: VIATICOS
A82: ALIMENTOS
A83: DESCRIPCION | E83: UNIDAD | F83: CANT. | G83: P.U. | H83: IMPORTE
A84: CONSUMO DE ALIMENTOS | E84: Pza | F84: 2 | G84: 600 | H84: =F84*G84 -> 1200
H85: =SUM(H84) -> 1200
A86: HOSPEDAJE
A87: DESCRIPCION | E87: UNIDAD | F87: CANT. | G87: P.U. | H87: IMPORTE
A88: HOTEL | E88: NOCHES | F88: 1 | G88: 1100 | H88: =F88*G88 -> 1100
G89: SUBT 8 | H89: =SUM(H88) -> 1100
G90: SUMA: | H90: =H70+H75+H80+H85+H89+H59+H58+H30 -> 7989.26
A91: EQUIPO DE PRUEBA
A92: DESCRIPCION | E92: UNIDAD | F92: CANT. | G92: P.U. | H92: IMPORTE | I92: TR | K92: S.E
A93: Megger | E93: jr | G93: 2200 | H93: =(F93*G93) -> 0
A94: TTR | E94: jr | G94: 2000 | H94: =(F94*G94) -> 0
A95: Factor de Potencia de 2.5 KV | E95: jr | G95: 7000 | H95: =(F95*G95) -> 0
A96: Factor de Potencia de 10.5 KV | E96: jr | G96: 15200 | H96: =(F96*G96) -> 0
A97: Ducter | E97: jr | G97: 2200 | H97: =(F97*G97) -> 0
A98: resistencia óhmica | E98: jr | G98: 2000 | H98: =(F98*G98) -> 0
A99: hipot de 80 KV vcd | E99: jr | G99: 2500 | H99: =(F99*G99) -> 0
A100: Rigidez dieléctrica al aceite 60 kv | E100: jr | G100: 1600 | H100: =(F100*G100) -> 0
A101: Terrómetro | E101: jr | G101: 1100 | H101: =(F101*G101) -> 0
...

Sheet M0  (5)
A1: I M M E E S. A. D E C. V.
A2: A N A L I S I S D E P R E C I O U N I T A R I O
A3: COTIZACION:
A4: FECHA:
A5: PARTIDA 1
A6: REV-06-feb-2021
A7: MATERIALES.
A8: DESCRIPCION | E8: UNIDAD | F8: CANT. | G8: P.U. | H8: IMPORTE | J8: MANO DE OBRA
A9: Consumible | E9: Pza | H9: =G9*F9 -> 0
E10: Pza | H10: =G10*F10 -> 0
E11: Pza | H11: =G11*F11 -> 0
E12: Pza | H12: =G12*F12 -> 0
E13: Pza | H13: =G13*F13 -> 0
E14: Pza | H14: =G14*F14 -> 0
E15: Pza | H15: =G15*F15 -> 0
E16: Pza | H16: =G16*F16 -> 0 | I16: =H16*1.455 -> 0
G17: SUBT 1 | H17: =SUM(H9:H16) -> 0
A19: MANO DE OBRA SIN INDIRECTOS | O19: HORARIOS DE TRABAJO | V19: HORAS RESULTANTES | Y19: PERSONAL PEOPUESTO
A20: PERSONAL. | E20: UNIDAD | F20: CANT. | G20: HORA NORMAL | H20: IMPORTE | I20: CANT. | J20: Hr. Extra | K20: IMPORTE | L20: CANT. | M20: Dom, ó Fest.TRIPLE | N20: IMPORTE | O20: L | P20: M | Q20: MI | R20: J | S20: V | T20: S | U20: D | V20: N | W20: D | X20: T
A21: SUPERVISOR DE SEGURIDAD CERTIFICADO | E21: hr | G21: 390.39 | H21: =F21*G21 -> 0 | J21: 358.81 | K21: =I21*J21 -> 0 | M21: 538.27 | N21: =L21*M21 -> 0 | V21: =+O21+P21+Q21+R21+S21+T21+U21-W21-X21 -> 0
A22: SUPERVISOR DE SEGURIDAD | E22: hr | F22: 4 | G22: 317.98 | H22: =F22*G22 -> 1271.92 | J22: 326.25 | K22: =I22*J22 -> 0 | M22: 489.37 | N22: =L22*M22 -> 0 | V22: =+O22+P22+Q22+R22+S22+T22+U22-W22-X22 -> 0 | Y22: OSWALDO Z-GABRIEL
A23: SUPERVISOR ELECTRICO | E23: hr | F23: 4 | G23: 237.68 | H23: =F23*G23 -> 950.72 | J23: 358.81 | K23: =I23*J23 -> 0 | M23: 538.22 | N23: =L23*M23 -> 0 | V23: =+O23+P23+Q23+R23+S23+T23+U23-W23-X23 -> 0 | Y23: ADRIAN
A24: TECNICO DE PRUEBAS ELECTRICAS | E24: hr | G24: 317.98 | H24: =F24*G24 -> 0 | J24: 244.27 | K24: =I24*J24 -> 0 | M24: 489.37 | N24: =L24*M24 -> 0 | V24: =+O24+P24+Q24+R24+S24+T24+U24-W24-X24 -> 0 | Y24: HECTOR
A25: CABO OBRA ELECTRICA | E25: hr | G25: 310.62 | H25: =F25*G25 -> 0 | J25: 335 | K25: =I25*J25 -> 0 | M25: 436.87 | N25: =L25*M25 -> 0 | V25: =+O25+P25+Q25+R25+S25+T25+U25-W25-X25 -> 0
A26: LINIERO | E26: hr | F26: 4 | G26: 209.25 | H26: =F26*G26 -> 837 | J26: 221.7 | K26: =I26*J26 -> 0 | M26: 437.63 | N26: =L26*M26 -> 0 | V26: =+O26+P26+Q26+R26+S26+T26+U26-W26-X26 -> 0 | Y26: JOSE J
A27: ESPECIALISTA DE MANTTO ELECTRICO | E27: hr | G27: 237.68 | H27: =F27*G27 -> 0 | J27: 277.97 | K27: =I27*J27 -> 0 | M27: 538.84 | N27: =L27*M27 -> 0 | V27: =+O27+P27+Q27+R27+S27+T27+U27-W27-X27 -> 0
A28: TECNICO EN INSTRUMENTACION | E28: hr | G28: 368.59 | H28: =F28*G28 -> 0 | J28: 221.7 | K28: =I28*J28 -> 0 | M28: 538.84 | N28: =L28*M28 -> 0 | V28: =+O28+P28+Q28+R28+S28+T28+U28-W28-X28 -> 0
A29: OFICIAL ELECTRICO/ELECTROMECANICO | E29: hr | F29: 9.5 | G29: 190.22 | H29: =F29*G29 -> 1807.09 | I29: 1 | J29: 165 | K29: =I29*J29 -> 165 | M29: 277.56 | N29: =L29*M29 -> 0 | V29: =+O29+P29+Q29+R29+S29+T29+U29-W29-X29 -> 0
A30: ASISTENTE DE DISEÑO | E30: hr | G30: 190.25 | H30: =F30*G30 -> 0 | J30: 221.7 | K30: =I30*J30 -> 0 | M30: 297.41 | N30: =L30*M30 -> 0 | V30: =+O30+P30+Q30+R30+S30+T30+U30-W30-X30 -> 0
A31: ELECTRICISTA -B | E31: hr | F31: 9.5 | G31: 119.54 | H31: =F31*G31 -> 1135.63 | I31: 1 | J31: 137.92 | K31: =I31*J31 -> 137.92 | M31: 0 | N31: =L31*M31 -> 0 | V31: =+O31+P31+Q31+R31+S31+T31+U31-W31-X31 -> 0 | Y31: GERMAN
A32: ELECTRICISTA -A | E32: hr | G32: 119.54 | H32: =F32*G32 -> 0 | J32: 137.92 | K32: =I32*J32 -> 0 | M32: 240.95 | N32: =L32*M32 -> 0 | V32: =+O32+P32+Q32+R32+S32+T32+U32-W32-X32 -> 0 | Y32: OSCAR-OSWALDO JIM
A33: AUXILIAR TECNICO | E33: hr | G33: 106.45 | H33: =F33*G33 -> 0 | J33: 137.92 | K33: =I33*J33 -> 0 | M33: 260.95 | N33: =L33*M33 -> 0 | V33: =+O33+P33+Q33+R33+S33+T33+U33-W33-X33 -> 0
A34: AYTE ELECTRICO - B | E34: hr | G34: 106.45 | H34: =F34*G34 -> 0 | J34: 122.4 | K34: =I34*J34 -> 0 | N34: =L34*M34 -> 0 | V34: =+O34+P34+Q34+R34+S34+T34+U34-W34-X34 -> 0
A35: AYTE DE ELECTR. -A | E35: hr | G35: 106.54 | H35: =F35*G35 -> 0 | J35: 122.4 | K35: =I35*J35 -> 0 | M35: 198.17 | N35: =L35*M35 -> 0 | V35: =+O35+P35+Q35+R35+S35+T35+U35-W35-X35 -> 0 | Y35: URIEL-GUILLERMO-ENRIQUE
A36: AYTE GENERAL | E36: hr | G36: 100.42 | H36: =F36*G36 -> 0 | J36: 122.4 | K36: =I36*J36 -> 0 | M36: 0 | N36: =L36*M36 -> 0 | V36: =+O36+P36+Q36+R36+S36+T36+U36-W36-X36 -> 0
A37: PROFESIONISTA | E37: hr | G37: 209.25 | H37: =F37*G37 -> 0 | J37: 406 | K37: =I37*J37 -> 0 | M37: 564.86 | N37: =L37*M37 -> 0 | V37: 0 | Y37: O.ZARCO-GABRIEL
A38: COORDINADOR DE OPERACIONES | E38: hr | G38: 0 | H38: =F38*G38 -> 0 | J38: 0 | K38: =I38*J38 -> 0 | M38: 0 | N38: =L38*M38 -> 0 | V38: =+O38+P38+Q38+R38+S38+T38+U38-W38-X38 -> 0
A39: INGENIERIA Y SOPORTE TEC. | E39: hr | G39: 339.75 | H39: =F39*G39 -> 0 | J39: 325.79 | K39: =I39*J39 -> 0 | M39: 488.68 | N39: =L39*M39 -> 0 | V39: =+O39+P39+Q39+R39+S39+T39+U39-W39-X39 -> 0
A40: INGENIERO DE SUBESTACIONES | E40: hr | G40: 339.75 | H40: =F40*G40 -> 0 | J40: 325.79 | K40: =I40*J40 -> 0 | M40: 488.68 | N40: =L40*M40 -> 0 | V40: =+O40+P40+Q40+R40+S40+T40+U40-W40-X40 -> 0
A41: INGENIERO DE PRUEBAS ELECTRICAS | E41: hr | G41: 339.75 | H41: =F41*G41 -> 0 | J41: 325.79 | K41: =I41*J41 -> 0 | M41: 488.68 | N41: =L41*M41 -> 0 | V41: =+O41+P41+Q41+R41+S41+T41+U41-W41-X41 -> 0
A42: ING. ESPECIALISTA EN PROTECCIONES | E42: hr | G42: 650 | H42: =F42*G42 -> 0 | J42: =G42*1.5 -> 975 | K42: =I42*J42 -> 0 | M42: 1747.46 | N42: =L42*M42 -> 0 | V42: =+O42+P42+Q42+R42+S42+T42+U42-W42-X42 -> 0
A43: SUPERINTENDENTE | E43: hr | H43: =F43*G43 -> 0 | J43: =G43*1.5 -> 0 | K43: =I43*J43 -> 0 | M43: =G43*2.25 -> 0 | N43: =L43*M43 -> 0 | V43: =+O43+P43+Q43+R43+S43+T43+U43-W43-X43 -> 0
F44: =V44 -> 0 | G44: SUBT 2 | H44: =SUM(H21:H43) -> 6002.36 | J44: SUBT. | K44: =SUM(K21:K43) -> 302.92 | M44: SUBT. | N44: =SUM(N21:N43) -> 0
G45: SUMA M.O. | H45: =H44+K44+N44 -> 6305.28
A46: HERRAMIENTA MENOR | G46: 1 a 10% | H46: =+H45*0.06 -> 378.3168
A49: VEHICULOS
A50: DESCRIPCION | E50: UNIDAD | F50: CANT. | G50: P.U. | H50: IMPORTE | J50: HR IDA | K50: HR RETORNO | L50: HR SITIO | M50: SUMA
A51: camioneta EXPRES VAN CARGO sin operador sin combustible | E51: HR | F51: 0 | G51: 150 | H51: =F51*G51 -> 0 | M51: =J51+K51+L51 -> 0
A52: camioneta RANGER sin operador sin combustible | E52: HR | F52: 0 | G52: 150 | H52: =F52*G52 -> 0 | M52: =J52+K52+L52 -> 0
A53: camioneta TORNADO Tornado sin operador sin combustible | E53: HR | F53: 0 | G53: 60 | H53: =F53*G53 -> 0 | M53: =J53+K53+L53 -> 0
A54: camioneta WV TRANSPORTER pasajeros | E54: HR | F54: 0 | G54: 120 | H54: =F54*G54 -> 0 | M54: =J54+K54+L54 -> 0
E55: HR | F55: 0 | H55: =F55*G55 -> 0 | M55: =J55+K55+L55 -> 0
E56: pza | F56: 0 | H56: =F56*G56 -> 0 | M56: =J56+K56+L56 -> 0
A57: Km. Recorrido (incluye conbustible y depresiación de Vehiculo | E57: KM | F57: 0 | G57: 2.5 | H57: =F57*G57 -> 0 | M57: =J57+K57+L57 -> 0
G58: SUBT 4 | H58: =SUM(H51:H57) -> 0
G59: SUMA: | H59: =H58+H45+H17 -> 6305.28
A60: EQUIPO DE PRUEBA
A61: DESCRIPCION | E61: UNIDAD | F61: CANT. | G61: P.U. | H61: IMPORTE | I61: TR | K61: S.E
A62: Megger | E62: jr | F62: 0.3 | G62: 2200 | H62: =(F62*G62) -> 660
A63: TTR | E63: jr | G63: 2000 | H63: =(F63*G63) -> 0
A64: Factor de Potencia de 2.5 KV | E64: jr | G64: 7000 | H64: =(F64*G64) -> 0
A65: Factor de Potencia de 10.5 KV | E65: jr | G65: 15200 | H65: =(F65*G65) -> 0
A66: Ducter | E66: jr | G66: 2200 | H66: =(F66*G66) -> 0
A67: resistencia óhmica | E67: jr | G67: 2000 | H67: =(F67*G67) -> 0
A68: hipot de 80 KV vcd | E68: jr | G68: 2500 | H68: =(F68*G68) -> 0
A69: Rigidez dieléctrica al aceite 60 kv | E69: jr | G69: 1600 | H69: =(F69*G69) -> 0
A70: Terrómetro | E70: jr | G70: 1100 | H70: =(F70*G70) -> 0
A71: Analizador de tiempos de interruptor | E71: jr | G71: 2700 | H71: =(F71*G71) -> 0
A72: Fuente de corriente para calibrador de relevadores | E72: jr | G72: 2500 | H72: =(F72*G72) -> 0
A73: Probador de relevador de Protecciones | E73: jr | G73: 13373 | H73: =(F73*G73) -> 0
A74: Fuente trifasica de voltaje | E74: jr | G74: 800 | H74: =(F74*G74) -> 0
... A82: Test Kit maleta de prueba G.E. | E82: jr | G82: 5800 | H82: =(F82*G82) -> 0
E83: jr | H83: =(F83*G83) -> 0
A84: Camara termografica | E84: jr | G84: 15000 | H84: =(F84*G84) -> 0
A85: Generador de Luz con combustible | E85: jr | F85: 1 | G85: 383.5 | H85: =(F85*G85) -> 383.5
G86: SUBT 9 | H86: =SUM(H62:H85) -> 1043.5
E88: 0 | H88: =+E88 -> 0 | I88: IMPUESTO | J88: INDIRECTO DISPONIBLE
F89: COSTO DIRECTO | H89: =H59+H86 -> 7348.78
F90: Indirectos | G90: 0.25 | H90: =H89*G90 -> 1837.195 | I90: =+M96 -> -657.65691 | J90: =H90-M96 -> 2494.8519 | N90: REV-06-feb-2021
F91: Subtotal 1 | H91: =H89+H90 -> 9185.975
F92: Financ. | G92: 0.06 | H92: =H91*G92 -> 551.1585 | K92: BASE IMPUESTO | L92: SIN UTILIDAD
F93: Subtotal 2 | H93: =H91+H92 -> 9737.1335 | J93: COMPRAS | K93: =+H17 -> 0
F94: Utilidad | G94: 0.2 | H94: =H93*G94 -> 1947.4267 | J94: M.O | K94: =H44 -> 6002.36
F95: Importe | H95: =H93+H94 -> 11684.56 | J95: GASTOS FACTURADOS | K95: =H59-H46 -> 5926.9632 | M95: IMP. 30%
F96: Materiales | H96: ='MAT (5)'!H124 -> 11178.573 | I96: FACTOR | J96: SUMA | K96: =SUM(K93:K95) -> 11929.323 | L96: =H95-H94 -> 9737.1335 | M96: =+(L96-K96)*0.3 -> -657.65691
B97: utilidad | F97: Total | H97: =H95+H96 -> 22863.133 | J97: =H95/H89 -> 1.59
B98: ime | C98: comisión | D98: total | H98: =H97/6 -> 3810.5221
B99: 0.275 | C99: 0.05 | D99: =B99+C99 -> 0.325

Sheet MAT (6)
A1: I M M E E S. A. D E C. V.
A2: A N A L I S I S D E P R E C I O U N I T A R I O
A3: COTIZACION:
A4: FECHA:
A5: PARTIDA 1
A6: REV-06-feb-2021
A7: MATERIALES.
A8: DESCRIPCION | E8: UNIDAD | F8: CANT. | G8: P.U. | H8: IMPORTE | J8: MATERIALES
A9: charola tipo escalera perfil Z para servicio pesado de 30" | E9: Pza | G9: 2540.01 | H9: =G9*F9 -> 0
A10: tapa para charola tipo escalera de 30". | E10: Pza | G10: 1001 | H10: =G10*F10 -> 0
A11: curva vertical exterior de 90° para charola tipo escalera de 30 | E11: Pza | G11: 450.5 | H11: =G11*F11 -> 0
A12: tapa para curva vertical exterior de 90° para charola tipo escalera para servicio pesado de 30" | E12: Pza | G12: 136.52 | H12: =G12*F12 -> 0
A13: curva horizontal de 90° para charola tipo escalera para servicio pesado de 30" | E13: Pza | G13: 620.97 | H13: =G13*F13 -> 0
A14: base de unicanal solido galvanizado de 4x4 | E14: Pza | G14: 382.32 | H14: =G14*F14 -> 0
A15: tornilleria galvanizada | E15: Pza | G15: 200 | H15: =G15*F15 -> 0
A16: varilla roscada galvanizada de 3 metros de largo X 1/2" | E16: Pza | G16: 70 | H16: =G16*F16 -> 0
A17: conector de charola para servicio pesado de 30 | E17: Pza | F17: 2 | G17: 467.05 | H17: =G17*F17 -> 934.1
A18: zapata ponchable para cable de cobre cañon largo calibre 500 KCM, con 2 ojillos de 1/2 | E18: Pza | G18: 495.41 | H18: =G18*F18 -> 0
A19: manga termocontractil para nivel de aislamiento de 600 V, en calibre 500 KCM. | E19: Pza | G19: 212.43 | H19: =G19*F19 -> 0
A20: tornillo tropicalizado de 1/2" con 2" de largo | E20: Pza | G20: 15 | H20: =G20*F20 -> 0
A21: tornillo tropicalizado de 1/2" con 4" de largo | E21: Pza | G21: 15 | H21: =G21*F21 -> 0
A22: sistema corta fuego con lana mineral y compuesto SF-ONE. | E22: Pza | G22: 698.25 | H22: =G22*F22 -> 0
A23: Materiales consumibles | E23: PZA | G23: 500 | H23: =G23*F23 -> 0
A24: cuellos de lona flexibles en gargantas primarias de generador electrico | E24: Pza | G24: 160.08 | H24: =G24*F24 -> 0
A25: cable de cobre THW calibre 12 AWG | E25: mt | G25: 12.63 | H25: =G25*F25 -> 0 | L25: NOTA: CONSIDERAR LA JORNADA DE 8.0 HORAS, AUNQUE EN IMMEE SE TRABAJE JORNADA LARGA CONVENIDA, Y DOMINGO DESCANSO
A26: tapones para unicanal de 4x4 y varilla roscada | E26: Pza | G26: 27.6 | H26: =G26*F26 -> 0
A27: tapones para esparrago | E27: Pza | G27: 70.34 | H27: =G27*F27 -> 0
A28: CONSUMIBLES | E28: CARRETE | F28: 1 | G28: 200 | H28: =G28*F28 -> 200
A29: Renta de una plataforma de elevacion | E29: Pza | G29: 48000 | H29: =G29*F29 -> 0 | I29: =H29*1.455 -> 0
G30: SUBT 1 | H30: =SUM(H9:H29) -> 1134.1
A32: MANO DE OBRA SIN INDIRECTOS | O32: HORARIOS DE TRABAJO | V32: HORAS RESULTANTES | Y32: PERSONAL PEOPUESTO
A33: PERSONAL. | E33: UNIDAD | F33: CANT. | G33: HORA NORMAL | H33: IMPORTE | I33: CANT. | J33: Hr. Extra | K33: IMPORTE | L33: CANT. | M33: Dom, ó Fest.TRIPLE | N33: IMPORTE | O33: L | P33: M | Q33: MI | R33: J | S33: V | T33: S | U33: D | V33: N | W33: D | X33: T
A34: SUPERVISOR DE SEGURIDAD CERTIFICADO | E34: hr | G34: 390.39 | H34: =F34*G34 -> 0 | J34: 358.81 | K34: =I34*J34 -> 0 | M34: 538.27 | N34: =L34*M34 -> 0 | V34: =+O34+P34+Q34+R34+S34+T34+U34-W34-X34 -> 0
A35: SUPERVISOR DE SEGURIDAD | E35: hr | G35: 243.45 | H35: =F35*G35 -> 0 | J35: 211.59 | K35: =I35*J35 -> 0 | M35: 317.39 | N35: =L35*M35 -> 0 | V35: =+O35+P35+Q35+R35+S35+T35+U35-W35-X35 -> 0 | Y35: OSWALDO Z-GABRIEL
A36: SUPERVISOR ELECTRICO | E36: hr | G36: 390.39 | H36: =F36*G36 -> 0 | J36: 358.81 | K36: =I36*J36 -> 0 | M36: 538.22 | N36: =L36*M36 -> 0 | V36: =+O36+P36+Q36+R36+S36+T36+U36-W36-X36 -> 0 | Y36: ADRIAN
A37: TECNICO DE PRUEBAS ELECTRICAS | E37: hr | G37: 231.67 | H37: =F37*G37 -> 0 | J37: 197.63 | K37: =I37*J37 -> 0 | M37: 296.45 | N37: =L37*M37 -> 0 | V37: =+O37+P37+Q37+R37+S37+T37+U37-W37-X37 -> 0 | Y37: HECTOR
A38: CABO OBRA ELECTRICA | E38: hr | G38: 310.62 | H38: =F38*G38 -> 0 | J38: 291.24 | K38: =I38*J38 -> 0 | M38: 436.87 | N38: =L38*M38 -> 0 | V38: =+O38+P38+Q38+R38+S38+T38+U38-W38-X38 -> 0
A39: LINIERO | E39: hr | G39: 310.62 | H39: =F39*G39 -> 0 | J39: 291.24 | K39: =I39*J39 -> 0 | M39: 436.87 | N39: =L39*M39 -> 0 | V39: =+O39+P39+Q39+R39+S39+T39+U39-W39-X39 -> 0 | Y39: JOSE J
A40: ESPECIALISTA DE MANTTO ELECTRICO | E40: hr | H40: =F40*G40 -> 0 | J40: 0 | K40: =I40*J40 -> 0 | M40: 0 | N40: =L40*M40 -> 0 | V40: =+O40+P40+Q40+R40+S40+T40+U40-W40-X40 -> 0
A41: TECNICO EN INSTRUMENTACION | E41: hr | G41: 199.6 | H41: =F41*G41 -> 0 | J41: 159.6 | K41: =I41*J41 -> 0 | M41: 239.4 | N41: =L41*M41 -> 0 | V41: =+O41+P41+Q41+R41+S41+T41+U41-W41-X41 -> 0
A42: OFICIAL ELECTRICO/ELECTROMECANICO | E42: hr | G42: 199.6 | H42: =F42*G42 -> 0 | J42: 159.6 | K42: =I42*J42 -> 0 | M42: 239.4 | N42: =L42*M42 -> 0 | V42: =+O42+P42+Q42+R42+S42+T42+U42-W42-X42 -> 0
A43: ASISTENTE DE DISEÑO | E43: hr | G43: 199.6 | H43: =F43*G43 -> 0 | J43: 159.6 | K43: =I43*J43 -> 0 | M43: 239.4 | N43: =L43*M43 -> 0 | V43: =+O43+P43+Q43+R43+S43+T43+U43-W43-X43 -> 0
A44: ELECTRICISTA -B | E44: hr | G44: 211.15 | H44: =F44*G44 -> 0 | J44: 173.29 | K44: =I44*J44 -> 0 | M44: 259.94 | N44: =L44*M44 -> 0 | V44: =+O44+P44+Q44+R44+S44+T44+U44-W44-X44 -> 0 | Y44: GERMAN
A45: ELECTRICISTA -A | E45: hr | G45: 199.6 | H45: =F45*G45 -> 0 | J45: 159.6 | K45: =I45*J45 -> 0 | M45: 239.4 | N45: =L45*M45 -> 0 | V45: =+O45+P45+Q45+R45+S45+T45+U45-W45-X45 -> 0 | Y45: OSCAR-OSWALDO JIM
A46: AUXILIAR TECNICO | E46: hr | G46: 187.81 | H46: =F46*G46 -> 0 | J46: 145.62 | K46: =I46*J46 -> 0 | M46: 218.43 | N46: =L46*M46 -> 0 | V46: =+O46+P46+Q46+R46+S46+T46+U46-W46-X46 -> 0
A47: AYTE ELECTRICO - B | E47: hr | H47: =F47*G47 -> 0 | J47: 0 | K47: =I47*J47 -> 0 | N47: =L47*M47 -> 0 | V47: =+O47+P47+Q47+R47+S47+T47+U47-W47-X47 -> 0
A48: AYTE DE ELECTR. -A | E48: hr | G48: 187.81 | H48: =F48*G48 -> 0 | J48: 145.62 | K48: =I48*J48 -> 0 | M48: 218.43 | N48: =L48*M48 -> 0 | V48: =+O48+P48+Q48+R48+S48+T48+U48-W48-X48 -> 0 | Y48: URIEL-GUILLERMO-ENRIQUE
A49: AYTE GENERAL | E49: hr | G49: 94.81 | H49: =F49*G49 -> 0 | J49: 145.62 | K49: =I49*J49 -> 0 | M49: 218.43 | N49: =L49*M49 -> 0 | V49: =+O49+P49+Q49+R49+S49+T49+U49-W49-X49 -> 0
A50: PROFESIONISTA | E50: hr | G50: 243.45 | H50: =F50*G50 -> 0 | J50: 211.59 | K50: =I50*J50 -> 0 | M50: 317.39 | N50: =L50*M50 -> 0 | V50: 0 | Y50: O.ZARCO-GABRIEL
A51: COORDINADOR DE OPERACIONES | E51: hr | G51: 339.75 | H51: =F51*G51 -> 0 | J51: 325.79 | K51: =I51*J51 -> 0 | M51: 488.68 | N51: =L51*M51 -> 0 | V51: =+O51+P51+Q51+R51+S51+T51+U51-W51-X51 -> 0
A52: INGENIERIA Y SOPORTE TEC. | E52: hr | G52: 339.75 | H52: =F52*G52 -> 0 | J52: 325.79 | K52: =I52*J52 -> 0 | M52: 488.68 | N52: =L52*M52 -> 0 | V52: =+O52+P52+Q52+R52+S52+T52+U52-W52-X52 -> 0
A53: INGENIERO DE SUBESTACIONES | E53: hr | G53: 339.75 | H53: =F53*G53 -> 0 | J53: 325.79 | K53: =I53*J53 -> 0 | M53: 488.68 | N53: =L53*M53 -> 0 | V53: =+O53+P53+Q53+R53+S53+T53+U53-W53-X53 -> 0
A54: INGENIERO DE PRUEBAS ELECTRICAS | E54: hr | G54: 339.75 | H54: =F54*G54 -> 0 | J54: 325.79 | K54: =I54*J54 -> 0 | M54: 488.68 | N54: =L54*M54 -> 0 | V54: =+O54+P54+Q54+R54+S54+T54+U54-W54-X54 -> 0
A55: ING. ESPECIALISTA EN PROTECCIONES | E55: hr | G55: 1004.49 | H55: =F55*G55 -> 0 | J55: 1164.98 | K55: =I55*J55 -> 0 | M55: 1747.46 | N55: =L55*M55 -> 0 | V55: =+O55+P55+Q55+R55+S55+T55+U55-W55-X55 -> 0
A56: SUPERINTENDENTE | E56: hr | H56: =F56*G56 -> 0 | J56: =G56*1.5 -> 0 | K56: =I56*J56 -> 0 | M56: =G56*2.25 -> 0 | N56: =L56*M56 -> 0 | V56: =+O56+P56+Q56+R56+S56+T56+U56-W56-X56 -> 0
F57: =V57 -> 0 | G57: SUBT 2 | H57: =SUM(H34:H56) -> 0 | J57: SUBT. | K57: =SUM(K34:K56) -> 0 | M57: SUBT. | N57: =SUM(N34:N56) -> 0
G58: SUMA M.O. | H58: =H57+K57+N57 -> 0
A59: HERRAMIENTA MENOR | G59: 1 a 10% | H59: =+H58*0.06 -> 0
H60: =+H58+H59 -> 0
A61: VEHICULOS
A62: DESCRIPCION | E62: UNIDAD | F62: CANT. | G62: P.U. | H62: IMPORTE | J62: HR IDA | K62: HR RETORNO | L62: HR SITIO | M62: SUMA
A63: camioneta EXPRES VAN CARGO sin operador sin combustible | E63: HR | F63: 0 | G63: 170 | H63: =F63*G63 -> 0 | M63: =J63+K63+L63 -> 0
A64: camioneta RANGER sin operador sin combustible | E64: HR | F64: 0.3 | G64: 180 | H64: =F64*G64 -> 54 | M64: =J64+K64+L64 -> 0
A65: camioneta TORNADO Tornado sin operador sin combustible | E65: HR | F65: 0 | G65: 80 | H65: =F65*G65 -> 0 | M65: =J65+K65+L65 -> 0
A66: camioneta WV TRANSPORTER pasajeros | E66: HR | F66: 0 | G66: 150 | H66: =F66*G66 -> 0 | M66: =J66+K66+L66 -> 0
E67: HR | F67: 0 | H67: =F67*G67 -> 0 | M67: =J67+K67+L67 -> 0
E68: pza | F68: 0 | H68: =F68*G68 -> 0 | M68: =J68+K68+L68 -> 0
A69: Km. Recorrido (incluye conbustible y depresiación de Vehiculo | E69: KM | F69: 0 | G69: 2.5 | H69: =F69*G69 -> 0 | M69: =J69+K69+L69 -> 0
G70: SUBT 4 | H70: =SUM(H63:H69) -> 54
A71: COMBUSTIBLE
A72: DESCRIPCION | E72: UNIDAD | F72: CANT. | G72: P.U. | H72: IMPORTE | J72: KM IDA | K72: KM RETORNO | L72: KM SITIO | M72: SUMA
A73: GASOLINA MAGNA | E73: LT | F73: 3 | G73: 23 | H73: =F73*G73 -> 69 | M73: =J73+K73+L73 -> 0
A74: DIESEL | E74: LT | F74: 0 | G74: 24 | H74: =F74*G74 -> 0 | M74: =J74+K74+L74 -> 0
G75: SUBT 5 | H75: =SUM(H73:H74) -> 69
A76: CASETAS
A77: DESCRIPCION | E77: UNIDAD | F77: CANT. | G77: P.U. | H77: IMPORTE
A78: Camion | E78: CASETA | F78: 1 | G78: 65 | H78: =F78*G78 -> 65
A79: camioneta pick up | E79: CASETA | F79: 2 | G79: 250 | H79: =F79*G79 -> 500
G80: SUBT 6 | H80: =SUM(H78:H79) -> 565
A81: VIATICOS
A82: ALIMENTOS
A83: DESCRIPCION | E83: UNIDAD | F83: CANT. | G83: P.U. | H83: IMPORTE
A84: CONSUMO DE ALIMENTOS | E84: Pza | F84: 0.5 | G84: 650 | H84: =F84*G84 -> 325
H85: =SUM(H84) -> 325
A86: HOSPEDAJE
A87: DESCRIPCION | E87: UNIDAD | F87: CANT. | G87: P.U. | H87: IMPORTE
A88: HOTEL | E88: NOCHES | F88: 0.3 | G88: 1100 | H88: =F88*G88 -> 330
G89: SUBT 8 | H89: =SUM(H88) -> 330
G90: SUMA: | H90: =H70+H75+H80+H85+H89+H59+H58+H30 -> 2477.1
A91: EQUIPO DE PRUEBA
A92: DESCRIPCION | E92: UNIDAD | F92: CANT. | G92: P.U. | H92: IMPORTE | I92: TR | K92: S.E
A93: Megger | E93: jr | G93: 2200 | H93: =(F93*G93) -> 0
A94: TTR | E94: jr | G94: 2000 | H94: =(F94*G94) -> 0
A95: Factor de Potencia de 2.5 KV | E95: jr | G95: 7000 | H95: =(F95*G95) -> 0
A96: Factor de Potencia de 10.5 KV | E96: jr | G96: 15200 | H96: =(F96*G96) -> 0
A97: Ducter | E97: jr | G97: 2200 | H97: =(F97*G97) -> 0
A98: resistencia óhmica | E98: jr | G98: 2000 | H98: =(F98*G98) -> 0
A99: hipot de 80 KV vcd | E99: jr | G99: 2500 | H99: =(F99*G99) -> 0
A100: Rigidez dieléctrica al aceite 60 kv | E100: jr | G100: 1600 | H100: =(F100*G100) -> 0
A101: Terrómetro | E101: jr | G101: 1100 | H101: =(F101*G101) -> 0
...

Sheet M0  (6)
A1: I M M E E S. A. D E C. V.
A2: A N A L I S I S D E P R E C I O U N I T A R I O
A3: COTIZACION:
A4: FECHA:
A5: PARTIDA 1
A6: REV-06-feb-2021
A7: MATERIALES.
A8: DESCRIPCION | E8: UNIDAD | F8: CANT. | G8: P.U. | H8: IMPORTE | J8: MANO DE OBRA
A9: Consumible | E9: Pza | H9: =G9*F9 -> 0
E10: Pza | H10: =G10*F10 -> 0
E11: Pza | H11: =G11*F11 -> 0
E12: Pza | H12: =G12*F12 -> 0
E13: Pza | H13: =G13*F13 -> 0
E14: Pza | H14: =G14*F14 -> 0
E15: Pza | H15: =G15*F15 -> 0
E16: Pza | H16: =G16*F16 -> 0 | I16: =H16*1.455 -> 0
G17: SUBT 1 | H17: =SUM(H9:H16) -> 0
A19: MANO DE OBRA SIN INDIRECTOS | O19: HORARIOS DE TRABAJO | V19: HORAS RESULTANTES | Y19: PERSONAL PEOPUESTO
A20: PERSONAL. | E20: UNIDAD | F20: CANT. | G20: HORA NORMAL | H20: IMPORTE | I20: CANT. | J20: Hr. Extra | K20: IMPORTE | L20: CANT. | M20: Dom, ó Fest.TRIPLE | N20: IMPORTE | O20: L | P20: M | Q20: MI | R20: J | S20: V | T20: S | U20: D | V20: N | W20: D | X20: T
A21: SUPERVISOR DE SEGURIDAD CERTIFICADO | E21: hr | G21: 390.39 | H21: =F21*G21 -> 0 | J21: 358.81 | K21: =I21*J21 -> 0 | M21: 538.27 | N21: =L21*M21 -> 0 | V21: =+O21+P21+Q21+R21+S21+T21+U21-W21-X21 -> 0
A22: SUPERVISOR DE SEGURIDAD | E22: hr | G22: 317.98 | H22: =F22*G22 -> 0 | J22: 326.25 | K22: =I22*J22 -> 0 | M22: 489.37 | N22: =L22*M22 -> 0 | V22: =+O22+P22+Q22+R22+S22+T22+U22-W22-X22 -> 0 | Y22: OSWALDO Z-GABRIEL
A23: SUPERVISOR ELECTRICO | E23: hr | F23: 1 | G23: 237.68 | H23: =F23*G23 -> 237.68 | I23: 0 | J23: 358.81 | K23: =I23*J23 -> 0 | M23: 538.22 | N23: =L23*M23 -> 0 | V23: =+O23+P23+Q23+R23+S23+T23+U23-W23-X23 -> 0 | Y23: ADRIAN
A24: TECNICO DE PRUEBAS ELECTRICAS | E24: hr | G24: 317.98 | H24: =F24*G24 -> 0 | J24: 244.27 | K24: =I24*J24 -> 0 | M24: 489.37 | N24: =L24*M24 -> 0 | V24: =+O24+P24+Q24+R24+S24+T24+U24-W24-X24 -> 0 | Y24: HECTOR
A25: CABO OBRA ELECTRICA | E25: hr | G25: 310.62 | H25: =F25*G25 -> 0 | J25: 335 | K25: =I25*J25 -> 0 | M25: 436.87 | N25: =L25*M25 -> 0 | V25: =+O25+P25+Q25+R25+S25+T25+U25-W25-X25 -> 0
A26: LINIERO | E26: hr | F26: 1 | G26: 209.25 | H26: =F26*G26 -> 209.25 | I26: 0 | J26: 221.7 | K26: =I26*J26 -> 0 | M26: 437.63 | N26: =L26*M26 -> 0 | V26: =+O26+P26+Q26+R26+S26+T26+U26-W26-X26 -> 0 | Y26: JOSE J
A27: ESPECIALISTA DE MANTTO ELECTRICO | E27: hr | G27: 237.68 | H27: =F27*G27 -> 0 | J27: 277.97 | K27: =I27*J27 -> 0 | M27: 538.84 | N27: =L27*M27 -> 0 | V27: =+O27+P27+Q27+R27+S27+T27+U27-W27-X27 -> 0
A28: TECNICO EN INSTRUMENTACION | E28: hr | G28: 368.59 | H28: =F28*G28 -> 0 | J28: 221.7 | K28: =I28*J28 -> 0 | M28: 538.84 | N28: =L28*M28 -> 0 | V28: =+O28+P28+Q28+R28+S28+T28+U28-W28-X28 -> 0
A29: OFICIAL ELECTRICO/ELECTROMECANICO | E29: hr | F29: 1 | G29: 190.22 | H29: =F29*G29 -> 190.22 | I29: 0 | J29: 165 | K29: =I29*J29 -> 0 | M29: 277.56 | N29: =L29*M29 -> 0 | V29: =+O29+P29+Q29+R29+S29+T29+U29-W29-X29 -> 0
A30: ASISTENTE DE DISEÑO | E30: hr | G30: 190.25 | H30: =F30*G30 -> 0 | J30: 221.7 | K30: =I30*J30 -> 0 | M30: 297.41 | N30: =L30*M30 -> 0 | V30: =+O30+P30+Q30+R30+S30+T30+U30-W30-X30 -> 0
A31: ELECTRICISTA -B | E31: hr | F31: 1 | G31: 119.54 | H31: =F31*G31 -> 119.54 | I31: 0 | J31: 137.92 | K31: =I31*J31 -> 0 | M31: 0 | N31: =L31*M31 -> 0 | V31: =+O31+P31+Q31+R31+S31+T31+U31-W31-X31 -> 0 | Y31: GERMAN
A32: ELECTRICISTA -A | E32: hr | G32: 119.54 | H32: =F32*G32 -> 0 | J32: 137.92 | K32: =I32*J32 -> 0 | M32: 240.95 | N32: =L32*M32 -> 0 | V32: =+O32+P32+Q32+R32+S32+T32+U32-W32-X32 -> 0 | Y32: OSCAR-OSWALDO JIM
A33: AUXILIAR TECNICO | E33: hr | G33: 106.45 | H33: =F33*G33 -> 0 | J33: 137.92 | K33: =I33*J33 -> 0 | M33: 260.95 | N33: =L33*M33 -> 0 | V33: =+O33+P33+Q33+R33+S33+T33+U33-W33-X33 -> 0
A34: AYTE ELECTRICO - B | E34: hr | G34: 106.45 | H34: =F34*G34 -> 0 | J34: 122.4 | K34: =I34*J34 -> 0 | N34: =L34*M34 -> 0 | V34: =+O34+P34+Q34+R34+S34+T34+U34-W34-X34 -> 0
A35: AYTE DE ELECTR. -A | E35: hr | G35: 106.54 | H35: =F35*G35 -> 0 | J35: 122.4 | K35: =I35*J35 -> 0 | M35: 198.17 | N35: =L35*M35 -> 0 | V35: =+O35+P35+Q35+R35+S35+T35+U35-W35-X35 -> 0 | Y35: URIEL-GUILLERMO-ENRIQUE
A36: AYTE GENERAL | E36: hr | G36: 100.42 | H36: =F36*G36 -> 0 | J36: 122.4 | K36: =I36*J36 -> 0 | M36: 0 | N36: =L36*M36 -> 0 | V36: =+O36+P36+Q36+R36+S36+T36+U36-W36-X36 -> 0
A37: PROFESIONISTA | E37: hr | G37: 209.25 | H37: =F37*G37 -> 0 | J37: 406 | K37: =I37*J37 -> 0 | M37: 564.86 | N37: =L37*M37 -> 0 | V37: 0 | Y37: O.ZARCO-GABRIEL
A38: COORDINADOR DE OPERACIONES | E38: hr | G38: 0 | H38: =F38*G38 -> 0 | J38: 0 | K38: =I38*J38 -> 0 | M38: 0 | N38: =L38*M38 -> 0 | V38: =+O38+P38+Q38+R38+S38+T38+U38-W38-X38 -> 0
A39: INGENIERIA Y SOPORTE TEC. | E39: hr | G39: 339.75 | H39: =F39*G39 -> 0 | J39: 325.79 | K39: =I39*J39 -> 0 | M39: 488.68 | N39: =L39*M39 -> 0 | V39: =+O39+P39+Q39+R39+S39+T39+U39-W39-X39 -> 0
A40: INGENIERO DE SUBESTACIONES | E40: hr | G40: 339.75 | H40: =F40*G40 -> 0 | J40: 325.79 | K40: =I40*J40 -> 0 | M40: 488.68 | N40: =L40*M40 -> 0 | V40: =+O40+P40+Q40+R40+S40+T40+U40-W40-X40 -> 0
A41: INGENIERO DE PRUEBAS ELECTRICAS | E41: hr | G41: 339.75 | H41: =F41*G41 -> 0 | J41: 325.79 | K41: =I41*J41 -> 0 | M41: 488.68 | N41: =L41*M41 -> 0 | V41: =+O41+P41+Q41+R41+S41+T41+U41-W41-X41 -> 0
A42: ING. ESPECIALISTA EN PROTECCIONES | E42: hr | G42: 650 | H42: =F42*G42 -> 0 | J42: =G42*1.5 -> 975 | K42: =I42*J42 -> 0 | M42: 1747.46 | N42: =L42*M42 -> 0 | V42: =+O42+P42+Q42+R42+S42+T42+U42-W42-X42 -> 0
A43: SUPERINTENDENTE | E43: hr | H43: =F43*G43 -> 0 | J43: =G43*1.5 -> 0 | K43: =I43*J43 -> 0 | M43: =G43*2.25 -> 0 | N43: =L43*M43 -> 0 | V43: =+O43+P43+Q43+R43+S43+T43+U43-W43-X43 -> 0
F44: =V44 -> 0 | G44: SUBT 2 | H44: =SUM(H21:H43) -> 756.69 | J44: SUBT. | K44: =SUM(K21:K43) -> 0 | M44: SUBT. | N44: =SUM(N21:N43) -> 0
G45: SUMA M.O. | H45: =H44+K44+N44 -> 756.69
A46: HERRAMIENTA MENOR | G46: 1 a 10% | H46: =+H45*0.06 -> 45.4014
A49: VEHICULOS
A50: DESCRIPCION | E50: UNIDAD | F50: CANT. | G50: P.U. | H50: IMPORTE | J50: HR IDA | K50: HR RETORNO | L50: HR SITIO | M50: SUMA
A51: camioneta EXPRES VAN CARGO sin operador sin combustible | E51: HR | F51: 0 | G51: 150 | H51: =F51*G51 -> 0 | M51: =J51+K51+L51 -> 0
A52: camioneta RANGER sin operador sin combustible | E52: HR | F52: 0 | G52: 150 | H52: =F52*G52 -> 0 | M52: =J52+K52+L52 -> 0
A53: camioneta TORNADO Tornado sin operador sin combustible | E53: HR | F53: 0 | G53: 60 | H53: =F53*G53 -> 0 | M53: =J53+K53+L53 -> 0
A54: camioneta WV TRANSPORTER pasajeros | E54: HR | F54: 0 | G54: 120 | H54: =F54*G54 -> 0 | M54: =J54+K54+L54 -> 0
E55: HR | F55: 0 | H55: =F55*G55 -> 0 | M55: =J55+K55+L55 -> 0
E56: pza | F56: 0 | H56: =F56*G56 -> 0 | M56: =J56+K56+L56 -> 0
A57: Km. Recorrido (incluye conbustible y depresiación de Vehiculo | E57: KM | F57: 0 | G57: 2.5 | H57: =F57*G57 -> 0 | M57: =J57+K57+L57 -> 0
G58: SUBT 4 | H58: =SUM(H51:H57) -> 0
G59: SUMA: | H59: =H58+H45+H17 -> 756.69
A60: EQUIPO DE PRUEBA
A61: DESCRIPCION | E61: UNIDAD | F61: CANT. | G61: P.U. | H61: IMPORTE | I61: TR | K61: S.E
A62: Megger | E62: jr | G62: 2200 | H62: =(F62*G62) -> 0
A63: TTR | E63: jr | G63: 2000 | H63: =(F63*G63) -> 0
A64: Factor de Potencia de 2.5 KV | E64: jr | G64: 7000 | H64: =(F64*G64) -> 0
A65: Factor de Potencia de 10.5 KV | E65: jr | G65: 15200 | H65: =(F65*G65) -> 0
A66: Ducter | E66: jr | G66: 2200 | H66: =(F66*G66) -> 0
A67: resistencia óhmica | E67: jr | G67: 2000 | H67: =(F67*G67) -> 0
A68: hipot de 80 KV vcd | E68: jr | G68: 2500 | H68: =(F68*G68) -> 0
A69: Rigidez dieléctrica al aceite 60 kv | E69: jr | G69: 1600 | H69: =(F69*G69) -> 0
A70: Terrómetro | E70: jr | G70: 1100 | H70: =(F70*G70) -> 0
A71: Analizador de tiempos de interruptor | E71: jr | G71: 2700 | H71: =(F71*G71) -> 0
A72: Fuente de corriente para calibrador de relevadores | E72: jr | G72: 2500 | H72: =(F72*G72) -> 0
A73: Probador de relevador de Protecciones | E73: jr | G73: 13373 | H73: =(F73*G73) -> 0
... A82: Test Kit maleta de prueba G.E. | E82: jr | G82: 5800 | H82: =(F82*G82) -> 0
E83: jr | H83: =(F83*G83) -> 0
A84: Camara termografica | E84: jr | G84: 15000 | H84: =(F84*G84) -> 0
A85: Generador de Luz con combustible | E85: jr | G85: 383.5 | H85: =(F85*G85) -> 0
G86: SUBT 9 | H86: =SUM(H62:H85) -> 0
E88: 0 | H88: =+E88 -> 0 | I88: IMPUESTO | J88: INDIRECTO DISPONIBLE
F89: COSTO DIRECTO | H89: =H59+H86 -> 756.69
F90: Indirectos | G90: 0.3 | H90: =H89*G90 -> 227.007 | I90: =+M96 -> -127.57793 | J90: =H90-M96 -> 354.58493 | N90: REV-06-feb-2021
F91: Subtotal 1 | H91: =H89+H90 -> 983.697
F92: Financ. | G92: 0.06 | H92: =H91*G92 -> 59.02182 | K92: BASE IMPUESTO | L92: SIN UTILIDAD
F93: Subtotal 2 | H93: =H91+H92 -> 1042.7188 | J93: COMPRAS | K93: =+H17 -> 0
F94: Utilidad | G94: 0.2 | H94: =H93*G94 -> 208.54376 | J94: M.O | K94: =H44 -> 756.69
F95: Importe | H95: =H93+H94 -> 1251.2626 | J95: GASTOS FACTURADOS | K95: =H59-H46 -> 711.2886 | M95: IMP. 30%
F96: Materiales | H96: ='MAT (6)'!H124 -> 3465.9583 | I96: FACTOR | J96: SUMA | K96: =SUM(K93:K95) -> 1467.9786 | L96: =H95-H94 -> 1042.7188 | M96: =+(L96-K96)*0.3 -> -127.57793
B97: utilidad | F97: Total | H97: =H95+H96 -> 4717.2209 | J97: =H95/H89 -> 1.6536
B98: ime | C98: comisión | D98: total | H98: =H97/2 -> 2358.6105
B99: 0.275 | C99: 0.05 | D99: =B99+C99 -> 0.325

Sheet MAT (7)
A1: I M M E E S. A. D E C. V.
A2: A N A L I S I S D E P R E C I O U N I T A R I O
A3: COTIZACION:
A4: FECHA:
A5: PARTIDA 1
A6: REV-06-feb-2021
A7: MATERIALES.
A8: DESCRIPCION | E8: UNIDAD | F8: CANT. | G8: P.U. | H8: IMPORTE | J8: MATERIALES
A9: charola tipo escalera perfil Z para servicio pesado de 30" | E9: Pza | G9: 2540.01 | H9: =G9*F9 -> 0
A10: tapa para charola tipo escalera de 30". | E10: Pza | G10: 1001 | H10: =G10*F10 -> 0
A11: curva vertical exterior de 90° para charola tipo escalera de 30 | E11: Pza | G11: 450.5 | H11: =G11*F11 -> 0
A12: tapa para curva vertical exterior de 90° para charola tipo escalera para servicio pesado de 30" | E12: Pza | G12: 136.52 | H12: =G12*F12 -> 0
A13: curva horizontal de 90° para charola tipo escalera para servicio pesado de 30" | E13: Pza | G13: 620.97 | H13: =G13*F13 -> 0
A14: base de unicanal solido galvanizado de 4x4 | E14: Pza | G14: 382.32 | H14: =G14*F14 -> 0
A15: tornilleria galvanizada | E15: Pza | G15: 200 | H15: =G15*F15 -> 0
A16: varilla roscada galvanizada de 3 metros de largo X 1/2" | E16: Pza | G16: 70 | H16: =G16*F16 -> 0
A17: conector de charola para servicio pesado de 30 | E17: Pza | G17: 467.05 | H17: =G17*F17 -> 0
A18: zapata ponchable para cable de cobre cañon largo calibre 500 KCM, con 2 ojillos de 1/2 | E18: Pza | F18: 80 | G18: 495.41 | H18: =G18*F18 -> 39632.8
A19: manga termocontractil para nivel de aislamiento de 600 V, en calibre 500 KCM. | E19: Pza | G19: 212.43 | H19: =G19*F19 -> 0
A20: tornillo tropicalizado de 1/2" con 2" de largo | E20: Pza | G20: 15 | H20: =G20*F20 -> 0
A21: tornillo tropicalizado de 1/2" con 4" de largo | E21: Pza | G21: 15 | H21: =G21*F21 -> 0
A22: sistema corta fuego con lana mineral y compuesto SF-ONE. | E22: Pza | G22: 698.25 | H22: =G22*F22 -> 0
A23: Materiales consumibles | E23: PZA | G23: 500 | H23: =G23*F23 -> 0
A24: cuellos de lona flexibles en gargantas primarias de generador electrico | E24: Pza | G24: 160.08 | H24: =G24*F24 -> 0
A25: cable de cobre THW calibre 12 AWG | E25: mt | G25: 12.63 | H25: =G25*F25 -> 0 | L25: NOTA: CONSIDERAR LA JORNADA DE 8.0 HORAS, AUNQUE EN IMMEE SE TRABAJE JORNADA LARGA CONVENIDA, Y DOMINGO DESCANSO
A26: tapones para unicanal de 4x4 y varilla roscada | E26: Pza | G26: 27.6 | H26: =G26*F26 -> 0
A27: tapones para esparrago | E27: Pza | G27: 70.34 | H27: =G27*F27 -> 0
A28: cable de cobre 500 mts THW LS calibre 500 MCM | E28: CARRETE | G28: 897.84 | H28: =G28*F28 -> 0
A29: Renta de pochadora | E29: Pza | F29: 1 | G29: 16000 | H29: =G29*F29 -> 16000
G30: SUBT 1 | H30: =SUM(H9:H29) -> 55632.8
A32: MANO DE OBRA SIN INDIRECTOS | O32: HORARIOS DE TRABAJO | V32: HORAS RESULTANTES | Y32: PERSONAL PEOPUESTO
A33: PERSONAL. | E33: UNIDAD | F33: CANT. | G33: HORA NORMAL | H33: IMPORTE | I33: CANT. | J33: Hr. Extra | K33: IMPORTE | L33: CANT. | M33: Dom, ó Fest.TRIPLE | N33: IMPORTE | O33: L | P33: M | Q33: MI | R33: J | S33: V | T33: S | U33: D | V33: N | W33: D | X33: T
A34: SUPERVISOR DE SEGURIDAD CERTIFICADO | E34: hr | G34: 390.39 | H34: =F34*G34 -> 0 | J34: 358.81 | K34: =I34*J34 -> 0 | M34: 538.27 | N34: =L34*M34 -> 0 | V34: =+O34+P34+Q34+R34+S34+T34+U34-W34-X34 -> 0
A35: SUPERVISOR DE SEGURIDAD | E35: hr | G35: 243.45 | H35: =F35*G35 -> 0 | J35: 211.59 | K35: =I35*J35 -> 0 | M35: 317.39 | N35: =L35*M35 -> 0 | V35: =+O35+P35+Q35+R35+S35+T35+U35-W35-X35 -> 0 | Y35: OSWALDO Z-GABRIEL
A36: SUPERVISOR ELECTRICO | E36: hr | G36: 390.39 | H36: =F36*G36 -> 0 | J36: 358.81 | K36: =I36*J36 -> 0 | M36: 538.22 | N36: =L36*M36 -> 0 | V36: =+O36+P36+Q36+R36+S36+T36+U36-W36-X36 -> 0 | Y36: ADRIAN
A37: TECNICO DE PRUEBAS ELECTRICAS | E37: hr | G37: 231.67 | H37: =F37*G37 -> 0 | J37: 197.63 | K37: =I37*J37 -> 0 | M37: 296.45 | N37: =L37*M37 -> 0 | V37: =+O37+P37+Q37+R37+S37+T37+U37-W37-X37 -> 0 | Y37: HECTOR
A38: CABO OBRA ELECTRICA | E38: hr | G38: 310.62 | H38: =F38*G38 -> 0 | J38: 291.24 | K38: =I38*J38 -> 0 | M38: 436.87 | N38: =L38*M38 -> 0 | V38: =+O38+P38+Q38+R38+S38+T38+U38-W38-X38 -> 0
A39: LINIERO | E39: hr | G39: 310.62 | H39: =F39*G39 -> 0 | J39: 291.24 | K39: =I39*J39 -> 0 | M39: 436.87 | N39: =L39*M39 -> 0 | V39: =+O39+P39+Q39+R39+S39+T39+U39-W39-X39 -> 0 | Y39: JOSE J
A40: ESPECIALISTA DE MANTTO ELECTRICO | E40: hr | H40: =F40*G40 -> 0 | J40: 0 | K40: =I40*J40 -> 0 | M40: 0 | N40: =L40*M40 -> 0 | V40: =+O40+P40+Q40+R40+S40+T40+U40-W40-X40 -> 0
A41: TECNICO EN INSTRUMENTACION | E41: hr | G41: 199.6 | H41: =F41*G41 -> 0 | J41: 159.6 | K41: =I41*J41 -> 0 | M41: 239.4 | N41: =L41*M41 -> 0 | V41: =+O41+P41+Q41+R41+S41+T41+U41-W41-X41 -> 0
A42: OFICIAL ELECTRICO/ELECTROMECANICO | E42: hr | G42: 199.6 | H42: =F42*G42 -> 0 | J42: 159.6 | K42: =I42*J42 -> 0 | M42: 239.4 | N42: =L42*M42 -> 0 | V42: =+O42+P42+Q42+R42+S42+T42+U42-W42-X42 -> 0
A43: ASISTENTE DE DISEÑO | E43: hr | G43: 199.6 | H43: =F43*G43 -> 0 | J43: 159.6 | K43: =I43*J43 -> 0 | M43: 239.4 | N43: =L43*M43 -> 0 | V43: =+O43+P43+Q43+R43+S43+T43+U43-W43-X43 -> 0
A44: ELECTRICISTA -B | E44: hr | G44: 211.15 | H44: =F44*G44 -> 0 | J44: 173.29 | K44: =I44*J44 -> 0 | M44: 259.94 | N44: =L44*M44 -> 0 | V44: =+O44+P44+Q44+R44+S44+T44+U44-W44-X44 -> 0 | Y44: GERMAN
A45: ELECTRICISTA -A | E45: hr | G45: 199.6 | H45: =F45*G45 -> 0 | J45: 159.6 | K45: =I45*J45 -> 0 | M45: 239.4 | N45: =L45*M45 -> 0 | V45: =+O45+P45+Q45+R45+S45+T45+U45-W45-X45 -> 0 | Y45: OSCAR-OSWALDO JIM
A46: AUXILIAR TECNICO | E46: hr | G46: 187.81 | H46: =F46*G46 -> 0 | J46: 145.62 | K46: =I46*J46 -> 0 | M46: 218.43 | N46: =L46*M46 -> 0 | V46: =+O46+P46+Q46+R46+S46+T46+U46-W46-X46 -> 0
A47: AYTE ELECTRICO - B | E47: hr | H47: =F47*G47 -> 0 | J47: 0 | K47: =I47*J47 -> 0 | N47: =L47*M47 -> 0 | V47: =+O47+P47+Q47+R47+S47+T47+U47-W47-X47 -> 0
A48: AYTE DE ELECTR. -A | E48: hr | G48: 187.81 | H48: =F48*G48 -> 0 | J48: 145.62 | K48: =I48*J48 -> 0 | M48: 218.43 | N48: =L48*M48 -> 0 | V48: =+O48+P48+Q48+R48+S48+T48+U48-W48-X48 -> 0 | Y48: URIEL-GUILLERMO-ENRIQUE
A49: AYTE GENERAL | E49: hr | G49: 94.81 | H49: =F49*G49 -> 0 | J49: 145.62 | K49: =I49*J49 -> 0 | M49: 218.43 | N49: =L49*M49 -> 0 | V49: =+O49+P49+Q49+R49+S49+T49+U49-W49-X49 -> 0
A50: PROFESIONISTA | E50: hr | G50: 243.45 | H50: =F50*G50 -> 0 | J50: 211.59 | K50: =I50*J50 -> 0 | M50: 317.39 | N50: =L50*M50 -> 0 | V50: 0 | Y50: O.ZARCO-GABRIEL
A51: COORDINADOR DE OPERACIONES | E51: hr | G51: 339.75 | H51: =F51*G51 -> 0 | J51: 325.79 | K51: =I51*J51 -> 0 | M51: 488.68 | N51: =L51*M51 -> 0 | V51: =+O51+P51+Q51+R51+S51+T51+U51-W51-X51 -> 0
A52: INGENIERIA Y SOPORTE TEC. | E52: hr | G52: 339.75 | H52: =F52*G52 -> 0 | J52: 325.79 | K52: =I52*J52 -> 0 | M52: 488.68 | N52: =L52*M52 -> 0 | V52: =+O52+P52+Q52+R52+S52+T52+U52-W52-X52 -> 0
A53: INGENIERO DE SUBESTACIONES | E53: hr | G53: 339.75 | H53: =F53*G53 -> 0 | J53: 325.79 | K53: =I53*J53 -> 0 | M53: 488.68 | N53: =L53*M53 -> 0 | V53: =+O53+P53+Q53+R53+S53+T53+U53-W53-X53 -> 0
A54: INGENIERO DE PRUEBAS ELECTRICAS | E54: hr | G54: 339.75 | H54: =F54*G54 -> 0 | J54: 325.79 | K54: =I54*J54 -> 0 | M54: 488.68 | N54: =L54*M54 -> 0 | V54: =+O54+P54+Q54+R54+S54+T54+U54-W54-X54 -> 0
A55: ING. ESPECIALISTA EN PROTECCIONES | E55: hr | G55: 1004.49 | H55: =F55*G55 -> 0 | J55: 1164.98 | K55: =I55*J55 -> 0 | M55: 1747.46 | N55: =L55*M55 -> 0 | V55: =+O55+P55+Q55+R55+S55+T55+U55-W55-X55 -> 0
A56: SUPERINTENDENTE | E56: hr | H56: =F56*G56 -> 0 | J56: =G56*1.5 -> 0 | K56: =I56*J56 -> 0 | M56: =G56*2.25 -> 0 | N56: =L56*M56 -> 0 | V56: =+O56+P56+Q56+R56+S56+T56+U56-W56-X56 -> 0
F57: =V57 -> 0 | G57: SUBT 2 | H57: =SUM(H34:H56) -> 0 | J57: SUBT. | K57: =SUM(K34:K56) -> 0 | M57: SUBT. | N57: =SUM(N34:N56) -> 0
G58: SUMA M.O. | H58: =H57+K57+N57 -> 0
A59: HERRAMIENTA MENOR | G59: 1 a 10% | H59: =+H58*0.06 -> 0
H60: =+H58+H59 -> 0
A61: VEHICULOS
A62: DESCRIPCION | E62: UNIDAD | F62: CANT. | G62: P.U. | H62: IMPORTE | J62: HR IDA | K62: HR RETORNO | L62: HR SITIO | M62: SUMA
A63: camioneta EXPRES VAN CARGO sin operador sin combustible | E63: HR | F63: 0 | G63: 170 | H63: =F63*G63 -> 0 | M63: =J63+K63+L63 -> 0
A64: camioneta RANGER sin operador sin combustible | E64: HR | F64: 2 | G64: 180 | H64: =F64*G64 -> 360 | M64: =J64+K64+L64 -> 0
A65: camioneta TORNADO Tornado sin operador sin combustible | E65: HR | F65: 0 | G65: 80 | H65: =F65*G65 -> 0 | M65: =J65+K65+L65 -> 0
A66: camioneta WV TRANSPORTER pasajeros | E66: HR | F66: 0 | G66: 150 | H66: =F66*G66 -> 0 | M66: =J66+K66+L66 -> 0
E67: HR | F67: 0 | H67: =F67*G67 -> 0 | M67: =J67+K67+L67 -> 0
E68: pza | F68: 0 | H68: =F68*G68 -> 0 | M68: =J68+K68+L68 -> 0
A69: Km. Recorrido (incluye conbustible y depresiación de Vehiculo | E69: KM | F69: 0 | G69: 2.5 | H69: =F69*G69 -> 0 | M69: =J69+K69+L69 -> 0
G70: SUBT 4 | H70: =SUM(H63:H69) -> 360
A71: COMBUSTIBLE
A72: DESCRIPCION | E72: UNIDAD | F72: CANT. | G72: P.U. | H72: IMPORTE | J72: KM IDA | K72: KM RETORNO | L72: KM SITIO | M72: SUMA
A73: GASOLINA MAGNA | E73: LT | F73: 40 | G73: 23 | H73: =F73*G73 -> 920 | M73: =J73+K73+L73 -> 0
A74: DIESEL | E74: LT | F74: 0 | G74: 24 | H74: =F74*G74 -> 0 | M74: =J74+K74+L74 -> 0
G75: SUBT 5 | H75: =SUM(H73:H74) -> 920
A76: CASETAS
A77: DESCRIPCION | E77: UNIDAD | F77: CANT. | G77: P.U. | H77: IMPORTE
A78: Camion | E78: CASETA | F78: 0 | G78: 65 | H78: =F78*G78 -> 0
A79: camioneta pick up | E79: CASETA | F79: 4 | G79: 250 | H79: =F79*G79 -> 1000
G80: SUBT 6 | H80: =SUM(H78:H79) -> 1000
A81: VIATICOS
A82: ALIMENTOS
A83: DESCRIPCION | E83: UNIDAD | F83: CANT. | G83: P.U. | H83: IMPORTE
A84: CONSUMO DE ALIMENTOS | E84: Pza | F84: 8 | G84: 650 | H84: =F84*G84 -> 5200
H85: =SUM(H84) -> 5200
A86: HOSPEDAJE
A87: DESCRIPCION | E87: UNIDAD | F87: CANT. | G87: P.U. | H87: IMPORTE
A88: HOTEL | E88: NOCHES | F88: 4 | G88: 1100 | H88: =F88*G88 -> 4400
G89: SUBT 8 | H89: =SUM(H88) -> 4400
G90: SUMA: | H90: =H70+H75+H80+H85+H89+H59+H58+H30 -> 67512.8
A91: EQUIPO DE PRUEBA
A92: DESCRIPCION | E92: UNIDAD | F92: CANT. | G92: P.U. | H92: IMPORTE | I92: TR | K92: S.E
A93: Megger | E93: jr | G93: 2200 | H93: =(F93*G93) -> 0
A94: TTR | E94: jr | G94: 2000 | H94: =(F94*G94) -> 0
A95: Factor de Potencia de 2.5 KV | E95: jr | G95: 7000 | H95: =(F95*G95) -> 0
A96: Factor de Potencia de 10.5 KV | E96: jr | G96: 15200 | H96: =(F96*G96) -> 0
A97: Ducter | E97: jr | G97: 2200 | H97: =(F97*G97) -> 0
A98: resistencia óhmica | E98: jr | G98: 2000 | H98: =(F98*G98) -> 0
A99: hipot de 80 KV vcd | E99: jr | G99: 2500 | H99: =(F99*G99) -> 0
A100: Rigidez dieléctrica al aceite 60 kv | E100: jr | G100: 1600 | H100: =(F100*G100) -> 0
A101: Terrómetro | E101: jr | G101: 1100 | H101: =(F101*G101) -> 0
...

Sheet M0  (7)
A1: I M M E E S. A. D E C. V.
A2: A N A L I S I S D E P R E C I O U N I T A R I O
A3: COTIZACION:
A4: FECHA:
A5: PARTIDA 1
A6: REV-06-feb-2021
A7: MATERIALES.
A8: DESCRIPCION | E8: UNIDAD | F8: CANT. | G8: P.U. | H8: IMPORTE | J8: MANO DE OBRA
A9: Consumible | E9: Pza | H9: =G9*F9 -> 0
E10: Pza | H10: =G10*F10 -> 0
E11: Pza | H11: =G11*F11 -> 0
E12: Pza | H12: =G12*F12 -> 0
E13: Pza | H13: =G13*F13 -> 0
E14: Pza | H14: =G14*F14 -> 0
E15: Pza | H15: =G15*F15 -> 0
E16: Pza | H16: =G16*F16 -> 0 | I16: =H16*1.455 -> 0
G17: SUBT 1 | H17: =SUM(H9:H16) -> 0
A19: MANO DE OBRA SIN INDIRECTOS | O19: HORARIOS DE TRABAJO | V19: HORAS RESULTANTES | Y19: PERSONAL PEOPUESTO
A20: PERSONAL. | E20: UNIDAD | F20: CANT. | G20: HORA NORMAL | H20: IMPORTE | I20: CANT. | J20: Hr. Extra | K20: IMPORTE | L20: CANT. | M20: Dom, ó Fest.TRIPLE | N20: IMPORTE | O20: L | P20: M | Q20: MI | R20: J | S20: V | T20: S | U20: D | V20: N | W20: D | X20: T
A21: SUPERVISOR DE SEGURIDAD CERTIFICADO | E21: hr | G21: 390.39 | H21: =F21*G21 -> 0 | J21: 358.81 | K21: =I21*J21 -> 0 | M21: 538.27 | N21: =L21*M21 -> 0 | V21: =+O21+P21+Q21+R21+S21+T21+U21-W21-X21 -> 0
A22: SUPERVISOR DE SEGURIDAD | E22: hr | F22: 16 | G22: 317.98 | H22: =F22*G22 -> 5087.68 | J22: 326.25 | K22: =I22*J22 -> 0 | M22: 489.37 | N22: =L22*M22 -> 0 | V22: =+O22+P22+Q22+R22+S22+T22+U22-W22-X22 -> 0 | Y22: OSWALDO Z-GABRIEL
A23: SUPERVISOR ELECTRICO | E23: hr | F23: 9.5 | G23: 237.68 | H23: =F23*G23 -> 2257.96 | I23: 4 | J23: 358.81 | K23: =I23*J23 -> 1435.24 | M23: 538.22 | N23: =L23*M23 -> 0 | V23: =+O23+P23+Q23+R23+S23+T23+U23-W23-X23 -> 0 | Y23: ADRIAN
A24: TECNICO DE PRUEBAS ELECTRICAS | E24: hr | G24: 317.98 | H24: =F24*G24 -> 0 | J24: 244.27 | K24: =I24*J24 -> 0 | M24: 489.37 | N24: =L24*M24 -> 0 | V24: =+O24+P24+Q24+R24+S24+T24+U24-W24-X24 -> 0 | Y24: HECTOR
A25: CABO OBRA ELECTRICA | E25: hr | G25: 310.62 | H25: =F25*G25 -> 0 | J25: 335 | K25: =I25*J25 -> 0 | M25: 436.87 | N25: =L25*M25 -> 0 | V25: =+O25+P25+Q25+R25+S25+T25+U25-W25-X25 -> 0
A26: LINIERO | E26: hr | F26: 19 | G26: 209.25 | H26: =F26*G26 -> 3975.75 | I26: 4 | J26: 221.7 | K26: =I26*J26 -> 886.8 | M26: 437.63 | N26: =L26*M26 -> 0 | V26: =+O26+P26+Q26+R26+S26+T26+U26-W26-X26 -> 0 | Y26: JOSE J
A27: ESPECIALISTA DE MANTTO ELECTRICO | E27: hr | G27: 237.68 | H27: =F27*G27 -> 0 | J27: 277.97 | K27: =I27*J27 -> 0 | M27: 538.84 | N27: =L27*M27 -> 0 | V27: =+O27+P27+Q27+R27+S27+T27+U27-W27-X27 -> 0
A28: TECNICO EN INSTRUMENTACION | E28: hr | G28: 368.59 | H28: =F28*G28 -> 0 | J28: 221.7 | K28: =I28*J28 -> 0 | M28: 538.84 | N28: =L28*M28 -> 0 | V28: =+O28+P28+Q28+R28+S28+T28+U28-W28-X28 -> 0
A29: OFICIAL ELECTRICO/ELECTROMECANICO | E29: hr | F29: 19 | G29: 190.22 | H29: =F29*G29 -> 3614.18 | I29: 4 | J29: 165 | K29: =I29*J29 -> 660 | M29: 277.56 | N29: =L29*M29 -> 0 | V29: =+O29+P29+Q29+R29+S29+T29+U29-W29-X29 -> 0
A30: ASISTENTE DE DISEÑO | E30: hr | G30: 190.25 | H30: =F30*G30 -> 0 | J30: 221.7 | K30: =I30*J30 -> 0 | M30: 297.41 | N30: =L30*M30 -> 0 | V30: =+O30+P30+Q30+R30+S30+T30+U30-W30-X30 -> 0
A31: ELECTRICISTA -B | E31: hr | F31: 9.5 | G31: 119.54 | H31: =F31*G31 -> 1135.63 | I31: 4 | J31: 137.92 | K31: =I31*J31 -> 551.68 | M31: 0 | N31: =L31*M31 -> 0 | V31: =+O31+P31+Q31+R31+S31+T31+U31-W31-X31 -> 0 | Y31: GERMAN
A32: ELECTRICISTA -A | E32: hr | G32: 119.54 | H32: =F32*G32 -> 0 | J32: 137.92 | K32: =I32*J32 -> 0 | M32: 240.95 | N32: =L32*M32 -> 0 | V32: =+O32+P32+Q32+R32+S32+T32+U32-W32-X32 -> 0 | Y32: OSCAR-OSWALDO JIM
A33: AUXILIAR TECNICO | E33: hr | G33: 106.45 | H33: =F33*G33 -> 0 | J33: 137.92 | K33: =I33*J33 -> 0 | M33: 260.95 | N33: =L33*M33 -> 0 | V33: =+O33+P33+Q33+R33+S33+T33+U33-W33-X33 -> 0
A34: AYTE ELECTRICO - B | E34: hr | G34: 106.45 | H34: =F34*G34 -> 0 | J34: 122.4 | K34: =I34*J34 -> 0 | N34: =L34*M34 -> 0 | V34: =+O34+P34+Q34+R34+S34+T34+U34-W34-X34 -> 0
A35: AYTE DE ELECTR. -A | E35: hr | G35: 106.54 | H35: =F35*G35 -> 0 | J35: 122.4 | K35: =I35*J35 -> 0 | M35: 198.17 | N35: =L35*M35 -> 0 | V35: =+O35+P35+Q35+R35+S35+T35+U35-W35-X35 -> 0 | Y35: URIEL-GUILLERMO-ENRIQUE
A36: AYTE GENERAL | E36: hr | G36: 100.42 | H36: =F36*G36 -> 0 | J36: 122.4 | K36: =I36*J36 -> 0 | M36: 0 | N36: =L36*M36 -> 0 | V36: =+O36+P36+Q36+R36+S36+T36+U36-W36-X36 -> 0
A37: PROFESIONISTA | E37: hr | G37: 209.25 | H37: =F37*G37 -> 0 | J37: 406 | K37: =I37*J37 -> 0 | M37: 564.86 | N37: =L37*M37 -> 0 | V37: 0 | Y37: O.ZARCO-GABRIEL
A38: COORDINADOR DE OPERACIONES | E38: hr | G38: 0 | H38: =F38*G38 -> 0 | J38: 0 | K38: =I38*J38 -> 0 | M38: 0 | N38: =L38*M38 -> 0 | V38: =+O38+P38+Q38+R38+S38+T38+U38-W38-X38 -> 0
A39: INGENIERIA Y SOPORTE TEC. | E39: hr | G39: 339.75 | H39: =F39*G39 -> 0 | J39: 325.79 | K39: =I39*J39 -> 0 | M39: 488.68 | N39: =L39*M39 -> 0 | V39: =+O39+P39+Q39+R39+S39+T39+U39-W39-X39 -> 0
A40: INGENIERO DE SUBESTACIONES | E40: hr | G40: 339.75 | H40: =F40*G40 -> 0 | J40: 325.79 | K40: =I40*J40 -> 0 | M40: 488.68 | N40: =L40*M40 -> 0 | V40: =+O40+P40+Q40+R40+S40+T40+U40-W40-X40 -> 0
A41: INGENIERO DE PRUEBAS ELECTRICAS | E41: hr | G41: 339.75 | H41: =F41*G41 -> 0 | J41: 325.79 | K41: =I41*J41 -> 0 | M41: 488.68 | N41: =L41*M41 -> 0 | V41: =+O41+P41+Q41+R41+S41+T41+U41-W41-X41 -> 0
A42: ING. ESPECIALISTA EN PROTECCIONES | E42: hr | G42: 650 | H42: =F42*G42 -> 0 | J42: =G42*1.5 -> 975 | K42: =I42*J42 -> 0 | M42: 1747.46 | N42: =L42*M42 -> 0 | V42: =+O42+P42+Q42+R42+S42+T42+U42-W42-X42 -> 0
A43: SUPERINTENDENTE | E43: hr | H43: =F43*G43 -> 0 | J43: =G43*1.5 -> 0 | K43: =I43*J43 -> 0 | M43: =G43*2.25 -> 0 | N43: =L43*M43 -> 0 | V43: =+O43+P43+Q43+R43+S43+T43+U43-W43-X43 -> 0
F44: =V44 -> 0 | G44: SUBT 2 | H44: =SUM(H21:H43) -> 16071.2 | J44: SUBT. | K44: =SUM(K21:K43) -> 3533.72 | M44: SUBT. | N44: =SUM(N21:N43) -> 0
G45: SUMA M.O. | H45: =H44+K44+N44 -> 19604.92
A46: HERRAMIENTA MENOR | G46: 1 a 10% | H46: =+H45*0.06 -> 1176.2952
A49: VEHICULOS
A50: DESCRIPCION | E50: UNIDAD | F50: CANT. | G50: P.U. | H50: IMPORTE | J50: HR IDA | K50: HR RETORNO | L50: HR SITIO | M50: SUMA
A51: camioneta EXPRES VAN CARGO sin operador sin combustible | E51: HR | F51: 0 | G51: 150 | H51: =F51*G51 -> 0 | M51: =J51+K51+L51 -> 0
A52: camioneta RANGER sin operador sin combustible | E52: HR | F52: 0 | G52: 150 | H52: =F52*G52 -> 0 | M52: =J52+K52+L52 -> 0
A53: camioneta TORNADO Tornado sin operador sin combustible | E53: HR | F53: 0 | G53: 60 | H53: =F53*G53 -> 0 | M53: =J53+K53+L53 -> 0
A54: camioneta WV TRANSPORTER pasajeros | E54: HR | F54: 0 | G54: 120 | H54: =F54*G54 -> 0 | M54: =J54+K54+L54 -> 0
E55: HR | F55: 0 | H55: =F55*G55 -> 0 | M55: =J55+K55+L55 -> 0
E56: pza | F56: 0 | H56: =F56*G56 -> 0 | M56: =J56+K56+L56 -> 0
A57: Km. Recorrido (incluye conbustible y depresiación de Vehiculo | E57: KM | F57: 0 | G57: 2.5 | H57: =F57*G57 -> 0 | M57: =J57+K57+L57 -> 0
G58: SUBT 4 | H58: =SUM(H51:H57) -> 0
G59: SUMA: | H59: =H58+H45+H17 -> 19604.92
A60: EQUIPO DE PRUEBA
A61: DESCRIPCION | E61: UNIDAD | F61: CANT. | G61: P.U. | H61: IMPORTE | I61: TR | K61: S.E
A62: Megger | E62: jr | G62: 2200 | H62: =(F62*G62) -> 0
A63: TTR | E63: jr | G63: 2000 | H63: =(F63*G63) -> 0
A64: Factor de Potencia de 2.5 KV | E64: jr | G64: 7000 | H64: =(F64*G64) -> 0
A65: Factor de Potencia de 10.5 KV | E65: jr | G65: 15200 | H65: =(F65*G65) -> 0
A66: Ducter | E66: jr | G66: 2200 | H66: =(F66*G66) -> 0
A67: resistencia óhmica | E67: jr | G67: 2000 | H67: =(F67*G67) -> 0
A68: hipot de 80 KV vcd | E68: jr | G68: 2500 | H68: =(F68*G68) -> 0
A69: Rigidez dieléctrica al aceite 60 kv | E69: jr | G69: 1600 | H69: =(F69*G69) -> 0
A70: Terrómetro | E70: jr | G70: 1100 | H70: =(F70*G70) -> 0
A71: Analizador de tiempos de interruptor | E71: jr | G71: 2700 | H71: =(F71*G71) -> 0
A72: Fuente de corriente para calibrador de relevadores | E72: jr | G72: 2500 | H72: =(F72*G72) -> 0
A73: Probador de relevador de Protecciones | E73: jr | G73: 13373 | H73: =(F73*G73) -> 0
... A82: Test Kit maleta de prueba G.E. | E82: jr | G82: 5800 | H82: =(F82*G82) -> 0
E83: jr | H83: =(F83*G83) -> 0
A84: Camara termografica | E84: jr | G84: 15000 | H84: =(F84*G84) -> 0
A85: Generador de Luz con combustible | E85: jr | G85: 383.5 | H85: =(F85*G85) -> 0
G86: SUBT 9 | H86: =SUM(H62:H85) -> 0
E88: 0 | H88: =+E88 -> 0 | I88: IMPUESTO | J88: INDIRECTO DISPONIBLE
F89: COSTO DIRECTO | H89: =H59+H86 -> 19604.92
F90: Indirectos | G90: 0.3 | H90: =H89*G90 -> 5881.476 | I90: =+M96 -> -2245.2735 | J90: =H90-M96 -> 8126.7495 | N90: REV-06-feb-2021
F91: Subtotal 1 | H91: =H89+H90 -> 25486.396
F92: Financ. | G92: 0.06 | H92: =H91*G92 -> 1529.1838 | K92: BASE IMPUESTO | L92: SIN UTILIDAD
F93: Subtotal 2 | H93: =H91+H92 -> 27015.58 | J93: COMPRAS | K93: =+H17 -> 0
F94: Utilidad | G94: 0.275 | H94: =H93*G94 -> 7429.2844 | J94: M.O | K94: =H44 -> 16071.2
F95: Importe | H95: =H93+H94 -> 34444.864 | J95: GASTOS FACTURADOS | K95: =H59-H46 -> 18428.625 | M95: IMP. 30%
F96: Materiales | H96: ='MAT (7)'!H124 -> 94463.91 | I96: FACTOR | J96: SUMA | K96: =SUM(K93:K95) -> 34499.825 | L96: =H95-H94 -> 27015.58 | M96: =+(L96-K96)*0.3 -> -2245.2735
B97: utilidad | F97: Total | H97: =H95+H96 -> 128908.77 | J97: =H95/H89 -> 1.75695
B98: ime | C98: comisión | D98: total | H98: =H97/80 -> 1611.3597
B99: 0.275 | C99: 0.05 | D99: =B99+C99 -> 0.325

Sheet MAT (8)
A1: I M M E E S. A. D E C. V.
A2: A N A L I S I S D E P R E C I O U N I T A R I O
A3: COTIZACION:
A4: FECHA:
A5: PARTIDA 1
A6: REV-06-feb-2021
A7: MATERIALES.
A8: DESCRIPCION | E8: UNIDAD | F8: CANT. | G8: P.U. | H8: IMPORTE | J8: MATERIALES
A9: charola tipo escalera perfil Z para servicio pesado de 30" | E9: Pza | G9: 2540.01 | H9: =G9*F9 -> 0
A10: tapa para charola tipo escalera de 30". | E10: Pza | G10: 1001 | H10: =G10*F10 -> 0
A11: curva vertical exterior de 90° para charola tipo escalera de 30 | E11: Pza | G11: 450.5 | H11: =G11*F11 -> 0
A12: tapa para curva vertical exterior de 90° para charola tipo escalera para servicio pesado de 30" | E12: Pza | G12: 136.52 | H12: =G12*F12 -> 0
A13: curva horizontal de 90° para charola tipo escalera para servicio pesado de 30" | E13: Pza | G13: 620.97 | H13: =G13*F13 -> 0
A14: base de unicanal solido galvanizado de 4x4 | E14: Pza | G14: 382.32 | H14: =G14*F14 -> 0
A15: tornilleria galvanizada | E15: Pza | G15: 200 | H15: =G15*F15 -> 0
A16: varilla roscada galvanizada de 3 metros de largo X 1/2" | E16: Pza | G16: 70 | H16: =G16*F16 -> 0
A17: conector de charola para servicio pesado de 30 | E17: Pza | G17: 467.05 | H17: =G17*F17 -> 0
A18: zapata ponchable para cable de cobre cañon largo calibre 500 KCM, con 2 ojillos de 1/2 | E18: Pza | G18: 495.41 | H18: =G18*F18 -> 0
A19: manga termocontractil para nivel de aislamiento de 600 V, en calibre 500 KCM. | E19: Pza | F19: 4 | G19: 212.43 | H19: =G19*F19 -> 849.72
A20: tornillo tropicalizado de 1/2" con 2" de largo | E20: Pza | G20: 15 | H20: =G20*F20 -> 0
A21: tornillo tropicalizado de 1/2" con 4" de largo | E21: Pza | G21: 15 | H21: =G21*F21 -> 0
A22: sistema corta fuego con lana mineral y compuesto SF-ONE. | E22: Pza | G22: 698.25 | H22: =G22*F22 -> 0
A23: Materiales consumibles | E23: PZA | G23: 500 | H23: =G23*F23 -> 0
A24: cuellos de lona flexibles en gargantas primarias de generador electrico | E24: Pza | G24: 160.08 | H24: =G24*F24 -> 0
A25: cable de cobre THW calibre 12 AWG | E25: mt | G25: 12.63 | H25: =G25*F25 -> 0 | L25: NOTA: CONSIDERAR LA JORNADA DE 8.0 HORAS, AUNQUE EN IMMEE SE TRABAJE JORNADA LARGA CONVENIDA, Y DOMINGO DESCANSO
A26: tapones para unicanal de 4x4 y varilla roscada | E26: Pza | G26: 27.6 | H26: =G26*F26 -> 0
A27: tapones para esparrago | E27: Pza | G27: 70.34 | H27: =G27*F27 -> 0
A28: cable de cobre 500 mts THW LS calibre 500 MCM | E28: CARRETE | G28: 897.84 | H28: =G28*F28 -> 0
A29: Renta de una plataforma de elevacion | E29: Pza | G29: 48000 | H29: =G29*F29 -> 0 | I29: =H29*1.455 -> 0
G30: SUBT 1 | H30: =SUM(H9:H29) -> 849.72
A32: MANO DE OBRA SIN INDIRECTOS | O32: HORARIOS DE TRABAJO | V32: HORAS RESULTANTES | Y32: PERSONAL PEOPUESTO
A33: PERSONAL. | E33: UNIDAD | F33: CANT. | G33: HORA NORMAL | H33: IMPORTE | I33: CANT. | J33: Hr. Extra | K33: IMPORTE | L33: CANT. | M33: Dom, ó Fest.TRIPLE | N33: IMPORTE | O33: L | P33: M | Q33: MI | R33: J | S33: V | T33: S | U33: D | V33: N | W33: D | X33: T
A34: SUPERVISOR DE SEGURIDAD CERTIFICADO | E34: hr | G34: 390.39 | H34: =F34*G34 -> 0 | J34: 358.81 | K34: =I34*J34 -> 0 | M34: 538.27 | N34: =L34*M34 -> 0 | V34: =+O34+P34+Q34+R34+S34+T34+U34-W34-X34 -> 0
A35: SUPERVISOR DE SEGURIDAD | E35: hr | G35: 243.45 | H35: =F35*G35 -> 0 | J35: 211.59 | K35: =I35*J35 -> 0 | M35: 317.39 | N35: =L35*M35 -> 0 | V35: =+O35+P35+Q35+R35+S35+T35+U35-W35-X35 -> 0 | Y35: OSWALDO Z-GABRIEL
A36: SUPERVISOR ELECTRICO | E36: hr | G36: 390.39 | H36: =F36*G36 -> 0 | J36: 358.81 | K36: =I36*J36 -> 0 | M36: 538.22 | N36: =L36*M36 -> 0 | V36: =+O36+P36+Q36+R36+S36+T36+U36-W36-X36 -> 0 | Y36: ADRIAN
A37: TECNICO DE PRUEBAS ELECTRICAS | E37: hr | G37: 231.67 | H37: =F37*G37 -> 0 | J37: 197.63 | K37: =I37*J37 -> 0 | M37: 296.45 | N37: =L37*M37 -> 0 | V37: =+O37+P37+Q37+R37+S37+T37+U37-W37-X37 -> 0 | Y37: HECTOR
A38: CABO OBRA ELECTRICA | E38: hr | G38: 310.62 | H38: =F38*G38 -> 0 | J38: 291.24 | K38: =I38*J38 -> 0 | M38: 436.87 | N38: =L38*M38 -> 0 | V38: =+O38+P38+Q38+R38+S38+T38+U38-W38-X38 -> 0
A39: LINIERO | E39: hr | G39: 310.62 | H39: =F39*G39 -> 0 | J39: 291.24 | K39: =I39*J39 -> 0 | M39: 436.87 | N39: =L39*M39 -> 0 | V39: =+O39+P39+Q39+R39+S39+T39+U39-W39-X39 -> 0 | Y39: JOSE J
A40: ESPECIALISTA DE MANTTO ELECTRICO | E40: hr | H40: =F40*G40 -> 0 | J40: 0 | K40: =I40*J40 -> 0 | M40: 0 | N40: =L40*M40 -> 0 | V40: =+O40+P40+Q40+R40+S40+T40+U40-W40-X40 -> 0
A41: TECNICO EN INSTRUMENTACION | E41: hr | G41: 199.6 | H41: =F41*G41 -> 0 | J41: 159.6 | K41: =I41*J41 -> 0 | M41: 239.4 | N41: =L41*M41 -> 0 | V41: =+O41+P41+Q41+R41+S41+T41+U41-W41-X41 -> 0
A42: OFICIAL ELECTRICO/ELECTROMECANICO | E42: hr | G42: 199.6 | H42: =F42*G42 -> 0 | J42: 159.6 | K42: =I42*J42 -> 0 | M42: 239.4 | N42: =L42*M42 -> 0 | V42: =+O42+P42+Q42+R42+S42+T42+U42-W42-X42 -> 0
A43: ASISTENTE DE DISEÑO | E43: hr | G43: 199.6 | H43: =F43*G43 -> 0 | J43: 159.6 | K43: =I43*J43 -> 0 | M43: 239.4 | N43: =L43*M43 -> 0 | V43: =+O43+P43+Q43+R43+S43+T43+U43-W43-X43 -> 0
A44: ELECTRICISTA -B | E44: hr | G44: 211.15 | H44: =F44*G44 -> 0 | J44: 173.29 | K44: =I44*J44 -> 0 | M44: 259.94 | N44: =L44*M44 -> 0 | V44: =+O44+P44+Q44+R44+S44+T44+U44-W44-X44 -> 0 | Y44: GERMAN
A45: ELECTRICISTA -A | E45: hr | G45: 199.6 | H45: =F45*G45 -> 0 | J45: 159.6 | K45: =I45*J45 -> 0 | M45: 239.4 | N45: =L45*M45 -> 0 | V45: =+O45+P45+Q45+R45+S45+T45+U45-W45-X45 -> 0 | Y45: OSCAR-OSWALDO JIM
A46: AUXILIAR TECNICO | E46: hr | G46: 187.81 | H46: =F46*G46 -> 0 | J46: 145.62 | K46: =I46*J46 -> 0 | M46: 218.43 | N46: =L46*M46 -> 0 | V46: =+O46+P46+Q46+R46+S46+T46+U46-W46-X46 -> 0
A47: AYTE ELECTRICO - B | E47: hr | H47: =F47*G47 -> 0 | J47: 0 | K47: =I47*J47 -> 0 | N47: =L47*M47 -> 0 | V47: =+O47+P47+Q47+R47+S47+T47+U47-W47-X47 -> 0
A48: AYTE DE ELECTR. -A | E48: hr | G48: 187.81 | H48: =F48*G48 -> 0 | J48: 145.62 | K48: =I48*J48 -> 0 | M48: 218.43 | N48: =L48*M48 -> 0 | V48: =+O48+P48+Q48+R48+S48+T48+U48-W48-X48 -> 0 | Y48: URIEL-GUILLERMO-ENRIQUE
A49: AYTE GENERAL | E49: hr | G49: 94.81 | H49: =F49*G49 -> 0 | J49: 145.62 | K49: =I49*J49 -> 0 | M49: 218.43 | N49: =L49*M49 -> 0 | V49: =+O49+P49+Q49+R49+S49+T49+U49-W49-X49 -> 0
A50: PROFESIONISTA | E50: hr | G50: 243.45 | H50: =F50*G50 -> 0 | J50: 211.59 | K50: =I50*J50 -> 0 | M50: 317.39 | N50: =L50*M50 -> 0 | V50: 0 | Y50: O.ZARCO-GABRIEL
A51: COORDINADOR DE OPERACIONES | E51: hr | G51: 339.75 | H51: =F51*G51 -> 0 | J51: 325.79 | K51: =I51*J51 -> 0 | M51: 488.68 | N51: =L51*M51 -> 0 | V51: =+O51+P51+Q51+R51+S51+T51+U51-W51-X51 -> 0
A52: INGENIERIA Y SOPORTE TEC. | E52: hr | G52: 339.75 | H52: =F52*G52 -> 0 | J52: 325.79 | K52: =I52*J52 -> 0 | M52: 488.68 | N52: =L52*M52 -> 0 | V52: =+O52+P52+Q52+R52+S52+T52+U52-W52-X52 -> 0
A53: INGENIERO DE SUBESTACIONES | E53: hr | G53: 339.75 | H53: =F53*G53 -> 0 | J53: 325.79 | K53: =I53*J53 -> 0 | M53: 488.68 | N53: =L53*M53 -> 0 | V53: =+O53+P53+Q53+R53+S53+T53+U53-W53-X53 -> 0
A54: INGENIERO DE PRUEBAS ELECTRICAS | E54: hr | G54: 339.75 | H54: =F54*G54 -> 0 | J54: 325.79 | K54: =I54*J54 -> 0 | M54: 488.68 | N54: =L54*M54 -> 0 | V54: =+O54+P54+Q54+R54+S54+T54+U54-W54-X54 -> 0
A55: ING. ESPECIALISTA EN PROTECCIONES | E55: hr | G55: 1004.49 | H55: =F55*G55 -> 0 | J55: 1164.98 | K55: =I55*J55 -> 0 | M55: 1747.46 | N55: =L55*M55 -> 0 | V55: =+O55+P55+Q55+R55+S55+T55+U55-W55-X55 -> 0
A56: SUPERINTENDENTE | E56: hr | H56: =F56*G56 -> 0 | J56: =G56*1.5 -> 0 | K56: =I56*J56 -> 0 | M56: =G56*2.25 -> 0 | N56: =L56*M56 -> 0 | V56: =+O56+P56+Q56+R56+S56+T56+U56-W56-X56 -> 0
F57: =V57 -> 0 | G57: SUBT 2 | H57: =SUM(H34:H56) -> 0 | J57: SUBT. | K57: =SUM(K34:K56) -> 0 | M57: SUBT. | N57: =SUM(N34:N56) -> 0
G58: SUMA M.O. | H58: =H57+K57+N57 -> 0
A59: HERRAMIENTA MENOR | G59: 1 a 10% | H59: =+H58*0.06 -> 0
H60: =+H58+H59 -> 0
A61: VEHICULOS
A62: DESCRIPCION | E62: UNIDAD | F62: CANT. | G62: P.U. | H62: IMPORTE | J62: HR IDA | K62: HR RETORNO | L62: HR SITIO | M62: SUMA
A63: camioneta EXPRES VAN CARGO sin operador sin combustible | E63: HR | F63: 0 | G63: 170 | H63: =F63*G63 -> 0 | M63: =J63+K63+L63 -> 0
A64: camioneta RANGER sin operador sin combustible | E64: HR | F64: 1 | G64: 180 | H64: =F64*G64 -> 180 | M64: =J64+K64+L64 -> 0
A65: camioneta TORNADO Tornado sin operador sin combustible | E65: HR | F65: 0 | G65: 80 | H65: =F65*G65 -> 0 | M65: =J65+K65+L65 -> 0
A66: camioneta WV TRANSPORTER pasajeros | E66: HR | F66: 0 | G66: 150 | H66: =F66*G66 -> 0 | M66: =J66+K66+L66 -> 0
E67: HR | F67: 0 | H67: =F67*G67 -> 0 | M67: =J67+K67+L67 -> 0
E68: pza | F68: 0 | H68: =F68*G68 -> 0 | M68: =J68+K68+L68 -> 0
A69: Km. Recorrido (incluye conbustible y depresiación de Vehiculo | E69: KM | F69: 0 | G69: 2.5 | H69: =F69*G69 -> 0 | M69: =J69+K69+L69 -> 0
G70: SUBT 4 | H70: =SUM(H63:H69) -> 180
A71: COMBUSTIBLE
A72: DESCRIPCION | E72: UNIDAD | F72: CANT. | G72: P.U. | H72: IMPORTE | J72: KM IDA | K72: KM RETORNO | L72: KM SITIO | M72: SUMA
A73: GASOLINA MAGNA | E73: LT | F73: 10 | G73: 23 | H73: =F73*G73 -> 230 | M73: =J73+K73+L73 -> 0
A74: DIESEL | E74: LT | F74: 0 | G74: 24 | H74: =F74*G74 -> 0 | M74: =J74+K74+L74 -> 0
G75: SUBT 5 | H75: =SUM(H73:H74) -> 230
A76: CASETAS
A77: DESCRIPCION | E77: UNIDAD | F77: CANT. | G77: P.U. | H77: IMPORTE
A78: Camion | E78: CASETA | F78: 2 | G78: 65 | H78: =F78*G78 -> 130
A79: camioneta pick up | E79: CASETA | G79: 250 | H79: =F79*G79 -> 0
G80: SUBT 6 | H80: =SUM(H78:H79) -> 130
A81: VIATICOS
A82: ALIMENTOS
A83: DESCRIPCION | E83: UNIDAD | F83: CANT. | G83: P.U. | H83: IMPORTE
A84: CONSUMO DE ALIMENTOS | E84: Pza | F84: 1 | G84: 600 | H84: =F84*G84 -> 600
H85: =SUM(H84) -> 600
A86: HOSPEDAJE
A87: DESCRIPCION | E87: UNIDAD | F87: CANT. | G87: P.U. | H87: IMPORTE
A88: HOTEL | E88: NOCHES | F88: 0.5 | G88: 1100 | H88: =F88*G88 -> 550
G89: SUBT 8 | H89: =SUM(H88) -> 550
G90: SUMA: | H90: =H70+H75+H80+H85+H89+H59+H58+H30 -> 2539.72
A91: EQUIPO DE PRUEBA
A92: DESCRIPCION | E92: UNIDAD | F92: CANT. | G92: P.U. | H92: IMPORTE | I92: TR | K92: S.E
A93: Megger | E93: jr | G93: 2200 | H93: =(F93*G93) -> 0
A94: TTR | E94: jr | G94: 2000 | H94: =(F94*G94) -> 0
A95: Factor de Potencia de 2.5 KV | E95: jr | G95: 7000 | H95: =(F95*G95) -> 0
A96: Factor de Potencia de 10.5 KV | E96: jr | G96: 15200 | H96: =(F96*G96) -> 0
A97: Ducter | E97: jr | G97: 2200 | H97: =(F97*G97) -> 0
A98: resistencia óhmica | E98: jr | G98: 2000 | H98: =(F98*G98) -> 0
A99: hipot de 80 KV vcd | E99: jr | G99: 2500 | H99: =(F99*G99) -> 0
A100: Rigidez dieléctrica al aceite 60 kv | E100: jr | G100: 1600 | H100: =(F100*G100) -> 0
A101: Terrómetro | E101: jr | G101: 1100 | H101: =(F101*G101) -> 0
...

Sheet M0  (8)
A1: I M M E E S. A. D E C. V.
A2: A N A L I S I S D E P R E C I O U N I T A R I O
A3: COTIZACION:
A4: FECHA:
A5: PARTIDA 1
A6: REV-06-feb-2021
A7: MATERIALES.
A8: DESCRIPCION | E8: UNIDAD | F8: CANT. | G8: P.U. | H8: IMPORTE | J8: MANO DE OBRA
A9: Consumible | E9: Pza | H9: =G9*F9 -> 0
E10: Pza | H10: =G10*F10 -> 0
E11: Pza | H11: =G11*F11 -> 0
E12: Pza | H12: =G12*F12 -> 0
E13: Pza | H13: =G13*F13 -> 0
E14: Pza | H14: =G14*F14 -> 0
E15: Pza | H15: =G15*F15 -> 0
E16: Pza | H16: =G16*F16 -> 0 | I16: =H16*1.455 -> 0
G17: SUBT 1 | H17: =SUM(H9:H16) -> 0
A19: MANO DE OBRA SIN INDIRECTOS | O19: HORARIOS DE TRABAJO | V19: HORAS RESULTANTES | Y19: PERSONAL PEOPUESTO
A20: PERSONAL. | E20: UNIDAD | F20: CANT. | G20: HORA NORMAL | H20: IMPORTE | I20: CANT. | J20: Hr. Extra | K20: IMPORTE | L20: CANT. | M20: Dom, ó Fest.TRIPLE | N20: IMPORTE | O20: L | P20: M | Q20: MI | R20: J | S20: V | T20: S | U20: D | V20: N | W20: D | X20: T
A21: SUPERVISOR DE SEGURIDAD CERTIFICADO | E21: hr | G21: 390.39 | H21: =F21*G21 -> 0 | J21: 358.81 | K21: =I21*J21 -> 0 | M21: 538.27 | N21: =L21*M21 -> 0 | V21: =+O21+P21+Q21+R21+S21+T21+U21-W21-X21 -> 0
A22: SUPERVISOR DE SEGURIDAD | E22: hr | F22: 8 | G22: 317.98 | H22: =F22*G22 -> 2543.84 | J22: 326.25 | K22: =I22*J22 -> 0 | M22: 489.37 | N22: =L22*M22 -> 0 | V22: =+O22+P22+Q22+R22+S22+T22+U22-W22-X22 -> 0 | Y22: OSWALDO Z-GABRIEL
A23: SUPERVISOR ELECTRICO | E23: hr | F23: 4 | G23: 237.68 | H23: =F23*G23 -> 950.72 | J23: 358.81 | K23: =I23*J23 -> 0 | M23: 538.22 | N23: =L23*M23 -> 0 | V23: =+O23+P23+Q23+R23+S23+T23+U23-W23-X23 -> 0 | Y23: ADRIAN
A24: TECNICO DE PRUEBAS ELECTRICAS | E24: hr | G24: 317.98 | H24: =F24*G24 -> 0 | J24: 244.27 | K24: =I24*J24 -> 0 | M24: 489.37 | N24: =L24*M24 -> 0 | V24: =+O24+P24+Q24+R24+S24+T24+U24-W24-X24 -> 0 | Y24: HECTOR
A25: CABO OBRA ELECTRICA | E25: hr | G25: 310.62 | H25: =F25*G25 -> 0 | J25: 335 | K25: =I25*J25 -> 0 | M25: 436.87 | N25: =L25*M25 -> 0 | V25: =+O25+P25+Q25+R25+S25+T25+U25-W25-X25 -> 0
A26: LINIERO | E26: hr | F26: 9.5 | G26: 209.25 | H26: =F26*G26 -> 1987.875 | J26: 221.7 | K26: =I26*J26 -> 0 | M26: 437.63 | N26: =L26*M26 -> 0 | V26: =+O26+P26+Q26+R26+S26+T26+U26-W26-X26 -> 0 | Y26: JOSE J
A27: ESPECIALISTA DE MANTTO ELECTRICO | E27: hr | G27: 237.68 | H27: =F27*G27 -> 0 | J27: 277.97 | K27: =I27*J27 -> 0 | M27: 538.84 | N27: =L27*M27 -> 0 | V27: =+O27+P27+Q27+R27+S27+T27+U27-W27-X27 -> 0
A28: TECNICO EN INSTRUMENTACION | E28: hr | G28: 368.59 | H28: =F28*G28 -> 0 | J28: 221.7 | K28: =I28*J28 -> 0 | M28: 538.84 | N28: =L28*M28 -> 0 | V28: =+O28+P28+Q28+R28+S28+T28+U28-W28-X28 -> 0
A29: OFICIAL ELECTRICO/ELECTROMECANICO | E29: hr | F29: 4 | G29: 190.22 | H29: =F29*G29 -> 760.88 | J29: 165 | K29: =I29*J29 -> 0 | M29: 277.56 | N29: =L29*M29 -> 0 | V29: =+O29+P29+Q29+R29+S29+T29+U29-W29-X29 -> 0
A30: ASISTENTE DE DISEÑO | E30: hr | G30: 190.25 | H30: =F30*G30 -> 0 | J30: 221.7 | K30: =I30*J30 -> 0 | M30: 297.41 | N30: =L30*M30 -> 0 | V30: =+O30+P30+Q30+R30+S30+T30+U30-W30-X30 -> 0
A31: ELECTRICISTA -B | E31: hr | F31: 2 | G31: 119.54 | H31: =F31*G31 -> 239.08 | J31: 137.92 | K31: =I31*J31 -> 0 | M31: 0 | N31: =L31*M31 -> 0 | V31: =+O31+P31+Q31+R31+S31+T31+U31-W31-X31 -> 0 | Y31: GERMAN
A32: ELECTRICISTA -A | E32: hr | G32: 119.54 | H32: =F32*G32 -> 0 | J32: 137.92 | K32: =I32*J32 -> 0 | M32: 240.95 | N32: =L32*M32 -> 0 | V32: =+O32+P32+Q32+R32+S32+T32+U32-W32-X32 -> 0 | Y32: OSCAR-OSWALDO JIM
A33: AUXILIAR TECNICO | E33: hr | G33: 106.45 | H33: =F33*G33 -> 0 | J33: 137.92 | K33: =I33*J33 -> 0 | M33: 260.95 | N33: =L33*M33 -> 0 | V33: =+O33+P33+Q33+R33+S33+T33+U33-W33-X33 -> 0
A34: AYTE ELECTRICO - B | E34: hr | G34: 106.45 | H34: =F34*G34 -> 0 | J34: 122.4 | K34: =I34*J34 -> 0 | N34: =L34*M34 -> 0 | V34: =+O34+P34+Q34+R34+S34+T34+U34-W34-X34 -> 0
A35: AYTE DE ELECTR. -A | E35: hr | G35: 106.54 | H35: =F35*G35 -> 0 | J35: 122.4 | K35: =I35*J35 -> 0 | M35: 198.17 | N35: =L35*M35 -> 0 | V35: =+O35+P35+Q35+R35+S35+T35+U35-W35-X35 -> 0 | Y35: URIEL-GUILLERMO-ENRIQUE
A36: AYTE GENERAL | E36: hr | G36: 100.42 | H36: =F36*G36 -> 0 | J36: 122.4 | K36: =I36*J36 -> 0 | M36: 0 | N36: =L36*M36 -> 0 | V36: =+O36+P36+Q36+R36+S36+T36+U36-W36-X36 -> 0
A37: PROFESIONISTA | E37: hr | G37: 209.25 | H37: =F37*G37 -> 0 | J37: 406 | K37: =I37*J37 -> 0 | M37: 564.86 | N37: =L37*M37 -> 0 | V37: 0 | Y37: O.ZARCO-GABRIEL
A38: COORDINADOR DE OPERACIONES | E38: hr | G38: 0 | H38: =F38*G38 -> 0 | J38: 0 | K38: =I38*J38 -> 0 | M38: 0 | N38: =L38*M38 -> 0 | V38: =+O38+P38+Q38+R38+S38+T38+U38-W38-X38 -> 0
A39: INGENIERIA Y SOPORTE TEC. | E39: hr | G39: 339.75 | H39: =F39*G39 -> 0 | J39: 325.79 | K39: =I39*J39 -> 0 | M39: 488.68 | N39: =L39*M39 -> 0 | V39: =+O39+P39+Q39+R39+S39+T39+U39-W39-X39 -> 0
A40: INGENIERO DE SUBESTACIONES | E40: hr | G40: 339.75 | H40: =F40*G40 -> 0 | J40: 325.79 | K40: =I40*J40 -> 0 | M40: 488.68 | N40: =L40*M40 -> 0 | V40: =+O40+P40+Q40+R40+S40+T40+U40-W40-X40 -> 0
A41: INGENIERO DE PRUEBAS ELECTRICAS | E41: hr | G41: 339.75 | H41: =F41*G41 -> 0 | J41: 325.79 | K41: =I41*J41 -> 0 | M41: 488.68 | N41: =L41*M41 -> 0 | V41: =+O41+P41+Q41+R41+S41+T41+U41-W41-X41 -> 0
A42: ING. ESPECIALISTA EN PROTECCIONES | E42: hr | G42: 650 | H42: =F42*G42 -> 0 | J42: =G42*1.5 -> 975 | K42: =I42*J42 -> 0 | M42: 1747.46 | N42: =L42*M42 -> 0 | V42: =+O42+P42+Q42+R42+S42+T42+U42-W42-X42 -> 0
A43: SUPERINTENDENTE | E43: hr | H43: =F43*G43 -> 0 | J43: =G43*1.5 -> 0 | K43: =I43*J43 -> 0 | M43: =G43*2.25 -> 0 | N43: =L43*M43 -> 0 | V43: =+O43+P43+Q43+R43+S43+T43+U43-W43-X43 -> 0
F44: =V44 -> 0 | G44: SUBT 2 | H44: =SUM(H21:H43) -> 6482.395 | J44: SUBT. | K44: =SUM(K21:K43) -> 0 | M44: SUBT. | N44: =SUM(N21:N43) -> 0
G45: SUMA M.O. | H45: =H44+K44+N44 -> 6482.395
A46: HERRAMIENTA MENOR | G46: 1 a 10% | H46: =+H45*0.06 -> 388.9437
A49: VEHICULOS
A50: DESCRIPCION | E50: UNIDAD | F50: CANT. | G50: P.U. | H50: IMPORTE | J50: HR IDA | K50: HR RETORNO | L50: HR SITIO | M50: SUMA
A51: camioneta EXPRES VAN CARGO sin operador sin combustible | E51: HR | F51: 0 | G51: 150 | H51: =F51*G51 -> 0 | M51: =J51+K51+L51 -> 0
A52: camioneta RANGER sin operador sin combustible | E52: HR | F52: 0 | G52: 150 | H52: =F52*G52 -> 0 | M52: =J52+K52+L52 -> 0
A53: camioneta TORNADO Tornado sin operador sin combustible | E53: HR | F53: 0 | G53: 60 | H53: =F53*G53 -> 0 | M53: =J53+K53+L53 -> 0
A54: camioneta WV TRANSPORTER pasajeros | E54: HR | F54: 0 | G54: 120 | H54: =F54*G54 -> 0 | M54: =J54+K54+L54 -> 0
E55: HR | F55: 0 | H55: =F55*G55 -> 0 | M55: =J55+K55+L55 -> 0
E56: pza | F56: 0 | H56: =F56*G56 -> 0 | M56: =J56+K56+L56 -> 0
A57: Km. Recorrido (incluye conbustible y depresiación de Vehiculo | E57: KM | F57: 0 | G57: 2.5 | H57: =F57*G57 -> 0 | M57: =J57+K57+L57 -> 0
G58: SUBT 4 | H58: =SUM(H51:H57) -> 0
G59: SUMA: | H59: =H58+H45+H17 -> 6482.395
A60: EQUIPO DE PRUEBA
A61: DESCRIPCION | E61: UNIDAD | F61: CANT. | G61: P.U. | H61: IMPORTE | I61: TR | K61: S.E
A62: Megger | E62: jr | G62: 2200 | H62: =(F62*G62) -> 0
A63: TTR | E63: jr | G63: 2000 | H63: =(F63*G63) -> 0
A64: Factor de Potencia de 2.5 KV | E64: jr | G64: 7000 | H64: =(F64*G64) -> 0
A65: Factor de Potencia de 10.5 KV | E65: jr | G65: 15200 | H65: =(F65*G65) -> 0
A66: Ducter | E66: jr | G66: 2200 | H66: =(F66*G66) -> 0
A67: resistencia óhmica | E67: jr | G67: 2000 | H67: =(F67*G67) -> 0
A68: hipot de 80 KV vcd | E68: jr | G68: 2500 | H68: =(F68*G68) -> 0
A69: Rigidez dieléctrica al aceite 60 kv | E69: jr | G69: 1600 | H69: =(F69*G69) -> 0
A70: Terrómetro | E70: jr | G70: 1100 | H70: =(F70*G70) -> 0
A71: Analizador de tiempos de interruptor | E71: jr | G71: 2700 | H71: =(F71*G71) -> 0
A72: Fuente de corriente para calibrador de relevadores | E72: jr | G72: 2500 | H72: =(F72*G72) -> 0
A73: Probador de relevador de Protecciones | E73: jr | G73: 13373 | H73: =(F73*G73) -> 0
... A82: Test Kit maleta de prueba G.E. | E82: jr | G82: 5800 | H82: =(F82*G82) -> 0
E83: jr | H83: =(F83*G83) -> 0
A84: Camara termografica | E84: jr | G84: 15000 | H84: =(F84*G84) -> 0
A85: Generador de Luz con combustible | E85: jr | G85: 383.5 | H85: =(F85*G85) -> 0
G86: SUBT 9 | H86: =SUM(H62:H85) -> 0
E88: 0 | H88: =+E88 -> 0 | I88: IMPUESTO | J88: INDIRECTO DISPONIBLE
F89: COSTO DIRECTO | H89: =H59+H86 -> 6482.395
F90: Indirectos | G90: 0.3 | H90: =H89*G90 -> 1944.7185 | I90: =+M96 -> -1092.9318 | J90: =H90-M96 -> 3037.6503 | N90: REV-06-feb-2021
F91: Subtotal 1 | H91: =H89+H90 -> 8427.1135
F92: Financ. | G92: 0.06 | H92: =H91*G92 -> 505.62681 | K92: BASE IMPUESTO | L92: SIN UTILIDAD
F93: Subtotal 2 | H93: =H91+H92 -> 8932.7403 | J93: COMPRAS | K93: =+H17 -> 0
F94: Utilidad | G94: 0.2 | H94: =H93*G94 -> 1786.5481 | J94: M.O | K94: =H44 -> 6482.395
F95: Importe | H95: =H93+H94 -> 10719.288 | J95: GASTOS FACTURADOS | K95: =H59-H46 -> 6093.4513 | M95: IMP. 30%
F96: Materiales | H96: ='MAT (8)'!H124 -> 3553.5762 | I96: FACTOR | J96: SUMA | K96: =SUM(K93:K95) -> 12575.846 | L96: =H95-H94 -> 8932.7403 | M96: =+(L96-K96)*0.3 -> -1092.9318
B97: utilidad | F97: Total | H97: =H95+H96 -> 14272.865 | J97: =H95/H89 -> 1.6536
B98: ime | C98: comisión | D98: total | H98: =H97/4 -> 3568.2161
B99: 0.275 | C99: 0.05 | D99: =B99+C99 -> 0.325

Sheet MAT (9)
A1: I M M E E S. A. D E C. V.
A2: A N A L I S I S D E P R E C I O U N I T A R I O
A3: COTIZACION:
A4: FECHA:
A5: PARTIDA 1
A6: REV-06-feb-2021
A7: MATERIALES.
A8: DESCRIPCION | E8: UNIDAD | F8: CANT. | G8: P.U. | H8: IMPORTE | J8: MATERIALES
A9: charola tipo escalera perfil Z para servicio pesado de 30" | E9: Pza | G9: 2540.01 | H9: =G9*F9 -> 0
A10: tapa para charola tipo escalera de 30". | E10: Pza | G10: 1001 | H10: =G10*F10 -> 0
A11: curva vertical exterior de 90° para charola tipo escalera de 30 | E11: Pza | G11: 450.5 | H11: =G11*F11 -> 0
A12: tapa para curva vertical exterior de 90° para charola tipo escalera para servicio pesado de 30" | E12: Pza | G12: 136.52 | H12: =G12*F12 -> 0
A13: curva horizontal de 90° para charola tipo escalera para servicio pesado de 30" | E13: Pza | G13: 620.97 | H13: =G13*F13 -> 0
A14: base de unicanal solido galvanizado de 4x4 | E14: Pza | G14: 382.32 | H14: =G14*F14 -> 0
A15: tornilleria galvanizada | E15: Pza | G15: 200 | H15: =G15*F15 -> 0
A16: varilla roscada galvanizada de 3 metros de largo X 1/2" | E16: Pza | G16: 70 | H16: =G16*F16 -> 0
A17: conector de charola para servicio pesado de 30 | E17: Pza | G17: 467.05 | H17: =G17*F17 -> 0
A18: zapata ponchable para cable de cobre cañon largo calibre 500 KCM, con 2 ojillos de 1/2 | E18: Pza | G18: 495.41 | H18: =G18*F18 -> 0
A19: manga termocontractil para nivel de aislamiento de 600 V, en calibre 500 KCM. | E19: Pza | G19: 212.43 | H19: =G19*F19 -> 0
A20: tornillo tropicalizado de 1/2" con 2" de largo | E20: Pza | G20: 15 | H20: =G20*F20 -> 0
A21: tornillo tropicalizado de 1/2" con 4" de largo | E21: Pza | G21: 15 | H21: =G21*F21 -> 0
A22: sistema corta fuego con lana mineral y compuesto SF-ONE.Sellador cortafuego intumescente de alto desempeño | E22: Pza | F22: 1 | G22: =M22 -> 21069.8 | H22: =G22*F22 -> 21069.8 | J22: 17369.8 | K22: 2700 | L22: 1000 | M22: =J22+K22+L22 -> 21069.8
A23: Materiales consumibles | E23: PZA | F23: 1 | G23: 500 | H23: =G23*F23 -> 500
A24: cuellos de lona flexibles en gargantas primarias de generador electrico | E24: Pza | H24: =G24*F24 -> 0
A25: cable de cobre THW calibre 12 AWG | E25: mt | H25: =G25*F25 -> 0 | L25: NOTA: CONSIDERAR LA JORNADA DE 8.0 HORAS, AUNQUE EN IMMEE SE TRABAJE JORNADA LARGA CONVENIDA, Y DOMINGO DESCANSO
A26: tapones para unicanal de 4x4 y varilla roscada | E26: Pza | H26: =G26*F26 -> 0
A27: tapones para esparrago | E27: Pza | H27: =G27*F27 -> 0
A28: cable de cobre 500 mts THW LS calibre 500 MCM | E28: CARRETE | H28: =G28*F28 -> 0
A29: Renta de una plataforma de elevacion | E29: Pza | G29: 48000 | H29: =G29*F29 -> 0 | I29: =H29*1.455 -> 0
G30: SUBT 1 | H30: =SUM(H9:H29) -> 21569.8
A32: MANO DE OBRA SIN INDIRECTOS | O32: HORARIOS DE TRABAJO | V32: HORAS RESULTANTES | Y32: PERSONAL PEOPUESTO
A33: PERSONAL. | E33: UNIDAD | F33: CANT. | G33: HORA NORMAL | H33: IMPORTE | I33: CANT. | J33: Hr. Extra | K33: IMPORTE | L33: CANT. | M33: Dom, ó Fest.TRIPLE | N33: IMPORTE | O33: L | P33: M | Q33: MI | R33: J | S33: V | T33: S | U33: D | V33: N | W33: D | X33: T
A34: SUPERVISOR DE SEGURIDAD CERTIFICADO | E34: hr | G34: 390.39 | H34: =F34*G34 -> 0 | J34: 358.81 | K34: =I34*J34 -> 0 | M34: 538.27 | N34: =L34*M34 -> 0 | V34: =+O34+P34+Q34+R34+S34+T34+U34-W34-X34 -> 0
A35: SUPERVISOR DE SEGURIDAD | E35: hr | G35: 243.45 | H35: =F35*G35 -> 0 | J35: 211.59 | K35: =I35*J35 -> 0 | M35: 317.39 | N35: =L35*M35 -> 0 | V35: =+O35+P35+Q35+R35+S35+T35+U35-W35-X35 -> 0 | Y35: OSWALDO Z-GABRIEL
A36: SUPERVISOR ELECTRICO | E36: hr | G36: 390.39 | H36: =F36*G36 -> 0 | J36: 358.81 | K36: =I36*J36 -> 0 | M36: 538.22 | N36: =L36*M36 -> 0 | V36: =+O36+P36+Q36+R36+S36+T36+U36-W36-X36 -> 0 | Y36: ADRIAN
A37: TECNICO DE PRUEBAS ELECTRICAS | E37: hr | G37: 231.67 | H37: =F37*G37 -> 0 | J37: 197.63 | K37: =I37*J37 -> 0 | M37: 296.45 | N37: =L37*M37 -> 0 | V37: =+O37+P37+Q37+R37+S37+T37+U37-W37-X37 -> 0 | Y37: HECTOR
A38: CABO OBRA ELECTRICA | E38: hr | G38: 310.62 | H38: =F38*G38 -> 0 | J38: 291.24 | K38: =I38*J38 -> 0 | M38: 436.87 | N38: =L38*M38 -> 0 | V38: =+O38+P38+Q38+R38+S38+T38+U38-W38-X38 -> 0
A39: LINIERO | E39: hr | G39: 310.62 | H39: =F39*G39 -> 0 | J39: 291.24 | K39: =I39*J39 -> 0 | M39: 436.87 | N39: =L39*M39 -> 0 | V39: =+O39+P39+Q39+R39+S39+T39+U39-W39-X39 -> 0 | Y39: JOSE J
A40: ESPECIALISTA DE MANTTO ELECTRICO | E40: hr | H40: =F40*G40 -> 0 | J40: 0 | K40: =I40*J40 -> 0 | M40: 0 | N40: =L40*M40 -> 0 | V40: =+O40+P40+Q40+R40+S40+T40+U40-W40-X40 -> 0
A41: TECNICO EN INSTRUMENTACION | E41: hr | G41: 199.6 | H41: =F41*G41 -> 0 | J41: 159.6 | K41: =I41*J41 -> 0 | M41: 239.4 | N41: =L41*M41 -> 0 | V41: =+O41+P41+Q41+R41+S41+T41+U41-W41-X41 -> 0
A42: OFICIAL ELECTRICO/ELECTROMECANICO | E42: hr | G42: 199.6 | H42: =F42*G42 -> 0 | J42: 159.6 | K42: =I42*J42 -> 0 | M42: 239.4 | N42: =L42*M42 -> 0 | V42: =+O42+P42+Q42+R42+S42+T42+U42-W42-X42 -> 0
A43: ASISTENTE DE DISEÑO | E43: hr | G43: 199.6 | H43: =F43*G43 -> 0 | J43: 159.6 | K43: =I43*J43 -> 0 | M43: 239.4 | N43: =L43*M43 -> 0 | V43: =+O43+P43+Q43+R43+S43+T43+U43-W43-X43 -> 0
A44: ELECTRICISTA -B | E44: hr | G44: 211.15 | H44: =F44*G44 -> 0 | J44: 173.29 | K44: =I44*J44 -> 0 | M44: 259.94 | N44: =L44*M44 -> 0 | V44: =+O44+P44+Q44+R44+S44+T44+U44-W44-X44 -> 0 | Y44: GERMAN
A45: ELECTRICISTA -A | E45: hr | G45: 199.6 | H45: =F45*G45 -> 0 | J45: 159.6 | K45: =I45*J45 -> 0 | M45: 239.4 | N45: =L45*M45 -> 0 | V45: =+O45+P45+Q45+R45+S45+T45+U45-W45-X45 -> 0 | Y45: OSCAR-OSWALDO JIM
A46: AUXILIAR TECNICO | E46: hr | G46: 187.81 | H46: =F46*G46 -> 0 | J46: 145.62 | K46: =I46*J46 -> 0 | M46: 218.43 | N46: =L46*M46 -> 0 | V46: =+O46+P46+Q46+R46+S46+T46+U46-W46-X46 -> 0
A47: AYTE ELECTRICO - B | E47: hr | H47: =F47*G47 -> 0 | J47: 0 | K47: =I47*J47 -> 0 | N47: =L47*M47 -> 0 | V47: =+O47+P47+Q47+R47+S47+T47+U47-W47-X47 -> 0
A48: AYTE DE ELECTR. -A | E48: hr | G48: 187.81 | H48: =F48*G48 -> 0 | J48: 145.62 | K48: =I48*J48 -> 0 | M48: 218.43 | N48: =L48*M48 -> 0 | V48: =+O48+P48+Q48+R48+S48+T48+U48-W48-X48 -> 0 | Y48: URIEL-GUILLERMO-ENRIQUE
A49: AYTE GENERAL | E49: hr | G49: 94.81 | H49: =F49*G49 -> 0 | J49: 145.62 | K49: =I49*J49 -> 0 | M49: 218.43 | N49: =L49*M49 -> 0 | V49: =+O49+P49+Q49+R49+S49+T49+U49-W49-X49 -> 0
A50: PROFESIONISTA | E50: hr | G50: 243.45 | H50: =F50*G50 -> 0 | J50: 211.59 | K50: =I50*J50 -> 0 | M50: 317.39 | N50: =L50*M50 -> 0 | V50: 0 | Y50: O.ZARCO-GABRIEL
A51: COORDINADOR DE OPERACIONES | E51: hr | G51: 339.75 | H51: =F51*G51 -> 0 | J51: 325.79 | K51: =I51*J51 -> 0 | M51: 488.68 | N51: =L51*M51 -> 0 | V51: =+O51+P51+Q51+R51+S51+T51+U51-W51-X51 -> 0
A52: INGENIERIA Y SOPORTE TEC. | E52: hr | G52: 339.75 | H52: =F52*G52 -> 0 | J52: 325.79 | K52: =I52*J52 -> 0 | M52: 488.68 | N52: =L52*M52 -> 0 | V52: =+O52+P52+Q52+R52+S52+T52+U52-W52-X52 -> 0
A53: INGENIERO DE SUBESTACIONES | E53: hr | G53: 339.75 | H53: =F53*G53 -> 0 | J53: 325.79 | K53: =I53*J53 -> 0 | M53: 488.68 | N53: =L53*M53 -> 0 | V53: =+O53+P53+Q53+R53+S53+T53+U53-W53-X53 -> 0
A54: INGENIERO DE PRUEBAS ELECTRICAS | E54: hr | G54: 339.75 | H54: =F54*G54 -> 0 | J54: 325.79 | K54: =I54*J54 -> 0 | M54: 488.68 | N54: =L54*M54 -> 0 | V54: =+O54+P54+Q54+R54+S54+T54+U54-W54-X54 -> 0
A55: ING. ESPECIALISTA EN PROTECCIONES | E55: hr | G55: 1004.49 | H55: =F55*G55 -> 0 | J55: 1164.98 | K55: =I55*J55 -> 0 | M55: 1747.46 | N55: =L55*M55 -> 0 | V55: =+O55+P55+Q55+R55+S55+T55+U55-W55-X55 -> 0
A56: SUPERINTENDENTE | E56: hr | H56: =F56*G56 -> 0 | J56: =G56*1.5 -> 0 | K56: =I56*J56 -> 0 | M56: =G56*2.25 -> 0 | N56: =L56*M56 -> 0 | V56: =+O56+P56+Q56+R56+S56+T56+U56-W56-X56 -> 0
F57: =V57 -> 0 | G57: SUBT 2 | H57: =SUM(H34:H56) -> 0 | J57: SUBT. | K57: =SUM(K34:K56) -> 0 | M57: SUBT. | N57: =SUM(N34:N56) -> 0
G58: SUMA M.O. | H58: =H57+K57+N57 -> 0
A59: HERRAMIENTA MENOR | G59: 1 a 10% | H59: =+H58*0.06 -> 0
H60: =+H58+H59 -> 0
A61: VEHICULOS
A62: DESCRIPCION | E62: UNIDAD | F62: CANT. | G62: P.U. | H62: IMPORTE | J62: HR IDA | K62: HR RETORNO | L62: HR SITIO | M62: SUMA
A63: camioneta EXPRES VAN CARGO sin operador sin combustible | E63: HR | F63: 0 | G63: 170 | H63: =F63*G63 -> 0 | M63: =J63+K63+L63 -> 0
A64: camioneta RANGER sin operador sin combustible | E64: HR | F64: 4 | G64: 180 | H64: =F64*G64 -> 720 | M64: =J64+K64+L64 -> 0
A65: camioneta TORNADO Tornado sin operador sin combustible | E65: HR | F65: 0 | G65: 80 | H65: =F65*G65 -> 0 | M65: =J65+K65+L65 -> 0
A66: camioneta WV TRANSPORTER pasajeros | E66: HR | F66: 0 | G66: 150 | H66: =F66*G66 -> 0 | M66: =J66+K66+L66 -> 0
E67: HR | F67: 0 | H67: =F67*G67 -> 0 | M67: =J67+K67+L67 -> 0
E68: pza | F68: 0 | H68: =F68*G68 -> 0 | M68: =J68+K68+L68 -> 0
A69: Km. Recorrido (incluye conbustible y depresiación de Vehiculo | E69: KM | F69: 0 | G69: 2.5 | H69: =F69*G69 -> 0 | M69: =J69+K69+L69 -> 0
G70: SUBT 4 | H70: =SUM(H63:H69) -> 720
A71: COMBUSTIBLE
A72: DESCRIPCION | E72: UNIDAD | F72: CANT. | G72: P.U. | H72: IMPORTE | J72: KM IDA | K72: KM RETORNO | L72: KM SITIO | M72: SUMA
A73: GASOLINA MAGNA | E73: LT | F73: 30 | G73: 23 | H73: =F73*G73 -> 690 | M73: =J73+K73+L73 -> 0
A74: DIESEL | E74: LT | F74: 0 | G74: 24 | H74: =F74*G74 -> 0 | M74: =J74+K74+L74 -> 0
G75: SUBT 5 | H75: =SUM(H73:H74) -> 690
A76: CASETAS
A77: DESCRIPCION | E77: UNIDAD | F77: CANT. | G77: P.U. | H77: IMPORTE
A78: Camion | E78: CASETA | F78: 0 | G78: 65 | H78: =F78*G78 -> 0
A79: camioneta pick up | E79: CASETA | F79: 2 | G79: 250 | H79: =F79*G79 -> 500
G80: SUBT 6 | H80: =SUM(H78:H79) -> 500
A81: VIATICOS
A82: ALIMENTOS
A83: DESCRIPCION | E83: UNIDAD | F83: CANT. | G83: P.U. | H83: IMPORTE
A84: CONSUMO DE ALIMENTOS | E84: Pza | F84: 4 | G84: 650 | H84: =F84*G84 -> 2600
H85: =SUM(H84) -> 2600
A86: HOSPEDAJE
A87: DESCRIPCION | E87: UNIDAD | F87: CANT. | G87: P.U. | H87: IMPORTE
A88: HOTEL | E88: NOCHES | F88: 2 | G88: 1100 | H88: =F88*G88 -> 2200
G89: SUBT 8 | H89: =SUM(H88) -> 2200
G90: SUMA: | H90: =H70+H75+H80+H85+H89+H59+H58+H30 -> 28279.8
A91: EQUIPO DE PRUEBA
A92: DESCRIPCION | E92: UNIDAD | F92: CANT. | G92: P.U. | H92: IMPORTE | I92: TR | K92: S.E
A93: Megger | E93: jr | G93: 2200 | H93: =(F93*G93) -> 0
A94: TTR | E94: jr | G94: 2000 | H94: =(F94*G94) -> 0
A95: Factor de Potencia de 2.5 KV | E95: jr | G95: 7000 | H95: =(F95*G95) -> 0
A96: Factor de Potencia de 10.5 KV | E96: jr | G96: 15200 | H96: =(F96*G96) -> 0
A97: Ducter | E97: jr | G97: 2200 | H97: =(F97*G97) -> 0
A98: resistencia óhmica | E98: jr | G98: 2000 | H98: =(F98*G98) -> 0
A99: hipot de 80 KV vcd | E99: jr | G99: 2500 | H99: =(F99*G99) -> 0
A100: Rigidez dieléctrica al aceite 60 kv | E100: jr | G100: 1600 | H100: =(F100*G100) -> 0
A101: Terrómetro | E101: jr | G101: 1100 | H101: =(F101*G101) -> 0
...

Sheet M0  (9)
A1: I M M E E S. A. D E C. V.
A2: A N A L I S I S D E P R E C I O U N I T A R I O
A3: COTIZACION:
A4: FECHA:
A5: PARTIDA 1
A6: REV-06-feb-2021
A7: MATERIALES.
A8: DESCRIPCION | E8: UNIDAD | F8: CANT. | G8: P.U. | H8: IMPORTE | J8: MANO DE OBRA
A9: Consumible | E9: Pza | H9: =G9*F9 -> 0
E10: Pza | H10: =G10*F10 -> 0
E11: Pza | H11: =G11*F11 -> 0
E12: Pza | H12: =G12*F12 -> 0
E13: Pza | H13: =G13*F13 -> 0
E14: Pza | H14: =G14*F14 -> 0
E15: Pza | H15: =G15*F15 -> 0
E16: Pza | H16: =G16*F16 -> 0 | I16: =H16*1.455 -> 0
G17: SUBT 1 | H17: =SUM(H9:H16) -> 0
A19: MANO DE OBRA SIN INDIRECTOS | O19: HORARIOS DE TRABAJO | V19: HORAS RESULTANTES | Y19: PERSONAL PEOPUESTO
A20: PERSONAL. | E20: UNIDAD | F20: CANT. | G20: HORA NORMAL | H20: IMPORTE | I20: CANT. | J20: Hr. Extra | K20: IMPORTE | L20: CANT. | M20: Dom, ó Fest.TRIPLE | N20: IMPORTE | O20: L | P20: M | Q20: MI | R20: J | S20: V | T20: S | U20: D | V20: N | W20: D | X20: T
A21: SUPERVISOR DE SEGURIDAD CERTIFICADO | E21: hr | G21: 390.39 | H21: =F21*G21 -> 0 | J21: 358.81 | K21: =I21*J21 -> 0 | M21: 538.27 | N21: =L21*M21 -> 0 | V21: =+O21+P21+Q21+R21+S21+T21+U21-W21-X21 -> 0
A22: SUPERVISOR DE SEGURIDAD | E22: hr | F22: 8 | G22: 317.98 | H22: =F22*G22 -> 2543.84 | J22: 326.25 | K22: =I22*J22 -> 0 | M22: 489.37 | N22: =L22*M22 -> 0 | V22: =+O22+P22+Q22+R22+S22+T22+U22-W22-X22 -> 0 | Y22: OSWALDO Z-GABRIEL
A23: SUPERVISOR ELECTRICO | E23: hr | F23: 9.5 | G23: 237.68 | H23: =F23*G23 -> 2257.96 | J23: 358.81 | K23: =I23*J23 -> 0 | M23: 538.22 | N23: =L23*M23 -> 0 | V23: =+O23+P23+Q23+R23+S23+T23+U23-W23-X23 -> 0 | Y23: ADRIAN
A24: TECNICO DE PRUEBAS ELECTRICAS | E24: hr | G24: 317.98 | H24: =F24*G24 -> 0 | J24: 244.27 | K24: =I24*J24 -> 0 | M24: 489.37 | N24: =L24*M24 -> 0 | V24: =+O24+P24+Q24+R24+S24+T24+U24-W24-X24 -> 0 | Y24: HECTOR
A25: CABO OBRA ELECTRICA | E25: hr | G25: 310.62 | H25: =F25*G25 -> 0 | J25: 335 | K25: =I25*J25 -> 0 | M25: 436.87 | N25: =L25*M25 -> 0 | V25: =+O25+P25+Q25+R25+S25+T25+U25-W25-X25 -> 0
A26: LINIERO | E26: hr | F26: 9.5 | G26: 209.25 | H26: =F26*G26 -> 1987.875 | I26: 2 | J26: 221.7 | K26: =I26*J26 -> 443.4 | M26: 437.63 | N26: =L26*M26 -> 0 | V26: =+O26+P26+Q26+R26+S26+T26+U26-W26-X26 -> 0 | Y26: JOSE J
A27: ESPECIALISTA DE MANTTO ELECTRICO | E27: hr | G27: 237.68 | H27: =F27*G27 -> 0 | J27: 277.97 | K27: =I27*J27 -> 0 | M27: 538.84 | N27: =L27*M27 -> 0 | V27: =+O27+P27+Q27+R27+S27+T27+U27-W27-X27 -> 0
A28: TECNICO EN INSTRUMENTACION | E28: hr | G28: 368.59 | H28: =F28*G28 -> 0 | J28: 221.7 | K28: =I28*J28 -> 0 | M28: 538.84 | N28: =L28*M28 -> 0 | V28: =+O28+P28+Q28+R28+S28+T28+U28-W28-X28 -> 0
A29: OFICIAL ELECTRICO/ELECTROMECANICO | E29: hr | F29: 9.5 | G29: 190.22 | H29: =F29*G29 -> 1807.09 | I29: 2 | J29: 165 | K29: =I29*J29 -> 330 | M29: 277.56 | N29: =L29*M29 -> 0 | V29: =+O29+P29+Q29+R29+S29+T29+U29-W29-X29 -> 0
A30: ASISTENTE DE DISEÑO | E30: hr | G30: 190.25 | H30: =F30*G30 -> 0 | J30: 221.7 | K30: =I30*J30 -> 0 | M30: 297.41 | N30: =L30*M30 -> 0 | V30: =+O30+P30+Q30+R30+S30+T30+U30-W30-X30 -> 0
A31: ELECTRICISTA -B | E31: hr | F31: 9.5 | G31: 119.54 | H31: =F31*G31 -> 1135.63 | I31: 2 | J31: 137.92 | K31: =I31*J31 -> 275.84 | M31: 0 | N31: =L31*M31 -> 0 | V31: =+O31+P31+Q31+R31+S31+T31+U31-W31-X31 -> 0 | Y31: GERMAN
A32: ELECTRICISTA -A | E32: hr | G32: 119.54 | H32: =F32*G32 -> 0 | J32: 137.92 | K32: =I32*J32 -> 0 | M32: 240.95 | N32: =L32*M32 -> 0 | V32: =+O32+P32+Q32+R32+S32+T32+U32-W32-X32 -> 0 | Y32: OSCAR-OSWALDO JIM
A33: AUXILIAR TECNICO | E33: hr | G33: 106.45 | H33: =F33*G33 -> 0 | J33: 137.92 | K33: =I33*J33 -> 0 | M33: 260.95 | N33: =L33*M33 -> 0 | V33: =+O33+P33+Q33+R33+S33+T33+U33-W33-X33 -> 0
A34: AYTE ELECTRICO - B | E34: hr | G34: 106.45 | H34: =F34*G34 -> 0 | J34: 122.4 | K34: =I34*J34 -> 0 | N34: =L34*M34 -> 0 | V34: =+O34+P34+Q34+R34+S34+T34+U34-W34-X34 -> 0
A35: AYTE DE ELECTR. -A | E35: hr | G35: 106.54 | H35: =F35*G35 -> 0 | J35: 122.4 | K35: =I35*J35 -> 0 | M35: 198.17 | N35: =L35*M35 -> 0 | V35: =+O35+P35+Q35+R35+S35+T35+U35-W35-X35 -> 0 | Y35: URIEL-GUILLERMO-ENRIQUE
A36: AYTE GENERAL | E36: hr | G36: 100.42 | H36: =F36*G36 -> 0 | J36: 122.4 | K36: =I36*J36 -> 0 | M36: 0 | N36: =L36*M36 -> 0 | V36: =+O36+P36+Q36+R36+S36+T36+U36-W36-X36 -> 0
A37: PROFESIONISTA | E37: hr | G37: 209.25 | H37: =F37*G37 -> 0 | J37: 406 | K37: =I37*J37 -> 0 | M37: 564.86 | N37: =L37*M37 -> 0 | V37: 0 | Y37: O.ZARCO-GABRIEL
A38: COORDINADOR DE OPERACIONES | E38: hr | G38: 0 | H38: =F38*G38 -> 0 | J38: 0 | K38: =I38*J38 -> 0 | M38: 0 | N38: =L38*M38 -> 0 | V38: =+O38+P38+Q38+R38+S38+T38+U38-W38-X38 -> 0
A39: INGENIERIA Y SOPORTE TEC. | E39: hr | G39: 339.75 | H39: =F39*G39 -> 0 | J39: 325.79 | K39: =I39*J39 -> 0 | M39: 488.68 | N39: =L39*M39 -> 0 | V39: =+O39+P39+Q39+R39+S39+T39+U39-W39-X39 -> 0
A40: INGENIERO DE SUBESTACIONES | E40: hr | G40: 339.75 | H40: =F40*G40 -> 0 | J40: 325.79 | K40: =I40*J40 -> 0 | M40: 488.68 | N40: =L40*M40 -> 0 | V40: =+O40+P40+Q40+R40+S40+T40+U40-W40-X40 -> 0
