Workbook

Sheet Cotizacion
D1: Calle Aquiles Serdán S/N
D2: C. P. 42820, Michimaloya Centro, Tula de Allende Hgo.
D3: Oficina +52 (773) 7240055
D4: www.immee.com.mx
D5: immee_013@hotmail.com
B8: Apoyando el consumo inteligente de energía eléctrica
A10: Ing. J. Eleazar Ramirez Caudillo | C10: Michimaloya, Hidalgo a 28 de Enero de 2025.
A11: PERSA Transmision y distribucion.
A13: Presente | E13: COT. IMM-033-025
A15: Atendiendo a su amable solicitud, le presentamos a su consideración el presupuesto por el servicio de "MANTENIMIENTO PREVENTIVO Y CORRECTIVO A EQUIPOS EN SUBESTACIÓN REDUCTORA 115 A 13.8. RAMOS ARIZPE COAHUILA. " en base al siguiente alcance.
A17: No.
A18: 1 | B18: MANTENIMIENTO A INTERRUPTOR SF6 DE 115KV TANQUE MUERTO PDS 72010. | G18: ='INTERRUPTOR MO '!H111 -> 30134.215
A19: 1.1 | B19: Prueba de resistencia de aislamiento | C19: pba | D19: 6 | E19: 850 | F19: =E19*D19 -> 5100
A20: 1.2 | B20: Prueba de resistencia de contactos | C20: Pba | D20: 3 | E20: 850 | F20: =E20*D20 -> 2550 | G20: =F19+F20+F21+F22+F23+F24+F25 -> 34350
A21: 1.3 | B21: Prueba de Factor potencia | C21: Pba | D21: 6 | E21: 1200 | F21: =E21*D21 -> 7200
A22: 1.4 | B22: Prueba de Collar Caliente | C22: Pba | D22: 3 | E22: 1200 | F22: =E22*D22 -> 3600
A23: 1.5 | B23: Pruebas de transformadores tipo bushing (integrados) saturación, polaridad, relación y resistencia Ohmica. | C23: Pba | D23: 3 | E23: 2200 | F23: =E23*D23 -> 6600
A24: 1.6 | B24: Prueba de punto de rocío | C24: Pba | D24: 1 | E24: 4800 | F24: =E24*D24 -> 4800
A25: 1.7 | B25: Prueba de Simultaneidad de contactos | C25: Pba | D25: 1 | E25: 4500 | F25: =E25*D25 -> 4500
A26: 2 | B26: MATENIMIENTO A CUCHILLAS CON O SIN PUESTA A TIERRA. | G26: ='CUCHILLAS MO'!H111 -> 65628.575
A27: 2.1 | B27: Limpieza de aislamiento a columnas de aisladores | C27: serv | D27: 1 | E27: 2100 | F27: =E27*D27 -> 2100
A28: 2.2 | B28: Prueba de resistencia de aislamiento | C28: Pba | D28: 6 | E28: 850 | F28: =E28*D28 -> 5100 | G28: =F28+F29+F30+F31 -> 24600
A29: 2.3 | B29: Prueba de resistencia de contactos | C29: Pba | D29: 6 | E29: 850 | F29: =E29*D29 -> 5100
A30: 2.4 | B30: Prueba de Factor potencia | C30: Pba | D30: 6 | E30: 1200 | F30: =E30*D30 -> 7200
A31: 2.5 | B31: Prueba de Collar Caliente | C31: Pba | D31: 6 | E31: 1200 | F31: =E31*D31 -> 7200
A32: 3 | B32: MANTENIMIENTO A TRANSFORMADOR DPS T1 DE 15MVA (PRUEBAS DE LABORATORIO Y AISLAMIENTO). | G32: ='TR 15MVA MO'!H111 -> 17975.803
A33: 3.1 | B33: Prueba de resistencia de aislamiento (megger) | C33: Pba | D33: 3 | E33: 850 | F33: =E33*D33 -> 2550 | G33: =F33+F34+F35+F36+E37+E38 -> 24890
A34: 3.2 | B34: Relación de transformación en el tap nominal. | C34: Pba | D34: 3 | E34: 1500 | F34: =E34*D34 -> 4500
A35: 3.3 | B35: Factor de potencia devanados | C35: Pba | D35: 6 | E35: 1200 | F35: =E35*D35 -> 7200
A36: 3.4 | B36: Resistencia Ohmica | C36: Pba | D36: 3 | E36: 850 | F36: =E36*D36 -> 2550
A37: 3.5 | B37: Análisis Físico-Químicos al aceite de transformador | C37: Pba | D37: 1 | E37: 3890 | F37: =E37*D37 -> 3890 | G37: ='ANALISIS MO'!H111 -> 8106.4859
A38: 3.7 | B38: Cromatografía de gases disueltos al aceite de transformador | C38: Pba | D38: 1 | E38: 4200 | F38: =E38*D38 -> 4200
A39: 3.9 | B39: *Reemplazo de deposito de pruebas (recipiente de plastico quebrado). | C39: Pba | D39: 0 | E39: no se cotiza por no tener medidas
A40: 4 | B40: MANTENIMIENTO A TABLEROS EN GENERAL (METAL CLAD: 6 CELDAS, INTERRUPTORES Y MODULO DE ALARMAS). | G40: ='TABLEROS GENERAL MO'!H111 -> 102752.25
A41: 4.1 | B41: Limpieza de celdas | C41: Serv | D41: 6 | E41: 650 | F41: =E41*D41 -> 3900 | G41: =F41+F42+F43+F44+F45+F46 -> 65400
A42: 4.2 | B42: Interruptores de baja tensión | C42: Serv | D42: 6 | E42: 350 | F42: =E42*D42 -> 2100
A43: 4.3 | B43: Resistencia de aislamiento | C43: Pba | D43: 36 | E43: 550 | F43: =E43*D43 -> 19800
A44: 4.4 | B44: Resistencia de contacto | C44: Pba | D44: 18 | E44: 650 | F44: =E44*D44 -> 11700
A45: 4.5 | B45: Modulo de alarmas | C45: Pba | D45: 6 | E45: 550 | F45: =E45*D45 -> 3300
A46: 4.6 | B46: Simultaneidad de contactos | C46: Pba | D46: 6 | E46: 4100 | F46: =E46*D46 -> 24600
A47: 5 | B47: MANTENIMIENTO A SISTEMA DE RESPALDO DE BATERIAS (BANCO DE BATERIAS Y RECTIFICADOR)
A48: 5.1 | B48: Verificación Y reposición de nivel del banco de batería | C48: Pba | D48: 1 | E48: 4600 | F48: =E48*D48 -> 4600
A49: 5.2 | B49: Pruebas de Voltaje y densidad del banco de bateria. | C49: Pba | D49: 1 | E49: 2700 | F49: =E49*D49 -> 2700
A50: 6 | B50: MANTENIMIENTO A SISTEMA DE TIERRAS Y PARARAYOS (PRUEBAS-MEDICIONES).
A51: 6.1 | B51: Medición de sistema de tierras de la S.E. principal, se consideran 30 puntos. | C51: serv | D51: 1 | E51: 34570 | F51: =D51*E51 -> 34570
A52: 7 | B52: VERIFICACION Y PRUEBAS DE OPERACIÓN DE LAS PROTECCIONES 115KV Y 13,8KV.
A53: 7.1 | B53: Verificación y operación de las protecciones en 115 y 13.8 kv | C53: Pba | D53: 11 | E53: 7670 | F53: =D53*E53 -> 84370
A54: 8 | B54: TERMOGRAFIA ANTES Y DESPUES DEL MANTENIMIENTO.
A55: 8.1 | B55: Termografías antes y después de MTTO en subestación reductora | C55: Serv | D55: 2 | E55: =TERMOGRAFIA!H109 -> 49904.8 | F55: =D55*E55 -> 99809.6
A56: 9 | B56: TRASLADOS DE PERSONAL Y MAQUINARIA AL SITIO
A57: 9.1 | B57: Traslado de personal y maquinaria al sitio de trabajo el dÍa de la libranza | C57: Serv | D57: 1 | E57: ='AUTOBUS Y ALIMENTOS '!H109 -> 91064.6 | F57: =D57*E57 -> 91064.6
E58: SUBTOTAL: | F58: =F57+F55+F53+F51+F49+F48+F46+F45+F43+F44+F42+F41+F38+F37+F36+F35+F34+F33+F31+F30+F29+F28+F27+F25+F24+F23+F22+F21+F20+F19 -> 468454.2
B59: CONDICIONES TÉCNICO-COMERCIALES:
B60: 1.- Plazo de ejecución: 1 larga Jornada.
B61: 2.- Condiciones economicas: 50% al fincar la orden de servicio y 100% contra entrega de reporte .
B62: 3.- Al importe se le aplicará el impuesto IVA al facturar.
B63: 4.- Vigencia de la cotización: 30 dias del calendario.
B64: 5.- Precios en moneda nacional.
B65: 6.- Todos equipos de prueba se encuentran calibrados
A67: Atentamente:
A73: Ing. José Esteban Garcia Monrroy.
A74: Gerencia Técnica.

Sheet  INTERRUPTOR MAT.
A1: I M M E E S. A. D E C. V.
A2: A N A L I S I S D E P R E C I O U N I T A R I O
A3: COTIZACION:
A4: FECHA:
A5: PARTIDA 1
A7: MATERIALES.
A8: DESCRIPCION | E8: UNIDAD | F8: CANT. | G8: P.U. | H8: IMPORTE
A9: Solvente Dielectrico | E9: L | F9: 2 | G9: 331 | H9: =G9*F9 -> 662 | J9: HR NORMAL | L9: FQ | M9: 801
A10: Trapo | E10: kg | F10: 2 | G10: 60 | H10: =G10*F10 -> 120 | J10: HR DOBLE | L10: CM GASES | M10: 1750
A11: consumibles | E11: pza | F11: 1 | G11: 200 | H11: =G11*F11 -> 200 | J11: HR TRIPLE | L11: PCB´S | M11: 1860
E12: Pza | F12: 1 | H12: =G12*F12 -> 0
E13: Pza | F13: 1 | H13: =G13*F13 -> 0
E14: Pza | F14: 1 | H14: =G14*F14 -> 0
E15: Pza | F15: 1 | H15: =G15*F15 -> 0
E16: Pza | F16: 1 | H16: =G16*F16 -> 0
G17: SUBT 1 | H17: =SUM(H9:H16) -> 982
A19: MANO DE OBRA SIN INDIRECTOS | O19: HORARIOS DE TRABAJO | V19: HORAS RESULTANTES
A20: PERSONAL. | E20: UNIDAD | F20: CANT. | G20: P.U. | H20: IMPORTE | I20: CANT. | J20: Hr. Extra | K20: IMPORTE | L20: CANT. | M20: Dom, ó Fest. | N20: IMPORTE | O20: L | P20: M | Q20: MI | R20: J | S20: V | T20: S | U20: D | V20: N | W20: D | X20: T
A21: COORDINADOR DE OPERACIONES | E21: hr | F21: =V21 -> 0 | G21: 185.69 | H21: =F21*G21 -> 0 | I21: =W21 -> 0 | J21: =G21*1.5 -> 278.535 | K21: =I21*J21 -> 0 | L21: =X21 -> 0 | M21: =G21*2.25 -> 417.8025 | N21: =L21*M21 -> 0 | V21: =SUM(O21:T21) -> 0
A22: INGENIERIA Y SOPORTE TEC. | E22: hr | F22: =V22 -> 0 | G22: 177.79 | H22: =F22*G22 -> 0 | I22: =W22 -> 0 | J22: =G22*1.5 -> 266.685 | K22: =I22*J22 -> 0 | L22: =X22 -> 0 | M22: =G22*2.25 -> 400.0275 | N22: =L22*M22 -> 0 | V22: =SUM(O22:T22) -> 0
A23: SUPERVISOR DE SEGURIDAD CERTIFICADO | E23: hr | F23: =V23 -> 0 | G23: 185.69 | H23: =F23*G23 -> 0 | I23: =W23 -> 0 | J23: =G23*1.5 -> 278.535 | K23: =I23*J23 -> 0 | L23: =X23 -> 0 | M23: =G23*2.25 -> 417.8025 | N23: =L23*M23 -> 0 | V23: =SUM(O23:T23) -> 0
A24: SUPERVISOR ELECTRICO | E24: hr | F24: 0 | G24: 148.16 | H24: =F24*G24 -> 0 | I24: =W24 -> 0 | J24: =G24*1.5 -> 222.24 | K24: =I24*J24 -> 0 | L24: =X24 -> 0 | M24: =G24*2.25 -> 333.36 | N24: =L24*M24 -> 0 | O24: 8 | P24: 8 | Q24: 8 | R24: 8 | S24: 8 | V24: =SUM(O24:T24) -> 40 | Y24: Fco, Oropeza
A25: TECNICO DE PRUEBAS ELECTRICAS | E25: hr | F25: =V25 -> 0 | G25: 136.31 | H25: =F25*G25 -> 0 | I25: =W25 -> 0 | J25: =G25*1.5 -> 204.465 | K25: =I25*J25 -> 0 | L25: =X25 -> 0 | M25: =G25*2.25 -> 306.6975 | N25: =L25*M25 -> 0 | V25: =SUM(O25:T25) -> 0
A26: CABO OBRA ELECTRICA | E26: hr | F26: =V26 -> 0 | G26: 136.31 | H26: =F26*G26 -> 0 | I26: =W26 -> 0 | J26: =G26*1.5 -> 204.465 | K26: =I26*J26 -> 0 | L26: =X26 -> 0 | M26: =G26*2.25 -> 306.6975 | N26: =L26*M26 -> 0 | V26: =SUM(O26:T26) -> 0
A27: LINIERO | E27: hr | F27: 0 | G27: 126.43 | H27: =F27*G27 -> 0 | I27: =W27 -> 0 | J27: =G27*1.5 -> 189.645 | K27: =I27*J27 -> 0 | L27: =X27 -> 0 | M27: =G27*2.25 -> 284.4675 | N27: =L27*M27 -> 0 | O27: 16 | P27: 16 | Q27: 16 | R27: 8 | S27: 8 | T27: 5 | V27: =SUM(O27:T27) -> 69 | Y27: josé - adrian | Z27: 2
A28: LINIERO | E28: hr | F28: 0 | G28: 126.43 | H28: =F28*G28 -> 0 | I28: =W28 -> 0 | J28: =G28*1.5 -> 189.645 | K28: =I28*J28 -> 0 | L28: =X28 -> 0 | M28: =G28*2.25 -> 284.4675 | N28: =L28*M28 -> 0 | O28: 16 | P28: 16 | Q28: 16 | R28: 8 | S28: 8 | T28: 5 | V28: =SUM(O28:T28) -> 69 | Y28: josé - adrian | Z28: 2
A29: ESPECIALISTA ELECTRICO | E29: hr | F29: =V29 -> 0 | G29: 110.63 | H29: =F29*G29 -> 0 | I29: =W29 -> 0 | J29: =G29*1.5 -> 165.945 | K29: =I29*J29 -> 0 | L29: =X29 -> 0 | M29: =G29*2.25 -> 248.9175 | N29: =L29*M29 -> 0 | V29: =SUM(O29:T29) -> 0
A30: TECNICO EN INSTRUMENTACION | E30: hr | F30: =V30 -> 0 | G30: 104.36 | H30: =F30*G30 -> 0 | I30: =W30 -> 0 | J30: =G30*1.5 -> 156.54 | K30: =I30*J30 -> 0 | L30: =X30 -> 0 | M30: =G30*2.25 -> 234.81 | N30: =L30*M30 -> 0 | V30: =SUM(O30:T30) -> 0
A31: OFICIAL ELECTRICO | E31: hr | F31: 0 | G31: 104.36 | H31: =F31*G31 -> 0 | I31: =W31 -> 0 | J31: =G31*1.5 -> 156.54 | K31: =I31*J31 -> 0 | L31: =X31 -> 0 | M31: =G31*2.25 -> 234.81 | N31: =L31*M31 -> 0 | V31: =SUM(O31:T31) -> 0 | Z31: 1
A32: ASISTENTE DE DISEÑO | E32: hr | F32: 0 | G32: 104.36 | H32: =F32*G32 -> 0 | I32: =W32 -> 0 | J32: =G32*1.5 -> 156.54 | K32: =I32*J32 -> 0 | L32: =X32 -> 0 | M32: =G32*2.25 -> 234.81 | N32: =L32*M32 -> 0 | V32: =SUM(O32:T32) -> 0
A33: ELECTRICISTA -B | E33: hr | F33: 0 | G33: 90.87 | H33: =F33*G33 -> 0 | I33: =W33 -> 0 | J33: =G33*1.5 -> 136.305 | K33: =I33*J33 -> 0 | L33: =X33 -> 0 | M33: =G33*2.25 -> 204.4575 | N33: =L33*M33 -> 0 | O33: 16 | P33: 16 | Q33: 16 | R33: 8 | S33: 8 | T33: 5 | V33: =SUM(O33:T33) -> 69 | Y33: Uno con categoría de: Alan/Eduardo
A34: ELECTRICISTA -A | E34: hr | F34: =V34 -> 0 | G34: 82.97 | H34: =F34*G34 -> 0 | I34: =W34 -> 0 | J34: =G34*1.5 -> 124.455 | K34: =I34*J34 -> 0 | L34: =X34 -> 0 | M34: =G34*2.25 -> 186.6825 | N34: =L34*M34 -> 0 | V34: =SUM(O34:T34) -> 0
A35: AUXILIAR TECNICO | E35: hr | F35: =V35 -> 0 | G35: 75.07 | H35: =F35*G35 -> 0 | I35: =W35 -> 0 | J35: =G35*1.5 -> 112.605 | K35: =I35*J35 -> 0 | L35: =X35 -> 0 | M35: =G35*2.25 -> 168.9075 | N35: =L35*M35 -> 0 | V35: =SUM(O35:T35) -> 0
A36: AYTE ELECTRICO - B | E36: hr | F36: 4 | G36: 75.07 | H36: =F36*G36 -> 300.28 | I36: =W36 -> 0 | J36: =G36*1.5 -> 112.605 | K36: =I36*J36 -> 0 | L36: =X36 -> 0 | M36: =G36*2.25 -> 168.9075 | N36: =L36*M36 -> 0 | V36: =SUM(O36:T36) -> 0
A37: AYTE DE ELECTR. -A | E37: hr | F37: 0 | G37: 63.21 | H37: =F37*G37 -> 0 | I37: =W37 -> 0 | J37: =G37*1.5 -> 94.815 | K37: =I37*J37 -> 0 | L37: =X37 -> 0 | M37: =G37*2.25 -> 142.2225 | N37: =L37*M37 -> 0 | O37: 8 | P37: 8 | Q37: 8 | R37: 8 | S37: 8 | V37: =SUM(O37:T37) -> 40 | Z37: 4
A38: AYTE GENERAL | E38: hr | F38: =V38 -> 0 | G38: 50.77 | H38: =F38*G38 -> 0 | I38: =W38 -> 0 | J38: =G38*1.5 -> 76.155 | K38: =I38*J38 -> 0 | L38: =X38 -> 0 | M38: =G38*2.25 -> 114.2325 | N38: =L38*M38 -> 0 | Y38: Guadalupe | Z38: 1
A39: INGENIERO DE SUBESTACIONES | E39: hr | F39: =V39 -> 0 | G39: 186 | H39: =F39*G39 -> 0 | I39: =W39 -> 0 | J39: 186 | K39: =I39*J39 -> 0 | L39: =X39 -> 0 | M39: 186 | N39: =L39*M39 -> 0 | V39: =SUM(O39:T39) -> 0 | Z39: =SUM(Z29:Z38) -> 6
A40: INGENIERO DE PRUEBAS ELECTRICAS | E40: hr | F40: =V40 -> 0 | G40: 186 | H40: =F40*G40 -> 0 | I40: =W40 -> 0 | J40: 186 | K40: =I40*J40 -> 0 | L40: =X40 -> 0 | M40: 186 | N40: =L40*M40 -> 0 | V40: =SUM(O40:T40) -> 0
A41: ING. ESPECIALISTA EN PROTECCIONES | E41: hr | F41: =V41 -> 0 | G41: 230.47 | H41: =F41*G41 -> 0 | I41: =W41 -> 0 | J41: 294 | K41: =I41*J41 -> 0 | L41: =X41 -> 0 | M41: 294 | N41: =L41*M41 -> 0 | V41: =SUM(O41:T41) -> 0
A42: SUPERINTENDENTE | E42: hr | F42: =V42 -> 0 | G42: 279.53 | H42: =F42*G42 -> 0 | I42: =W42 -> 0 | J42: 372.71 | K42: =I42*J42 -> 0 | L42: =X42 -> 0 | M42: 559.07 | N42: =L42*M42 -> 0 | V42: =SUM(O42:T42) -> 0
F43: =V43 -> 287 | G43: SUBT 2 | H43: =SUM(H21:H42) -> 300.28 | J43: SUBT. | K43: =SUM(K22:K41) -> 0 | M43: SUBT. | N43: =SUM(N22:N41) -> 0 | V43: =SUM(V21:V42) -> 287 | W43: 45 | Z43: =+V43/W43 -> 6.3777778
G44: SUMA M.O. | H44: =H43+K43+N43 -> 300.28
A45: HERRAMIENTA MENOR | G45: 1 a 10% | H45: =+H44*0.06 -> 18.0168
A47: VEHICULOS
A48: DESCRIPCION | E48: UNIDAD | F48: CANT. | G48: P.U. | H48: IMPORTE | J48: HR IDA | K48: HR RETORNO | L48: HR SITIO | M48: SUMA
A49: camioneta RANGER sin operador sin combustible | E49: HR | F49: 0 | G49: 102.29 | H49: =F49*G49 -> 0 | J49: 0 | K49: 0 | L49: 0 | M49: =J49+K49+L49 -> 0
A50: camioneta NISSAN sin operador sin combustible | E50: HR | F50: 0 | G50: 68.7 | H50: =F50*G50 -> 0 | J50: 0 | K50: 0 | M50: =J50+K50+L50 -> 0
A51: camioneta TORNADO Tornado sin operador sin combustible | E51: HR | F51: 0 | G51: 54.43 | H51: =F51*G51 -> 0 | J51: 0.45 | K51: 0.45 | M51: =J51+K51+L51 -> 0.9
A52: Camion con grua sin operador sin conbustible. | E52: HR | F52: =M52 -> 0 | G52: 203.19 | H52: =F52*G52 -> 0 | M52: =J52+K52+L52 -> 0
A53: Camion con grua con operador con conbustible. | E53: HR | G53: 407.62 | H53: =F53*G53 -> 0
A54: autobus | E54: pza | G54: 5000 | H54: =F54*G54 -> 0
A55: Km. Recorrido (incluye conbustible y depresiación de Vehiculo | E55: KM | G55: 2.5 | H55: =F55*G55 -> 0
G56: SUBT 4 | H56: =SUM(H49:H55) -> 0
A57: COMBUSTIBLE
A58: DESCRIPCION | E58: UNIDAD | F58: CANT. | G58: P.U. | H58: IMPORTE | J58: KM IDA | K58: KM RETORNO | L58: KM SITIO | M58: SUMA
A59: GASOLINA MAGNA | E59: LT | F59: 0 | G59: 16.48 | H59: =F59*G59 -> 0 | J59: 22 | K59: 22 | M59: =J59+K59+L59 -> 44
A60: DIESEL | E60: LT | F60: =M60/4.5 -> 0 | G60: 0 | H60: =F60*G60 -> 0 | M60: =J60+K60+L60 -> 0
G61: SUBT 5 | H61: =SUM(H59:H60) -> 0
A62: CASETAS
A63: DESCRIPCION | E63: UNIDAD | F63: CANT. | G63: P.U. | H63: IMPORTE
A64: camioneta pick up | E64: CASETA | F64: 0 | G64: 180 | H64: =F64*G64 -> 0
A65: camioneta pick up | E65: CASETA | G65: 65 | H65: =F65*G65 -> 0
G66: SUBT 6 | H66: =SUM(H64:H65) -> 0
A67: VIATICOS
A68: ALIMENTOS
A69: DESCRIPCION | E69: UNIDAD | F69: CANT. | G69: P.U. | H69: IMPORTE
A70: CONSUMO DE ALIMENTOS | E70: Pza | F70: 1 | G70: 650 | H70: =F70*G70 -> 650
H71: =SUM(H70) -> 650
A72: HOSPEDAJE
A73: DESCRIPCION | E73: UNIDAD | F73: CANT. | G73: P.U. | H73: IMPORTE
A74: HOTEL | E74: NOCHES | F74: 1 | G74: 900 | H74: =F74*G74 -> 900
G75: SUBT 8 | H75: =SUM(H74) -> 900
G76: SUMA: | H76: =H56+H61+H66+H71+H75+H45+H44+H17 -> 2850.2968
A77: EQUIPO DE PRUEBA
A78: DESCRIPCION | E78: UNIDAD | F78: CANT. | G78: P.U. | H78: IMPORTE | I78: TR | K78: S.E
A79: Megger | E79: jr | G79: 2200 | H79: =(F79*G79) -> 0
A80: TTR | E80: jr | G80: 2000 | H80: =(F80*G80) -> 0
A81: Factor de Potencia de 2.5 KV | E81: jr | G81: 7000 | H81: =(F81*G81) -> 0
A82: Factor de Potencia de 10.5 KV | E82: jr | G82: 15200 | H82: =(F82*G82) -> 0
A83: Ducter | E83: jr | G83: 2200 | H83: =(F83*G83) -> 0
A84: resistencia óhmica | E84: jr | G84: 2000 | H84: =(F84*G84) -> 0
A85: hipot de 80 KV vcd | E85: jr | G85: 2500 | H85: =(F85*G85) -> 0
A86: Rigidez dieléctrica al aceite 60 kv | E86: jr | G86: 1600 | H86: =(F86*G86) -> 0
A87: Terrómetro | E87: jr | G87: 1100 | H87: =(F87*G87) -> 0
A88: Analizador de tiempos de interruptor | E88: jr | G88: 2700 | H88: =(F88*G88) -> 0
A89: Fuente de corriente para calibrador de relevadores | E89: jr | G89: 2500 | H89: =(F89*G89) -> 0
A90: Probador de relevador de Protecciones | E90: jr | G90: 13373 | H90: =(F90*G90) -> 0
... A98: Generador de Luz con combustible | E98: jr | G98: 383.5 | H98: =(F98*G98) -> 0
G99: SUBT 9 | H99: =SUM(H79:H98) -> 0
E101: 0 | H101: =+E101 -> 0 | I101: % DE IMP. | J101: INDIRECTO DISPONIBLE
G102: COSTO DIRECTO | H102: =H76+H99 -> 2850.2968
F103: Indirectos | G103: 0.1 | H103: =H102*G103 -> 285.02968 | I103: =(M109*100)/H103 -> -113.24031 | J103: =H103-M109 -> 607.79816
F104: Subtotal 1 | H104: =H102+H103 -> 3135.3265
K105: BASE IMPUESTO
F106: Financ. | G106: 0.06 | H106: =H104*G106 -> 188.11959 | I106: =H106+[1]Part.2!H84+[1]Part.3!H84+[1]Part.4!H84+[1]part.5!H84+[1]traslado!H66 -> 398.33163 | J106: COMPRAS | K106: =+H17 -> 982
F107: Subtotal 2 | H107: =H104+H106 -> 3323.4461 | J107: M.O | K107: =H44 -> 300.28
F108: Utilidad | G108: 0.1 | H108: =H107*G108 -> 332.34461 | J108: GASTOS FACTURADOS | K108: =H76-H56 -> 2850.2968 | M108: IMP. 32%
F109: Importe | H109: =H107+H108 -> 3655.7907 | J109: SUMA | K109: =SUM(K106:K108) -> 4132.5768 | L109: =H109-H108-(H103*0.7)-K109 -> -1008.6515 | M109: =0.32*L109 -> -322.76848
I110: FACTOR | J110: =H109/H102 -> 1.2826
B112: utilidad
...

Sheet INTERRUPTOR MO 
A1: I M M E E S. A. D E C. V.
A2: A N A L I S I S D E P R E C I O U N I T A R I O
A3: COTIZACION:
A4: FECHA:
A5: PARTIDA 1
A7: MATERIALES.
A8: DESCRIPCION | E8: UNIDAD | F8: CANT. | G8: P.U. | H8: IMPORTE
E9: Pza | F9: 1 | G9: 0 | H9: =G9 -> 0 | J9: HR NORMAL
E10: Pza | J10: HR DOBLE
E11: Pza | J11: HR TRIPLE
E12: Pza
E13: Pza
E14: Pza
E15: Pza
E16: Pza | I16: =H16*1.455 -> 0
G17: SUBT 1 | H17: =SUM(H9:H16) -> 0
A19: MANO DE OBRA SIN INDIRECTOS | O19: HORARIOS DE TRABAJO | V19: HORAS RESULTANTES
A20: PERSONAL. | E20: UNIDAD | F20: CANT. | G20: P.U. | H20: IMPORTE | I20: CANT. | J20: Hr. Extra | K20: IMPORTE | L20: CANT. | M20: Dom, ó Fest. | N20: IMPORTE | O20: L | P20: M | Q20: MI | R20: J | S20: V | T20: S | U20: D | V20: N | W20: D | X20: T
A21: COORDINADOR DE OPERACIONES | E21: hr | F21: =V21 -> 0 | G21: 185.69 | H21: =F21*G21 -> 0 | I21: =W21 -> 0 | J21: =G21*1.5 -> 278.535 | K21: =I21*J21 -> 0 | L21: =X21 -> 0 | M21: =G21*2.25 -> 417.8025 | N21: =L21*M21 -> 0 | V21: =SUM(O21:T21) -> 0
A22: INGENIERIA Y SOPORTE TEC. | E22: hr | F22: =V22 -> 0 | G22: 177.79 | H22: =F22*G22 -> 0 | I22: =W22 -> 0 | J22: =G22*1.5 -> 266.685 | K22: =I22*J22 -> 0 | L22: =X22 -> 0 | M22: =G22*2.25 -> 400.0275 | N22: =L22*M22 -> 0 | V22: =SUM(O22:T22) -> 0
A23: SUPERVISOR DE SEGURIDAD CERTIFICADO | E23: hr | F23: =V23 -> 0 | G23: 185.69 | H23: =F23*G23 -> 0 | I23: =W23 -> 0 | J23: =G23*1.5 -> 278.535 | K23: =I23*J23 -> 0 | L23: =X23 -> 0 | M23: =G23*2.25 -> 417.8025 | N23: =L23*M23 -> 0 | V23: =SUM(O23:T23) -> 0
A24: SUPERVISOR ELECTRICO | E24: hr | F24: 4 | G24: 237 | H24: =F24*G24 -> 948 | I24: =W24 -> 0 | J24: =G24*1.5 -> 355.5 | K24: =I24*J24 -> 0 | L24: =X24 -> 0 | M24: =G24*2.25 -> 533.25 | N24: =L24*M24 -> 0 | O24: 8 | P24: 8 | Q24: 8 | R24: 8 | S24: 8 | V24: =SUM(O24:T24) -> 40
A25: TECNICO DE PRUEBAS ELECTRICAS | E25: hr | F25: 16 | G25: 209.25 | H25: =F25*G25 -> 3348 | I25: 6 | J25: =G25*1.5 -> 313.875 | K25: =I25*J25 -> 1883.25 | L25: =X25 -> 0 | M25: =G25*2.25 -> 470.8125 | N25: =L25*M25 -> 0 | V25: =SUM(O25:T25) -> 0
A26: CABO OBRA ELECTRICA | E26: hr | F26: =V26 -> 0 | G26: 136.31 | H26: =F26*G26 -> 0 | I26: =W26 -> 0 | J26: =G26*1.5 -> 204.465 | K26: =I26*J26 -> 0 | L26: =X26 -> 0 | M26: =G26*2.25 -> 306.6975 | N26: =L26*M26 -> 0 | V26: =SUM(O26:T26) -> 0
A27: LINIERO | E27: hr | F27: 16 | G27: 190.22 | H27: =F27*G27 -> 3043.52 | I27: 6 | J27: =G27*1.5 -> 285.33 | K27: =I27*J27 -> 1711.98 | L27: =X27 -> 0 | M27: =G27*2.25 -> 427.995 | N27: =L27*M27 -> 0 | O27: 16 | P27: 16 | Q27: 16 | R27: 8 | S27: 8 | T27: 5 | V27: =SUM(O27:T27) -> 69
A28: LINIERO | E28: hr | F28: 0 | G28: 126.43 | H28: =F28*G28 -> 0 | I28: =W28 -> 0 | J28: =G28*1.5 -> 189.645 | K28: =I28*J28 -> 0 | L28: =X28 -> 0 | M28: =G28*2.25 -> 284.4675 | N28: =L28*M28 -> 0 | O28: 16 | P28: 16 | Q28: 16 | R28: 8 | S28: 8 | T28: 5 | V28: =SUM(O28:T28) -> 69
A29: ESPECIALISTA ELECTRICO | E29: hr | F29: 0 | G29: 110.63 | H29: =F29*G29 -> 0 | I29: =W29 -> 0 | J29: =G29*1.5 -> 165.945 | K29: =I29*J29 -> 0 | L29: =X29 -> 0 | M29: =G29*2.25 -> 248.9175 | N29: =L29*M29 -> 0 | V29: =SUM(O29:T29) -> 0
A30: TECNICO EN INSTRUMENTACION | E30: hr | F30: =V30 -> 0 | G30: 104.36 | H30: =F30*G30 -> 0 | I30: =W30 -> 0 | J30: =G30*1.5 -> 156.54 | K30: =I30*J30 -> 0 | L30: =X30 -> 0 | M30: =G30*2.25 -> 234.81 | N30: =L30*M30 -> 0 | V30: =SUM(O30:T30) -> 0
A31: OFICIAL ELECTRICO | E31: hr | F31: 0 | G31: 104.36 | H31: =F31*G31 -> 0 | I31: =W31 -> 0 | J31: =G31*1.5 -> 156.54 | K31: =I31*J31 -> 0 | L31: =X31 -> 0 | M31: =G31*2.25 -> 234.81 | N31: =L31*M31 -> 0 | V31: =SUM(O31:T31) -> 0
A32: ASISTENTE DE DISEÑO | E32: hr | F32: =V32 -> 0 | G32: 104.36 | H32: =F32*G32 -> 0 | I32: =W32 -> 0 | J32: =G32*1.5 -> 156.54 | K32: =I32*J32 -> 0 | L32: =X32 -> 0 | M32: =G32*2.25 -> 234.81 | N32: =L32*M32 -> 0 | V32: =SUM(O32:T32) -> 0
A33: ELECTRICISTA -B | E33: hr | F33: 0 | G33: 90.87 | H33: =F33*G33 -> 0 | I33: =W33 -> 0 | J33: =G33*1.5 -> 136.305 | K33: =I33*J33 -> 0 | L33: =X33 -> 0 | M33: =G33*2.25 -> 204.4575 | N33: =L33*M33 -> 0 | O33: 16 | P33: 16 | Q33: 16 | R33: 8 | S33: 8 | T33: 5 | V33: =SUM(O33:T33) -> 69
A34: ELECTRICISTA -A | E34: hr | F34: 0 | G34: 82.97 | H34: =F34*G34 -> 0 | I34: =W34 -> 0 | J34: =G34*1.5 -> 124.455 | K34: =I34*J34 -> 0 | L34: =X34 -> 0 | M34: =G34*2.25 -> 186.6825 | N34: =L34*M34 -> 0 | V34: =SUM(O34:T34) -> 0
A35: AUXILIAR TECNICO | E35: hr | F35: 0 | G35: 75.07 | H35: =F35*G35 -> 0 | I35: =W35 -> 0 | J35: =G35*1.5 -> 112.605 | K35: =I35*J35 -> 0 | L35: =X35 -> 0 | M35: =G35*2.25 -> 168.9075 | N35: =L35*M35 -> 0 | V35: =SUM(O35:T35) -> 0
A36: AYTE ELECTRICO - B | E36: hr | F36: 0 | G36: 75.07 | H36: =F36*G36 -> 0 | I36: =W36 -> 0 | J36: =G36*1.5 -> 112.605 | K36: =I36*J36 -> 0 | L36: =X36 -> 0 | M36: =G36*2.25 -> 168.9075 | N36: =L36*M36 -> 0 | V36: =SUM(O36:T36) -> 0
A37: AYTE DE ELECTR. -A | E37: hr | F37: 0 | G37: 63.21 | H37: =F37*G37 -> 0 | I37: =W37 -> 0 | J37: =G37*1.5 -> 94.815 | K37: =I37*J37 -> 0 | L37: =X37 -> 0 | M37: =G37*2.25 -> 142.2225 | N37: =L37*M37 -> 0 | O37: 8 | P37: 8 | Q37: 8 | R37: 8 | S37: 8 | V37: =SUM(O37:T37) -> 40
A38: AYTE GENERAL | E38: hr | F38: 0 | G38: 50.77 | H38: =F38*G38 -> 0 | I38: =W38 -> 0 | J38: =G38*1.5 -> 76.155 | K38: =I38*J38 -> 0 | L38: =X38 -> 0 | M38: =G38*2.25 -> 114.2325 | N38: =L38*M38 -> 0
A39: INGENIERO DE SUBESTACIONES | E39: hr | F39: 0 | G39: 186 | H39: =F39*G39 -> 0 | I39: =W39 -> 0 | J39: 186 | K39: =I39*J39 -> 0 | L39: =X39 -> 0 | M39: 186 | N39: =L39*M39 -> 0 | V39: =SUM(O39:T39) -> 0
A40: INGENIERO DE PRUEBAS ELECTRICAS | E40: hr | F40: 0 | G40: 186 | H40: =F40*G40 -> 0 | I40: =W40 -> 0 | J40: 186 | K40: =I40*J40 -> 0 | L40: =X40 -> 0 | M40: 186 | N40: =L40*M40 -> 0 | V40: =SUM(O40:T40) -> 0
A41: ING. ESPECIALISTA EN PROTECCIONES | E41: hr | F41: 0 | G41: 230.47 | H41: =F41*G41 -> 0 | I41: =W41 -> 0 | J41: 294 | K41: =I41*J41 -> 0 | L41: =X41 -> 0 | M41: 294 | N41: =L41*M41 -> 0 | V41: =SUM(O41:T41) -> 0
A42: SUPERINTENDENTE | E42: hr | F42: =V42 -> 0 | G42: 279.53 | H42: =F42*G42 -> 0 | I42: =W42 -> 0 | J42: 372.71 | K42: =I42*J42 -> 0 | L42: =X42 -> 0 | M42: 559.07 | N42: =L42*M42 -> 0 | V42: =SUM(O42:T42) -> 0
F43: =V43 -> 287 | G43: SUBT 2 | H43: =SUM(H21:H42) -> 7339.52 | J43: SUBT. | K43: =SUM(K22:K41) -> 3595.23 | M43: SUBT. | N43: =SUM(N22:N41) -> 0 | V43: =SUM(V21:V42) -> 287 | W43: 45
G44: SUMA M.O. | H44: =H43+K43+N43 -> 10934.75
A45: HERRAMIENTA MENOR | G45: 1 a 10% | H45: =+H44*0.06 -> 656.085
A47: VEHICULOS
A48: DESCRIPCION | E48: UNIDAD | F48: CANT. | G48: P.U. | H48: IMPORTE | J48: HR IDA | K48: HR RETORNO | L48: HR SITIO | M48: SUMA
A49: camioneta RANGER sin operador sin combustible | E49: HR | G49: 102.29 | H49: =F49*G49 -> 0 | J49: 0 | K49: 0 | L49: 0 | M49: =J49+K49+L49 -> 0
A50: camioneta NISSAN sin operador sin combustible | E50: HR | F50: 0 | G50: 68.7 | H50: =F50*G50 -> 0 | J50: 0 | K50: 0 | M50: =J50+K50+L50 -> 0
A51: camioneta TORNADO Tornado sin operador sin combustible | E51: HR | F51: 0 | G51: 54.43 | H51: =F51*G51 -> 0 | J51: 0.45 | K51: 0.45 | M51: =J51+K51+L51 -> 0.9
A52: Camion con grua sin operador sin conbustible. | E52: HR | F52: 0 | G52: 203.19 | H52: =F52*G52 -> 0 | M52: =J52+K52+L52 -> 0
A53: Camion con grua con operador con conbustible. | E53: HR | F53: 0 | G53: 407.62 | H53: =F53*G53 -> 0
A54: autobus | E54: pza | F54: 0 | G54: 5000 | H54: =F54*G54 -> 0
A55: Km. Recorrido (incluye conbustible y depresiación de Vehiculo | E55: KM | F55: 0 | G55: 2.5 | H55: =F55*G55 -> 0
G56: SUBT 4 | H56: =SUM(H49:H55) -> 0
A57: COMBUSTIBLE
A58: DESCRIPCION | E58: UNIDAD | F58: CANT. | G58: P.U. | H58: IMPORTE | J58: KM IDA | K58: KM RETORNO | L58: KM SITIO | M58: SUMA
A59: GASOLINA MAGNA | E59: LT | F59: 0 | G59: 19 | H59: =F59*G59 -> 0 | J59: 22 | K59: 22 | M59: =J59+K59+L59 -> 44
A60: DIESEL | E60: LT | F60: =M60/4.5 -> 0 | G60: 0 | H60: =F60*G60 -> 0 | M60: =J60+K60+L60 -> 0
G61: SUBT 5 | H61: =SUM(H59:H60) -> 0
A62: CASETAS
A63: DESCRIPCION | E63: UNIDAD | F63: CANT. | G63: P.U. | H63: IMPORTE
A64: camioneta pick up | E64: CASETA | F64: 0 | G64: 100 | H64: =F64*G64 -> 0
A65: camioneta pick up | E65: CASETA | F65: 0 | G65: 65 | H65: =F65*G65 -> 0
G66: SUBT 6 | H66: =SUM(H64:H65) -> 0
A67: VIATICOS
A68: ALIMENTOS
A69: DESCRIPCION | E69: UNIDAD | F69: CANT. | G69: P.U. | H69: IMPORTE
A70: CONSUMO DE ALIMENTOS | E70: Pza | F70: 0 | G70: 450 | H70: =F70*G70 -> 0
H71: =SUM(H70) -> 0
A72: HOSPEDAJE
A73: DESCRIPCION | E73: UNIDAD | F73: CANT. | G73: P.U. | H73: IMPORTE
A74: HOTEL | E74: NOCHES | F74: 0 | G74: 900 | H74: =F74*G74 -> 0
G75: SUBT 8 | H75: =SUM(H74) -> 0
G76: SUMA: | H76: =H56+H61+H66+H71+H75+H45+H44+H17 -> 11590.835
A77: EQUIPO DE PRUEBA
A78: DESCRIPCION | E78: UNIDAD | F78: CANT. | G78: P.U. | H78: IMPORTE | I78: TR | K78: S.E
A79: Megger | E79: jr | F79: 0.5 | G79: 2200 | H79: =(F79*G79) -> 1100
A80: TTR | E80: jr | F80: 0.5 | G80: 2000 | H80: =(F80*G80) -> 1000
A81: Factor de Potencia de 2.5 KV | E81: jr | F81: 0 | G81: 7000 | H81: =(F81*G81) -> 0
A82: Factor de Potencia de 10.5 KV | E82: jr | F82: 0.3 | G82: 15200 | H82: =(F82*G82) -> 4560
A83: Ducter | E83: jr | F83: 0.3 | G83: 2200 | H83: =(F83*G83) -> 660
A84: resistencia óhmica | E84: jr | F84: 0.3 | G84: 2000 | H84: =(F84*G84) -> 600
A85: hipot de 80 KV vcd | E85: jr | G85: 2500 | H85: =(F85*G85) -> 0
A86: Rigidez dieléctrica al aceite 60 kv | E86: jr | G86: 1600 | H86: =(F86*G86) -> 0
A87: Terrómetro | E87: jr | G87: 1100 | H87: =(F87*G87) -> 0
A88: Analizador de tiempos de interruptor | E88: jr | G88: 2700 | H88: =(F88*G88) -> 0
A89: Fuente de corriente para calibrador de relevadores | E89: jr | F89: 0.3 | G89: 2500 | H89: =(F89*G89) -> 750
A90: Probador de relevador de Protecciones | E90: jr | G90: 13373 | H90: =(F90*G90) -> 0
A91: Fuente trifasica de voltaje | E91: jr | G91: 800 | H91: =(F91*G91) -> 0
A92: Analizador de energía trifásica | E92: jr | G92: 1900 | H92: =(F92*G92) -> 0
A93: Medidor de presión y llenado de gas SF6 | E93: jr | G93: 2000 | H93: =(F93*G93) -> 0
A94: Medidor de secuencia de fases | E94: jr | G94: 200 | H94: =(F94*G94) -> 0
A95: Unidad de Pba y config. Para relevadores de Int. ABB | E95: jr | G95: 1100 | H95: =(F95*G95) -> 0
A96: Máquina centrifugadora de aceite | E96: jr | G96: 2200 | H96: =(F96*G96) -> 0
A97: Luxómetro | E97: jr | G97: 1420 | H97: =(F97*G97) -> 0
A98: Generador de Luz con combustible | E98: jr | F98: 1 | G98: 383.5 | H98: =(F98*G98) -> 383.5
G99: SUBT 9 | H99: =SUM(H79:H98) -> 9053.5
E101: 0 | H101: =+E101 -> 0 | I101: % DE IMP. | J101: INDIRECTO DISPONIBLE
G102: COSTO DIRECTO | H102: =H76+H99 -> 20644.335
F103: Indirectos | G103: 0.1 | H103: =H102*G103 -> 2064.4335 | I103: =(M109*100)/H103 -> 1.5594579 | J103: =H103-M109 -> 2032.2395
F104: Subtotal 1 | H104: =H102+H103 -> 22708.768
...

Sheet TERMOGRAFIA 
A1: I M M E E S. A. D E C. V.
A2: A N A L I S I S D E P R E C I O U N I T A R I O
A3: COTIZACION:
A4: FECHA:
A5: PARTIDA 1
A7: MATERIALES.
A8: DESCRIPCION | E8: UNIDAD | F8: CANT. | G8: P.U. | H8: IMPORTE
A9: CROMATOGRAFIA DE GASES | E9: Pza | F9: 1 | G9: 2813 | H9: =G9*F9 -> 2813 | J9: HR NORMAL
A10: BPC`s | E10: Pza | F10: 0 | G10: 2997.44 | H10: =G10*F10 -> 0 | J10: HR DOBLE
A11: FQ | E11: Pza | F11: 1 | G11: 1656 | H11: =G11*F11 -> 1656 | J11: HR TRIPLE
A12: JERINGA | E12: Pza | F12: 1 | G12: 50 | H12: =G12*F12 -> 50
A13: RECIPIENTE DE MUESTREO | E13: Pza | F13: 1 | G13: 70 | H13: =G13*F13 -> 70
E14: Pza | F14: 1 | H14: =G14*F14 -> 0
E15: Pza | F15: 1 | H15: =G15*F15 -> 0
E16: Pza | F16: 1 | H16: =G16*F16 -> 0
G17: SUBT 1 | H17: =SUM(H9:H16) -> 4589
A19: MANO DE OBRA SIN INDIRECTOS | O19: HORARIOS DE TRABAJO | V19: HORAS RESULTANTES
A20: PERSONAL. | E20: UNIDAD | F20: CANT. | G20: P.U. | H20: IMPORTE | I20: CANT. | J20: Hr. Extra | K20: IMPORTE | L20: CANT. | M20: Dom, ó Fest. | N20: IMPORTE | O20: L | P20: M | Q20: MI | R20: J | S20: V | T20: S | U20: D | V20: N | W20: D | X20: T
A21: COORDINADOR DE OPERACIONES | E21: hr | F21: =V21 -> 0 | G21: 185.69 | H21: =F21*G21 -> 0 | I21: =W21 -> 0 | J21: =G21*1.5 -> 278.535 | K21: =I21*J21 -> 0 | L21: =X21 -> 0 | M21: =G21*2.25 -> 417.8025 | N21: =L21*M21 -> 0 | V21: =SUM(O21:T21) -> 0
A22: INGENIERIA Y SOPORTE TEC. | E22: hr | F22: =V22 -> 0 | G22: 177.79 | H22: =F22*G22 -> 0 | I22: =W22 -> 0 | J22: =G22*1.5 -> 266.685 | K22: =I22*J22 -> 0 | L22: =X22 -> 0 | M22: =G22*2.25 -> 400.0275 | N22: =L22*M22 -> 0 | V22: =SUM(O22:T22) -> 0
A23: SUPERVISOR DE SEGURIDAD CERTIFICADO | E23: hr | F23: =V23 -> 0 | G23: 185.69 | H23: =F23*G23 -> 0 | I23: =W23 -> 0 | J23: =G23*1.5 -> 278.535 | K23: =I23*J23 -> 0 | L23: =X23 -> 0 | M23: =G23*2.25 -> 417.8025 | N23: =L23*M23 -> 0 | V23: =SUM(O23:T23) -> 0
A24: SUPERVISOR ELECTRICO | E24: hr | F24: 0 | G24: 148.16 | H24: =F24*G24 -> 0 | I24: =W24 -> 0 | J24: =G24*1.5 -> 222.24 | K24: =I24*J24 -> 0 | L24: =X24 -> 0 | M24: =G24*2.25 -> 333.36 | N24: =L24*M24 -> 0 | O24: 8 | P24: 8 | Q24: 8 | R24: 8 | S24: 8 | V24: =SUM(O24:T24) -> 40 | Y24: Fco, Oropeza
A25: TECNICO DE PRUEBAS ELECTRICAS | E25: hr | F25: =V25 -> 0 | G25: 136.31 | H25: =F25*G25 -> 0 | I25: =W25 -> 0 | J25: =G25*1.5 -> 204.465 | K25: =I25*J25 -> 0 | L25: =X25 -> 0 | M25: =G25*2.25 -> 306.6975 | N25: =L25*M25 -> 0 | V25: =SUM(O25:T25) -> 0
A26: CABO OBRA ELECTRICA | E26: hr | F26: =V26 -> 0 | G26: 136.31 | H26: =F26*G26 -> 0 | I26: =W26 -> 0 | J26: =G26*1.5 -> 204.465 | K26: =I26*J26 -> 0 | L26: =X26 -> 0 | M26: =G26*2.25 -> 306.6975 | N26: =L26*M26 -> 0 | V26: =SUM(O26:T26) -> 0
A27: LINIERO | E27: hr | F27: 0 | G27: 126.43 | H27: =F27*G27 -> 0 | I27: =W27 -> 0 | J27: =G27*1.5 -> 189.645 | K27: =I27*J27 -> 0 | L27: =X27 -> 0 | M27: =G27*2.25 -> 284.4675 | N27: =L27*M27 -> 0 | O27: 16 | P27: 16 | Q27: 16 | R27: 8 | S27: 8 | T27: 5 | V27: =SUM(O27:T27) -> 69 | Y27: josé - adrian | Z27: 2
A28: LINIERO | E28: hr | F28: 0 | G28: 126.43 | H28: =F28*G28 -> 0 | I28: =W28 -> 0 | J28: =G28*1.5 -> 189.645 | K28: =I28*J28 -> 0 | L28: =X28 -> 0 | M28: =G28*2.25 -> 284.4675 | N28: =L28*M28 -> 0 | O28: 16 | P28: 16 | Q28: 16 | R28: 8 | S28: 8 | T28: 5 | V28: =SUM(O28:T28) -> 69 | Y28: josé - adrian | Z28: 2
A29: ESPECIALISTA ELECTRICO | E29: hr | F29: =V29 -> 0 | G29: 110.63 | H29: =F29*G29 -> 0 | I29: =W29 -> 0 | J29: =G29*1.5 -> 165.945 | K29: =I29*J29 -> 0 | L29: =X29 -> 0 | M29: =G29*2.25 -> 248.9175 | N29: =L29*M29 -> 0 | V29: =SUM(O29:T29) -> 0
A30: TECNICO EN INSTRUMENTACION | E30: hr | F30: =V30 -> 0 | G30: 104.36 | H30: =F30*G30 -> 0 | I30: =W30 -> 0 | J30: =G30*1.5 -> 156.54 | K30: =I30*J30 -> 0 | L30: =X30 -> 0 | M30: =G30*2.25 -> 234.81 | N30: =L30*M30 -> 0 | V30: =SUM(O30:T30) -> 0
A31: OFICIAL ELECTRICO | E31: hr | F31: 0 | G31: 104.36 | H31: =F31*G31 -> 0 | I31: =W31 -> 0 | J31: =G31*1.5 -> 156.54 | K31: =I31*J31 -> 0 | L31: =X31 -> 0 | M31: =G31*2.25 -> 234.81 | N31: =L31*M31 -> 0 | V31: =SUM(O31:T31) -> 0 | Z31: 1
A32: ASISTENTE DE DISEÑO | E32: hr | F32: 0 | G32: 104.36 | H32: =F32*G32 -> 0 | I32: =W32 -> 0 | J32: =G32*1.5 -> 156.54 | K32: =I32*J32 -> 0 | L32: =X32 -> 0 | M32: =G32*2.25 -> 234.81 | N32: =L32*M32 -> 0 | V32: =SUM(O32:T32) -> 0
A33: ELECTRICISTA -B | E33: hr | F33: 0 | G33: 90.87 | H33: =F33*G33 -> 0 | I33: =W33 -> 0 | J33: =G33*1.5 -> 136.305 | K33: =I33*J33 -> 0 | L33: =X33 -> 0 | M33: =G33*2.25 -> 204.4575 | N33: =L33*M33 -> 0 | O33: 16 | P33: 16 | Q33: 16 | R33: 8 | S33: 8 | T33: 5 | V33: =SUM(O33:T33) -> 69 | Y33: Uno con categoría de: Alan/Eduardo
A34: ELECTRICISTA -A | E34: hr | F34: =V34 -> 0 | G34: 82.97 | H34: =F34*G34 -> 0 | I34: =W34 -> 0 | J34: =G34*1.5 -> 124.455 | K34: =I34*J34 -> 0 | L34: =X34 -> 0 | M34: =G34*2.25 -> 186.6825 | N34: =L34*M34 -> 0 | V34: =SUM(O34:T34) -> 0
A35: AUXILIAR TECNICO | E35: hr | F35: =V35 -> 0 | G35: 75.07 | H35: =F35*G35 -> 0 | I35: =W35 -> 0 | J35: =G35*1.5 -> 112.605 | K35: =I35*J35 -> 0 | L35: =X35 -> 0 | M35: =G35*2.25 -> 168.9075 | N35: =L35*M35 -> 0 | V35: =SUM(O35:T35) -> 0
A36: AYTE ELECTRICO - B | E36: hr | F36: 0 | G36: 75.07 | H36: =F36*G36 -> 0 | I36: =W36 -> 0 | J36: =G36*1.5 -> 112.605 | K36: =I36*J36 -> 0 | L36: =X36 -> 0 | M36: =G36*2.25 -> 168.9075 | N36: =L36*M36 -> 0 | V36: =SUM(O36:T36) -> 0
A37: AYTE DE ELECTR. -A | E37: hr | F37: 0 | G37: 63.21 | H37: =F37*G37 -> 0 | I37: =W37 -> 0 | J37: =G37*1.5 -> 94.815 | K37: =I37*J37 -> 0 | L37: =X37 -> 0 | M37: =G37*2.25 -> 142.2225 | N37: =L37*M37 -> 0 | O37: 8 | P37: 8 | Q37: 8 | R37: 8 | S37: 8 | V37: =SUM(O37:T37) -> 40 | Z37: 4
A38: AYTE GENERAL | E38: hr | F38: =V38 -> 0 | G38: 50.77 | H38: =F38*G38 -> 0 | I38: =W38 -> 0 | J38: =G38*1.5 -> 76.155 | K38: =I38*J38 -> 0 | L38: =X38 -> 0 | M38: =G38*2.25 -> 114.2325 | N38: =L38*M38 -> 0 | Y38: Guadalupe | Z38: 1
A39: INGENIERO DE SUBESTACIONES | E39: hr | F39: =V39 -> 0 | G39: 186 | H39: =F39*G39 -> 0 | I39: =W39 -> 0 | J39: 186 | K39: =I39*J39 -> 0 | L39: =X39 -> 0 | M39: 186 | N39: =L39*M39 -> 0 | V39: =SUM(O39:T39) -> 0 | Z39: =SUM(Z29:Z38) -> 6
A40: INGENIERO DE PRUEBAS ELECTRICAS | E40: hr | F40: =V40 -> 0 | G40: 186 | H40: =F40*G40 -> 0 | I40: =W40 -> 0 | J40: 186 | K40: =I40*J40 -> 0 | L40: =X40 -> 0 | M40: 186 | N40: =L40*M40 -> 0 | V40: =SUM(O40:T40) -> 0
A41: ING. ESPECIALISTA EN PROTECCIONES | E41: hr | F41: =V41 -> 0 | G41: 230.47 | H41: =F41*G41 -> 0 | I41: =W41 -> 0 | J41: 294 | K41: =I41*J41 -> 0 | L41: =X41 -> 0 | M41: 294 | N41: =L41*M41 -> 0 | V41: =SUM(O41:T41) -> 0
A42: SUPERINTENDENTE | E42: hr | F42: =V42 -> 0 | G42: 279.53 | H42: =F42*G42 -> 0 | I42: =W42 -> 0 | J42: 372.71 | K42: =I42*J42 -> 0 | L42: =X42 -> 0 | M42: 559.07 | N42: =L42*M42 -> 0 | V42: =SUM(O42:T42) -> 0
F43: =V43 -> 287 | G43: SUBT 2 | H43: =SUM(H21:H42) -> 0 | J43: SUBT. | K43: =SUM(K22:K41) -> 0 | M43: SUBT. | N43: =SUM(N22:N41) -> 0 | V43: =SUM(V21:V42) -> 287 | W43: 45 | Z43: =+V43/W43 -> 6.3777778
G44: SUMA M.O. | H44: =H43+K43+N43 -> 0
A45: HERRAMIENTA MENOR | G45: 1 a 10% | H45: =+H44*0.06 -> 0
A47: VEHICULOS
A48: DESCRIPCION | E48: UNIDAD | F48: CANT. | G48: P.U. | H48: IMPORTE | J48: HR IDA | K48: HR RETORNO | L48: HR SITIO | M48: SUMA
A49: camioneta RANGER sin operador sin combustible | E49: HR | F49: 0 | G49: 102.29 | H49: =F49*G49 -> 0 | J49: 0 | K49: 0 | L49: 0 | M49: =J49+K49+L49 -> 0
A50: camioneta NISSAN sin operador sin combustible | E50: HR | F50: 0 | G50: 68.7 | H50: =F50*G50 -> 0 | J50: 0 | K50: 0 | M50: =J50+K50+L50 -> 0
A51: camioneta TORNADO Tornado sin operador sin combustible | E51: HR | F51: 0 | G51: 54.43 | H51: =F51*G51 -> 0 | J51: 0.45 | K51: 0.45 | M51: =J51+K51+L51 -> 0.9
A52: Camion con grua sin operador sin conbustible. | E52: HR | F52: =M52 -> 0 | G52: 203.19 | H52: =F52*G52 -> 0 | M52: =J52+K52+L52 -> 0
A53: Camion con grua con operador con conbustible. | E53: HR | G53: 407.62 | H53: =F53*G53 -> 0
A54: autobus | E54: pza | G54: 5000 | H54: =F54*G54 -> 0
A55: Km. Recorrido (incluye conbustible y depresiación de Vehiculo | E55: KM | G55: 2.5 | H55: =F55*G55 -> 0
G56: SUBT 4 | H56: =SUM(H49:H55) -> 0
A57: COMBUSTIBLE
A58: DESCRIPCION | E58: UNIDAD | F58: CANT. | G58: P.U. | H58: IMPORTE | J58: KM IDA | K58: KM RETORNO | L58: KM SITIO | M58: SUMA
A59: GASOLINA MAGNA | E59: LT | F59: 0 | G59: 16.48 | H59: =F59*G59 -> 0 | J59: 22 | K59: 22 | M59: =J59+K59+L59 -> 44
A60: DIESEL | E60: LT | F60: =M60/4.5 -> 0 | G60: 0 | H60: =F60*G60 -> 0 | M60: =J60+K60+L60 -> 0
G61: SUBT 5 | H61: =SUM(H59:H60) -> 0
A62: CASETAS
A63: DESCRIPCION | E63: UNIDAD | F63: CANT. | G63: P.U. | H63: IMPORTE
A64: camioneta pick up | E64: CASETA | F64: 0 | G64: 180 | H64: =F64*G64 -> 0
A65: camioneta pick up | E65: CASETA | G65: 65 | H65: =F65*G65 -> 0
G66: SUBT 6 | H66: =SUM(H64:H65) -> 0
A67: VIATICOS
A68: ALIMENTOS
A69: DESCRIPCION | E69: UNIDAD | F69: CANT. | G69: P.U. | H69: IMPORTE
A70: CONSUMO DE ALIMENTOS | E70: Pza | F70: 0 | G70: 450 | H70: =F70*G70 -> 0
H71: =SUM(H70) -> 0
A72: HOSPEDAJE
A73: DESCRIPCION | E73: UNIDAD | F73: CANT. | G73: P.U. | H73: IMPORTE
A74: HOTEL | E74: NOCHES | F74: 0 | G74: 900 | H74: =F74*G74 -> 0
G75: SUBT 8 | H75: =SUM(H74) -> 0
G76: SUMA: | H76: =H56+H61+H66+H71+H75+H45+H44+H17 -> 4589
A77: EQUIPO DE PRUEBA
A78: DESCRIPCION | E78: UNIDAD | F78: CANT. | G78: P.U. | H78: IMPORTE | I78: TR | K78: S.E
A79: Megger | E79: jr | G79: 2200 | H79: =(F79*G79) -> 0
A80: TTR | E80: jr | G80: 2000 | H80: =(F80*G80) -> 0
A81: Factor de Potencia de 2.5 KV | E81: jr | G81: 7000 | H81: =(F81*G81) -> 0
A82: Factor de Potencia de 10.5 KV | E82: jr | G82: 15200 | H82: =(F82*G82) -> 0
A83: Ducter | E83: jr | G83: 2200 | H83: =(F83*G83) -> 0
A84: resistencia óhmica | E84: jr | G84: 2000 | H84: =(F84*G84) -> 0
A85: hipot de 80 KV vcd | E85: jr | G85: 2500 | H85: =(F85*G85) -> 0
A86: Rigidez dieléctrica al aceite 60 kv | E86: jr | G86: 1600 | H86: =(F86*G86) -> 0
A87: Terrómetro | E87: jr | G87: 1100 | H87: =(F87*G87) -> 0
A88: Analizador de tiempos de interruptor | E88: jr | G88: 2700 | H88: =(F88*G88) -> 0
A89: Fuente de corriente para calibrador de relevadores | E89: jr | G89: 2500 | H89: =(F89*G89) -> 0
A90: Probador de relevador de Protecciones | E90: jr | G90: 13373 | H90: =(F90*G90) -> 0
... A98: Generador de Luz con combustible | E98: jr | G98: 383.5 | H98: =(F98*G98) -> 0
G99: SUBT 9 | H99: =SUM(H79:H98) -> 0
E101: 0 | H101: =+E101 -> 0 | I101: % DE IMP. | J101: INDIRECTO DISPONIBLE
G102: COSTO DIRECTO | H102: =H76+H99 -> 4589
F103: Indirectos | G103: 0.1 | H103: =H102*G103 -> 458.9 | I103: =(M109*100)/H103 -> -289.28 | J103: =H103-M109 -> 1786.4059
F104: Subtotal 1 | H104: =H102+H103 -> 5047.9
K105: BASE IMPUESTO
F106: Financ. | G106: 0.06 | H106: =H104*G106 -> 302.874 | I106: =H106+[1]Part.2!H84+[1]Part.3!H84+[1]Part.4!H84+[1]part.5!H84+[1]traslado!H66 -> 513.08604 | J106: COMPRAS | K106: =+H17 -> 4589
F107: Subtotal 2 | H107: =H104+H106 -> 5350.774 | J107: M.O | K107: =H44 -> 0
F108: Utilidad | G108: 0.1 | H108: =H107*G108 -> 535.0774 | J108: GASTOS FACTURADOS | K108: =H76-H56 -> 4589 | M108: IMP. 32%
F109: Importe | H109: =H107+H108 -> 5885.8514 | J109: SUMA | K109: =SUM(K106:K108) -> 9178 | L109: =H109-H108-(H103*0.7)-K109 -> -4148.456 | M109: =0.32*L109 -> -1327.5059
I110: FACTOR | J110: =H109/H102 -> 1.2826
B112: utilidad
...

Sheet ANALISIS MO
A1: I M M E E S. A. D E C. V.
A2: A N A L I S I S D E P R E C I O U N I T A R I O
A3: COTIZACION:
A4: FECHA:
A5: PARTIDA 1
A7: MATERIALES.
A8: DESCRIPCION | E8: UNIDAD | F8: CANT. | G8: P.U. | H8: IMPORTE
E9: Pza | J9: HR NORMAL
E10: Pza | J10: HR DOBLE
E11: Pza | J11: HR TRIPLE
E12: Pza
E13: Pza
E14: Pza
E15: Pza
E16: Pza | I16: =H16*1.455 -> 0
G17: SUBT 1 | H17: =SUM(H9:H16) -> 0
A19: MANO DE OBRA SIN INDIRECTOS | O19: HORARIOS DE TRABAJO | V19: HORAS RESULTANTES
A20: PERSONAL. | E20: UNIDAD | F20: CANT. | G20: P.U. | H20: IMPORTE | I20: CANT. | J20: Hr. Extra | K20: IMPORTE | L20: CANT. | M20: Dom, ó Fest. | N20: IMPORTE | O20: L | P20: M | Q20: MI | R20: J | S20: V | T20: S | U20: D | V20: N | W20: D | X20: T
A21: COORDINADOR DE OPERACIONES | E21: hr | F21: =V21 -> 0 | G21: 185.69 | H21: =F21*G21 -> 0 | I21: =W21 -> 0 | J21: =G21*1.5 -> 278.535 | K21: =I21*J21 -> 0 | L21: =X21 -> 0 | M21: =G21*2.25 -> 417.8025 | N21: =L21*M21 -> 0 | V21: =SUM(O21:T21) -> 0
A22: INGENIERIA Y SOPORTE TEC. | E22: hr | F22: =V22 -> 0 | G22: 177.79 | H22: =F22*G22 -> 0 | I22: =W22 -> 0 | J22: =G22*1.5 -> 266.685 | K22: =I22*J22 -> 0 | L22: =X22 -> 0 | M22: =G22*2.25 -> 400.0275 | N22: =L22*M22 -> 0 | V22: =SUM(O22:T22) -> 0
A23: SUPERVISOR DE SEGURIDAD CERTIFICADO | E23: hr | F23: =V23 -> 0 | G23: 185.69 | H23: =F23*G23 -> 0 | I23: =W23 -> 0 | J23: =G23*1.5 -> 278.535 | K23: =I23*J23 -> 0 | L23: =X23 -> 0 | M23: =G23*2.25 -> 417.8025 | N23: =L23*M23 -> 0 | V23: =SUM(O23:T23) -> 0
A24: SUPERVISOR ELECTRICO | E24: hr | F24: 0 | G24: 148.16 | H24: =F24*G24 -> 0 | I24: =W24 -> 0 | J24: =G24*1.5 -> 222.24 | K24: =I24*J24 -> 0 | L24: =X24 -> 0 | M24: =G24*2.25 -> 333.36 | N24: =L24*M24 -> 0 | O24: 8 | P24: 8 | Q24: 8 | R24: 8 | S24: 8 | V24: =SUM(O24:T24) -> 40 | Y24: Fco, Oropeza
A25: TECNICO DE PRUEBAS ELECTRICAS | E25: hr | F25: 4 | G25: 136.31 | H25: =F25*G25 -> 545.24 | I25: =W25 -> 0 | J25: =G25*1.5 -> 204.465 | K25: =I25*J25 -> 0 | L25: =X25 -> 0 | M25: =G25*2.25 -> 306.6975 | N25: =L25*M25 -> 0 | V25: =SUM(O25:T25) -> 0
A26: CABO OBRA ELECTRICA | E26: hr | F26: =V26 -> 0 | G26: 136.31 | H26: =F26*G26 -> 0 | I26: =W26 -> 0 | J26: =G26*1.5 -> 204.465 | K26: =I26*J26 -> 0 | L26: =X26 -> 0 | M26: =G26*2.25 -> 306.6975 | N26: =L26*M26 -> 0 | V26: =SUM(O26:T26) -> 0
A27: LINIERO | E27: hr | F27: 0 | G27: 126.43 | H27: =F27*G27 -> 0 | I27: =W27 -> 0 | J27: =G27*1.5 -> 189.645 | K27: =I27*J27 -> 0 | L27: =X27 -> 0 | M27: =G27*2.25 -> 284.4675 | N27: =L27*M27 -> 0 | O27: 16 | P27: 16 | Q27: 16 | R27: 8 | S27: 8 | T27: 5 | V27: =SUM(O27:T27) -> 69 | Y27: josé - adrian | Z27: 2
A28: LINIERO | E28: hr | F28: 0 | G28: 126.43 | H28: =F28*G28 -> 0 | I28: =W28 -> 0 | J28: =G28*1.5 -> 189.645 | K28: =I28*J28 -> 0 | L28: =X28 -> 0 | M28: =G28*2.25 -> 284.4675 | N28: =L28*M28 -> 0 | O28: 16 | P28: 16 | Q28: 16 | R28: 8 | S28: 8 | T28: 5 | V28: =SUM(O28:T28) -> 69 | Y28: josé - adrian | Z28: 2
A29: ESPECIALISTA ELECTRICO | E29: hr | F29: 0 | G29: 110.63 | H29: =F29*G29 -> 0 | I29: =W29 -> 0 | J29: =G29*1.5 -> 165.945 | K29: =I29*J29 -> 0 | L29: =X29 -> 0 | M29: =G29*2.25 -> 248.9175 | N29: =L29*M29 -> 0 | V29: =SUM(O29:T29) -> 0
A30: TECNICO EN INSTRUMENTACION | E30: hr | F30: =V30 -> 0 | G30: 104.36 | H30: =F30*G30 -> 0 | I30: =W30 -> 0 | J30: =G30*1.5 -> 156.54 | K30: =I30*J30 -> 0 | L30: =X30 -> 0 | M30: =G30*2.25 -> 234.81 | N30: =L30*M30 -> 0 | V30: =SUM(O30:T30) -> 0
A31: OFICIAL ELECTRICO | E31: hr | F31: 0 | G31: 104.36 | H31: =F31*G31 -> 0 | I31: =W31 -> 0 | J31: =G31*1.5 -> 156.54 | K31: =I31*J31 -> 0 | L31: =X31 -> 0 | M31: =G31*2.25 -> 234.81 | N31: =L31*M31 -> 0 | V31: =SUM(O31:T31) -> 0 | Z31: 1
A32: ASISTENTE DE DISEÑO | E32: hr | F32: =V32 -> 0 | G32: 104.36 | H32: =F32*G32 -> 0 | I32: =W32 -> 0 | J32: =G32*1.5 -> 156.54 | K32: =I32*J32 -> 0 | L32: =X32 -> 0 | M32: =G32*2.25 -> 234.81 | N32: =L32*M32 -> 0 | V32: =SUM(O32:T32) -> 0
A33: ELECTRICISTA -B | E33: hr | F33: 8 | G33: 119 | H33: =F33*G33 -> 952 | I33: =W33 -> 0 | J33: =G33*1.5 -> 178.5 | K33: =I33*J33 -> 0 | L33: =X33 -> 0 | M33: =G33*2.25 -> 267.75 | N33: =L33*M33 -> 0 | O33: 16 | P33: 16 | Q33: 16 | R33: 8 | S33: 8 | T33: 5 | V33: =SUM(O33:T33) -> 69 | Y33: Uno con categoría de: Alan/Eduardo
A34: ELECTRICISTA -A | E34: hr | F34: 0 | G34: 82.97 | H34: =F34*G34 -> 0 | I34: =W34 -> 0 | J34: =G34*1.5 -> 124.455 | K34: =I34*J34 -> 0 | L34: =X34 -> 0 | M34: =G34*2.25 -> 186.6825 | N34: =L34*M34 -> 0 | V34: =SUM(O34:T34) -> 0
A35: AUXILIAR TECNICO | E35: hr | F35: 0 | G35: 75.07 | H35: =F35*G35 -> 0 | I35: =W35 -> 0 | J35: =G35*1.5 -> 112.605 | K35: =I35*J35 -> 0 | L35: =X35 -> 0 | M35: =G35*2.25 -> 168.9075 | N35: =L35*M35 -> 0 | V35: =SUM(O35:T35) -> 0
A36: AYTE ELECTRICO - B | E36: hr | F36: 0 | G36: 75.07 | H36: =F36*G36 -> 0 | I36: =W36 -> 0 | J36: =G36*1.5 -> 112.605 | K36: =I36*J36 -> 0 | L36: =X36 -> 0 | M36: =G36*2.25 -> 168.9075 | N36: =L36*M36 -> 0 | V36: =SUM(O36:T36) -> 0
A37: AYTE DE ELECTR. -A | E37: hr | F37: 0 | G37: 63.21 | H37: =F37*G37 -> 0 | I37: =W37 -> 0 | J37: =G37*1.5 -> 94.815 | K37: =I37*J37 -> 0 | L37: =X37 -> 0 | M37: =G37*2.25 -> 142.2225 | N37: =L37*M37 -> 0 | O37: 8 | P37: 8 | Q37: 8 | R37: 8 | S37: 8 | V37: =SUM(O37:T37) -> 40 | Z37: 4
A38: AYTE GENERAL | E38: hr | F38: 0 | G38: 50.77 | H38: =F38*G38 -> 0 | I38: =W38 -> 0 | J38: =G38*1.5 -> 76.155 | K38: =I38*J38 -> 0 | L38: =X38 -> 0 | M38: =G38*2.25 -> 114.2325 | N38: =L38*M38 -> 0 | Y38: Guadalupe | Z38: 1
A39: INGENIERO DE SUBESTACIONES | E39: hr | F39: 0 | G39: 186 | H39: =F39*G39 -> 0 | I39: =W39 -> 0 | J39: 186 | K39: =I39*J39 -> 0 | L39: =X39 -> 0 | M39: 186 | N39: =L39*M39 -> 0 | V39: =SUM(O39:T39) -> 0 | Z39: =SUM(Z29:Z38) -> 6
A40: INGENIERO DE PRUEBAS ELECTRICAS | E40: hr | F40: 0 | G40: 186 | H40: =F40*G40 -> 0 | I40: =W40 -> 0 | J40: 186 | K40: =I40*J40 -> 0 | L40: =X40 -> 0 | M40: 186 | N40: =L40*M40 -> 0 | V40: =SUM(O40:T40) -> 0
A41: ING. ESPECIALISTA EN PROTECCIONES | E41: hr | F41: 0 | G41: 230.47 | H41: =F41*G41 -> 0 | I41: =W41 -> 0 | J41: 294 | K41: =I41*J41 -> 0 | L41: =X41 -> 0 | M41: 294 | N41: =L41*M41 -> 0 | V41: =SUM(O41:T41) -> 0
A42: SUPERINTENDENTE | E42: hr | F42: =V42 -> 0 | G42: 279.53 | H42: =F42*G42 -> 0 | I42: =W42 -> 0 | J42: 372.71 | K42: =I42*J42 -> 0 | L42: =X42 -> 0 | M42: 559.07 | N42: =L42*M42 -> 0 | V42: =SUM(O42:T42) -> 0
F43: =V43 -> 287 | G43: SUBT 2 | H43: =SUM(H21:H42) -> 1497.24 | J43: SUBT. | K43: =SUM(K22:K41) -> 0 | M43: SUBT. | N43: =SUM(N22:N41) -> 0 | V43: =SUM(V21:V42) -> 287 | W43: 45 | Z43: =+V43/W43 -> 6.3777778
G44: SUMA M.O. | H44: =H43+K43+N43 -> 1497.24
A45: HERRAMIENTA MENOR | G45: 1 a 10% | H45: =+H44*0.06 -> 89.8344
A47: VEHICULOS
A48: DESCRIPCION | E48: UNIDAD | F48: CANT. | G48: P.U. | H48: IMPORTE | J48: HR IDA | K48: HR RETORNO | L48: HR SITIO | M48: SUMA
A49: camioneta RANGER sin operador sin combustible | E49: HR | F49: 0 | G49: 102.29 | H49: =F49*G49 -> 0 | J49: 0 | K49: 0 | L49: 0 | M49: =J49+K49+L49 -> 0
A50: camioneta NISSAN sin operador sin combustible | E50: HR | F50: 0 | G50: 68.7 | H50: =F50*G50 -> 0 | J50: 0 | K50: 0 | M50: =J50+K50+L50 -> 0
A51: camioneta TORNADO Tornado sin operador sin combustible | E51: HR | F51: 0 | G51: 54.43 | H51: =F51*G51 -> 0 | J51: 0.45 | K51: 0.45 | M51: =J51+K51+L51 -> 0.9
A52: Camion con grua sin operador sin conbustible. | E52: HR | F52: 0 | G52: 203.19 | H52: =F52*G52 -> 0 | M52: =J52+K52+L52 -> 0
A53: Camion con grua con operador con conbustible. | E53: HR | F53: 0 | G53: 407.62 | H53: =F53*G53 -> 0
A54: autobus | E54: pza | F54: 0 | G54: 5000 | H54: =F54*G54 -> 0
A55: Km. Recorrido (incluye conbustible y depresiación de Vehiculo | E55: KM | F55: 0 | G55: 2.5 | H55: =F55*G55 -> 0
G56: SUBT 4 | H56: =SUM(H49:H55) -> 0
A57: COMBUSTIBLE
A58: DESCRIPCION | E58: UNIDAD | F58: CANT. | G58: P.U. | H58: IMPORTE | J58: KM IDA | K58: KM RETORNO | L58: KM SITIO | M58: SUMA
A59: GASOLINA MAGNA | E59: LT | F59: 0 | G59: 19 | H59: =F59*G59 -> 0 | J59: 22 | K59: 22 | M59: =J59+K59+L59 -> 44
A60: DIESEL | E60: LT | F60: =M60/4.5 -> 0 | G60: 0 | H60: =F60*G60 -> 0 | M60: =J60+K60+L60 -> 0
G61: SUBT 5 | H61: =SUM(H59:H60) -> 0
A62: CASETAS
A63: DESCRIPCION | E63: UNIDAD | F63: CANT. | G63: P.U. | H63: IMPORTE
A64: camioneta pick up | E64: CASETA | F64: 0 | G64: 100 | H64: =F64*G64 -> 0
A65: camioneta pick up | E65: CASETA | F65: 0 | G65: 65 | H65: =F65*G65 -> 0
G66: SUBT 6 | H66: =SUM(H64:H65) -> 0
A67: VIATICOS
A68: ALIMENTOS
A69: DESCRIPCION | E69: UNIDAD | F69: CANT. | G69: P.U. | H69: IMPORTE
A70: CONSUMO DE ALIMENTOS | E70: Pza | F70: 0 | G70: 450 | H70: =F70*G70 -> 0
H71: =SUM(H70) -> 0
A72: HOSPEDAJE
A73: DESCRIPCION | E73: UNIDAD | F73: CANT. | G73: P.U. | H73: IMPORTE
A74: HOTEL | E74: NOCHES | F74: 0 | G74: 900 | H74: =F74*G74 -> 0
G75: SUBT 8 | H75: =SUM(H74) -> 0
G76: SUMA: | H76: =H56+H61+H66+H71+H75+H45+H44+H17 -> 1587.0744
A77: EQUIPO DE PRUEBA
A78: DESCRIPCION | E78: UNIDAD | F78: CANT. | G78: P.U. | H78: IMPORTE | I78: TR | K78: S.E
A79: Megger | E79: jr | G79: 2200 | H79: =(F79*G79) -> 0
A80: TTR | E80: jr | G80: 2000 | H80: =(F80*G80) -> 0
A81: Factor de Potencia de 2.5 KV | E81: jr | G81: 7000 | H81: =(F81*G81) -> 0
A82: Factor de Potencia de 10.5 KV | E82: jr | G82: 15200 | H82: =(F82*G82) -> 0
A83: Ducter | E83: jr | G83: 2200 | H83: =(F83*G83) -> 0
A84: resistencia óhmica | E84: jr | G84: 2000 | H84: =(F84*G84) -> 0
A85: hipot de 80 KV vcd | E85: jr | G85: 2500 | H85: =(F85*G85) -> 0
A86: Rigidez dieléctrica al aceite 60 kv | E86: jr | G86: 1600 | H86: =(F86*G86) -> 0
A87: Terrómetro | E87: jr | G87: 1100 | H87: =(F87*G87) -> 0
A88: Analizador de tiempos de interruptor | E88: jr | G88: 2700 | H88: =(F88*G88) -> 0
A89: Fuente de corriente para calibrador de relevadores | E89: jr | G89: 2500 | H89: =(F89*G89) -> 0
A90: Probador de relevador de Protecciones | E90: jr | G90: 13373 | H90: =(F90*G90) -> 0
... A98: Generador de Luz con combustible | E98: jr | G98: 383.5 | H98: =(F98*G98) -> 0
G99: SUBT 9 | H99: =SUM(H79:H98) -> 0
E101: 0 | H101: =+E101 -> 0 | I101: % DE IMP. | J101: INDIRECTO DISPONIBLE
G102: COSTO DIRECTO | H102: =H76+H99 -> 1587.0744
F103: Indirectos | G103: 0.1 | H103: =H102*G103 -> 158.70744 | I103: =(M109*100)/H103 -> -271.16679 | J103: =H103-M109 -> 589.06931
F104: Subtotal 1 | H104: =H102+H103 -> 1745.7818
K105: BASE IMPUESTO
F106: Financ. | G106: 0.06 | H106: =H104*G106 -> 104.74691 | I106: =H106+[1]Part.2!H84+[1]Part.3!H84+[1]Part.4!H84+[1]part.5!H84+[1]traslado!H66 -> 314.95896 | J106: COMPRAS | K106: =+H17 -> 0
F107: Subtotal 2 | H107: =H104+H106 -> 1850.5288 | J107: M.O | K107: =H44 -> 1497.24
F108: Utilidad | G108: 0.2 | H108: =H107*G108 -> 370.10575 | J108: GASTOS FACTURADOS | K108: =H76-H56 -> 1587.0744 | M108: IMP. 32%
F109: Importe | H109: =H107+H108 -> 2220.6345 | J109: SUMA | K109: =SUM(K106:K108) -> 3084.3144 | L109: =H109-H108-(H103*0.7)-K109 -> -1344.8809 | M109: =0.32*L109 -> -430.36187
F110: Materiales | H110: ='TERMOGRAFIA '!H109 -> 5885.8514 | I110: FACTOR | J110: =H109/H102 -> 1.3992
F111: Total | H111: =H109+H110 -> 8106.4859
...

Sheet TERMOGRAFIA
A1: I M M E E S. A. D E C. V.
A2: A N A L I S I S D E P R E C I O U N I T A R I O
A3: COTIZACION:
A4: FECHA:
A5: PARTIDA 1
A7: MATERIALES.
A8: DESCRIPCION | E8: UNIDAD | F8: CANT. | G8: P.U. | H8: IMPORTE
A9: TERMOGRAFIA | E9: Pza | F9: 1 | G9: 40000 | H9: =G9*F9 -> 40000 | J9: HR NORMAL
E10: kg | F10: 1 | H10: =G10*F10 -> 0 | J10: HR DOBLE
E11: pza | F11: 1 | H11: =G11*F11 -> 0 | J11: HR TRIPLE
E12: Pza | F12: 1 | H12: =G12*F12 -> 0
E13: Pza | F13: 1 | H13: =G13*F13 -> 0
E14: Pza | F14: 1 | H14: =G14*F14 -> 0
E15: Pza | F15: 1 | H15: =G15*F15 -> 0
E16: Pza | F16: 1 | H16: =G16*F16 -> 0
G17: SUBT 1 | H17: =SUM(H9:H16) -> 40000
A19: MANO DE OBRA SIN INDIRECTOS | O19: HORARIOS DE TRABAJO | V19: HORAS RESULTANTES
A20: PERSONAL. | E20: UNIDAD | F20: CANT. | G20: P.U. | H20: IMPORTE | I20: CANT. | J20: Hr. Extra | K20: IMPORTE | L20: CANT. | M20: Dom, ó Fest. | N20: IMPORTE | O20: L | P20: M | Q20: MI | R20: J | S20: V | T20: S | U20: D | V20: N | W20: D | X20: T
A21: COORDINADOR DE OPERACIONES | E21: hr | F21: =V21 -> 0 | G21: 185.69 | H21: =F21*G21 -> 0 | I21: =W21 -> 0 | J21: =G21*1.5 -> 278.535 | K21: =I21*J21 -> 0 | L21: =X21 -> 0 | M21: =G21*2.25 -> 417.8025 | N21: =L21*M21 -> 0 | V21: =SUM(O21:T21) -> 0
A22: INGENIERIA Y SOPORTE TEC. | E22: hr | F22: =V22 -> 0 | G22: 177.79 | H22: =F22*G22 -> 0 | I22: =W22 -> 0 | J22: =G22*1.5 -> 266.685 | K22: =I22*J22 -> 0 | L22: =X22 -> 0 | M22: =G22*2.25 -> 400.0275 | N22: =L22*M22 -> 0 | V22: =SUM(O22:T22) -> 0
A23: SUPERVISOR DE SEGURIDAD CERTIFICADO | E23: hr | F23: =V23 -> 0 | G23: 185.69 | H23: =F23*G23 -> 0 | I23: =W23 -> 0 | J23: =G23*1.5 -> 278.535 | K23: =I23*J23 -> 0 | L23: =X23 -> 0 | M23: =G23*2.25 -> 417.8025 | N23: =L23*M23 -> 0 | V23: =SUM(O23:T23) -> 0
A24: SUPERVISOR ELECTRICO | E24: hr | F24: 0 | G24: 148.16 | H24: =F24*G24 -> 0 | I24: =W24 -> 0 | J24: =G24*1.5 -> 222.24 | K24: =I24*J24 -> 0 | L24: =X24 -> 0 | M24: =G24*2.25 -> 333.36 | N24: =L24*M24 -> 0 | O24: 8 | P24: 8 | Q24: 8 | R24: 8 | S24: 8 | V24: =SUM(O24:T24) -> 40 | Y24: Fco, Oropeza
A25: TECNICO DE PRUEBAS ELECTRICAS | E25: hr | F25: =V25 -> 0 | G25: 136.31 | H25: =F25*G25 -> 0 | I25: =W25 -> 0 | J25: =G25*1.5 -> 204.465 | K25: =I25*J25 -> 0 | L25: =X25 -> 0 | M25: =G25*2.25 -> 306.6975 | N25: =L25*M25 -> 0 | V25: =SUM(O25:T25) -> 0
A26: CABO OBRA ELECTRICA | E26: hr | F26: =V26 -> 0 | G26: 136.31 | H26: =F26*G26 -> 0 | I26: =W26 -> 0 | J26: =G26*1.5 -> 204.465 | K26: =I26*J26 -> 0 | L26: =X26 -> 0 | M26: =G26*2.25 -> 306.6975 | N26: =L26*M26 -> 0 | V26: =SUM(O26:T26) -> 0
A27: LINIERO | E27: hr | F27: 0 | G27: 126.43 | H27: =F27*G27 -> 0 | I27: =W27 -> 0 | J27: =G27*1.5 -> 189.645 | K27: =I27*J27 -> 0 | L27: =X27 -> 0 | M27: =G27*2.25 -> 284.4675 | N27: =L27*M27 -> 0 | O27: 16 | P27: 16 | Q27: 16 | R27: 8 | S27: 8 | T27: 5 | V27: =SUM(O27:T27) -> 69 | Y27: josé - adrian | Z27: 2
A28: LINIERO | E28: hr | F28: 0 | G28: 126.43 | H28: =F28*G28 -> 0 | I28: =W28 -> 0 | J28: =G28*1.5 -> 189.645 | K28: =I28*J28 -> 0 | L28: =X28 -> 0 | M28: =G28*2.25 -> 284.4675 | N28: =L28*M28 -> 0 | O28: 16 | P28: 16 | Q28: 16 | R28: 8 | S28: 8 | T28: 5 | V28: =SUM(O28:T28) -> 69 | Y28: josé - adrian | Z28: 2
A29: ESPECIALISTA ELECTRICO | E29: hr | F29: =V29 -> 0 | G29: 110.63 | H29: =F29*G29 -> 0 | I29: =W29 -> 0 | J29: =G29*1.5 -> 165.945 | K29: =I29*J29 -> 0 | L29: =X29 -> 0 | M29: =G29*2.25 -> 248.9175 | N29: =L29*M29 -> 0 | V29: =SUM(O29:T29) -> 0
A30: TECNICO EN INSTRUMENTACION | E30: hr | F30: =V30 -> 0 | G30: 104.36 | H30: =F30*G30 -> 0 | I30: =W30 -> 0 | J30: =G30*1.5 -> 156.54 | K30: =I30*J30 -> 0 | L30: =X30 -> 0 | M30: =G30*2.25 -> 234.81 | N30: =L30*M30 -> 0 | V30: =SUM(O30:T30) -> 0
A31: OFICIAL ELECTRICO | E31: hr | F31: 0 | G31: 104.36 | H31: =F31*G31 -> 0 | I31: =W31 -> 0 | J31: =G31*1.5 -> 156.54 | K31: =I31*J31 -> 0 | L31: =X31 -> 0 | M31: =G31*2.25 -> 234.81 | N31: =L31*M31 -> 0 | V31: =SUM(O31:T31) -> 0 | Z31: 1
A32: ASISTENTE DE DISEÑO | E32: hr | F32: 0 | G32: 104.36 | H32: =F32*G32 -> 0 | I32: =W32 -> 0 | J32: =G32*1.5 -> 156.54 | K32: =I32*J32 -> 0 | L32: =X32 -> 0 | M32: =G32*2.25 -> 234.81 | N32: =L32*M32 -> 0 | V32: =SUM(O32:T32) -> 0
A33: ELECTRICISTA -B | E33: hr | F33: 0 | G33: 90.87 | H33: =F33*G33 -> 0 | I33: =W33 -> 0 | J33: =G33*1.5 -> 136.305 | K33: =I33*J33 -> 0 | L33: =X33 -> 0 | M33: =G33*2.25 -> 204.4575 | N33: =L33*M33 -> 0 | O33: 16 | P33: 16 | Q33: 16 | R33: 8 | S33: 8 | T33: 5 | V33: =SUM(O33:T33) -> 69 | Y33: Uno con categoría de: Alan/Eduardo
A34: ELECTRICISTA -A | E34: hr | F34: =V34 -> 0 | G34: 82.97 | H34: =F34*G34 -> 0 | I34: =W34 -> 0 | J34: =G34*1.5 -> 124.455 | K34: =I34*J34 -> 0 | L34: =X34 -> 0 | M34: =G34*2.25 -> 186.6825 | N34: =L34*M34 -> 0 | V34: =SUM(O34:T34) -> 0
A35: AUXILIAR TECNICO | E35: hr | F35: =V35 -> 0 | G35: 75.07 | H35: =F35*G35 -> 0 | I35: =W35 -> 0 | J35: =G35*1.5 -> 112.605 | K35: =I35*J35 -> 0 | L35: =X35 -> 0 | M35: =G35*2.25 -> 168.9075 | N35: =L35*M35 -> 0 | V35: =SUM(O35:T35) -> 0
A36: AYTE ELECTRICO - B | E36: hr | F36: 0 | G36: 75.07 | H36: =F36*G36 -> 0 | I36: =W36 -> 0 | J36: =G36*1.5 -> 112.605 | K36: =I36*J36 -> 0 | L36: =X36 -> 0 | M36: =G36*2.25 -> 168.9075 | N36: =L36*M36 -> 0 | V36: =SUM(O36:T36) -> 0
A37: AYTE DE ELECTR. -A | E37: hr | F37: 0 | G37: 63.21 | H37: =F37*G37 -> 0 | I37: =W37 -> 0 | J37: =G37*1.5 -> 94.815 | K37: =I37*J37 -> 0 | L37: =X37 -> 0 | M37: =G37*2.25 -> 142.2225 | N37: =L37*M37 -> 0 | O37: 8 | P37: 8 | Q37: 8 | R37: 8 | S37: 8 | V37: =SUM(O37:T37) -> 40 | Z37: 4
A38: AYTE GENERAL | E38: hr | F38: =V38 -> 0 | G38: 50.77 | H38: =F38*G38 -> 0 | I38: =W38 -> 0 | J38: =G38*1.5 -> 76.155 | K38: =I38*J38 -> 0 | L38: =X38 -> 0 | M38: =G38*2.25 -> 114.2325 | N38: =L38*M38 -> 0 | Y38: Guadalupe | Z38: 1
A39: INGENIERO DE SUBESTACIONES | E39: hr | F39: =V39 -> 0 | G39: 186 | H39: =F39*G39 -> 0 | I39: =W39 -> 0 | J39: 186 | K39: =I39*J39 -> 0 | L39: =X39 -> 0 | M39: 186 | N39: =L39*M39 -> 0 | V39: =SUM(O39:T39) -> 0 | Z39: =SUM(Z29:Z38) -> 6
A40: INGENIERO DE PRUEBAS ELECTRICAS | E40: hr | F40: =V40 -> 0 | G40: 186 | H40: =F40*G40 -> 0 | I40: =W40 -> 0 | J40: 186 | K40: =I40*J40 -> 0 | L40: =X40 -> 0 | M40: 186 | N40: =L40*M40 -> 0 | V40: =SUM(O40:T40) -> 0
A41: ING. ESPECIALISTA EN PROTECCIONES | E41: hr | F41: =V41 -> 0 | G41: 230.47 | H41: =F41*G41 -> 0 | I41: =W41 -> 0 | J41: 294 | K41: =I41*J41 -> 0 | L41: =X41 -> 0 | M41: 294 | N41: =L41*M41 -> 0 | V41: =SUM(O41:T41) -> 0
A42: SUPERINTENDENTE | E42: hr | F42: =V42 -> 0 | G42: 279.53 | H42: =F42*G42 -> 0 | I42: =W42 -> 0 | J42: 372.71 | K42: =I42*J42 -> 0 | L42: =X42 -> 0 | M42: 559.07 | N42: =L42*M42 -> 0 | V42: =SUM(O42:T42) -> 0
F43: =V43 -> 287 | G43: SUBT 2 | H43: =SUM(H21:H42) -> 0 | J43: SUBT. | K43: =SUM(K22:K41) -> 0 | M43: SUBT. | N43: =SUM(N22:N41) -> 0 | V43: =SUM(V21:V42) -> 287 | W43: 45 | Z43: =+V43/W43 -> 6.3777778
G44: SUMA M.O. | H44: =H43+K43+N43 -> 0
A45: HERRAMIENTA MENOR | G45: 1 a 10% | H45: =+H44*0.06 -> 0
A47: VEHICULOS
A48: DESCRIPCION | E48: UNIDAD | F48: CANT. | G48: P.U. | H48: IMPORTE | J48: HR IDA | K48: HR RETORNO | L48: HR SITIO | M48: SUMA
A49: camioneta RANGER sin operador sin combustible | E49: HR | F49: 0 | G49: 102.29 | H49: =F49*G49 -> 0 | J49: 0 | K49: 0 | L49: 0 | M49: =J49+K49+L49 -> 0
A50: camioneta NISSAN sin operador sin combustible | E50: HR | F50: 0 | G50: 68.7 | H50: =F50*G50 -> 0 | J50: 0 | K50: 0 | M50: =J50+K50+L50 -> 0
A51: camioneta TORNADO Tornado sin operador sin combustible | E51: HR | F51: 0 | G51: 54.43 | H51: =F51*G51 -> 0 | J51: 0.45 | K51: 0.45 | M51: =J51+K51+L51 -> 0.9
A52: Camion con grua sin operador sin conbustible. | E52: HR | F52: =M52 -> 0 | G52: 203.19 | H52: =F52*G52 -> 0 | M52: =J52+K52+L52 -> 0
A53: Camion con grua con operador con conbustible. | E53: HR | G53: 407.62 | H53: =F53*G53 -> 0
A54: autobus | E54: pza | G54: 5000 | H54: =F54*G54 -> 0
A55: Km. Recorrido (incluye conbustible y depresiación de Vehiculo | E55: KM | G55: 2.5 | H55: =F55*G55 -> 0
G56: SUBT 4 | H56: =SUM(H49:H55) -> 0
A57: COMBUSTIBLE
A58: DESCRIPCION | E58: UNIDAD | F58: CANT. | G58: P.U. | H58: IMPORTE | J58: KM IDA | K58: KM RETORNO | L58: KM SITIO | M58: SUMA
A59: GASOLINA MAGNA | E59: LT | F59: 0 | G59: 16.48 | H59: =F59*G59 -> 0 | J59: 22 | K59: 22 | M59: =J59+K59+L59 -> 44
A60: DIESEL | E60: LT | F60: =M60/4.5 -> 0 | G60: 0 | H60: =F60*G60 -> 0 | M60: =J60+K60+L60 -> 0
G61: SUBT 5 | H61: =SUM(H59:H60) -> 0
A62: CASETAS
A63: DESCRIPCION | E63: UNIDAD | F63: CANT. | G63: P.U. | H63: IMPORTE
A64: camioneta pick up | E64: CASETA | F64: 0 | G64: 180 | H64: =F64*G64 -> 0
A65: camioneta pick up | E65: CASETA | G65: 65 | H65: =F65*G65 -> 0
G66: SUBT 6 | H66: =SUM(H64:H65) -> 0
A67: VIATICOS
A68: ALIMENTOS
A69: DESCRIPCION | E69: UNIDAD | F69: CANT. | G69: P.U. | H69: IMPORTE
A70: CONSUMO DE ALIMENTOS | E70: Pza | F70: 0 | G70: 450 | H70: =F70*G70 -> 0
H71: =SUM(H70) -> 0
A72: HOSPEDAJE
A73: DESCRIPCION | E73: UNIDAD | F73: CANT. | G73: P.U. | H73: IMPORTE
A74: HOTEL | E74: NOCHES | F74: 0 | G74: 900 | H74: =F74*G74 -> 0
G75: SUBT 8 | H75: =SUM(H74) -> 0
G76: SUMA: | H76: =H56+H61+H66+H71+H75+H45+H44+H17 -> 40000
A77: EQUIPO DE PRUEBA
A78: DESCRIPCION | E78: UNIDAD | F78: CANT. | G78: P.U. | H78: IMPORTE | I78: TR | K78: S.E
A79: Megger | E79: jr | G79: 2200 | H79: =(F79*G79) -> 0
A80: TTR | E80: jr | G80: 2000 | H80: =(F80*G80) -> 0
A81: Factor de Potencia de 2.5 KV | E81: jr | G81: 7000 | H81: =(F81*G81) -> 0
A82: Factor de Potencia de 10.5 KV | E82: jr | G82: 15200 | H82: =(F82*G82) -> 0
A83: Ducter | E83: jr | G83: 2200 | H83: =(F83*G83) -> 0
A84: resistencia óhmica | E84: jr | G84: 2000 | H84: =(F84*G84) -> 0
A85: hipot de 80 KV vcd | E85: jr | G85: 2500 | H85: =(F85*G85) -> 0
A86: Rigidez dieléctrica al aceite 60 kv | E86: jr | G86: 1600 | H86: =(F86*G86) -> 0
A87: Terrómetro | E87: jr | G87: 1100 | H87: =(F87*G87) -> 0
A88: Analizador de tiempos de interruptor | E88: jr | G88: 2700 | H88: =(F88*G88) -> 0
A89: Fuente de corriente para calibrador de relevadores | E89: jr | G89: 2500 | H89: =(F89*G89) -> 0
A90: Probador de relevador de Protecciones | E90: jr | G90: 13373 | H90: =(F90*G90) -> 0
... A98: Generador de Luz con combustible | E98: jr | G98: 383.5 | H98: =(F98*G98) -> 0
G99: SUBT 9 | H99: =SUM(H79:H98) -> 0
E101: 0 | H101: =+E101 -> 0 | I101: % DE IMP. | J101: INDIRECTO DISPONIBLE
G102: COSTO DIRECTO | H102: =H76+H99 -> 40000
F103: Indirectos | G103: 0.1 | H103: =H102*G103 -> 4000 | I103: =(M109*100)/H103 -> -289.28 | J103: =H103-M109 -> 15571.2
F104: Subtotal 1 | H104: =H102+H103 -> 44000
K105: BASE IMPUESTO
F106: Financ. | H106: =H104*G107 -> 2640 | I106: =H106+[1]Part.2!H84+[1]Part.3!H84+[1]Part.4!H84+[1]part.5!H84+[1]traslado!H66 -> 2850.212 | J106: COMPRAS | K106: =+H17 -> 40000
F107: Subtotal 2 | G107: 0.06 | H107: =H104+H106 -> 46640 | J107: M.O | K107: =H44 -> 0
F108: Utilidad | G108: 0.07 | H108: =H107*G108 -> 3264.8 | J108: GASTOS FACTURADOS | K108: =H76-H56 -> 40000 | M108: IMP. 32%
F109: Importe | H109: =H107+H108 -> 49904.8 | J109: SUMA | K109: =SUM(K106:K108) -> 80000 | L109: =H109-H108-(H103*0.7)-K109 -> -36160 | M109: =0.32*L109 -> -11571.2
I110: FACTOR | J110: =H109/H102 -> 1.24762
B112: utilidad
...

Sheet CUCHILLAS MO
A1: I M M E E S. A. D E C. V.
A2: A N A L I S I S D E P R E C I O U N I T A R I O
A3: COTIZACION:
A4: FECHA:
A5: PARTIDA 1
A7: MATERIALES.
A8: DESCRIPCION | E8: UNIDAD | F8: CANT. | G8: P.U. | H8: IMPORTE
E9: Pza | J9: HR NORMAL
E10: Pza | J10: HR DOBLE
E11: Pza | J11: HR TRIPLE
E12: Pza
E13: Pza
E14: Pza
E15: Pza
E16: Pza | I16: =H16*1.455 -> 0
G17: SUBT 1 | H17: =SUM(H9:H16) -> 0
A19: MANO DE OBRA SIN INDIRECTOS | O19: HORARIOS DE TRABAJO | V19: HORAS RESULTANTES
A20: PERSONAL. | E20: UNIDAD | F20: CANT. | G20: P.U. | H20: IMPORTE | I20: CANT. | J20: Hr. Extra | K20: IMPORTE | L20: CANT. | M20: Dom, ó Fest. | N20: IMPORTE | O20: L | P20: M | Q20: MI | R20: J | S20: V | T20: S | U20: D | V20: N | W20: D | X20: T
A21: COORDINADOR DE OPERACIONES | E21: hr | F21: =V21 -> 0 | G21: 185.69 | H21: =F21*G21 -> 0 | I21: =W21 -> 0 | J21: =G21*1.5 -> 278.535 | K21: =I21*J21 -> 0 | L21: =X21 -> 0 | M21: =G21*2.25 -> 417.8025 | N21: =L21*M21 -> 0 | V21: =SUM(O21:T21) -> 0
A22: INGENIERIA Y SOPORTE TEC. | E22: hr | F22: =V22 -> 0 | G22: 177.79 | H22: =F22*G22 -> 0 | I22: =W22 -> 0 | J22: =G22*1.5 -> 266.685 | K22: =I22*J22 -> 0 | L22: =X22 -> 0 | M22: =G22*2.25 -> 400.0275 | N22: =L22*M22 -> 0 | V22: =SUM(O22:T22) -> 0
A23: SUPERVISOR DE SEGURIDAD CERTIFICADO | E23: hr | F23: =V23 -> 0 | G23: 185.69 | H23: =F23*G23 -> 0 | I23: =W23 -> 0 | J23: =G23*1.5 -> 278.535 | K23: =I23*J23 -> 0 | L23: =X23 -> 0 | M23: =G23*2.25 -> 417.8025 | N23: =L23*M23 -> 0 | V23: =SUM(O23:T23) -> 0
A24: SUPERVISOR ELECTRICO | E24: hr | F24: 8 | G24: 148.16 | H24: =F24*G24 -> 1185.28 | I24: 0 | J24: =G24*1.5 -> 222.24 | K24: =I24*J24 -> 0 | L24: =X24 -> 0 | M24: =G24*2.25 -> 333.36 | N24: =L24*M24 -> 0 | O24: 8 | P24: 8 | Q24: 8 | R24: 8 | S24: 8 | V24: =SUM(O24:T24) -> 40 | Y24: Fco, Oropeza
A25: TECNICO DE PRUEBAS ELECTRICAS | E25: hr | F25: 8 | G25: 136.31 | H25: =F25*G25 -> 1090.48 | I25: =W25 -> 0 | J25: =G25*1.5 -> 204.465 | K25: =I25*J25 -> 0 | L25: =X25 -> 0 | M25: =G25*2.25 -> 306.6975 | N25: =L25*M25 -> 0 | V25: =SUM(O25:T25) -> 0
A26: CABO OBRA ELECTRICA | E26: hr | F26: =V26 -> 0 | G26: 136.31 | H26: =F26*G26 -> 0 | I26: =W26 -> 0 | J26: =G26*1.5 -> 204.465 | K26: =I26*J26 -> 0 | L26: =X26 -> 0 | M26: =G26*2.25 -> 306.6975 | N26: =L26*M26 -> 0 | V26: =SUM(O26:T26) -> 0
A27: LINIERO | E27: hr | F27: 8 | G27: 126.43 | H27: =F27*G27 -> 1011.44 | I27: =W27 -> 0 | J27: =G27*1.5 -> 189.645 | K27: =I27*J27 -> 0 | L27: =X27 -> 0 | M27: =G27*2.25 -> 284.4675 | N27: =L27*M27 -> 0 | O27: 16 | P27: 16 | Q27: 16 | R27: 8 | S27: 8 | T27: 5 | V27: =SUM(O27:T27) -> 69 | Y27: josé - adrian | Z27: 2
A28: LINIERO | E28: hr | F28: 0 | G28: 126.43 | H28: =F28*G28 -> 0 | I28: =W28 -> 0 | J28: =G28*1.5 -> 189.645 | K28: =I28*J28 -> 0 | L28: =X28 -> 0 | M28: =G28*2.25 -> 284.4675 | N28: =L28*M28 -> 0 | O28: 16 | P28: 16 | Q28: 16 | R28: 8 | S28: 8 | T28: 5 | V28: =SUM(O28:T28) -> 69 | Y28: josé - adrian | Z28: 2
A29: ESPECIALISTA ELECTRICO | E29: hr | F29: 8 | G29: 110.63 | H29: =F29*G29 -> 885.04 | I29: 0 | J29: =G29*1.5 -> 165.945 | K29: =I29*J29 -> 0 | L29: =X29 -> 0 | M29: =G29*2.25 -> 248.9175 | N29: =L29*M29 -> 0 | V29: =SUM(O29:T29) -> 0
A30: TECNICO EN INSTRUMENTACION | E30: hr | F30: =V30 -> 0 | G30: 104.36 | H30: =F30*G30 -> 0 | I30: =W30 -> 0 | J30: =G30*1.5 -> 156.54 | K30: =I30*J30 -> 0 | L30: =X30 -> 0 | M30: =G30*2.25 -> 234.81 | N30: =L30*M30 -> 0 | V30: =SUM(O30:T30) -> 0
A31: OFICIAL ELECTRICO | E31: hr | F31: 8 | G31: 104.36 | H31: =F31*G31 -> 834.88 | I31: 0 | J31: =G31*1.5 -> 156.54 | K31: =I31*J31 -> 0 | L31: =X31 -> 0 | M31: =G31*2.25 -> 234.81 | N31: =L31*M31 -> 0 | V31: =SUM(O31:T31) -> 0 | Z31: 1
A32: ASISTENTE DE DISEÑO | E32: hr | F32: =V32 -> 0 | G32: 104.36 | H32: =F32*G32 -> 0 | I32: =W32 -> 0 | J32: =G32*1.5 -> 156.54 | K32: =I32*J32 -> 0 | L32: =X32 -> 0 | M32: =G32*2.25 -> 234.81 | N32: =L32*M32 -> 0 | V32: =SUM(O32:T32) -> 0
A33: ELECTRICISTA -B | E33: hr | F33: 0 | G33: 90.87 | H33: =F33*G33 -> 0 | I33: =W33 -> 0 | J33: =G33*1.5 -> 136.305 | K33: =I33*J33 -> 0 | L33: =X33 -> 0 | M33: =G33*2.25 -> 204.4575 | N33: =L33*M33 -> 0 | O33: 16 | P33: 16 | Q33: 16 | R33: 8 | S33: 8 | T33: 5 | V33: =SUM(O33:T33) -> 69 | Y33: Uno con categoría de: Alan/Eduardo
A34: ELECTRICISTA -A | E34: hr | F34: 0 | G34: 82.97 | H34: =F34*G34 -> 0 | I34: =W34 -> 0 | J34: =G34*1.5 -> 124.455 | K34: =I34*J34 -> 0 | L34: =X34 -> 0 | M34: =G34*2.25 -> 186.6825 | N34: =L34*M34 -> 0 | V34: =SUM(O34:T34) -> 0
A35: AUXILIAR TECNICO | E35: hr | F35: 0 | G35: 75.07 | H35: =F35*G35 -> 0 | I35: =W35 -> 0 | J35: =G35*1.5 -> 112.605 | K35: =I35*J35 -> 0 | L35: =X35 -> 0 | M35: =G35*2.25 -> 168.9075 | N35: =L35*M35 -> 0 | V35: =SUM(O35:T35) -> 0
A36: AYTE ELECTRICO - B | E36: hr | F36: 0 | G36: 75.07 | H36: =F36*G36 -> 0 | I36: =W36 -> 0 | J36: =G36*1.5 -> 112.605 | K36: =I36*J36 -> 0 | L36: =X36 -> 0 | M36: =G36*2.25 -> 168.9075 | N36: =L36*M36 -> 0 | V36: =SUM(O36:T36) -> 0
A37: AYTE DE ELECTR. -A | E37: hr | F37: 0 | G37: 63.21 | H37: =F37*G37 -> 0 | I37: =W37 -> 0 | J37: =G37*1.5 -> 94.815 | K37: =I37*J37 -> 0 | L37: =X37 -> 0 | M37: =G37*2.25 -> 142.2225 | N37: =L37*M37 -> 0 | O37: 8 | P37: 8 | Q37: 8 | R37: 8 | S37: 8 | V37: =SUM(O37:T37) -> 40 | Z37: 4
A38: AYTE GENERAL | E38: hr | F38: 0 | G38: 50.77 | H38: =F38*G38 -> 0 | I38: =W38 -> 0 | J38: =G38*1.5 -> 76.155 | K38: =I38*J38 -> 0 | L38: =X38 -> 0 | M38: =G38*2.25 -> 114.2325 | N38: =L38*M38 -> 0 | Y38: Guadalupe | Z38: 1
A39: INGENIERO DE SUBESTACIONES | E39: hr | F39: 0 | G39: 186 | H39: =F39*G39 -> 0 | I39: =W39 -> 0 | J39: 186 | K39: =I39*J39 -> 0 | L39: =X39 -> 0 | M39: 186 | N39: =L39*M39 -> 0 | V39: =SUM(O39:T39) -> 0 | Z39: =SUM(Z29:Z38) -> 6
A40: INGENIERO DE PRUEBAS ELECTRICAS | E40: hr | F40: 0 | G40: 186 | H40: =F40*G40 -> 0 | I40: =W40 -> 0 | J40: 186 | K40: =I40*J40 -> 0 | L40: =X40 -> 0 | M40: 186 | N40: =L40*M40 -> 0 | V40: =SUM(O40:T40) -> 0
A41: ING. ESPECIALISTA EN PROTECCIONES | E41: hr | F41: 0 | G41: 230.47 | H41: =F41*G41 -> 0 | I41: =W41 -> 0 | J41: 294 | K41: =I41*J41 -> 0 | L41: =X41 -> 0 | M41: 294 | N41: =L41*M41 -> 0 | V41: =SUM(O41:T41) -> 0
A42: SUPERINTENDENTE | E42: hr | F42: =V42 -> 0 | G42: 279.53 | H42: =F42*G42 -> 0 | I42: =W42 -> 0 | J42: 372.71 | K42: =I42*J42 -> 0 | L42: =X42 -> 0 | M42: 559.07 | N42: =L42*M42 -> 0 | V42: =SUM(O42:T42) -> 0
F43: =V43 -> 287 | G43: SUBT 2 | H43: =SUM(H21:H42) -> 5007.12 | J43: SUBT. | K43: =SUM(K22:K41) -> 0 | M43: SUBT. | N43: =SUM(N22:N41) -> 0 | V43: =SUM(V21:V42) -> 287 | W43: 45 | Z43: =+V43/W43 -> 6.3777778
G44: SUMA M.O. | H44: =H43+K43+N43 -> 5007.12
A45: HERRAMIENTA MENOR | G45: 1 a 10% | H45: =+H44*0.06 -> 300.4272
A47: VEHICULOS
A48: DESCRIPCION | E48: UNIDAD | F48: CANT. | G48: P.U. | H48: IMPORTE | J48: HR IDA | K48: HR RETORNO | L48: HR SITIO | M48: SUMA
A49: camioneta RANGER sin operador sin combustible | E49: HR | F49: 0 | G49: 102.29 | H49: =F49*G49 -> 0 | J49: 0 | K49: 0 | L49: 0 | M49: =J49+K49+L49 -> 0
A50: camioneta NISSAN sin operador sin combustible | E50: HR | F50: 0 | G50: 68.7 | H50: =F50*G50 -> 0 | J50: 0 | K50: 0 | M50: =J50+K50+L50 -> 0
A51: camioneta TORNADO Tornado sin operador sin combustible | E51: HR | F51: 0 | G51: 54.43 | H51: =F51*G51 -> 0 | J51: 0.45 | K51: 0.45 | M51: =J51+K51+L51 -> 0.9
A52: Camion con grua sin operador sin conbustible. | E52: HR | F52: 0 | G52: 203.19 | H52: =F52*G52 -> 0 | M52: =J52+K52+L52 -> 0
A53: Camion con grua con operador con conbustible. | E53: HR | F53: 0 | G53: 407.62 | H53: =F53*G53 -> 0
A54: autobus | E54: pza | F54: 0 | G54: 5000 | H54: =F54*G54 -> 0
A55: Km. Recorrido (incluye conbustible y depresiación de Vehiculo | E55: KM | F55: 0 | G55: 2.5 | H55: =F55*G55 -> 0
G56: SUBT 4 | H56: =SUM(H49:H55) -> 0
A57: COMBUSTIBLE
A58: DESCRIPCION | E58: UNIDAD | F58: CANT. | G58: P.U. | H58: IMPORTE | J58: KM IDA | K58: KM RETORNO | L58: KM SITIO | M58: SUMA
A59: GASOLINA MAGNA | E59: LT | F59: 0 | G59: 19 | H59: =F59*G59 -> 0 | J59: 22 | K59: 22 | M59: =J59+K59+L59 -> 44
A60: DIESEL | E60: LT | F60: =M60/4.5 -> 0 | G60: 0 | H60: =F60*G60 -> 0 | M60: =J60+K60+L60 -> 0
G61: SUBT 5 | H61: =SUM(H59:H60) -> 0
A62: CASETAS
A63: DESCRIPCION | E63: UNIDAD | F63: CANT. | G63: P.U. | H63: IMPORTE
A64: camioneta pick up | E64: CASETA | F64: 0 | G64: 100 | H64: =F64*G64 -> 0
A65: camioneta pick up | E65: CASETA | F65: 0 | G65: 65 | H65: =F65*G65 -> 0
G66: SUBT 6 | H66: =SUM(H64:H65) -> 0
A67: VIATICOS
A68: ALIMENTOS
A69: DESCRIPCION | E69: UNIDAD | F69: CANT. | G69: P.U. | H69: IMPORTE
A70: CONSUMO DE ALIMENTOS | E70: Pza | F70: 0 | G70: 450 | H70: =F70*G70 -> 0
H71: =SUM(H70) -> 0
A72: HOSPEDAJE
A73: DESCRIPCION | E73: UNIDAD | F73: CANT. | G73: P.U. | H73: IMPORTE
A74: HOTEL | E74: NOCHES | F74: 0 | G74: 900 | H74: =F74*G74 -> 0
G75: SUBT 8 | H75: =SUM(H74) -> 0
G76: SUMA: | H76: =H56+H61+H66+H71+H75+H45+H44+H17 -> 5307.5472
A77: EQUIPO DE PRUEBA
A78: DESCRIPCION | E78: UNIDAD | F78: CANT. | G78: P.U. | H78: IMPORTE | I78: TR | K78: S.E
A79: Megger | E79: jr | F79: 0.5 | G79: 2200 | H79: =(F79*G79) -> 1100
A80: TTR | E80: jr | G80: 2000 | H80: =(F80*G80) -> 0
A81: Factor de Potencia de 2.5 KV | E81: jr | G81: 7000 | H81: =(F81*G81) -> 0
A82: Factor de Potencia de 10.5 KV | E82: jr | F82: 0.3 | G82: 15200 | H82: =(F82*G82) -> 4560
A83: Ducter | E83: jr | F83: 0.5 | G83: 2200 | H83: =(F83*G83) -> 1100
A84: resistencia óhmica | E84: jr | G84: 2000 | H84: =(F84*G84) -> 0
A85: hipot de 80 KV vcd | E85: jr | G85: 2500 | H85: =(F85*G85) -> 0
A86: Rigidez dieléctrica al aceite 60 kv | E86: jr | G86: 1600 | H86: =(F86*G86) -> 0
A87: Terrómetro | E87: jr | G87: 1100 | H87: =(F87*G87) -> 0
A88: Analizador de tiempos de interruptor | E88: jr | G88: 2700 | H88: =(F88*G88) -> 0
A89: Fuente de corriente para calibrador de relevadores | E89: jr | G89: 2500 | H89: =(F89*G89) -> 0
A90: Probador de relevador de Protecciones | E90: jr | G90: 13373 | H90: =(F90*G90) -> 0
A91: Fuente trifasica de voltaje | E91: jr | G91: 800 | H91: =(F91*G91) -> 0
A92: Analizador de energía trifásica | E92: jr | G92: 1900 | H92: =(F92*G92) -> 0
A93: Medidor de presión y llenado de gas SF6 | E93: jr | G93: 2000 | H93: =(F93*G93) -> 0
A94: Medidor de secuencia de fases | E94: jr | G94: 200 | H94: =(F94*G94) -> 0
A95: Unidad de Pba y config. Para relevadores de Int. ABB | E95: jr | G95: 1100 | H95: =(F95*G95) -> 0
... A97: Luxómetro | E97: jr | G97: 1420 | H97: =(F97*G97) -> 0
A98: Generador de Luz con combustible | E98: jr | F98: 0.5 | G98: 383.5 | H98: =(F98*G98) -> 191.75
G99: SUBT 9 | H99: =SUM(H79:H98) -> 6951.75
E101: 0 | H101: =+E101 -> 0 | I101: % DE IMP. | J101: INDIRECTO DISPONIBLE
G102: COSTO DIRECTO | H102: =H76+H99 -> 12259.297
F103: Indirectos | G103: 0.1 | H103: =H102*G103 -> 1225.9297 | I103: =(M109*100)/H103 -> 81.479973 | J103: =H103-M109 -> 227.04251
F104: Subtotal 1 | H104: =H102+H103 -> 13485.227
K105: BASE IMPUESTO
...

Sheet TR 15MVA MAT.
A1: I M M E E S. A. D E C. V.
A2: A N A L I S I S D E P R E C I O U N I T A R I O
A3: COTIZACION:
A4: FECHA:
A5: PARTIDA 1
A7: MATERIALES.
A8: DESCRIPCION | E8: UNIDAD | F8: CANT. | G8: P.U. | H8: IMPORTE
A9: Solvente Dielectrico | E9: L | F9: 1 | G9: 331 | H9: =G9*F9 -> 331 | J9: HR NORMAL
A10: Trapo | E10: kg | F10: 1 | G10: 60 | H10: =G10*F10 -> 60 | J10: HR DOBLE
A11: consumibles | E11: pza | F11: 1 | G11: 200 | H11: =G11*F11 -> 200 | J11: HR TRIPLE
E12: Pza | F12: 1 | H12: =G12*F12 -> 0
E13: Pza | F13: 1 | H13: =G13*F13 -> 0
E14: Pza | F14: 1 | H14: =G14*F14 -> 0
E15: Pza | F15: 1 | H15: =G15*F15 -> 0
E16: Pza | F16: 1 | H16: =G16*F16 -> 0
G17: SUBT 1 | H17: =SUM(H9:H16) -> 591
A19: MANO DE OBRA SIN INDIRECTOS | O19: HORARIOS DE TRABAJO | V19: HORAS RESULTANTES
A20: PERSONAL. | E20: UNIDAD | F20: CANT. | G20: P.U. | H20: IMPORTE | I20: CANT. | J20: Hr. Extra | K20: IMPORTE | L20: CANT. | M20: Dom, ó Fest. | N20: IMPORTE | O20: L | P20: M | Q20: MI | R20: J | S20: V | T20: S | U20: D | V20: N | W20: D | X20: T
A21: COORDINADOR DE OPERACIONES | E21: hr | F21: =V21 -> 0 | G21: 185.69 | H21: =F21*G21 -> 0 | I21: =W21 -> 0 | J21: =G21*1.5 -> 278.535 | K21: =I21*J21 -> 0 | L21: =X21 -> 0 | M21: =G21*2.25 -> 417.8025 | N21: =L21*M21 -> 0 | V21: =SUM(O21:T21) -> 0
A22: INGENIERIA Y SOPORTE TEC. | E22: hr | F22: =V22 -> 0 | G22: 177.79 | H22: =F22*G22 -> 0 | I22: =W22 -> 0 | J22: =G22*1.5 -> 266.685 | K22: =I22*J22 -> 0 | L22: =X22 -> 0 | M22: =G22*2.25 -> 400.0275 | N22: =L22*M22 -> 0 | V22: =SUM(O22:T22) -> 0
A23: SUPERVISOR DE SEGURIDAD CERTIFICADO | E23: hr | F23: =V23 -> 0 | G23: 185.69 | H23: =F23*G23 -> 0 | I23: =W23 -> 0 | J23: =G23*1.5 -> 278.535 | K23: =I23*J23 -> 0 | L23: =X23 -> 0 | M23: =G23*2.25 -> 417.8025 | N23: =L23*M23 -> 0 | V23: =SUM(O23:T23) -> 0
A24: SUPERVISOR ELECTRICO | E24: hr | F24: 0 | G24: 148.16 | H24: =F24*G24 -> 0 | I24: =W24 -> 0 | J24: =G24*1.5 -> 222.24 | K24: =I24*J24 -> 0 | L24: =X24 -> 0 | M24: =G24*2.25 -> 333.36 | N24: =L24*M24 -> 0 | O24: 8 | P24: 8 | Q24: 8 | R24: 8 | S24: 8 | V24: =SUM(O24:T24) -> 40 | Y24: Fco, Oropeza
A25: TECNICO DE PRUEBAS ELECTRICAS | E25: hr | F25: 0 | G25: 136.31 | H25: =F25*G25 -> 0 | I25: =W25 -> 0 | J25: =G25*1.5 -> 204.465 | K25: =I25*J25 -> 0 | L25: =X25 -> 0 | M25: =G25*2.25 -> 306.6975 | N25: =L25*M25 -> 0 | V25: =SUM(O25:T25) -> 0
A26: CABO OBRA ELECTRICA | E26: hr | F26: =V26 -> 0 | G26: 136.31 | H26: =F26*G26 -> 0 | I26: =W26 -> 0 | J26: =G26*1.5 -> 204.465 | K26: =I26*J26 -> 0 | L26: =X26 -> 0 | M26: =G26*2.25 -> 306.6975 | N26: =L26*M26 -> 0 | V26: =SUM(O26:T26) -> 0
A27: LINIERO | E27: hr | F27: 0 | G27: 126.43 | H27: =F27*G27 -> 0 | I27: =W27 -> 0 | J27: =G27*1.5 -> 189.645 | K27: =I27*J27 -> 0 | L27: =X27 -> 0 | M27: =G27*2.25 -> 284.4675 | N27: =L27*M27 -> 0 | O27: 16 | P27: 16 | Q27: 16 | R27: 8 | S27: 8 | T27: 5 | V27: =SUM(O27:T27) -> 69 | Y27: josé - adrian | Z27: 2
A28: LINIERO | E28: hr | F28: 0 | G28: 126.43 | H28: =F28*G28 -> 0 | I28: =W28 -> 0 | J28: =G28*1.5 -> 189.645 | K28: =I28*J28 -> 0 | L28: =X28 -> 0 | M28: =G28*2.25 -> 284.4675 | N28: =L28*M28 -> 0 | O28: 16 | P28: 16 | Q28: 16 | R28: 8 | S28: 8 | T28: 5 | V28: =SUM(O28:T28) -> 69 | Y28: josé - adrian | Z28: 2
A29: ESPECIALISTA ELECTRICO | E29: hr | F29: =V29 -> 0 | G29: 110.63 | H29: =F29*G29 -> 0 | I29: =W29 -> 0 | J29: =G29*1.5 -> 165.945 | K29: =I29*J29 -> 0 | L29: =X29 -> 0 | M29: =G29*2.25 -> 248.9175 | N29: =L29*M29 -> 0 | V29: =SUM(O29:T29) -> 0
A30: TECNICO EN INSTRUMENTACION | E30: hr | F30: =V30 -> 0 | G30: 104.36 | H30: =F30*G30 -> 0 | I30: =W30 -> 0 | J30: =G30*1.5 -> 156.54 | K30: =I30*J30 -> 0 | L30: =X30 -> 0 | M30: =G30*2.25 -> 234.81 | N30: =L30*M30 -> 0 | V30: =SUM(O30:T30) -> 0
A31: OFICIAL ELECTRICO | E31: hr | F31: 0 | G31: 104.36 | H31: =F31*G31 -> 0 | I31: =W31 -> 0 | J31: =G31*1.5 -> 156.54 | K31: =I31*J31 -> 0 | L31: =X31 -> 0 | M31: =G31*2.25 -> 234.81 | N31: =L31*M31 -> 0 | V31: =SUM(O31:T31) -> 0 | Z31: 1
A32: ASISTENTE DE DISEÑO | E32: hr | F32: 0 | G32: 104.36 | H32: =F32*G32 -> 0 | I32: =W32 -> 0 | J32: =G32*1.5 -> 156.54 | K32: =I32*J32 -> 0 | L32: =X32 -> 0 | M32: =G32*2.25 -> 234.81 | N32: =L32*M32 -> 0 | V32: =SUM(O32:T32) -> 0
A33: ELECTRICISTA -B | E33: hr | F33: 0 | G33: 90.87 | H33: =F33*G33 -> 0 | I33: =W33 -> 0 | J33: =G33*1.5 -> 136.305 | K33: =I33*J33 -> 0 | L33: =X33 -> 0 | M33: =G33*2.25 -> 204.4575 | N33: =L33*M33 -> 0 | O33: 16 | P33: 16 | Q33: 16 | R33: 8 | S33: 8 | T33: 5 | V33: =SUM(O33:T33) -> 69 | Y33: Uno con categoría de: Alan/Eduardo
A34: ELECTRICISTA -A | E34: hr | F34: 0 | G34: 82.97 | H34: =F34*G34 -> 0 | I34: =W34 -> 0 | J34: =G34*1.5 -> 124.455 | K34: =I34*J34 -> 0 | L34: =X34 -> 0 | M34: =G34*2.25 -> 186.6825 | N34: =L34*M34 -> 0 | V34: =SUM(O34:T34) -> 0
A35: AUXILIAR TECNICO | E35: hr | F35: =V35 -> 0 | G35: 75.07 | H35: =F35*G35 -> 0 | I35: =W35 -> 0 | J35: =G35*1.5 -> 112.605 | K35: =I35*J35 -> 0 | L35: =X35 -> 0 | M35: =G35*2.25 -> 168.9075 | N35: =L35*M35 -> 0 | V35: =SUM(O35:T35) -> 0
A36: AYTE ELECTRICO - B | E36: hr | F36: 0 | G36: 75.07 | H36: =F36*G36 -> 0 | I36: =W36 -> 0 | J36: =G36*1.5 -> 112.605 | K36: =I36*J36 -> 0 | L36: =X36 -> 0 | M36: =G36*2.25 -> 168.9075 | N36: =L36*M36 -> 0 | V36: =SUM(O36:T36) -> 0
A37: AYTE DE ELECTR. -A | E37: hr | F37: 0 | G37: 63.21 | H37: =F37*G37 -> 0 | I37: =W37 -> 0 | J37: =G37*1.5 -> 94.815 | K37: =I37*J37 -> 0 | L37: =X37 -> 0 | M37: =G37*2.25 -> 142.2225 | N37: =L37*M37 -> 0 | O37: 8 | P37: 8 | Q37: 8 | R37: 8 | S37: 8 | V37: =SUM(O37:T37) -> 40 | Z37: 4
A38: AYTE GENERAL | E38: hr | F38: =V38 -> 0 | G38: 50.77 | H38: =F38*G38 -> 0 | I38: =W38 -> 0 | J38: =G38*1.5 -> 76.155 | K38: =I38*J38 -> 0 | L38: =X38 -> 0 | M38: =G38*2.25 -> 114.2325 | N38: =L38*M38 -> 0 | Y38: Guadalupe | Z38: 1
A39: INGENIERO DE SUBESTACIONES | E39: hr | F39: =V39 -> 0 | G39: 186 | H39: =F39*G39 -> 0 | I39: =W39 -> 0 | J39: 186 | K39: =I39*J39 -> 0 | L39: =X39 -> 0 | M39: 186 | N39: =L39*M39 -> 0 | V39: =SUM(O39:T39) -> 0 | Z39: =SUM(Z29:Z38) -> 6
A40: INGENIERO DE PRUEBAS ELECTRICAS | E40: hr | F40: =V40 -> 0 | G40: 186 | H40: =F40*G40 -> 0 | I40: =W40 -> 0 | J40: 186 | K40: =I40*J40 -> 0 | L40: =X40 -> 0 | M40: 186 | N40: =L40*M40 -> 0 | V40: =SUM(O40:T40) -> 0
A41: ING. ESPECIALISTA EN PROTECCIONES | E41: hr | F41: =V41 -> 0 | G41: 230.47 | H41: =F41*G41 -> 0 | I41: =W41 -> 0 | J41: 294 | K41: =I41*J41 -> 0 | L41: =X41 -> 0 | M41: 294 | N41: =L41*M41 -> 0 | V41: =SUM(O41:T41) -> 0
A42: SUPERINTENDENTE | E42: hr | F42: =V42 -> 0 | G42: 279.53 | H42: =F42*G42 -> 0 | I42: =W42 -> 0 | J42: 372.71 | K42: =I42*J42 -> 0 | L42: =X42 -> 0 | M42: 559.07 | N42: =L42*M42 -> 0 | V42: =SUM(O42:T42) -> 0
F43: =V43 -> 287 | G43: SUBT 2 | H43: =SUM(H21:H42) -> 0 | J43: SUBT. | K43: =SUM(K22:K41) -> 0 | M43: SUBT. | N43: =SUM(N22:N41) -> 0 | V43: =SUM(V21:V42) -> 287 | W43: 45 | Z43: =+V43/W43 -> 6.3777778
G44: SUMA M.O. | H44: =H43+K43+N43 -> 0
A45: HERRAMIENTA MENOR | G45: 1 a 10% | H45: =+H44*0.06 -> 0
A47: VEHICULOS
A48: DESCRIPCION | E48: UNIDAD | F48: CANT. | G48: P.U. | H48: IMPORTE | J48: HR IDA | K48: HR RETORNO | L48: HR SITIO | M48: SUMA
A49: camioneta RANGER sin operador sin combustible | E49: HR | F49: 0 | G49: 102.29 | H49: =F49*G49 -> 0 | J49: 0 | K49: 0 | L49: 0 | M49: =J49+K49+L49 -> 0
A50: camioneta NISSAN sin operador sin combustible | E50: HR | F50: 0 | G50: 68.7 | H50: =F50*G50 -> 0 | J50: 0 | K50: 0 | M50: =J50+K50+L50 -> 0
A51: camioneta TORNADO Tornado sin operador sin combustible | E51: HR | F51: 0 | G51: 54.43 | H51: =F51*G51 -> 0 | J51: 0.45 | K51: 0.45 | M51: =J51+K51+L51 -> 0.9
A52: Camion con grua sin operador sin conbustible. | E52: HR | F52: =M52 -> 0 | G52: 203.19 | H52: =F52*G52 -> 0 | M52: =J52+K52+L52 -> 0
A53: Camion con grua con operador con conbustible. | E53: HR | G53: 407.62 | H53: =F53*G53 -> 0
A54: autobus | E54: pza | G54: 5000 | H54: =F54*G54 -> 0
A55: Km. Recorrido (incluye conbustible y depresiación de Vehiculo | E55: KM | G55: 2.5 | H55: =F55*G55 -> 0
G56: SUBT 4 | H56: =SUM(H49:H55) -> 0
A57: COMBUSTIBLE
A58: DESCRIPCION | E58: UNIDAD | F58: CANT. | G58: P.U. | H58: IMPORTE | J58: KM IDA | K58: KM RETORNO | L58: KM SITIO | M58: SUMA
A59: GASOLINA MAGNA | E59: LT | F59: 40 | G59: 16.48 | H59: =F59*G59 -> 659.2 | J59: 22 | K59: 22 | M59: =J59+K59+L59 -> 44
A60: DIESEL | E60: LT | F60: =M60/4.5 -> 0 | G60: 0 | H60: =F60*G60 -> 0 | M60: =J60+K60+L60 -> 0
G61: SUBT 5 | H61: =SUM(H59:H60) -> 659.2
A62: CASETAS
A63: DESCRIPCION | E63: UNIDAD | F63: CANT. | G63: P.U. | H63: IMPORTE
A64: camioneta pick up | E64: CASETA | F64: 3 | G64: 180 | H64: =F64*G64 -> 540
A65: camioneta pick up | E65: CASETA | G65: 65 | H65: =F65*G65 -> 0
G66: SUBT 6 | H66: =SUM(H64:H65) -> 540
A67: VIATICOS
A68: ALIMENTOS
A69: DESCRIPCION | E69: UNIDAD | F69: CANT. | G69: P.U. | H69: IMPORTE
A70: CONSUMO DE ALIMENTOS | E70: Pza | F70: 1 | G70: 450 | H70: =F70*G70 -> 450
H71: =SUM(H70) -> 450
A72: HOSPEDAJE
A73: DESCRIPCION | E73: UNIDAD | F73: CANT. | G73: P.U. | H73: IMPORTE
A74: HOTEL | E74: NOCHES | F74: 0 | G74: 900 | H74: =F74*G74 -> 0
G75: SUBT 8 | H75: =SUM(H74) -> 0
G76: SUMA: | H76: =H56+H61+H66+H71+H75+H45+H44+H17 -> 2240.2
A77: EQUIPO DE PRUEBA
A78: DESCRIPCION | E78: UNIDAD | F78: CANT. | G78: P.U. | H78: IMPORTE | I78: TR | K78: S.E
A79: Megger | E79: jr | G79: 2200 | H79: =(F79*G79) -> 0
A80: TTR | E80: jr | G80: 2000 | H80: =(F80*G80) -> 0
A81: Factor de Potencia de 2.5 KV | E81: jr | G81: 7000 | H81: =(F81*G81) -> 0
A82: Factor de Potencia de 10.5 KV | E82: jr | G82: 15200 | H82: =(F82*G82) -> 0
A83: Ducter | E83: jr | G83: 2200 | H83: =(F83*G83) -> 0
A84: resistencia óhmica | E84: jr | G84: 2000 | H84: =(F84*G84) -> 0
A85: hipot de 80 KV vcd | E85: jr | G85: 2500 | H85: =(F85*G85) -> 0
A86: Rigidez dieléctrica al aceite 60 kv | E86: jr | G86: 1600 | H86: =(F86*G86) -> 0
A87: Terrómetro | E87: jr | G87: 1100 | H87: =(F87*G87) -> 0
A88: Analizador de tiempos de interruptor | E88: jr | G88: 2700 | H88: =(F88*G88) -> 0
A89: Fuente de corriente para calibrador de relevadores | E89: jr | G89: 2500 | H89: =(F89*G89) -> 0
A90: Probador de relevador de Protecciones | E90: jr | G90: 13373 | H90: =(F90*G90) -> 0
... A98: Generador de Luz con combustible | E98: jr | G98: 383.5 | H98: =(F98*G98) -> 0
G99: SUBT 9 | H99: =SUM(H79:H98) -> 0
E101: 0 | H101: =+E101 -> 0 | I101: % DE IMP. | J101: INDIRECTO DISPONIBLE
G102: COSTO DIRECTO | H102: =H76+H99 -> 2240.2
F103: Indirectos | G103: 0.1 | H103: =H102*G103 -> 224.02 | I103: =(M109*100)/H103 -> -53.701034 | J103: =H103-M109 -> 344.32106
F104: Subtotal 1 | H104: =H102+H103 -> 2464.22
K105: BASE IMPUESTO
F106: Financ. | G106: 0.06 | H106: =H104*G106 -> 147.8532 | I106: =H106+[1]Part.2!H84+[1]Part.3!H84+[1]Part.4!H84+[1]part.5!H84+[1]traslado!H66 -> 358.06524 | J106: COMPRAS | K106: =+H17 -> 591
F107: Subtotal 2 | H107: =H104+H106 -> 2612.0732 | J107: M.O | K107: =H44 -> 0
F108: Utilidad | G108: 0.1 | H108: =H107*G108 -> 261.20732 | J108: GASTOS FACTURADOS | K108: =H76-H56 -> 2240.2 | M108: IMP. 32%
F109: Importe | H109: =H107+H108 -> 2873.2805 | J109: SUMA | K109: =SUM(K106:K108) -> 2831.2 | L109: =H109-H108-(H103*0.7)-K109 -> -375.9408 | M109: =0.32*L109 -> -120.30106
I110: FACTOR | J110: =H109/H102 -> 1.2826
B112: utilidad
...

Sheet TR 15MVA MO
A1: I M M E E S. A. D E C. V.
A2: A N A L I S I S D E P R E C I O U N I T A R I O
A3: COTIZACION:
A4: FECHA:
A5: PARTIDA 1
A7: MATERIALES.
A8: DESCRIPCION | E8: UNIDAD | F8: CANT. | G8: P.U. | H8: IMPORTE
E9: Pza | J9: HR NORMAL
E10: Pza | J10: HR DOBLE
E11: Pza | J11: HR TRIPLE
E12: Pza
E13: Pza
E14: Pza
E15: Pza
E16: Pza | I16: =H16*1.455 -> 0
G17: SUBT 1 | H17: =SUM(H9:H16) -> 0
A19: MANO DE OBRA SIN INDIRECTOS | O19: HORARIOS DE TRABAJO | V19: HORAS RESULTANTES
A20: PERSONAL. | E20: UNIDAD | F20: CANT. | G20: P.U. | H20: IMPORTE | I20: CANT. | J20: Hr. Extra | K20: IMPORTE | L20: CANT. | M20: Dom, ó Fest. | N20: IMPORTE | O20: L | P20: M | Q20: MI | R20: J | S20: V | T20: S | U20: D | V20: N | W20: D | X20: T
A21: COORDINADOR DE OPERACIONES | E21: hr | F21: =V21 -> 0 | G21: 185.69 | H21: =F21*G21 -> 0 | I21: =W21 -> 0 | J21: =G21*1.5 -> 278.535 | K21: =I21*J21 -> 0 | L21: =X21 -> 0 | M21: =G21*2.25 -> 417.8025 | N21: =L21*M21 -> 0 | V21: =SUM(O21:T21) -> 0
A22: INGENIERIA Y SOPORTE TEC. | E22: hr | F22: =V22 -> 0 | G22: 177.79 | H22: =F22*G22 -> 0 | I22: =W22 -> 0 | J22: =G22*1.5 -> 266.685 | K22: =I22*J22 -> 0 | L22: =X22 -> 0 | M22: =G22*2.25 -> 400.0275 | N22: =L22*M22 -> 0 | V22: =SUM(O22:T22) -> 0
A23: SUPERVISOR DE SEGURIDAD CERTIFICADO | E23: hr | F23: =V23 -> 0 | G23: 185.69 | H23: =F23*G23 -> 0 | I23: =W23 -> 0 | J23: =G23*1.5 -> 278.535 | K23: =I23*J23 -> 0 | L23: =X23 -> 0 | M23: =G23*2.25 -> 417.8025 | N23: =L23*M23 -> 0 | V23: =SUM(O23:T23) -> 0
A24: SUPERVISOR ELECTRICO | E24: hr | F24: 9 | G24: 148.16 | H24: =F24*G24 -> 1333.44 | I24: 0 | J24: =G24*1.5 -> 222.24 | K24: =I24*J24 -> 0 | L24: =X24 -> 0 | M24: =G24*2.25 -> 333.36 | N24: =L24*M24 -> 0 | O24: 8 | P24: 8 | Q24: 8 | R24: 8 | S24: 8 | V24: =SUM(O24:T24) -> 40 | Y24: Fco, Oropeza
A25: TECNICO DE PRUEBAS ELECTRICAS | E25: hr | F25: 9 | G25: 136.31 | H25: =F25*G25 -> 1226.79 | I25: 0 | J25: =G25*1.5 -> 204.465 | K25: =I25*J25 -> 0 | L25: =X25 -> 0 | M25: =G25*2.25 -> 306.6975 | N25: =L25*M25 -> 0 | V25: =SUM(O25:T25) -> 0
A26: CABO OBRA ELECTRICA | E26: hr | F26: =V26 -> 0 | G26: 136.31 | H26: =F26*G26 -> 0 | I26: =W26 -> 0 | J26: =G26*1.5 -> 204.465 | K26: =I26*J26 -> 0 | L26: =X26 -> 0 | M26: =G26*2.25 -> 306.6975 | N26: =L26*M26 -> 0 | V26: =SUM(O26:T26) -> 0
A27: LINIERO | E27: hr | F27: 0 | G27: 126.43 | H27: =F27*G27 -> 0 | I27: =W27 -> 0 | J27: =G27*1.5 -> 189.645 | K27: =I27*J27 -> 0 | L27: =X27 -> 0 | M27: =G27*2.25 -> 284.4675 | N27: =L27*M27 -> 0 | O27: 16 | P27: 16 | Q27: 16 | R27: 8 | S27: 8 | T27: 5 | V27: =SUM(O27:T27) -> 69 | Y27: josé - adrian | Z27: 2
A28: LINIERO | E28: hr | F28: 0 | G28: 126.43 | H28: =F28*G28 -> 0 | I28: =W28 -> 0 | J28: =G28*1.5 -> 189.645 | K28: =I28*J28 -> 0 | L28: =X28 -> 0 | M28: =G28*2.25 -> 284.4675 | N28: =L28*M28 -> 0 | O28: 16 | P28: 16 | Q28: 16 | R28: 8 | S28: 8 | T28: 5 | V28: =SUM(O28:T28) -> 69 | Y28: josé - adrian | Z28: 2
A29: ESPECIALISTA ELECTRICO | E29: hr | F29: 0 | G29: 110.63 | H29: =F29*G29 -> 0 | I29: =W29 -> 0 | J29: =G29*1.5 -> 165.945 | K29: =I29*J29 -> 0 | L29: =X29 -> 0 | M29: =G29*2.25 -> 248.9175 | N29: =L29*M29 -> 0 | V29: =SUM(O29:T29) -> 0
A30: TECNICO EN INSTRUMENTACION | E30: hr | F30: =V30 -> 0 | G30: 104.36 | H30: =F30*G30 -> 0 | I30: =W30 -> 0 | J30: =G30*1.5 -> 156.54 | K30: =I30*J30 -> 0 | L30: =X30 -> 0 | M30: =G30*2.25 -> 234.81 | N30: =L30*M30 -> 0 | V30: =SUM(O30:T30) -> 0
A31: OFICIAL ELECTRICO | E31: hr | F31: 9 | G31: 104.36 | H31: =F31*G31 -> 939.24 | I31: 0 | J31: =G31*1.5 -> 156.54 | K31: =I31*J31 -> 0 | L31: =X31 -> 0 | M31: =G31*2.25 -> 234.81 | N31: =L31*M31 -> 0 | V31: =SUM(O31:T31) -> 0 | Z31: 1
A32: ASISTENTE DE DISEÑO | E32: hr | F32: =V32 -> 0 | G32: 104.36 | H32: =F32*G32 -> 0 | I32: =W32 -> 0 | J32: =G32*1.5 -> 156.54 | K32: =I32*J32 -> 0 | L32: =X32 -> 0 | M32: =G32*2.25 -> 234.81 | N32: =L32*M32 -> 0 | V32: =SUM(O32:T32) -> 0
A33: ELECTRICISTA -B | E33: hr | F33: 0 | G33: 90.87 | H33: =F33*G33 -> 0 | I33: 0 | J33: =G33*1.5 -> 136.305 | K33: =I33*J33 -> 0 | L33: =X33 -> 0 | M33: =G33*2.25 -> 204.4575 | N33: =L33*M33 -> 0 | O33: 16 | P33: 16 | Q33: 16 | R33: 8 | S33: 8 | T33: 5 | V33: =SUM(O33:T33) -> 69 | Y33: Uno con categoría de: Alan/Eduardo
A34: ELECTRICISTA -A | E34: hr | F34: 0 | G34: 82.97 | H34: =F34*G34 -> 0 | I34: =W34 -> 0 | J34: =G34*1.5 -> 124.455 | K34: =I34*J34 -> 0 | L34: =X34 -> 0 | M34: =G34*2.25 -> 186.6825 | N34: =L34*M34 -> 0 | V34: =SUM(O34:T34) -> 0
A35: AUXILIAR TECNICO | E35: hr | F35: 0 | G35: 75.07 | H35: =F35*G35 -> 0 | I35: =W35 -> 0 | J35: =G35*1.5 -> 112.605 | K35: =I35*J35 -> 0 | L35: =X35 -> 0 | M35: =G35*2.25 -> 168.9075 | N35: =L35*M35 -> 0 | V35: =SUM(O35:T35) -> 0
A36: AYTE ELECTRICO - B | E36: hr | F36: 0 | G36: 75.07 | H36: =F36*G36 -> 0 | I36: =W36 -> 0 | J36: =G36*1.5 -> 112.605 | K36: =I36*J36 -> 0 | L36: =X36 -> 0 | M36: =G36*2.25 -> 168.9075 | N36: =L36*M36 -> 0 | V36: =SUM(O36:T36) -> 0
A37: AYTE DE ELECTR. -A | E37: hr | F37: 0 | G37: 63.21 | H37: =F37*G37 -> 0 | I37: =W37 -> 0 | J37: =G37*1.5 -> 94.815 | K37: =I37*J37 -> 0 | L37: =X37 -> 0 | M37: =G37*2.25 -> 142.2225 | N37: =L37*M37 -> 0 | O37: 8 | P37: 8 | Q37: 8 | R37: 8 | S37: 8 | V37: =SUM(O37:T37) -> 40 | Z37: 4
A38: AYTE GENERAL | E38: hr | F38: 0 | G38: 50.77 | H38: =F38*G38 -> 0 | I38: =W38 -> 0 | J38: =G38*1.5 -> 76.155 | K38: =I38*J38 -> 0 | L38: =X38 -> 0 | M38: =G38*2.25 -> 114.2325 | N38: =L38*M38 -> 0 | Y38: Guadalupe | Z38: 1
A39: INGENIERO DE SUBESTACIONES | E39: hr | F39: 0 | G39: 186 | H39: =F39*G39 -> 0 | I39: =W39 -> 0 | J39: 186 | K39: =I39*J39 -> 0 | L39: =X39 -> 0 | M39: 186 | N39: =L39*M39 -> 0 | V39: =SUM(O39:T39) -> 0 | Z39: =SUM(Z29:Z38) -> 6
A40: INGENIERO DE PRUEBAS ELECTRICAS | E40: hr | F40: 0 | G40: 186 | H40: =F40*G40 -> 0 | I40: =W40 -> 0 | J40: 186 | K40: =I40*J40 -> 0 | L40: =X40 -> 0 | M40: 186 | N40: =L40*M40 -> 0 | V40: =SUM(O40:T40) -> 0
A41: ING. ESPECIALISTA EN PROTECCIONES | E41: hr | F41: 0 | G41: 230.47 | H41: =F41*G41 -> 0 | I41: =W41 -> 0 | J41: 294 | K41: =I41*J41 -> 0 | L41: =X41 -> 0 | M41: 294 | N41: =L41*M41 -> 0 | V41: =SUM(O41:T41) -> 0
A42: SUPERINTENDENTE | E42: hr | F42: =V42 -> 0 | G42: 279.53 | H42: =F42*G42 -> 0 | I42: =W42 -> 0 | J42: 372.71 | K42: =I42*J42 -> 0 | L42: =X42 -> 0 | M42: 559.07 | N42: =L42*M42 -> 0 | V42: =SUM(O42:T42) -> 0
F43: =V43 -> 287 | G43: SUBT 2 | H43: =SUM(H21:H42) -> 3499.47 | J43: SUBT. | K43: =SUM(K22:K41) -> 0 | M43: SUBT. | N43: =SUM(N22:N41) -> 0 | V43: =SUM(V21:V42) -> 287 | W43: 45 | Z43: =+V43/W43 -> 6.3777778
G44: SUMA M.O. | H44: =H43+K43+N43 -> 3499.47
A45: HERRAMIENTA MENOR | G45: 1 a 10% | H45: =+H44*0.06 -> 209.9682
A47: VEHICULOS
A48: DESCRIPCION | E48: UNIDAD | F48: CANT. | G48: P.U. | H48: IMPORTE | J48: HR IDA | K48: HR RETORNO | L48: HR SITIO | M48: SUMA
A49: camioneta RANGER sin operador sin combustible | E49: HR | F49: 6 | G49: 102.29 | H49: =F49*G49 -> 613.74 | J49: 0 | K49: 0 | L49: 0 | M49: =J49+K49+L49 -> 0
A50: camioneta NISSAN sin operador sin combustible | E50: HR | F50: 0 | G50: 68.7 | H50: =F50*G50 -> 0 | J50: 0 | K50: 0 | M50: =J50+K50+L50 -> 0
A51: camioneta TORNADO Tornado sin operador sin combustible | E51: HR | F51: 0 | G51: 54.43 | H51: =F51*G51 -> 0 | J51: 0.45 | K51: 0.45 | M51: =J51+K51+L51 -> 0.9
A52: Camion con grua sin operador sin conbustible. | E52: HR | F52: 0 | G52: 203.19 | H52: =F52*G52 -> 0 | M52: =J52+K52+L52 -> 0
A53: Camion con grua con operador con conbustible. | E53: HR | F53: 0 | G53: 407.62 | H53: =F53*G53 -> 0
A54: autobus | E54: pza | F54: 0 | G54: 5000 | H54: =F54*G54 -> 0
A55: Km. Recorrido (incluye conbustible y depresiación de Vehiculo | E55: KM | F55: 0 | G55: 2.5 | H55: =F55*G55 -> 0
G56: SUBT 4 | H56: =SUM(H49:H55) -> 613.74
A57: COMBUSTIBLE
A58: DESCRIPCION | E58: UNIDAD | F58: CANT. | G58: P.U. | H58: IMPORTE | J58: KM IDA | K58: KM RETORNO | L58: KM SITIO | M58: SUMA
A59: GASOLINA MAGNA | E59: LT | F59: 0 | G59: 19 | H59: =F59*G59 -> 0 | J59: 22 | K59: 22 | M59: =J59+K59+L59 -> 44
A60: DIESEL | E60: LT | F60: =M60/4.5 -> 0 | G60: 0 | H60: =F60*G60 -> 0 | M60: =J60+K60+L60 -> 0
G61: SUBT 5 | H61: =SUM(H59:H60) -> 0
A62: CASETAS
A63: DESCRIPCION | E63: UNIDAD | F63: CANT. | G63: P.U. | H63: IMPORTE
A64: camioneta pick up | E64: CASETA | F64: 0 | G64: 100 | H64: =F64*G64 -> 0
A65: camioneta pick up | E65: CASETA | F65: 0 | G65: 65 | H65: =F65*G65 -> 0
G66: SUBT 6 | H66: =SUM(H64:H65) -> 0
A67: VIATICOS
A68: ALIMENTOS
A69: DESCRIPCION | E69: UNIDAD | F69: CANT. | G69: P.U. | H69: IMPORTE
A70: CONSUMO DE ALIMENTOS | E70: Pza | F70: 0 | G70: 450 | H70: =F70*G70 -> 0
H71: =SUM(H70) -> 0
A72: HOSPEDAJE
A73: DESCRIPCION | E73: UNIDAD | F73: CANT. | G73: P.U. | H73: IMPORTE
A74: HOTEL | E74: NOCHES | F74: 0 | G74: 900 | H74: =F74*G74 -> 0
G75: SUBT 8 | H75: =SUM(H74) -> 0
G76: SUMA: | H76: =H56+H61+H66+H71+H75+H45+H44+H17 -> 4323.1782
A77: EQUIPO DE PRUEBA
A78: DESCRIPCION | E78: UNIDAD | F78: CANT. | G78: P.U. | H78: IMPORTE | I78: TR | K78: S.E
A79: Megger | E79: jr | F79: 0.5 | G79: 2200 | H79: =(F79*G79) -> 1100
A80: TTR | E80: jr | F80: 0.5 | G80: 2000 | H80: =(F80*G80) -> 1000
A81: Factor de Potencia de 2.5 KV | E81: jr | F81: 0 | G81: 7000 | H81: =(F81*G81) -> 0
A82: Factor de Potencia de 10.5 KV | E82: jr | F82: 0.3 | G82: 15200 | H82: =(F82*G82) -> 4560
A83: Ducter | E83: jr | G83: 2200 | H83: =(F83*G83) -> 0
A84: resistencia óhmica | E84: jr | F84: 0.3 | G84: 2000 | H84: =(F84*G84) -> 600
A85: hipot de 80 KV vcd | E85: jr | G85: 2500 | H85: =(F85*G85) -> 0
A86: Rigidez dieléctrica al aceite 60 kv | E86: jr | G86: 1600 | H86: =(F86*G86) -> 0
A87: Terrómetro | E87: jr | G87: 1100 | H87: =(F87*G87) -> 0
A88: Analizador de tiempos de interruptor | E88: jr | G88: 2700 | H88: =(F88*G88) -> 0
A89: Fuente de corriente para calibrador de relevadores | E89: jr | G89: 2500 | H89: =(F89*G89) -> 0
A90: Probador de relevador de Protecciones | E90: jr | G90: 13373 | H90: =(F90*G90) -> 0
A91: Fuente trifasica de voltaje | E91: jr | G91: 800 | H91: =(F91*G91) -> 0
A92: Analizador de energía trifásica | E92: jr | G92: 1900 | H92: =(F92*G92) -> 0
A93: Medidor de presión y llenado de gas SF6 | E93: jr | G93: 2000 | H93: =(F93*G93) -> 0
A94: Medidor de secuencia de fases | E94: jr | G94: 200 | H94: =(F94*G94) -> 0
A95: Unidad de Pba y config. Para relevadores de Int. ABB | E95: jr | G95: 1100 | H95: =(F95*G95) -> 0
A96: Máquina centrifugadora de aceite | E96: jr | G96: 2200 | H96: =(F96*G96) -> 0
A97: Luxómetro | E97: jr | G97: 1420 | H97: =(F97*G97) -> 0
A98: Generador de Luz con combustible | E98: jr | F98: 0.5 | G98: 383.5 | H98: =(F98*G98) -> 191.75
G99: SUBT 9 | H99: =SUM(H79:H98) -> 7451.75
E101: 0 | H101: =+E101 -> 0 | I101: % DE IMP. | J101: INDIRECTO DISPONIBLE
G102: COSTO DIRECTO | H102: =H76+H99 -> 11774.928
F103: Indirectos | G103: 0.1 | H103: =H102*G103 -> 1177.4928 | I103: =(M109*100)/H103 -> 154.80792 | J103: =H103-M109 -> -645.35937
F104: Subtotal 1 | H104: =H102+H103 -> 12952.421
...

Sheet AUTOBUS Y ALIMENTOS 
A1: I M M E E S. A. D E C. V.
A2: A N A L I S I S D E P R E C I O U N I T A R I O
A3: COTIZACION:
A4: FECHA:
A5: PARTIDA 1
A7: MATERIALES.
A8: DESCRIPCION | E8: UNIDAD | F8: CANT. | G8: P.U. | H8: IMPORTE
A9: autobus | E9: 1 | F9: 1 | G9: 45000 | H9: =F9*G9 -> 45000 | J9: HR NORMAL
J10: HR DOBLE
H11: =G11*F11 -> 0 | J11: HR TRIPLE
E12: Pza | F12: 1 | H12: =G12*F12 -> 0
E13: Pza | F13: 1 | H13: =G13*F13 -> 0
E14: Pza | F14: 1 | H14: =G14*F14 -> 0
E15: Pza | F15: 1 | H15: =G15*F15 -> 0
E16: Pza | F16: 1 | H16: =G16*F16 -> 0
G17: SUBT 1 | H17: =SUM(H9:H16) -> 45000
A19: MANO DE OBRA SIN INDIRECTOS | O19: HORARIOS DE TRABAJO | V19: HORAS RESULTANTES
A20: PERSONAL. | E20: UNIDAD | F20: CANT. | G20: P.U. | H20: IMPORTE | I20: CANT. | J20: Hr. Extra | K20: IMPORTE | L20: CANT. | M20: Dom, ó Fest. | N20: IMPORTE | O20: L | P20: M | Q20: MI | R20: J | S20: V | T20: S | U20: D | V20: N | W20: D | X20: T
A21: COORDINADOR DE OPERACIONES | E21: hr | F21: =V21 -> 0 | G21: 185.69 | H21: =F21*G21 -> 0 | I21: =W21 -> 0 | J21: =G21*1.5 -> 278.535 | K21: =I21*J21 -> 0 | L21: =X21 -> 0 | M21: =G21*2.25 -> 417.8025 | N21: =L21*M21 -> 0 | V21: =SUM(O21:T21) -> 0
A22: INGENIERIA Y SOPORTE TEC. | E22: hr | F22: =V22 -> 0 | G22: 177.79 | H22: =F22*G22 -> 0 | I22: =W22 -> 0 | J22: =G22*1.5 -> 266.685 | K22: =I22*J22 -> 0 | L22: =X22 -> 0 | M22: =G22*2.25 -> 400.0275 | N22: =L22*M22 -> 0 | V22: =SUM(O22:T22) -> 0
A23: SUPERVISOR DE SEGURIDAD CERTIFICADO | E23: hr | F23: =V23 -> 0 | G23: 185.69 | H23: =F23*G23 -> 0 | I23: =W23 -> 0 | J23: =G23*1.5 -> 278.535 | K23: =I23*J23 -> 0 | L23: =X23 -> 0 | M23: =G23*2.25 -> 417.8025 | N23: =L23*M23 -> 0 | V23: =SUM(O23:T23) -> 0
A24: SUPERVISOR ELECTRICO | E24: hr | F24: 0 | G24: 148.16 | H24: =F24*G24 -> 0 | I24: =W24 -> 0 | J24: =G24*1.5 -> 222.24 | K24: =I24*J24 -> 0 | L24: =X24 -> 0 | M24: =G24*2.25 -> 333.36 | N24: =L24*M24 -> 0 | O24: 8 | P24: 8 | Q24: 8 | R24: 8 | S24: 8 | V24: =SUM(O24:T24) -> 40 | Y24: Fco, Oropeza
A25: TECNICO DE PRUEBAS ELECTRICAS | E25: hr | F25: 0 | G25: 136.31 | H25: =F25*G25 -> 0 | I25: =W25 -> 0 | J25: =G25*1.5 -> 204.465 | K25: =I25*J25 -> 0 | L25: =X25 -> 0 | M25: =G25*2.25 -> 306.6975 | N25: =L25*M25 -> 0 | V25: =SUM(O25:T25) -> 0
A26: CABO OBRA ELECTRICA | E26: hr | F26: =V26 -> 0 | G26: 136.31 | H26: =F26*G26 -> 0 | I26: =W26 -> 0 | J26: =G26*1.5 -> 204.465 | K26: =I26*J26 -> 0 | L26: =X26 -> 0 | M26: =G26*2.25 -> 306.6975 | N26: =L26*M26 -> 0 | V26: =SUM(O26:T26) -> 0
A27: LINIERO | E27: hr | F27: 0 | G27: 126.43 | H27: =F27*G27 -> 0 | I27: =W27 -> 0 | J27: =G27*1.5 -> 189.645 | K27: =I27*J27 -> 0 | L27: =X27 -> 0 | M27: =G27*2.25 -> 284.4675 | N27: =L27*M27 -> 0 | O27: 16 | P27: 16 | Q27: 16 | R27: 8 | S27: 8 | T27: 5 | V27: =SUM(O27:T27) -> 69 | Y27: josé - adrian | Z27: 2
A28: LINIERO | E28: hr | F28: 0 | G28: 126.43 | H28: =F28*G28 -> 0 | I28: =W28 -> 0 | J28: =G28*1.5 -> 189.645 | K28: =I28*J28 -> 0 | L28: =X28 -> 0 | M28: =G28*2.25 -> 284.4675 | N28: =L28*M28 -> 0 | O28: 16 | P28: 16 | Q28: 16 | R28: 8 | S28: 8 | T28: 5 | V28: =SUM(O28:T28) -> 69 | Y28: josé - adrian | Z28: 2
A29: ESPECIALISTA ELECTRICO | E29: hr | F29: 0 | G29: 110.63 | H29: =F29*G29 -> 0 | I29: =W29 -> 0 | J29: =G29*1.5 -> 165.945 | K29: =I29*J29 -> 0 | L29: =X29 -> 0 | M29: =G29*2.25 -> 248.9175 | N29: =L29*M29 -> 0 | V29: =SUM(O29:T29) -> 0
A30: TECNICO EN INSTRUMENTACION | E30: hr | F30: =V30 -> 0 | G30: 104.36 | H30: =F30*G30 -> 0 | I30: =W30 -> 0 | J30: =G30*1.5 -> 156.54 | K30: =I30*J30 -> 0 | L30: =X30 -> 0 | M30: =G30*2.25 -> 234.81 | N30: =L30*M30 -> 0 | V30: =SUM(O30:T30) -> 0
A31: OFICIAL ELECTRICO | E31: hr | F31: 0 | G31: 104.36 | H31: =F31*G31 -> 0 | I31: =W31 -> 0 | J31: =G31*1.5 -> 156.54 | K31: =I31*J31 -> 0 | L31: =X31 -> 0 | M31: =G31*2.25 -> 234.81 | N31: =L31*M31 -> 0 | V31: =SUM(O31:T31) -> 0 | Z31: 1
A32: ASISTENTE DE DISEÑO | E32: hr | F32: 0 | G32: 104.36 | H32: =F32*G32 -> 0 | I32: =W32 -> 0 | J32: =G32*1.5 -> 156.54 | K32: =I32*J32 -> 0 | L32: =X32 -> 0 | M32: =G32*2.25 -> 234.81 | N32: =L32*M32 -> 0 | V32: =SUM(O32:T32) -> 0
A33: ELECTRICISTA -B | E33: hr | G33: 90.87 | H33: =F33*G33 -> 0 | I33: =W33 -> 0 | J33: =G33*1.5 -> 136.305 | K33: =I33*J33 -> 0 | L33: =X33 -> 0 | M33: =G33*2.25 -> 204.4575 | N33: =L33*M33 -> 0 | O33: 16 | P33: 16 | Q33: 16 | R33: 8 | S33: 8 | T33: 5 | V33: =SUM(O33:T33) -> 69 | Y33: Uno con categoría de: Alan/Eduardo
A34: ELECTRICISTA -A | E34: hr | F34: =V34 -> 0 | G34: 82.97 | H34: =F34*G34 -> 0 | I34: =W34 -> 0 | J34: =G34*1.5 -> 124.455 | K34: =I34*J34 -> 0 | L34: =X34 -> 0 | M34: =G34*2.25 -> 186.6825 | N34: =L34*M34 -> 0 | V34: =SUM(O34:T34) -> 0
A35: AUXILIAR TECNICO | E35: hr | G35: 75.07 | H35: =F35*G35 -> 0 | I35: =W35 -> 0 | J35: =G35*1.5 -> 112.605 | K35: =I35*J35 -> 0 | L35: =X35 -> 0 | M35: =G35*2.25 -> 168.9075 | N35: =L35*M35 -> 0 | V35: =SUM(O35:T35) -> 0
A36: AYTE ELECTRICO - B | E36: hr | F36: 0 | G36: 75.07 | H36: =F36*G36 -> 0 | I36: =W36 -> 0 | J36: =G36*1.5 -> 112.605 | K36: =I36*J36 -> 0 | L36: =X36 -> 0 | M36: =G36*2.25 -> 168.9075 | N36: =L36*M36 -> 0 | V36: =SUM(O36:T36) -> 0
A37: AYTE DE ELECTR. -A | E37: hr | F37: 0 | G37: 63.21 | H37: =F37*G37 -> 0 | I37: =W37 -> 0 | J37: =G37*1.5 -> 94.815 | K37: =I37*J37 -> 0 | L37: =X37 -> 0 | M37: =G37*2.25 -> 142.2225 | N37: =L37*M37 -> 0 | O37: 8 | P37: 8 | Q37: 8 | R37: 8 | S37: 8 | V37: =SUM(O37:T37) -> 40 | Z37: 4
A38: AYTE GENERAL | E38: hr | F38: =V38 -> 0 | G38: 50.77 | H38: =F38*G38 -> 0 | I38: =W38 -> 0 | J38: =G38*1.5 -> 76.155 | K38: =I38*J38 -> 0 | L38: =X38 -> 0 | M38: =G38*2.25 -> 114.2325 | N38: =L38*M38 -> 0 | Y38: Guadalupe | Z38: 1
A39: INGENIERO DE SUBESTACIONES | E39: hr | F39: =V39 -> 0 | G39: 186 | H39: =F39*G39 -> 0 | I39: =W39 -> 0 | J39: 186 | K39: =I39*J39 -> 0 | L39: =X39 -> 0 | M39: 186 | N39: =L39*M39 -> 0 | V39: =SUM(O39:T39) -> 0 | Z39: =SUM(Z29:Z38) -> 6
A40: INGENIERO DE PRUEBAS ELECTRICAS | E40: hr | F40: =V40 -> 0 | G40: 186 | H40: =F40*G40 -> 0 | I40: =W40 -> 0 | J40: 186 | K40: =I40*J40 -> 0 | L40: =X40 -> 0 | M40: 186 | N40: =L40*M40 -> 0 | V40: =SUM(O40:T40) -> 0
A41: ING. ESPECIALISTA EN PROTECCIONES | E41: hr | F41: =V41 -> 0 | G41: 230.47 | H41: =F41*G41 -> 0 | I41: =W41 -> 0 | J41: 294 | K41: =I41*J41 -> 0 | L41: =X41 -> 0 | M41: 294 | N41: =L41*M41 -> 0 | V41: =SUM(O41:T41) -> 0
A42: SUPERINTENDENTE | E42: hr | F42: =V42 -> 0 | G42: 279.53 | H42: =F42*G42 -> 0 | I42: =W42 -> 0 | J42: 372.71 | K42: =I42*J42 -> 0 | L42: =X42 -> 0 | M42: 559.07 | N42: =L42*M42 -> 0 | V42: =SUM(O42:T42) -> 0
F43: =V43 -> 287 | G43: SUBT 2 | H43: =SUM(H21:H42) -> 0 | J43: SUBT. | K43: =SUM(K22:K41) -> 0 | M43: SUBT. | N43: =SUM(N22:N41) -> 0 | V43: =SUM(V21:V42) -> 287 | W43: 45 | Z43: =+V43/W43 -> 6.3777778
G44: SUMA M.O. | H44: =H43+K43+N43 -> 0
A45: HERRAMIENTA MENOR | G45: 1 a 10% | H45: =+H44*0.06 -> 0
A47: VEHICULOS
A48: DESCRIPCION | E48: UNIDAD | F48: CANT. | G48: P.U. | H48: IMPORTE | J48: HR IDA | K48: HR RETORNO | L48: HR SITIO | M48: SUMA
A49: camioneta RANGER sin operador sin combustible | E49: HR | F49: 0 | G49: 102.29 | H49: =F49*G49 -> 0 | J49: 0 | K49: 0 | L49: 0 | M49: =J49+K49+L49 -> 0
A50: camioneta NISSAN sin operador sin combustible | E50: HR | F50: 0 | G50: 68.7 | H50: =F50*G50 -> 0 | J50: 0 | K50: 0 | M50: =J50+K50+L50 -> 0
A51: camioneta TORNADO Tornado sin operador sin combustible | E51: HR | F51: 0 | G51: 54.43 | H51: =F51*G51 -> 0 | J51: 0.45 | K51: 0.45 | M51: =J51+K51+L51 -> 0.9
A52: Camion con grua sin operador sin conbustible. | E52: HR | F52: =M52 -> 0 | G52: 203.19 | H52: =F52*G52 -> 0 | M52: =J52+K52+L52 -> 0
A53: Camion con grua con operador con conbustible. | E53: HR | G53: 407.62 | H53: =F53*G53 -> 0
A54: autobus | E54: pza | G54: 5000 | H54: =F54*G54 -> 0
A55: Km. Recorrido (incluye conbustible y depresiación de Vehiculo | E55: KM | G55: 2.5 | H55: =F55*G55 -> 0
G56: SUBT 4 | H56: =SUM(H49:H55) -> 0
A57: COMBUSTIBLE
A58: DESCRIPCION | E58: UNIDAD | F58: CANT. | G58: P.U. | H58: IMPORTE | J58: KM IDA | K58: KM RETORNO | L58: KM SITIO | M58: SUMA
A59: GASOLINA MAGNA | E59: LT | G59: 16.48 | H59: =F59*G59 -> 0 | J59: 22 | K59: 22 | M59: =J59+K59+L59 -> 44
A60: DIESEL | E60: LT | F60: =M60/4.5 -> 0 | G60: 0 | H60: =F60*G60 -> 0 | M60: =J60+K60+L60 -> 0
G61: SUBT 5 | H61: =SUM(H59:H60) -> 0
A62: CASETAS
A63: DESCRIPCION | E63: UNIDAD | F63: CANT. | G63: P.U. | H63: IMPORTE
A64: camioneta pick up | E64: CASETA | G64: 180 | H64: =F64*G64 -> 0
A65: camioneta pick up | E65: CASETA | G65: 65 | H65: =F65*G65 -> 0
G66: SUBT 6 | H66: =SUM(H64:H65) -> 0
A67: VIATICOS
A68: ALIMENTOS
A69: DESCRIPCION | E69: UNIDAD | F69: CANT. | G69: P.U. | H69: IMPORTE
A70: CONSUMO DE ALIMENTOS | E70: Pza | F70: 40 | G70: 650 | H70: =F70*G70 -> 26000
H71: =SUM(H70) -> 26000
A72: HOSPEDAJE
A73: DESCRIPCION | E73: UNIDAD | F73: CANT. | G73: P.U. | H73: IMPORTE
A74: HOTEL | E74: NOCHES | F74: 0 | G74: 900 | H74: =F74*G74 -> 0
G75: SUBT 8 | H75: =SUM(H74) -> 0
G76: SUMA: | H76: =H56+H61+H66+H71+H75+H45+H44+H17 -> 71000
A77: EQUIPO DE PRUEBA
A78: DESCRIPCION | E78: UNIDAD | F78: CANT. | G78: P.U. | H78: IMPORTE | I78: TR | K78: S.E
A79: Megger | E79: jr | G79: 2200 | H79: =(F79*G79) -> 0
A80: TTR | E80: jr | G80: 2000 | H80: =(F80*G80) -> 0
A81: Factor de Potencia de 2.5 KV | E81: jr | G81: 7000 | H81: =(F81*G81) -> 0
A82: Factor de Potencia de 10.5 KV | E82: jr | G82: 15200 | H82: =(F82*G82) -> 0
A83: Ducter | E83: jr | G83: 2200 | H83: =(F83*G83) -> 0
A84: resistencia óhmica | E84: jr | G84: 2000 | H84: =(F84*G84) -> 0
A85: hipot de 80 KV vcd | E85: jr | G85: 2500 | H85: =(F85*G85) -> 0
A86: Rigidez dieléctrica al aceite 60 kv | E86: jr | G86: 1600 | H86: =(F86*G86) -> 0
A87: Terrómetro | E87: jr | G87: 1100 | H87: =(F87*G87) -> 0
A88: Analizador de tiempos de interruptor | E88: jr | G88: 2700 | H88: =(F88*G88) -> 0
A89: Fuente de corriente para calibrador de relevadores | E89: jr | G89: 2500 | H89: =(F89*G89) -> 0
A90: Probador de relevador de Protecciones | E90: jr | G90: 13373 | H90: =(F90*G90) -> 0
... A98: Generador de Luz con combustible | E98: jr | G98: 383.5 | H98: =(F98*G98) -> 0
G99: SUBT 9 | H99: =SUM(H79:H98) -> 0
E101: 0 | H101: =+E101 -> 0 | I101: % DE IMP. | J101: INDIRECTO DISPONIBLE
G102: COSTO DIRECTO | H102: =H76+H99 -> 71000
F103: Indirectos | G103: 0.1 | H103: =H102*G103 -> 7100 | I103: =(M109*100)/H103 -> -172.0969 | J103: =H103-M109 -> 19318.88
F104: Subtotal 1 | H104: =H102+H103 -> 78100
K105: BASE IMPUESTO
F106: Financ. | G106: 0.06 | H106: =H104*G106 -> 4686 | I106: =H106+[1]Part.2!H84+[1]Part.3!H84+[1]Part.4!H84+[1]part.5!H84+[1]traslado!H66 -> 4896.212 | J106: COMPRAS | K106: =+H17 -> 45000
F107: Subtotal 2 | H107: =H104+H106 -> 82786 | J107: M.O | K107: =H44 -> 0
F108: Utilidad | G108: 0.1 | H108: =H107*G108 -> 8278.6 | J108: GASTOS FACTURADOS | K108: =H76-H56 -> 71000 | M108: IMP. 32%
F109: Importe | H109: =H107+H108 -> 91064.6 | J109: SUMA | K109: =SUM(K106:K108) -> 116000 | L109: =H109-H108-(H103*0.7)-K109 -> -38184 | M109: =0.32*L109 -> -12218.88
I110: FACTOR | J110: =H109/H102 -> 1.2826
B112: utilidad
...

Sheet TABLEROS GENERAL MO
A1: I M M E E S. A. D E C. V.
A2: A N A L I S I S D E P R E C I O U N I T A R I O
A3: COTIZACION:
A4: FECHA:
A5: PARTIDA 1
A7: MATERIALES.
A8: DESCRIPCION | E8: UNIDAD | F8: CANT. | G8: P.U. | H8: IMPORTE
E9: Pza | J9: HR NORMAL
E10: Pza | J10: HR DOBLE
E11: Pza | J11: HR TRIPLE
E12: Pza
E13: Pza
E14: Pza
E15: Pza
E16: Pza | I16: =H16*1.455 -> 0
G17: SUBT 1 | H17: =SUM(H9:H16) -> 0
A19: MANO DE OBRA SIN INDIRECTOS | O19: HORARIOS DE TRABAJO | V19: HORAS RESULTANTES
A20: PERSONAL. | E20: UNIDAD | F20: CANT. | G20: P.U. | H20: IMPORTE | I20: CANT. | J20: Hr. Extra | K20: IMPORTE | L20: CANT. | M20: Dom, ó Fest. | N20: IMPORTE | O20: L | P20: M | Q20: MI | R20: J | S20: V | T20: S | U20: D | V20: N | W20: D | X20: T
A21: COORDINADOR DE OPERACIONES | E21: hr | F21: =V21 -> 0 | G21: 185.69 | H21: =F21*G21 -> 0 | I21: =W21 -> 0 | J21: =G21*1.5 -> 278.535 | K21: =I21*J21 -> 0 | L21: =X21 -> 0 | M21: =G21*2.25 -> 417.8025 | N21: =L21*M21 -> 0 | V21: =SUM(O21:T21) -> 0
A22: INGENIERIA Y SOPORTE TEC. | E22: hr | F22: =V22 -> 0 | G22: 177.79 | H22: =F22*G22 -> 0 | I22: =W22 -> 0 | J22: =G22*1.5 -> 266.685 | K22: =I22*J22 -> 0 | L22: =X22 -> 0 | M22: =G22*2.25 -> 400.0275 | N22: =L22*M22 -> 0 | V22: =SUM(O22:T22) -> 0
A23: SUPERVISOR DE SEGURIDAD CERTIFICADO | E23: hr | F23: =V23 -> 0 | G23: 185.69 | H23: =F23*G23 -> 0 | I23: =W23 -> 0 | J23: =G23*1.5 -> 278.535 | K23: =I23*J23 -> 0 | L23: =X23 -> 0 | M23: =G23*2.25 -> 417.8025 | N23: =L23*M23 -> 0 | V23: =SUM(O23:T23) -> 0
A24: SUPERVISOR ELECTRICO | E24: hr | F24: 9 | G24: 148.16 | H24: =F24*G24 -> 1333.44 | I24: 0 | J24: =G24*1.5 -> 222.24 | K24: =I24*J24 -> 0 | L24: =X24 -> 0 | M24: =G24*2.25 -> 333.36 | N24: =L24*M24 -> 0 | O24: 8 | P24: 8 | Q24: 8 | R24: 8 | S24: 8 | V24: =SUM(O24:T24) -> 40 | Y24: Fco, Oropeza
A25: TECNICO DE PRUEBAS ELECTRICAS | E25: hr | F25: =V25 -> 0 | G25: 136.31 | H25: =F25*G25 -> 0 | I25: 0 | J25: =G25*1.5 -> 204.465 | K25: =I25*J25 -> 0 | L25: =X25 -> 0 | M25: =G25*2.25 -> 306.6975 | N25: =L25*M25 -> 0 | V25: =SUM(O25:T25) -> 0
A26: CABO OBRA ELECTRICA | E26: hr | F26: =V26 -> 0 | G26: 136.31 | H26: =F26*G26 -> 0 | I26: =W26 -> 0 | J26: =G26*1.5 -> 204.465 | K26: =I26*J26 -> 0 | L26: =X26 -> 0 | M26: =G26*2.25 -> 306.6975 | N26: =L26*M26 -> 0 | V26: =SUM(O26:T26) -> 0
A27: LINIERO | E27: hr | F27: 0 | G27: 126.43 | H27: =F27*G27 -> 0 | I27: =W27 -> 0 | J27: =G27*1.5 -> 189.645 | K27: =I27*J27 -> 0 | L27: =X27 -> 0 | M27: =G27*2.25 -> 284.4675 | N27: =L27*M27 -> 0 | O27: 16 | P27: 16 | Q27: 16 | R27: 8 | S27: 8 | T27: 5 | V27: =SUM(O27:T27) -> 69 | Y27: josé - adrian | Z27: 2
A28: LINIERO | E28: hr | F28: 0 | G28: 126.43 | H28: =F28*G28 -> 0 | I28: =W28 -> 0 | J28: =G28*1.5 -> 189.645 | K28: =I28*J28 -> 0 | L28: =X28 -> 0 | M28: =G28*2.25 -> 284.4675 | N28: =L28*M28 -> 0 | O28: 16 | P28: 16 | Q28: 16 | R28: 8 | S28: 8 | T28: 5 | V28: =SUM(O28:T28) -> 69 | Y28: josé - adrian | Z28: 2
A29: ESPECIALISTA ELECTRICO | E29: hr | F29: 0 | G29: 110.63 | H29: =F29*G29 -> 0 | I29: =W29 -> 0 | J29: =G29*1.5 -> 165.945 | K29: =I29*J29 -> 0 | L29: =X29 -> 0 | M29: =G29*2.25 -> 248.9175 | N29: =L29*M29 -> 0 | V29: =SUM(O29:T29) -> 0
A30: TECNICO EN INSTRUMENTACION | E30: hr | F30: =V30 -> 0 | G30: 104.36 | H30: =F30*G30 -> 0 | I30: =W30 -> 0 | J30: =G30*1.5 -> 156.54 | K30: =I30*J30 -> 0 | L30: =X30 -> 0 | M30: =G30*2.25 -> 234.81 | N30: =L30*M30 -> 0 | V30: =SUM(O30:T30) -> 0
A31: OFICIAL ELECTRICO | E31: hr | F31: 9 | G31: 104.36 | H31: =F31*G31 -> 939.24 | I31: =W31 -> 0 | J31: =G31*1.5 -> 156.54 | K31: =I31*J31 -> 0 | L31: =X31 -> 0 | M31: =G31*2.25 -> 234.81 | N31: =L31*M31 -> 0 | V31: =SUM(O31:T31) -> 0 | Z31: 1
A32: ASISTENTE DE DISEÑO | E32: hr | F32: =V32 -> 0 | G32: 104.36 | H32: =F32*G32 -> 0 | I32: =W32 -> 0 | J32: =G32*1.5 -> 156.54 | K32: =I32*J32 -> 0 | L32: =X32 -> 0 | M32: =G32*2.25 -> 234.81 | N32: =L32*M32 -> 0 | V32: =SUM(O32:T32) -> 0
A33: ELECTRICISTA -B | E33: hr | F33: 9 | G33: 90.87 | H33: =F33*G33 -> 817.83 | I33: 0 | J33: =G33*1.5 -> 136.305 | K33: =I33*J33 -> 0 | L33: =X33 -> 0 | M33: =G33*2.25 -> 204.4575 | N33: =L33*M33 -> 0 | O33: 16 | P33: 16 | Q33: 16 | R33: 8 | S33: 8 | T33: 5 | V33: =SUM(O33:T33) -> 69 | Y33: Uno con categoría de: Alan/Eduardo
A34: ELECTRICISTA -A | E34: hr | F34: 9 | G34: 82.97 | H34: =F34*G34 -> 746.73 | I34: =W34 -> 0 | J34: =G34*1.5 -> 124.455 | K34: =I34*J34 -> 0 | L34: =X34 -> 0 | M34: =G34*2.25 -> 186.6825 | N34: =L34*M34 -> 0 | V34: =SUM(O34:T34) -> 0
A35: AUXILIAR TECNICO | E35: hr | F35: 0 | G35: 75.07 | H35: =F35*G35 -> 0 | I35: =W35 -> 0 | J35: =G35*1.5 -> 112.605 | K35: =I35*J35 -> 0 | L35: =X35 -> 0 | M35: =G35*2.25 -> 168.9075 | N35: =L35*M35 -> 0 | V35: =SUM(O35:T35) -> 0
A36: AYTE ELECTRICO - B | E36: hr | F36: 0 | G36: 75.07 | H36: =F36*G36 -> 0 | I36: =W36 -> 0 | J36: =G36*1.5 -> 112.605 | K36: =I36*J36 -> 0 | L36: =X36 -> 0 | M36: =G36*2.25 -> 168.9075 | N36: =L36*M36 -> 0 | V36: =SUM(O36:T36) -> 0
A37: AYTE DE ELECTR. -A | E37: hr | F37: 0 | G37: 63.21 | H37: =F37*G37 -> 0 | I37: =W37 -> 0 | J37: =G37*1.5 -> 94.815 | K37: =I37*J37 -> 0 | L37: =X37 -> 0 | M37: =G37*2.25 -> 142.2225 | N37: =L37*M37 -> 0 | O37: 8 | P37: 8 | Q37: 8 | R37: 8 | S37: 8 | V37: =SUM(O37:T37) -> 40 | Z37: 4
A38: AYTE GENERAL | E38: hr | F38: 9 | G38: 50.77 | H38: =F38*G38 -> 456.93 | I38: =W38 -> 0 | J38: =G38*1.5 -> 76.155 | K38: =I38*J38 -> 0 | L38: =X38 -> 0 | M38: =G38*2.25 -> 114.2325 | N38: =L38*M38 -> 0 | Y38: Guadalupe | Z38: 1
A39: INGENIERO DE SUBESTACIONES | E39: hr | F39: 0 | G39: 186 | H39: =F39*G39 -> 0 | I39: =W39 -> 0 | J39: 186 | K39: =I39*J39 -> 0 | L39: =X39 -> 0 | M39: 186 | N39: =L39*M39 -> 0 | V39: =SUM(O39:T39) -> 0 | Z39: =SUM(Z29:Z38) -> 6
A40: INGENIERO DE PRUEBAS ELECTRICAS | E40: hr | F40: 0 | G40: 186 | H40: =F40*G40 -> 0 | I40: =W40 -> 0 | J40: 186 | K40: =I40*J40 -> 0 | L40: =X40 -> 0 | M40: 186 | N40: =L40*M40 -> 0 | V40: =SUM(O40:T40) -> 0
A41: ING. ESPECIALISTA EN PROTECCIONES | E41: hr | F41: 0 | G41: 230.47 | H41: =F41*G41 -> 0 | I41: =W41 -> 0 | J41: 294 | K41: =I41*J41 -> 0 | L41: =X41 -> 0 | M41: 294 | N41: =L41*M41 -> 0 | V41: =SUM(O41:T41) -> 0
A42: SUPERINTENDENTE | E42: hr | F42: =V42 -> 0 | G42: 279.53 | H42: =F42*G42 -> 0 | I42: =W42 -> 0 | J42: 372.71 | K42: =I42*J42 -> 0 | L42: =X42 -> 0 | M42: 559.07 | N42: =L42*M42 -> 0 | V42: =SUM(O42:T42) -> 0
F43: =V43 -> 287 | G43: SUBT 2 | H43: =SUM(H21:H42) -> 4294.17 | J43: SUBT. | K43: =SUM(K22:K41) -> 0 | M43: SUBT. | N43: =SUM(N22:N41) -> 0 | V43: =SUM(V21:V42) -> 287 | W43: 45 | Z43: =+V43/W43 -> 6.3777778
G44: SUMA M.O. | H44: =H43+K43+N43 -> 4294.17
A45: HERRAMIENTA MENOR | G45: 1 a 10% | H45: =+H44*0.06 -> 257.6502
A47: VEHICULOS
A48: DESCRIPCION | E48: UNIDAD | F48: CANT. | G48: P.U. | H48: IMPORTE | J48: HR IDA | K48: HR RETORNO | L48: HR SITIO | M48: SUMA
A49: camioneta RANGER sin operador sin combustible | E49: HR | F49: 0 | G49: 102.29 | H49: =F49*G49 -> 0 | J49: 0 | K49: 0 | L49: 0 | M49: =J49+K49+L49 -> 0
A50: camioneta NISSAN sin operador sin combustible | E50: HR | F50: 0 | G50: 68.7 | H50: =F50*G50 -> 0 | J50: 0 | K50: 0 | M50: =J50+K50+L50 -> 0
A51: camioneta TORNADO Tornado sin operador sin combustible | E51: HR | F51: 0 | G51: 54.43 | H51: =F51*G51 -> 0 | J51: 0.45 | K51: 0.45 | M51: =J51+K51+L51 -> 0.9
A52: Camion con grua sin operador sin conbustible. | E52: HR | F52: 0 | G52: 203.19 | H52: =F52*G52 -> 0 | M52: =J52+K52+L52 -> 0
A53: Camion con grua con operador con conbustible. | E53: HR | F53: 0 | G53: 407.62 | H53: =F53*G53 -> 0
A54: autobus | E54: pza | F54: 0 | G54: 5000 | H54: =F54*G54 -> 0
A55: Km. Recorrido (incluye conbustible y depresiación de Vehiculo | E55: KM | F55: 0 | G55: 2.5 | H55: =F55*G55 -> 0
G56: SUBT 4 | H56: =SUM(H49:H55) -> 0
A57: COMBUSTIBLE
A58: DESCRIPCION | E58: UNIDAD | F58: CANT. | G58: P.U. | H58: IMPORTE | J58: KM IDA | K58: KM RETORNO | L58: KM SITIO | M58: SUMA
A59: GASOLINA MAGNA | E59: LT | F59: 0 | G59: 19 | H59: =F59*G59 -> 0 | J59: 22 | K59: 22 | M59: =J59+K59+L59 -> 44
A60: DIESEL | E60: LT | F60: =M60/4.5 -> 0 | G60: 0 | H60: =F60*G60 -> 0 | M60: =J60+K60+L60 -> 0
G61: SUBT 5 | H61: =SUM(H59:H60) -> 0
A62: CASETAS
A63: DESCRIPCION | E63: UNIDAD | F63: CANT. | G63: P.U. | H63: IMPORTE
A64: camioneta pick up | E64: CASETA | F64: 0 | G64: 100 | H64: =F64*G64 -> 0
A65: camioneta pick up | E65: CASETA | F65: 0 | G65: 65 | H65: =F65*G65 -> 0
G66: SUBT 6 | H66: =SUM(H64:H65) -> 0
A67: VIATICOS
A68: ALIMENTOS
A69: DESCRIPCION | E69: UNIDAD | F69: CANT. | G69: P.U. | H69: IMPORTE
A70: CONSUMO DE ALIMENTOS | E70: Pza | F70: 0 | G70: 450 | H70: =F70*G70 -> 0
H71: =SUM(H70) -> 0
A72: HOSPEDAJE
A73: DESCRIPCION | E73: UNIDAD | F73: CANT. | G73: P.U. | H73: IMPORTE
A74: HOTEL | E74: NOCHES | F74: 0 | G74: 900 | H74: =F74*G74 -> 0
G75: SUBT 8 | H75: =SUM(H74) -> 0
G76: SUMA: | H76: =H56+H61+H66+H71+H75+H45+H44+H17 -> 4551.8202
A77: EQUIPO DE PRUEBA
A78: DESCRIPCION | E78: UNIDAD | F78: CANT. | G78: P.U. | H78: IMPORTE | I78: TR | K78: S.E
A79: Megger | E79: jr | F79: 0.5 | G79: 2200 | H79: =(F79*G79) -> 1100
A80: TTR | E80: jr | G80: 2000 | H80: =(F80*G80) -> 0
A81: Factor de Potencia de 2.5 KV | E81: jr | G81: 7000 | H81: =(F81*G81) -> 0
A82: Factor de Potencia de 10.5 KV | E82: jr | G82: 15200 | H82: =(F82*G82) -> 0
A83: Ducter | E83: jr | F83: 0.5 | G83: 2200 | H83: =(F83*G83) -> 1100
A84: resistencia óhmica | E84: jr | G84: 2000 | H84: =(F84*G84) -> 0
A85: hipot de 80 KV vcd | E85: jr | G85: 2500 | H85: =(F85*G85) -> 0
A86: Rigidez dieléctrica al aceite 60 kv | E86: jr | G86: 1600 | H86: =(F86*G86) -> 0
A87: Terrómetro | E87: jr | G87: 1100 | H87: =(F87*G87) -> 0
A88: Analizador de tiempos de interruptor | E88: jr | G88: 2700 | H88: =(F88*G88) -> 0
A89: Fuente de corriente para calibrador de relevadores | E89: jr | G89: 2500 | H89: =(F89*G89) -> 0
A90: Probador de relevador de Protecciones | E90: jr | G90: 13373 | H90: =(F90*G90) -> 0
A91: Fuente trifasica de voltaje | E91: jr | G91: 800 | H91: =(F91*G91) -> 0
A92: Analizador de energía trifásica | E92: jr | G92: 1900 | H92: =(F92*G92) -> 0
A93: Medidor de presión y llenado de gas SF6 | E93: jr | F93: 0 | G93: 2000 | H93: =(F93*G93) -> 0
A94: Medidor de secuencia de fases | E94: jr | G94: 200 | H94: =(F94*G94) -> 0
A95: Unidad de Pba y config. Para relevadores de Int. ABB | E95: jr | G95: 1100 | H95: =(F95*G95) -> 0
A96: Máquina centrifugadora de aceite | E96: jr | G96: 2200 | H96: =(F96*G96) -> 0
A97: Luxómetro | E97: jr | G97: 1420 | H97: =(F97*G97) -> 0
A98: Generador de Luz con combustible | E98: jr | F98: 1 | G98: 383.5 | H98: =(F98*G98) -> 383.5
G99: SUBT 9 | H99: =SUM(H79:H98) -> 2583.5
E101: 0 | H101: =+E101 -> 0 | I101: % DE IMP. | J101: INDIRECTO DISPONIBLE
G102: COSTO DIRECTO | H102: =H76+H99 -> 7135.3202
F103: Indirectos | G103: 0.3 | H103: =H102*G103 -> 2140.5961 | I103: =(M109*100)/H103 -> -9.0396559 | J103: =H103-M109 -> 2334.0986
F104: Subtotal 1 | H104: =H102+H103 -> 9275.9163
...

Sheet BANCO DE BATERIAS MAT.
A1: I M M E E S. A. D E C. V.
A2: A N A L I S I S D E P R E C I O U N I T A R I O
A3: COTIZACION:
A4: FECHA:
A5: PARTIDA 1
A7: MATERIALES.
A8: DESCRIPCION | E8: UNIDAD | F8: CANT. | G8: P.U. | H8: IMPORTE
A9: Solvente Dielectrico | E9: L | F9: 1 | G9: 331 | H9: =G9*F9 -> 331 | J9: HR NORMAL
A10: Trapo | E10: kg | F10: 1 | G10: 2346.71 | H10: =G10*F10 -> 2346.71 | J10: HR DOBLE
J11: HR TRIPLE
E12: Pza | F12: 1 | H12: =G12*F12 -> 0
E13: Pza | F13: 1 | H13: =G13*F13 -> 0
E14: Pza | F14: 1 | H14: =G14*F14 -> 0
E15: Pza | F15: 1 | H15: =G15*F15 -> 0
E16: Pza | F16: 1 | H16: =G16*F16 -> 0
G17: SUBT 1 | H17: =SUM(H9:H16) -> 2677.71
A19: MANO DE OBRA SIN INDIRECTOS | O19: HORARIOS DE TRABAJO | V19: HORAS RESULTANTES
A20: PERSONAL. | E20: UNIDAD | F20: CANT. | G20: P.U. | H20: IMPORTE | I20: CANT. | J20: Hr. Extra | K20: IMPORTE | L20: CANT. | M20: Dom, ó Fest. | N20: IMPORTE | O20: L | P20: M | Q20: MI | R20: J | S20: V | T20: S | U20: D | V20: N | W20: D | X20: T
A21: COORDINADOR DE OPERACIONES | E21: hr | F21: =V21 -> 0 | G21: 185.69 | H21: =F21*G21 -> 0 | I21: =W21 -> 0 | J21: =G21*1.5 -> 278.535 | K21: =I21*J21 -> 0 | L21: =X21 -> 0 | M21: =G21*2.25 -> 417.8025 | N21: =L21*M21 -> 0 | V21: =SUM(O21:T21) -> 0
A22: INGENIERIA Y SOPORTE TEC. | E22: hr | F22: =V22 -> 0 | G22: 177.79 | H22: =F22*G22 -> 0 | I22: =W22 -> 0 | J22: =G22*1.5 -> 266.685 | K22: =I22*J22 -> 0 | L22: =X22 -> 0 | M22: =G22*2.25 -> 400.0275 | N22: =L22*M22 -> 0 | V22: =SUM(O22:T22) -> 0
A23: SUPERVISOR DE SEGURIDAD CERTIFICADO | E23: hr | F23: =V23 -> 0 | G23: 185.69 | H23: =F23*G23 -> 0 | I23: =W23 -> 0 | J23: =G23*1.5 -> 278.535 | K23: =I23*J23 -> 0 | L23: =X23 -> 0 | M23: =G23*2.25 -> 417.8025 | N23: =L23*M23 -> 0 | V23: =SUM(O23:T23) -> 0
A24: SUPERVISOR ELECTRICO | E24: hr | F24: 0 | G24: 148.16 | H24: =F24*G24 -> 0 | I24: =W24 -> 0 | J24: =G24*1.5 -> 222.24 | K24: =I24*J24 -> 0 | L24: =X24 -> 0 | M24: =G24*2.25 -> 333.36 | N24: =L24*M24 -> 0 | O24: 8 | P24: 8 | Q24: 8 | R24: 8 | S24: 8 | V24: =SUM(O24:T24) -> 40
A25: TECNICO DE PRUEBAS ELECTRICAS | E25: hr | F25: 0 | G25: 136.31 | H25: =F25*G25 -> 0 | I25: =W25 -> 0 | J25: =G25*1.5 -> 204.465 | K25: =I25*J25 -> 0 | L25: =X25 -> 0 | M25: =G25*2.25 -> 306.6975 | N25: =L25*M25 -> 0 | V25: =SUM(O25:T25) -> 0
A26: CABO OBRA ELECTRICA | E26: hr | F26: =V26 -> 0 | G26: 136.31 | H26: =F26*G26 -> 0 | I26: =W26 -> 0 | J26: =G26*1.5 -> 204.465 | K26: =I26*J26 -> 0 | L26: =X26 -> 0 | M26: =G26*2.25 -> 306.6975 | N26: =L26*M26 -> 0 | V26: =SUM(O26:T26) -> 0
A27: LINIERO | E27: hr | F27: 0 | G27: 126.43 | H27: =F27*G27 -> 0 | I27: =W27 -> 0 | J27: =G27*1.5 -> 189.645 | K27: =I27*J27 -> 0 | L27: =X27 -> 0 | M27: =G27*2.25 -> 284.4675 | N27: =L27*M27 -> 0 | O27: 16 | P27: 16 | Q27: 16 | R27: 8 | S27: 8 | T27: 5 | V27: =SUM(O27:T27) -> 69
A28: LINIERO | E28: hr | F28: 0 | G28: 126.43 | H28: =F28*G28 -> 0 | I28: =W28 -> 0 | J28: =G28*1.5 -> 189.645 | K28: =I28*J28 -> 0 | L28: =X28 -> 0 | M28: =G28*2.25 -> 284.4675 | N28: =L28*M28 -> 0 | O28: 16 | P28: 16 | Q28: 16 | R28: 8 | S28: 8 | T28: 5 | V28: =SUM(O28:T28) -> 69
A29: ESPECIALISTA ELECTRICO | E29: hr | F29: 0 | G29: 110.63 | H29: =F29*G29 -> 0 | I29: =W29 -> 0 | J29: =G29*1.5 -> 165.945 | K29: =I29*J29 -> 0 | L29: =X29 -> 0 | M29: =G29*2.25 -> 248.9175 | N29: =L29*M29 -> 0 | V29: =SUM(O29:T29) -> 0
A30: TECNICO EN INSTRUMENTACION | E30: hr | F30: =V30 -> 0 | G30: 104.36 | H30: =F30*G30 -> 0 | I30: =W30 -> 0 | J30: =G30*1.5 -> 156.54 | K30: =I30*J30 -> 0 | L30: =X30 -> 0 | M30: =G30*2.25 -> 234.81 | N30: =L30*M30 -> 0 | V30: =SUM(O30:T30) -> 0
A31: OFICIAL ELECTRICO | E31: hr | F31: 0 | G31: 104.36 | H31: =F31*G31 -> 0 | I31: =W31 -> 0 | J31: =G31*1.5 -> 156.54 | K31: =I31*J31 -> 0 | L31: =X31 -> 0 | M31: =G31*2.25 -> 234.81 | N31: =L31*M31 -> 0 | V31: =SUM(O31:T31) -> 0
A32: ASISTENTE DE DISEÑO | E32: hr | F32: 0 | G32: 104.36 | H32: =F32*G32 -> 0 | I32: =W32 -> 0 | J32: =G32*1.5 -> 156.54 | K32: =I32*J32 -> 0 | L32: =X32 -> 0 | M32: =G32*2.25 -> 234.81 | N32: =L32*M32 -> 0 | V32: =SUM(O32:T32) -> 0
A33: ELECTRICISTA -B | E33: hr | F33: 8 | G33: 90.87 | H33: =F33*G33 -> 726.96 | I33: =W33 -> 0 | J33: =G33*1.5 -> 136.305 | K33: =I33*J33 -> 0 | L33: =X33 -> 0 | M33: =G33*2.25 -> 204.4575 | N33: =L33*M33 -> 0 | O33: 16 | P33: 16 | Q33: 16 | R33: 8 | S33: 8 | T33: 5 | V33: =SUM(O33:T33) -> 69
A34: ELECTRICISTA -A | E34: hr | F34: =V34 -> 0 | G34: 82.97 | H34: =F34*G34 -> 0 | I34: =W34 -> 0 | J34: =G34*1.5 -> 124.455 | K34: =I34*J34 -> 0 | L34: =X34 -> 0 | M34: =G34*2.25 -> 186.6825 | N34: =L34*M34 -> 0 | V34: =SUM(O34:T34) -> 0
A35: AUXILIAR TECNICO | E35: hr | F35: 4 | G35: 75.07 | H35: =F35*G35 -> 300.28 | I35: =W35 -> 0 | J35: =G35*1.5 -> 112.605 | K35: =I35*J35 -> 0 | L35: =X35 -> 0 | M35: =G35*2.25 -> 168.9075 | N35: =L35*M35 -> 0 | V35: =SUM(O35:T35) -> 0
A36: AYTE ELECTRICO - B | E36: hr | F36: 0 | G36: 75.07 | H36: =F36*G36 -> 0 | I36: =W36 -> 0 | J36: =G36*1.5 -> 112.605 | K36: =I36*J36 -> 0 | L36: =X36 -> 0 | M36: =G36*2.25 -> 168.9075 | N36: =L36*M36 -> 0 | V36: =SUM(O36:T36) -> 0
A37: AYTE DE ELECTR. -A | E37: hr | F37: 0 | G37: 63.21 | H37: =F37*G37 -> 0 | I37: =W37 -> 0 | J37: =G37*1.5 -> 94.815 | K37: =I37*J37 -> 0 | L37: =X37 -> 0 | M37: =G37*2.25 -> 142.2225 | N37: =L37*M37 -> 0 | O37: 8 | P37: 8 | Q37: 8 | R37: 8 | S37: 8 | V37: =SUM(O37:T37) -> 40
A38: AYTE GENERAL | E38: hr | F38: =V38 -> 0 | G38: 50.77 | H38: =F38*G38 -> 0 | I38: =W38 -> 0 | J38: =G38*1.5 -> 76.155 | K38: =I38*J38 -> 0 | L38: =X38 -> 0 | M38: =G38*2.25 -> 114.2325 | N38: =L38*M38 -> 0
A39: INGENIERO DE SUBESTACIONES | E39: hr | F39: =V39 -> 0 | G39: 186 | H39: =F39*G39 -> 0 | I39: =W39 -> 0 | J39: 186 | K39: =I39*J39 -> 0 | L39: =X39 -> 0 | M39: 186 | N39: =L39*M39 -> 0 | V39: =SUM(O39:T39) -> 0
A40: INGENIERO DE PRUEBAS ELECTRICAS | E40: hr | F40: =V40 -> 0 | G40: 186 | H40: =F40*G40 -> 0 | I40: =W40 -> 0 | J40: 186 | K40: =I40*J40 -> 0 | L40: =X40 -> 0 | M40: 186 | N40: =L40*M40 -> 0 | V40: =SUM(O40:T40) -> 0
A41: ING. ESPECIALISTA EN PROTECCIONES | E41: hr | F41: =V41 -> 0 | G41: 230.47 | H41: =F41*G41 -> 0 | I41: =W41 -> 0 | J41: 294 | K41: =I41*J41 -> 0 | L41: =X41 -> 0 | M41: 294 | N41: =L41*M41 -> 0 | V41: =SUM(O41:T41) -> 0
A42: SUPERINTENDENTE | E42: hr | F42: =V42 -> 0 | G42: 279.53 | H42: =F42*G42 -> 0 | I42: =W42 -> 0 | J42: 372.71 | K42: =I42*J42 -> 0 | L42: =X42 -> 0 | M42: 559.07 | N42: =L42*M42 -> 0 | V42: =SUM(O42:T42) -> 0
F43: =V43 -> 287 | G43: SUBT 2 | H43: =SUM(H21:H42) -> 1027.24 | J43: SUBT. | K43: =SUM(K22:K41) -> 0 | M43: SUBT. | N43: =SUM(N22:N41) -> 0 | V43: =SUM(V21:V42) -> 287 | W43: 45
G44: SUMA M.O. | H44: =H43+K43+N43 -> 1027.24
A45: HERRAMIENTA MENOR | G45: 1 a 10% | H45: =+H44*0.06 -> 61.6344
A47: VEHICULOS
A48: DESCRIPCION | E48: UNIDAD | F48: CANT. | G48: P.U. | H48: IMPORTE | J48: HR IDA | K48: HR RETORNO | L48: HR SITIO | M48: SUMA
A49: camioneta RANGER sin operador sin combustible | E49: HR | F49: 0 | G49: 102.29 | H49: =F49*G49 -> 0 | J49: 0 | K49: 0 | L49: 0 | M49: =J49+K49+L49 -> 0
A50: camioneta NISSAN sin operador sin combustible | E50: HR | F50: 0 | G50: 68.7 | H50: =F50*G50 -> 0 | J50: 0 | K50: 0 | M50: =J50+K50+L50 -> 0
A51: camioneta TORNADO Tornado sin operador sin combustible | E51: HR | F51: 8 | G51: 54.43 | H51: =F51*G51 -> 435.44 | J51: 0.45 | K51: 0.45 | M51: =J51+K51+L51 -> 0.9
A52: Camion con grua sin operador sin conbustible. | E52: HR | F52: =M52 -> 0 | G52: 203.19 | H52: =F52*G52 -> 0 | M52: =J52+K52+L52 -> 0
A53: Camion con grua con operador con conbustible. | E53: HR | G53: 407.62 | H53: =F53*G53 -> 0
A54: autobus | E54: pza | G54: 5000 | H54: =F54*G54 -> 0
A55: Km. Recorrido (incluye conbustible y depresiación de Vehiculo | E55: KM | G55: 2.5 | H55: =F55*G55 -> 0
G56: SUBT 4 | H56: =SUM(H49:H55) -> 435.44
A57: COMBUSTIBLE
A58: DESCRIPCION | E58: UNIDAD | F58: CANT. | G58: P.U. | H58: IMPORTE | J58: KM IDA | K58: KM RETORNO | L58: KM SITIO | M58: SUMA
A59: GASOLINA MAGNA | E59: LT | F59: 30 | G59: 16.48 | H59: =F59*G59 -> 494.4 | J59: 22 | K59: 22 | M59: =J59+K59+L59 -> 44
A60: DIESEL | E60: LT | F60: =M60/4.5 -> 0 | G60: 0 | H60: =F60*G60 -> 0 | M60: =J60+K60+L60 -> 0
G61: SUBT 5 | H61: =SUM(H59:H60) -> 494.4
A62: CASETAS
A63: DESCRIPCION | E63: UNIDAD | F63: CANT. | G63: P.U. | H63: IMPORTE
A64: camioneta pick up | E64: CASETA | F64: 2 | G64: 180 | H64: =F64*G64 -> 360
A65: camioneta pick up | E65: CASETA | G65: 65 | H65: =F65*G65 -> 0
G66: SUBT 6 | H66: =SUM(H64:H65) -> 360
A67: VIATICOS
A68: ALIMENTOS
A69: DESCRIPCION | E69: UNIDAD | F69: CANT. | G69: P.U. | H69: IMPORTE
A70: CONSUMO DE ALIMENTOS | E70: Pza | F70: 0.5 | G70: 450 | H70: =F70*G70 -> 225
H71: =SUM(H70) -> 225
A72: HOSPEDAJE
A73: DESCRIPCION | E73: UNIDAD | F73: CANT. | G73: P.U. | H73: IMPORTE
A74: HOTEL | E74: NOCHES | F74: 0 | G74: 900 | H74: =F74*G74 -> 0
G75: SUBT 8 | H75: =SUM(H74) -> 0
G76: SUMA: | H76: =H56+H61+H66+H71+H75+H45+H44+H17 -> 5281.4244
A77: EQUIPO DE PRUEBA
A78: DESCRIPCION | E78: UNIDAD | F78: CANT. | G78: P.U. | H78: IMPORTE | I78: TR | K78: S.E
A79: Megger | E79: jr | G79: 2200 | H79: =(F79*G79) -> 0
A80: TTR | E80: jr | G80: 2000 | H80: =(F80*G80) -> 0
A81: Factor de Potencia de 2.5 KV | E81: jr | G81: 7000 | H81: =(F81*G81) -> 0
A82: Factor de Potencia de 10.5 KV | E82: jr | G82: 15200 | H82: =(F82*G82) -> 0
A83: Ducter | E83: jr | G83: 2200 | H83: =(F83*G83) -> 0
A84: resistencia óhmica | E84: jr | G84: 2000 | H84: =(F84*G84) -> 0
A85: hipot de 80 KV vcd | E85: jr | G85: 2500 | H85: =(F85*G85) -> 0
A86: Rigidez dieléctrica al aceite 60 kv | E86: jr | G86: 1600 | H86: =(F86*G86) -> 0
A87: Terrómetro | E87: jr | G87: 1100 | H87: =(F87*G87) -> 0
A88: Analizador de tiempos de interruptor | E88: jr | G88: 2700 | H88: =(F88*G88) -> 0
A89: Fuente de corriente para calibrador de relevadores | E89: jr | G89: 2500 | H89: =(F89*G89) -> 0
A90: Probador de relevador de Protecciones | E90: jr | G90: 13373 | H90: =(F90*G90) -> 0
... A98: Generador de Luz con combustible | E98: jr | G98: 383.5 | H98: =(F98*G98) -> 0
G99: SUBT 9 | H99: =SUM(H79:H98) -> 0
E101: 0 | H101: =+E101 -> 0 | I101: % DE IMP. | J101: INDIRECTO DISPONIBLE
G102: COSTO DIRECTO | H102: =H76+H99 -> 5281.4244
F103: Indirectos | G103: 0.1 | H103: =H102*G103 -> 528.14244 | I103: =(M109*100)/H103 -> -170.89868 | J103: =H103-M109 -> 1430.7309
F104: Subtotal 1 | H104: =H102+H103 -> 5809.5668
K105: BASE IMPUESTO
F106: Financ. | G106: 0.05 | H106: =H104*G106 -> 290.47834 | I106: =H106+[1]Part.2!H84+[1]Part.3!H84+[1]Part.4!H84+[1]part.5!H84+[1]traslado!H66 -> 500.69039 | J106: COMPRAS | K106: =+H17 -> 2677.71
F107: Subtotal 2 | H107: =H104+H106 -> 6100.0452 | J107: M.O | K107: =H44 -> 1027.24
F108: Utilidad | G108: 0.2 | H108: =H107*G108 -> 1220.009 | J108: GASTOS FACTURADOS | K108: =H76-H56 -> 4845.9844 | M108: IMP. 32%
F109: Importe | H109: =H107+H108 -> 7320.0542 | J109: SUMA | K109: =SUM(K106:K108) -> 8550.9344 | L109: =H109-H108-(H103*0.7)-K109 -> -2820.5889 | M109: =0.32*L109 -> -902.58846
I110: FACTOR | J110: =H109/H102 -> 1.386

Sheet BANCO DE BATERIAS MO
A1: I M M E E S. A. D E C. V.
A2: A N A L I S I S D E P R E C I O U N I T A R I O
A3: COTIZACION:
A4: FECHA:
A5: PARTIDA 1
A7: MATERIALES.
A8: DESCRIPCION | E8: UNIDAD | F8: CANT. | G8: P.U. | H8: IMPORTE
E9: Pza | F9: 1 | G9: 0 | H9: =G9 -> 0 | J9: HR NORMAL
E10: Pza | J10: HR DOBLE
E11: Pza | J11: HR TRIPLE
E12: Pza
E13: Pza
E14: Pza
E15: Pza
E16: Pza | I16: =H16*1.455 -> 0
G17: SUBT 1 | H17: =SUM(H9:H16) -> 0
A19: MANO DE OBRA SIN INDIRECTOS | O19: HORARIOS DE TRABAJO | V19: HORAS RESULTANTES
A20: PERSONAL. | E20: UNIDAD | F20: CANT. | G20: P.U. | H20: IMPORTE | I20: CANT. | J20: Hr. Extra | K20: IMPORTE | L20: CANT. | M20: Dom, ó Fest. | N20: IMPORTE | O20: L | P20: M | Q20: MI | R20: J | S20: V | T20: S | U20: D | V20: N | W20: D | X20: T
A21: COORDINADOR DE OPERACIONES | E21: hr | F21: =V21 -> 0 | G21: 185.69 | H21: =F21*G21 -> 0 | I21: =W21 -> 0 | J21: =G21*1.5 -> 278.535 | K21: =I21*J21 -> 0 | L21: =X21 -> 0 | M21: =G21*2.25 -> 417.8025 | N21: =L21*M21 -> 0 | V21: =SUM(O21:T21) -> 0
A22: INGENIERIA Y SOPORTE TEC. | E22: hr | F22: =V22 -> 0 | G22: 177.79 | H22: =F22*G22 -> 0 | I22: =W22 -> 0 | J22: =G22*1.5 -> 266.685 | K22: =I22*J22 -> 0 | L22: =X22 -> 0 | M22: =G22*2.25 -> 400.0275 | N22: =L22*M22 -> 0 | V22: =SUM(O22:T22) -> 0
A23: SUPERVISOR DE SEGURIDAD CERTIFICADO | E23: hr | F23: =V23 -> 0 | G23: 185.69 | H23: =F23*G23 -> 0 | I23: =W23 -> 0 | J23: =G23*1.5 -> 278.535 | K23: =I23*J23 -> 0 | L23: =X23 -> 0 | M23: =G23*2.25 -> 417.8025 | N23: =L23*M23 -> 0 | V23: =SUM(O23:T23) -> 0
A24: SUPERVISOR ELECTRICO | E24: hr | F24: 4 | G24: 237 | H24: =F24*G24 -> 948 | I24: =W24 -> 0 | J24: =G24*1.5 -> 355.5 | K24: =I24*J24 -> 0 | L24: =X24 -> 0 | M24: =G24*2.25 -> 533.25 | N24: =L24*M24 -> 0 | O24: 8 | P24: 8 | Q24: 8 | R24: 8 | S24: 8 | V24: =SUM(O24:T24) -> 40
A25: TECNICO DE PRUEBAS ELECTRICAS | E25: hr | F25: 16 | G25: 209.25 | H25: =F25*G25 -> 3348 | I25: 6 | J25: =G25*1.5 -> 313.875 | K25: =I25*J25 -> 1883.25 | L25: =X25 -> 0 | M25: =G25*2.25 -> 470.8125 | N25: =L25*M25 -> 0 | V25: =SUM(O25:T25) -> 0
A26: CABO OBRA ELECTRICA | E26: hr | F26: =V26 -> 0 | G26: 136.31 | H26: =F26*G26 -> 0 | I26: =W26 -> 0 | J26: =G26*1.5 -> 204.465 | K26: =I26*J26 -> 0 | L26: =X26 -> 0 | M26: =G26*2.25 -> 306.6975 | N26: =L26*M26 -> 0 | V26: =SUM(O26:T26) -> 0
A27: LINIERO | E27: hr | F27: 16 | G27: 190.22 | H27: =F27*G27 -> 3043.52 | I27: 6 | J27: =G27*1.5 -> 285.33 | K27: =I27*J27 -> 1711.98 | L27: =X27 -> 0 | M27: =G27*2.25 -> 427.995 | N27: =L27*M27 -> 0 | O27: 16 | P27: 16 | Q27: 16 | R27: 8 | S27: 8 | T27: 5 | V27: =SUM(O27:T27) -> 69
A28: LINIERO | E28: hr | F28: 0 | G28: 126.43 | H28: =F28*G28 -> 0 | I28: =W28 -> 0 | J28: =G28*1.5 -> 189.645 | K28: =I28*J28 -> 0 | L28: =X28 -> 0 | M28: =G28*2.25 -> 284.4675 | N28: =L28*M28 -> 0 | O28: 16 | P28: 16 | Q28: 16 | R28: 8 | S28: 8 | T28: 5 | V28: =SUM(O28:T28) -> 69
A29: ESPECIALISTA ELECTRICO | E29: hr | F29: 0 | G29: 110.63 | H29: =F29*G29 -> 0 | I29: =W29 -> 0 | J29: =G29*1.5 -> 165.945 | K29: =I29*J29 -> 0 | L29: =X29 -> 0 | M29: =G29*2.25 -> 248.9175 | N29: =L29*M29 -> 0 | V29: =SUM(O29:T29) -> 0
A30: TECNICO EN INSTRUMENTACION | E30: hr | F30: =V30 -> 0 | G30: 104.36 | H30: =F30*G30 -> 0 | I30: =W30 -> 0 | J30: =G30*1.5 -> 156.54 | K30: =I30*J30 -> 0 | L30: =X30 -> 0 | M30: =G30*2.25 -> 234.81 | N30: =L30*M30 -> 0 | V30: =SUM(O30:T30) -> 0
A31: OFICIAL ELECTRICO | E31: hr | F31: 0 | G31: 104.36 | H31: =F31*G31 -> 0 | I31: =W31 -> 0 | J31: =G31*1.5 -> 156.54 | K31: =I31*J31 -> 0 | L31: =X31 -> 0 | M31: =G31*2.25 -> 234.81 | N31: =L31*M31 -> 0 | V31: =SUM(O31:T31) -> 0
A32: ASISTENTE DE DISEÑO | E32: hr | F32: =V32 -> 0 | G32: 104.36 | H32: =F32*G32 -> 0 | I32: =W32 -> 0 | J32: =G32*1.5 -> 156.54 | K32: =I32*J32 -> 0 | L32: =X32 -> 0 | M32: =G32*2.25 -> 234.81 | N32: =L32*M32 -> 0 | V32: =SUM(O32:T32) -> 0
A33: ELECTRICISTA -B | E33: hr | F33: 0 | G33: 90.87 | H33: =F33*G33 -> 0 | I33: =W33 -> 0 | J33: =G33*1.5 -> 136.305 | K33: =I33*J33 -> 0 | L33: =X33 -> 0 | M33: =G33*2.25 -> 204.4575 | N33: =L33*M33 -> 0 | O33: 16 | P33: 16 | Q33: 16 | R33: 8 | S33: 8 | T33: 5 | V33: =SUM(O33:T33) -> 69
A34: ELECTRICISTA -A | E34: hr | F34: 0 | G34: 82.97 | H34: =F34*G34 -> 0 | I34: =W34 -> 0 | J34: =G34*1.5 -> 124.455 | K34: =I34*J34 -> 0 | L34: =X34 -> 0 | M34: =G34*2.25 -> 186.6825 | N34: =L34*M34 -> 0 | V34: =SUM(O34:T34) -> 0
A35: AUXILIAR TECNICO | E35: hr | F35: 0 | G35: 75.07 | H35: =F35*G35 -> 0 | I35: =W35 -> 0 | J35: =G35*1.5 -> 112.605 | K35: =I35*J35 -> 0 | L35: =X35 -> 0 | M35: =G35*2.25 -> 168.9075 | N35: =L35*M35 -> 0 | V35: =SUM(O35:T35) -> 0
A36: AYTE ELECTRICO - B | E36: hr | F36: 0 | G36: 75.07 | H36: =F36*G36 -> 0 | I36: =W36 -> 0 | J36: =G36*1.5 -> 112.605 | K36: =I36*J36 -> 0 | L36: =X36 -> 0 | M36: =G36*2.25 -> 168.9075 | N36: =L36*M36 -> 0 | V36: =SUM(O36:T36) -> 0
A37: AYTE DE ELECTR. -A | E37: hr | F37: 0 | G37: 63.21 | H37: =F37*G37 -> 0 | I37: =W37 -> 0 | J37: =G37*1.5 -> 94.815 | K37: =I37*J37 -> 0 | L37: =X37 -> 0 | M37: =G37*2.25 -> 142.2225 | N37: =L37*M37 -> 0 | O37: 8 | P37: 8 | Q37: 8 | R37: 8 | S37: 8 | V37: =SUM(O37:T37) -> 40
A38: AYTE GENERAL | E38: hr | F38: 0 | G38: 50.77 | H38: =F38*G38 -> 0 | I38: =W38 -> 0 | J38: =G38*1.5 -> 76.155 | K38: =I38*J38 -> 0 | L38: =X38 -> 0 | M38: =G38*2.25 -> 114.2325 | N38: =L38*M38 -> 0
A39: INGENIERO DE SUBESTACIONES | E39: hr | F39: 0 | G39: 186 | H39: =F39*G39 -> 0 | I39: =W39 -> 0 | J39: 186 | K39: =I39*J39 -> 0 | L39: =X39 -> 0 | M39: 186 | N39: =L39*M39 -> 0 | V39: =SUM(O39:T39) -> 0
A40: INGENIERO DE PRUEBAS ELECTRICAS | E40: hr | F40: 0 | G40: 186 | H40: =F40*G40 -> 0 | I40: =W40 -> 0 | J40: 186 | K40: =I40*J40 -> 0 | L40: =X40 -> 0 | M40: 186 | N40: =L40*M40 -> 0 | V40: =SUM(O40:T40) -> 0
A41: ING. ESPECIALISTA EN PROTECCIONES | E41: hr | F41: 0 | G41: 230.47 | H41: =F41*G41 -> 0 | I41: =W41 -> 0 | J41: 294 | K41: =I41*J41 -> 0 | L41: =X41 -> 0 | M41: 294 | N41: =L41*M41 -> 0 | V41: =SUM(O41:T41) -> 0
A42: SUPERINTENDENTE | E42: hr | F42: =V42 -> 0 | G42: 279.53 | H42: =F42*G42 -> 0 | I42: =W42 -> 0 | J42: 372.71 | K42: =I42*J42 -> 0 | L42: =X42 -> 0 | M42: 559.07 | N42: =L42*M42 -> 0 | V42: =SUM(O42:T42) -> 0
F43: =V43 -> 287 | G43: SUBT 2 | H43: =SUM(H21:H42) -> 7339.52 | J43: SUBT. | K43: =SUM(K22:K41) -> 3595.23 | M43: SUBT. | N43: =SUM(N22:N41) -> 0 | V43: =SUM(V21:V42) -> 287 | W43: 45
G44: SUMA M.O. | H44: =H43+K43+N43 -> 10934.75
A45: HERRAMIENTA MENOR | G45: 1 a 10% | H45: =+H44*0.06 -> 656.085
A47: VEHICULOS
A48: DESCRIPCION | E48: UNIDAD | F48: CANT. | G48: P.U. | H48: IMPORTE | J48: HR IDA | K48: HR RETORNO | L48: HR SITIO | M48: SUMA
A49: camioneta RANGER sin operador sin combustible | E49: HR | G49: 102.29 | H49: =F49*G49 -> 0 | J49: 0 | K49: 0 | L49: 0 | M49: =J49+K49+L49 -> 0
A50: camioneta NISSAN sin operador sin combustible | E50: HR | F50: 0 | G50: 68.7 | H50: =F50*G50 -> 0 | J50: 0 | K50: 0 | M50: =J50+K50+L50 -> 0
A51: camioneta TORNADO Tornado sin operador sin combustible | E51: HR | F51: 0 | G51: 54.43 | H51: =F51*G51 -> 0 | J51: 0.45 | K51: 0.45 | M51: =J51+K51+L51 -> 0.9
A52: Camion con grua sin operador sin conbustible. | E52: HR | F52: 0 | G52: 203.19 | H52: =F52*G52 -> 0 | M52: =J52+K52+L52 -> 0
A53: Camion con grua con operador con conbustible. | E53: HR | F53: 0 | G53: 407.62 | H53: =F53*G53 -> 0
A54: autobus | E54: pza | F54: 0 | G54: 5000 | H54: =F54*G54 -> 0
A55: Km. Recorrido (incluye conbustible y depresiación de Vehiculo | E55: KM | F55: 0 | G55: 2.5 | H55: =F55*G55 -> 0
G56: SUBT 4 | H56: =SUM(H49:H55) -> 0
A57: COMBUSTIBLE
A58: DESCRIPCION | E58: UNIDAD | F58: CANT. | G58: P.U. | H58: IMPORTE | J58: KM IDA | K58: KM RETORNO | L58: KM SITIO | M58: SUMA
A59: GASOLINA MAGNA | E59: LT | F59: 0 | G59: 19 | H59: =F59*G59 -> 0 | J59: 22 | K59: 22 | M59: =J59+K59+L59 -> 44
A60: DIESEL | E60: LT | F60: =M60/4.5 -> 0 | G60: 0 | H60: =F60*G60 -> 0 | M60: =J60+K60+L60 -> 0
G61: SUBT 5 | H61: =SUM(H59:H60) -> 0
A62: CASETAS
A63: DESCRIPCION | E63: UNIDAD | F63: CANT. | G63: P.U. | H63: IMPORTE
A64: camioneta pick up | E64: CASETA | F64: 0 | G64: 100 | H64: =F64*G64 -> 0
A65: camioneta pick up | E65: CASETA | F65: 0 | G65: 65 | H65: =F65*G65 -> 0
G66: SUBT 6 | H66: =SUM(H64:H65) -> 0
A67: VIATICOS
A68: ALIMENTOS
A69: DESCRIPCION | E69: UNIDAD | F69: CANT. | G69: P.U. | H69: IMPORTE
A70: CONSUMO DE ALIMENTOS | E70: Pza | F70: 0 | G70: 450 | H70: =F70*G70 -> 0
H71: =SUM(H70) -> 0
A72: HOSPEDAJE
A73: DESCRIPCION | E73: UNIDAD | F73: CANT. | G73: P.U. | H73: IMPORTE
A74: HOTEL | E74: NOCHES | F74: 0 | G74: 900 | H74: =F74*G74 -> 0
G75: SUBT 8 | H75: =SUM(H74) -> 0
G76: SUMA: | H76: =H56+H61+H66+H71+H75+H45+H44+H17 -> 11590.835
A77: EQUIPO DE PRUEBA
A78: DESCRIPCION | E78: UNIDAD | F78: CANT. | G78: P.U. | H78: IMPORTE | I78: TR | K78: S.E
A79: Megger | E79: jr | F79: 0.5 | G79: 2200 | H79: =(F79*G79) -> 1100
A80: TTR | E80: jr | F80: 0.5 | G80: 2000 | H80: =(F80*G80) -> 1000
A81: Factor de Potencia de 2.5 KV | E81: jr | F81: 0 | G81: 7000 | H81: =(F81*G81) -> 0
A82: Factor de Potencia de 10.5 KV | E82: jr | F82: 0.3 | G82: 15200 | H82: =(F82*G82) -> 4560
A83: Ducter | E83: jr | F83: 0.3 | G83: 2200 | H83: =(F83*G83) -> 660
A84: resistencia óhmica | E84: jr | F84: 0.3 | G84: 2000 | H84: =(F84*G84) -> 600
A85: hipot de 80 KV vcd | E85: jr | G85: 2500 | H85: =(F85*G85) -> 0
A86: Rigidez dieléctrica al aceite 60 kv | E86: jr | G86: 1600 | H86: =(F86*G86) -> 0
A87: Terrómetro | E87: jr | G87: 1100 | H87: =(F87*G87) -> 0
A88: Analizador de tiempos de interruptor | E88: jr | G88: 2700 | H88: =(F88*G88) -> 0
A89: Fuente de corriente para calibrador de relevadores | E89: jr | F89: 0.3 | G89: 2500 | H89: =(F89*G89) -> 750
A90: Probador de relevador de Protecciones | E90: jr | G90: 13373 | H90: =(F90*G90) -> 0
A91: Fuente trifasica de voltaje | E91: jr | G91: 800 | H91: =(F91*G91) -> 0
A92: Analizador de energía trifásica | E92: jr | G92: 1900 | H92: =(F92*G92) -> 0
A93: Medidor de presión y llenado de gas SF6 | E93: jr | G93: 2000 | H93: =(F93*G93) -> 0
A94: Medidor de secuencia de fases | E94: jr | G94: 200 | H94: =(F94*G94) -> 0
A95: Unidad de Pba y config. Para relevadores de Int. ABB | E95: jr | G95: 1100 | H95: =(F95*G95) -> 0
A96: Máquina centrifugadora de aceite | E96: jr | G96: 2200 | H96: =(F96*G96) -> 0
A97: Luxómetro | E97: jr | G97: 1420 | H97: =(F97*G97) -> 0
A98: Generador de Luz con combustible | E98: jr | F98: 1 | G98: 383.5 | H98: =(F98*G98) -> 383.5
G99: SUBT 9 | H99: =SUM(H79:H98) -> 9053.5
E101: 0 | H101: =+E101 -> 0 | I101: % DE IMP. | J101: INDIRECTO DISPONIBLE
G102: COSTO DIRECTO | H102: =H76+H99 -> 20644.335
F103: Indirectos | G103: 0.1 | H103: =H102*G103 -> 2064.4335 | I103: =(M109*100)/H103 -> 1.5594579 | J103: =H103-M109 -> 2032.2395
F104: Subtotal 1 | H104: =H102+H103 -> 22708.768
...

Sheet TIERRAS FISICA MAT.
A1: I M M E E S. A. D E C. V.
A2: A N A L I S I S D E P R E C I O U N I T A R I O
A3: COTIZACION:
A4: FECHA:
A5: PARTIDA 1
A7: MATERIALES.
A8: DESCRIPCION | E8: UNIDAD | F8: CANT. | G8: P.U. | H8: IMPORTE
A9: Solvente Dielectrico | E9: Pza | F9: 1 | G9: 1000 | H9: =G9*F9 -> 1000 | J9: HR NORMAL
A10: Trapo | E10: Pza | F10: 10 | G10: 2346.71 | H10: =G10*F10 -> 23467.1 | J10: HR DOBLE
A11: Cepillo de alambre | E11: Pza | F11: 1 | H11: =G11*F11 -> 0 | J11: HR TRIPLE
A12: Fibra scoch | E12: Pza | F12: 1 | H12: =G12*F12 -> 0
E14: Pza | F14: 1 | H14: =G14*F14 -> 0
E15: Pza | F15: 1 | H15: =G15*F15 -> 0
E16: Pza | F16: 1 | H16: =G16*F16 -> 0
G17: SUBT 1 | H17: =SUM(H9:H16) -> 24467.1
A19: MANO DE OBRA SIN INDIRECTOS | O19: HORARIOS DE TRABAJO | V19: HORAS RESULTANTES
A20: PERSONAL. | E20: UNIDAD | F20: CANT. | G20: P.U. | H20: IMPORTE | I20: CANT. | J20: Hr. Extra | K20: IMPORTE | L20: CANT. | M20: Dom, ó Fest. | N20: IMPORTE | O20: L | P20: M | Q20: MI | R20: J | S20: V | T20: S | U20: D | V20: N | W20: D | X20: T
A21: COORDINADOR DE OPERACIONES | E21: hr | F21: =V21 -> 0 | G21: 185.69 | H21: =F21*G21 -> 0 | I21: =W21 -> 0 | J21: =G21*1.5 -> 278.535 | K21: =I21*J21 -> 0 | L21: =X21 -> 0 | M21: =G21*2.25 -> 417.8025 | N21: =L21*M21 -> 0 | V21: =SUM(O21:T21) -> 0
A22: INGENIERIA Y SOPORTE TEC. | E22: hr | F22: =V22 -> 0 | G22: 177.79 | H22: =F22*G22 -> 0 | I22: =W22 -> 0 | J22: =G22*1.5 -> 266.685 | K22: =I22*J22 -> 0 | L22: =X22 -> 0 | M22: =G22*2.25 -> 400.0275 | N22: =L22*M22 -> 0 | V22: =SUM(O22:T22) -> 0
A23: SUPERVISOR DE SEGURIDAD CERTIFICADO | E23: hr | F23: =V23 -> 0 | G23: 185.69 | H23: =F23*G23 -> 0 | I23: =W23 -> 0 | J23: =G23*1.5 -> 278.535 | K23: =I23*J23 -> 0 | L23: =X23 -> 0 | M23: =G23*2.25 -> 417.8025 | N23: =L23*M23 -> 0 | V23: =SUM(O23:T23) -> 0
A24: SUPERVISOR ELECTRICO | E24: hr | F24: 0 | G24: 148.16 | H24: =F24*G24 -> 0 | I24: =W24 -> 0 | J24: =G24*1.5 -> 222.24 | K24: =I24*J24 -> 0 | L24: =X24 -> 0 | M24: =G24*2.25 -> 333.36 | N24: =L24*M24 -> 0 | O24: 8 | P24: 8 | Q24: 8 | R24: 8 | S24: 8 | V24: =SUM(O24:T24) -> 40
A25: TECNICO DE PRUEBAS ELECTRICAS | E25: hr | F25: 0 | G25: 136.31 | H25: =F25*G25 -> 0 | I25: =W25 -> 0 | J25: =G25*1.5 -> 204.465 | K25: =I25*J25 -> 0 | L25: =X25 -> 0 | M25: =G25*2.25 -> 306.6975 | N25: =L25*M25 -> 0 | V25: =SUM(O25:T25) -> 0
A26: CABO OBRA ELECTRICA | E26: hr | F26: =V26 -> 0 | G26: 136.31 | H26: =F26*G26 -> 0 | I26: =W26 -> 0 | J26: =G26*1.5 -> 204.465 | K26: =I26*J26 -> 0 | L26: =X26 -> 0 | M26: =G26*2.25 -> 306.6975 | N26: =L26*M26 -> 0 | V26: =SUM(O26:T26) -> 0
A27: LINIERO | E27: hr | F27: 0 | G27: 126.43 | H27: =F27*G27 -> 0 | I27: =W27 -> 0 | J27: =G27*1.5 -> 189.645 | K27: =I27*J27 -> 0 | L27: =X27 -> 0 | M27: =G27*2.25 -> 284.4675 | N27: =L27*M27 -> 0 | O27: 16 | P27: 16 | Q27: 16 | R27: 8 | S27: 8 | T27: 5 | V27: =SUM(O27:T27) -> 69
A28: LINIERO | E28: hr | F28: 0 | G28: 126.43 | H28: =F28*G28 -> 0 | I28: =W28 -> 0 | J28: =G28*1.5 -> 189.645 | K28: =I28*J28 -> 0 | L28: =X28 -> 0 | M28: =G28*2.25 -> 284.4675 | N28: =L28*M28 -> 0 | O28: 16 | P28: 16 | Q28: 16 | R28: 8 | S28: 8 | T28: 5 | V28: =SUM(O28:T28) -> 69
A29: ESPECIALISTA ELECTRICO | E29: hr | F29: 0 | G29: 110.63 | H29: =F29*G29 -> 0 | I29: =W29 -> 0 | J29: =G29*1.5 -> 165.945 | K29: =I29*J29 -> 0 | L29: =X29 -> 0 | M29: =G29*2.25 -> 248.9175 | N29: =L29*M29 -> 0 | V29: =SUM(O29:T29) -> 0
A30: TECNICO EN INSTRUMENTACION | E30: hr | F30: =V30 -> 0 | G30: 104.36 | H30: =F30*G30 -> 0 | I30: =W30 -> 0 | J30: =G30*1.5 -> 156.54 | K30: =I30*J30 -> 0 | L30: =X30 -> 0 | M30: =G30*2.25 -> 234.81 | N30: =L30*M30 -> 0 | V30: =SUM(O30:T30) -> 0
A31: OFICIAL ELECTRICO | E31: hr | F31: 0 | G31: 104.36 | H31: =F31*G31 -> 0 | I31: =W31 -> 0 | J31: =G31*1.5 -> 156.54 | K31: =I31*J31 -> 0 | L31: =X31 -> 0 | M31: =G31*2.25 -> 234.81 | N31: =L31*M31 -> 0 | V31: =SUM(O31:T31) -> 0
A32: ASISTENTE DE DISEÑO | E32: hr | F32: 0 | G32: 104.36 | H32: =F32*G32 -> 0 | I32: =W32 -> 0 | J32: =G32*1.5 -> 156.54 | K32: =I32*J32 -> 0 | L32: =X32 -> 0 | M32: =G32*2.25 -> 234.81 | N32: =L32*M32 -> 0 | V32: =SUM(O32:T32) -> 0
A33: ELECTRICISTA -B | E33: hr | F33: 8 | G33: 90.87 | H33: =F33*G33 -> 726.96 | I33: =W33 -> 0 | J33: =G33*1.5 -> 136.305 | K33: =I33*J33 -> 0 | L33: =X33 -> 0 | M33: =G33*2.25 -> 204.4575 | N33: =L33*M33 -> 0 | O33: 16 | P33: 16 | Q33: 16 | R33: 8 | S33: 8 | T33: 5 | V33: =SUM(O33:T33) -> 69
A34: ELECTRICISTA -A | E34: hr | F34: =V34 -> 0 | G34: 82.97 | H34: =F34*G34 -> 0 | I34: =W34 -> 0 | J34: =G34*1.5 -> 124.455 | K34: =I34*J34 -> 0 | L34: =X34 -> 0 | M34: =G34*2.25 -> 186.6825 | N34: =L34*M34 -> 0 | V34: =SUM(O34:T34) -> 0
A35: AUXILIAR TECNICO | E35: hr | F35: 4 | G35: 75.07 | H35: =F35*G35 -> 300.28 | I35: =W35 -> 0 | J35: =G35*1.5 -> 112.605 | K35: =I35*J35 -> 0 | L35: =X35 -> 0 | M35: =G35*2.25 -> 168.9075 | N35: =L35*M35 -> 0 | V35: =SUM(O35:T35) -> 0
A36: AYTE ELECTRICO - B | E36: hr | F36: 0 | G36: 75.07 | H36: =F36*G36 -> 0 | I36: =W36 -> 0 | J36: =G36*1.5 -> 112.605 | K36: =I36*J36 -> 0 | L36: =X36 -> 0 | M36: =G36*2.25 -> 168.9075 | N36: =L36*M36 -> 0 | V36: =SUM(O36:T36) -> 0
A37: AYTE DE ELECTR. -A | E37: hr | F37: 0 | G37: 63.21 | H37: =F37*G37 -> 0 | I37: =W37 -> 0 | J37: =G37*1.5 -> 94.815 | K37: =I37*J37 -> 0 | L37: =X37 -> 0 | M37: =G37*2.25 -> 142.2225 | N37: =L37*M37 -> 0 | O37: 8 | P37: 8 | Q37: 8 | R37: 8 | S37: 8 | V37: =SUM(O37:T37) -> 40
A38: AYTE GENERAL | E38: hr | F38: =V38 -> 0 | G38: 50.77 | H38: =F38*G38 -> 0 | I38: =W38 -> 0 | J38: =G38*1.5 -> 76.155 | K38: =I38*J38 -> 0 | L38: =X38 -> 0 | M38: =G38*2.25 -> 114.2325 | N38: =L38*M38 -> 0
A39: INGENIERO DE SUBESTACIONES | E39: hr | F39: =V39 -> 0 | G39: 186 | H39: =F39*G39 -> 0 | I39: =W39 -> 0 | J39: 186 | K39: =I39*J39 -> 0 | L39: =X39 -> 0 | M39: 186 | N39: =L39*M39 -> 0 | V39: =SUM(O39:T39) -> 0
A40: INGENIERO DE PRUEBAS ELECTRICAS | E40: hr | F40: =V40 -> 0 | G40: 186 | H40: =F40*G40 -> 0 | I40: =W40 -> 0 | J40: 186 | K40: =I40*J40 -> 0 | L40: =X40 -> 0 | M40: 186 | N40: =L40*M40 -> 0 | V40: =SUM(O40:T40) -> 0
A41: ING. ESPECIALISTA EN PROTECCIONES | E41: hr | F41: =V41 -> 0 | G41: 230.47 | H41: =F41*G41 -> 0 | I41: =W41 -> 0 | J41: 294 | K41: =I41*J41 -> 0 | L41: =X41 -> 0 | M41: 294 | N41: =L41*M41 -> 0 | V41: =SUM(O41:T41) -> 0
A42: SUPERINTENDENTE | E42: hr | F42: =V42 -> 0 | G42: 279.53 | H42: =F42*G42 -> 0 | I42: =W42 -> 0 | J42: 372.71 | K42: =I42*J42 -> 0 | L42: =X42 -> 0 | M42: 559.07 | N42: =L42*M42 -> 0 | V42: =SUM(O42:T42) -> 0
F43: =V43 -> 287 | G43: SUBT 2 | H43: =SUM(H21:H42) -> 1027.24 | J43: SUBT. | K43: =SUM(K22:K41) -> 0 | M43: SUBT. | N43: =SUM(N22:N41) -> 0 | V43: =SUM(V21:V42) -> 287 | W43: 45
G44: SUMA M.O. | H44: =H43+K43+N43 -> 1027.24
A45: HERRAMIENTA MENOR | G45: 1 a 10% | H45: =+H44*0.06 -> 61.6344
A47: VEHICULOS
A48: DESCRIPCION | E48: UNIDAD | F48: CANT. | G48: P.U. | H48: IMPORTE | J48: HR IDA | K48: HR RETORNO | L48: HR SITIO | M48: SUMA
A49: camioneta RANGER sin operador sin combustible | E49: HR | F49: 0 | G49: 102.29 | H49: =F49*G49 -> 0 | J49: 0 | K49: 0 | L49: 0 | M49: =J49+K49+L49 -> 0
A50: camioneta NISSAN sin operador sin combustible | E50: HR | F50: 0 | G50: 68.7 | H50: =F50*G50 -> 0 | J50: 0 | K50: 0 | M50: =J50+K50+L50 -> 0
A51: camioneta TORNADO Tornado sin operador sin combustible | E51: HR | F51: 8 | G51: 54.43 | H51: =F51*G51 -> 435.44 | J51: 0.45 | K51: 0.45 | M51: =J51+K51+L51 -> 0.9
A52: Camion con grua sin operador sin conbustible. | E52: HR | F52: =M52 -> 0 | G52: 203.19 | H52: =F52*G52 -> 0 | M52: =J52+K52+L52 -> 0
A53: Camion con grua con operador con conbustible. | E53: HR | G53: 407.62 | H53: =F53*G53 -> 0
A54: autobus | E54: pza | G54: 5000 | H54: =F54*G54 -> 0
A55: Km. Recorrido (incluye conbustible y depresiación de Vehiculo | E55: KM | G55: 2.5 | H55: =F55*G55 -> 0
G56: SUBT 4 | H56: =SUM(H49:H55) -> 435.44
A57: COMBUSTIBLE
A58: DESCRIPCION | E58: UNIDAD | F58: CANT. | G58: P.U. | H58: IMPORTE | J58: KM IDA | K58: KM RETORNO | L58: KM SITIO | M58: SUMA
A59: GASOLINA MAGNA | E59: LT | F59: 30 | G59: 16.48 | H59: =F59*G59 -> 494.4 | J59: 22 | K59: 22 | M59: =J59+K59+L59 -> 44
A60: DIESEL | E60: LT | F60: =M60/4.5 -> 0 | G60: 0 | H60: =F60*G60 -> 0 | M60: =J60+K60+L60 -> 0
G61: SUBT 5 | H61: =SUM(H59:H60) -> 494.4
A62: CASETAS
A63: DESCRIPCION | E63: UNIDAD | F63: CANT. | G63: P.U. | H63: IMPORTE
A64: camioneta pick up | E64: CASETA | F64: 2 | G64: 180 | H64: =F64*G64 -> 360
A65: camioneta pick up | E65: CASETA | G65: 65 | H65: =F65*G65 -> 0
G66: SUBT 6 | H66: =SUM(H64:H65) -> 360
A67: VIATICOS
A68: ALIMENTOS
A69: DESCRIPCION | E69: UNIDAD | F69: CANT. | G69: P.U. | H69: IMPORTE
A70: CONSUMO DE ALIMENTOS | E70: Pza | F70: 0.5 | G70: 450 | H70: =F70*G70 -> 225
H71: =SUM(H70) -> 225
A72: HOSPEDAJE
A73: DESCRIPCION | E73: UNIDAD | F73: CANT. | G73: P.U. | H73: IMPORTE
A74: HOTEL | E74: NOCHES | F74: 0 | G74: 900 | H74: =F74*G74 -> 0
G75: SUBT 8 | H75: =SUM(H74) -> 0
G76: SUMA: | H76: =H56+H61+H66+H71+H75+H45+H44+H17 -> 27070.814
A77: EQUIPO DE PRUEBA
A78: DESCRIPCION | E78: UNIDAD | F78: CANT. | G78: P.U. | H78: IMPORTE | I78: TR | K78: S.E
A79: Megger | E79: jr | G79: 2200 | H79: =(F79*G79) -> 0
A80: TTR | E80: jr | G80: 2000 | H80: =(F80*G80) -> 0
A81: Factor de Potencia de 2.5 KV | E81: jr | G81: 7000 | H81: =(F81*G81) -> 0
A82: Factor de Potencia de 10.5 KV | E82: jr | G82: 15200 | H82: =(F82*G82) -> 0
A83: Ducter | E83: jr | G83: 2200 | H83: =(F83*G83) -> 0
A84: resistencia óhmica | E84: jr | G84: 2000 | H84: =(F84*G84) -> 0
A85: hipot de 80 KV vcd | E85: jr | G85: 2500 | H85: =(F85*G85) -> 0
A86: Rigidez dieléctrica al aceite 60 kv | E86: jr | G86: 1600 | H86: =(F86*G86) -> 0
A87: Terrómetro | E87: jr | G87: 1100 | H87: =(F87*G87) -> 0
A88: Analizador de tiempos de interruptor | E88: jr | G88: 2700 | H88: =(F88*G88) -> 0
A89: Fuente de corriente para calibrador de relevadores | E89: jr | G89: 2500 | H89: =(F89*G89) -> 0
A90: Probador de relevador de Protecciones | E90: jr | G90: 13373 | H90: =(F90*G90) -> 0
... A98: Generador de Luz con combustible | E98: jr | G98: 383.5 | H98: =(F98*G98) -> 0
G99: SUBT 9 | H99: =SUM(H79:H98) -> 0
E101: 0 | H101: =+E101 -> 0 | I101: % DE IMP. | J101: INDIRECTO DISPONIBLE
G102: COSTO DIRECTO | H102: =H76+H99 -> 27070.814
F103: Indirectos | G103: 0.1 | H103: =H102*G103 -> 2707.0814 | I103: =(M109*100)/H103 -> -269.01746 | J103: =H103-M109 -> 9989.6033
F104: Subtotal 1 | H104: =H102+H103 -> 29777.896
K105: BASE IMPUESTO
F106: Financ. | G106: 0.05 | H106: =H104*G106 -> 1488.8948 | I106: =H106+[1]Part.2!H84+[1]Part.3!H84+[1]Part.4!H84+[1]part.5!H84+[1]traslado!H66 -> 1699.1068 | J106: COMPRAS | K106: =+H17 -> 24467.1
F107: Subtotal 2 | H107: =H104+H106 -> 31266.791 | J107: M.O | K107: =H44 -> 1027.24
F108: Utilidad | G108: 0.2 | H108: =H107*G108 -> 6253.3581 | J108: GASTOS FACTURADOS | K108: =H76-H56 -> 26635.374 | M108: IMP. 32%
F109: Importe | H109: =H107+H108 -> 37520.149 | J109: SUMA | K109: =SUM(K106:K108) -> 52129.714 | L109: =H109-H108-(H103*0.7)-K109 -> -22757.881 | M109: =0.32*L109 -> -7282.5218
I110: FACTOR | J110: =H109/H102 -> 1.386

Sheet TIERRAS FISICAS MO
A1: I M M E E S. A. D E C. V.
A2: A N A L I S I S D E P R E C I O U N I T A R I O
A3: COTIZACION:
A4: FECHA:
A5: PARTIDA 1
A7: MATERIALES.
A8: DESCRIPCION | E8: UNIDAD | F8: CANT. | G8: P.U. | H8: IMPORTE
E9: Pza | F9: 1 | G9: 0 | H9: =G9 -> 0 | J9: HR NORMAL
E10: Pza | J10: HR DOBLE
E11: Pza | J11: HR TRIPLE
E12: Pza
E13: Pza
E14: Pza
E15: Pza
E16: Pza | I16: =H16*1.455 -> 0
G17: SUBT 1 | H17: =SUM(H9:H16) -> 0
A19: MANO DE OBRA SIN INDIRECTOS | O19: HORARIOS DE TRABAJO | V19: HORAS RESULTANTES
A20: PERSONAL. | E20: UNIDAD | F20: CANT. | G20: P.U. | H20: IMPORTE | I20: CANT. | J20: Hr. Extra | K20: IMPORTE | L20: CANT. | M20: Dom, ó Fest. | N20: IMPORTE | O20: L | P20: M | Q20: MI | R20: J | S20: V | T20: S | U20: D | V20: N | W20: D | X20: T
A21: COORDINADOR DE OPERACIONES | E21: hr | F21: =V21 -> 0 | G21: 185.69 | H21: =F21*G21 -> 0 | I21: =W21 -> 0 | J21: =G21*1.5 -> 278.535 | K21: =I21*J21 -> 0 | L21: =X21 -> 0 | M21: =G21*2.25 -> 417.8025 | N21: =L21*M21 -> 0 | V21: =SUM(O21:T21) -> 0
A22: INGENIERIA Y SOPORTE TEC. | E22: hr | F22: =V22 -> 0 | G22: 177.79 | H22: =F22*G22 -> 0 | I22: =W22 -> 0 | J22: =G22*1.5 -> 266.685 | K22: =I22*J22 -> 0 | L22: =X22 -> 0 | M22: =G22*2.25 -> 400.0275 | N22: =L22*M22 -> 0 | V22: =SUM(O22:T22) -> 0
A23: SUPERVISOR DE SEGURIDAD CERTIFICADO | E23: hr | F23: =V23 -> 0 | G23: 185.69 | H23: =F23*G23 -> 0 | I23: =W23 -> 0 | J23: =G23*1.5 -> 278.535 | K23: =I23*J23 -> 0 | L23: =X23 -> 0 | M23: =G23*2.25 -> 417.8025 | N23: =L23*M23 -> 0 | V23: =SUM(O23:T23) -> 0
A24: SUPERVISOR ELECTRICO | E24: hr | F24: 4 | G24: 237 | H24: =F24*G24 -> 948 | I24: =W24 -> 0 | J24: =G24*1.5 -> 355.5 | K24: =I24*J24 -> 0 | L24: =X24 -> 0 | M24: =G24*2.25 -> 533.25 | N24: =L24*M24 -> 0 | O24: 8 | P24: 8 | Q24: 8 | R24: 8 | S24: 8 | V24: =SUM(O24:T24) -> 40
A25: TECNICO DE PRUEBAS ELECTRICAS | E25: hr | F25: 16 | G25: 209.25 | H25: =F25*G25 -> 3348 | I25: 6 | J25: =G25*1.5 -> 313.875 | K25: =I25*J25 -> 1883.25 | L25: =X25 -> 0 | M25: =G25*2.25 -> 470.8125 | N25: =L25*M25 -> 0 | V25: =SUM(O25:T25) -> 0
A26: CABO OBRA ELECTRICA | E26: hr | F26: =V26 -> 0 | G26: 136.31 | H26: =F26*G26 -> 0 | I26: =W26 -> 0 | J26: =G26*1.5 -> 204.465 | K26: =I26*J26 -> 0 | L26: =X26 -> 0 | M26: =G26*2.25 -> 306.6975 | N26: =L26*M26 -> 0 | V26: =SUM(O26:T26) -> 0
A27: LINIERO | E27: hr | F27: 16 | G27: 190.22 | H27: =F27*G27 -> 3043.52 | I27: 6 | J27: =G27*1.5 -> 285.33 | K27: =I27*J27 -> 1711.98 | L27: =X27 -> 0 | M27: =G27*2.25 -> 427.995 | N27: =L27*M27 -> 0 | O27: 16 | P27: 16 | Q27: 16 | R27: 8 | S27: 8 | T27: 5 | V27: =SUM(O27:T27) -> 69
A28: LINIERO | E28: hr | F28: 0 | G28: 126.43 | H28: =F28*G28 -> 0 | I28: =W28 -> 0 | J28: =G28*1.5 -> 189.645 | K28: =I28*J28 -> 0 | L28: =X28 -> 0 | M28: =G28*2.25 -> 284.4675 | N28: =L28*M28 -> 0 | O28: 16 | P28: 16 | Q28: 16 | R28: 8 | S28: 8 | T28: 5 | V28: =SUM(O28:T28) -> 69
A29: ESPECIALISTA ELECTRICO | E29: hr | F29: 0 | G29: 110.63 | H29: =F29*G29 -> 0 | I29: =W29 -> 0 | J29: =G29*1.5 -> 165.945 | K29: =I29*J29 -> 0 | L29: =X29 -> 0 | M29: =G29*2.25 -> 248.9175 | N29: =L29*M29 -> 0 | V29: =SUM(O29:T29) -> 0
A30: TECNICO EN INSTRUMENTACION | E30: hr | F30: =V30 -> 0 | G30: 104.36 | H30: =F30*G30 -> 0 | I30: =W30 -> 0 | J30: =G30*1.5 -> 156.54 | K30: =I30*J30 -> 0 | L30: =X30 -> 0 | M30: =G30*2.25 -> 234.81 | N30: =L30*M30 -> 0 | V30: =SUM(O30:T30) -> 0
A31: OFICIAL ELECTRICO | E31: hr | F31: 0 | G31: 104.36 | H31: =F31*G31 -> 0 | I31: =W31 -> 0 | J31: =G31*1.5 -> 156.54 | K31: =I31*J31 -> 0 | L31: =X31 -> 0 | M31: =G31*2.25 -> 234.81 | N31: =L31*M31 -> 0 | V31: =SUM(O31:T31) -> 0
A32: ASISTENTE DE DISEÑO | E32: hr | F32: =V32 -> 0 | G32: 104.36 | H32: =F32*G32 -> 0 | I32: =W32 -> 0 | J32: =G32*1.5 -> 156.54 | K32: =I32*J32 -> 0 | L32: =X32 -> 0 | M32: =G32*2.25 -> 234.81 | N32: =L32*M32 -> 0 | V32: =SUM(O32:T32) -> 0
A33: ELECTRICISTA -B | E33: hr | F33: 0 | G33: 90.87 | H33: =F33*G33 -> 0 | I33: =W33 -> 0 | J33: =G33*1.5 -> 136.305 | K33: =I33*J33 -> 0 | L33: =X33 -> 0 | M33: =G33*2.25 -> 204.4575 | N33: =L33*M33 -> 0 | O33: 16 | P33: 16 | Q33: 16 | R33: 8 | S33: 8 | T33: 5 | V33: =SUM(O33:T33) -> 69
A34: ELECTRICISTA -A | E34: hr | F34: 0 | G34: 82.97 | H34: =F34*G34 -> 0 | I34: =W34 -> 0 | J34: =G34*1.5 -> 124.455 | K34: =I34*J34 -> 0 | L34: =X34 -> 0 | M34: =G34*2.25 -> 186.6825 | N34: =L34*M34 -> 0 | V34: =SUM(O34:T34) -> 0
A35: AUXILIAR TECNICO | E35: hr | F35: 0 | G35: 75.07 | H35: =F35*G35 -> 0 | I35: =W35 -> 0 | J35: =G35*1.5 -> 112.605 | K35: =I35*J35 -> 0 | L35: =X35 -> 0 | M35: =G35*2.25 -> 168.9075 | N35: =L35*M35 -> 0 | V35: =SUM(O35:T35) -> 0
A36: AYTE ELECTRICO - B | E36: hr | F36: 0 | G36: 75.07 | H36: =F36*G36 -> 0 | I36: =W36 -> 0 | J36: =G36*1.5 -> 112.605 | K36: =I36*J36 -> 0 | L36: =X36 -> 0 | M36: =G36*2.25 -> 168.9075 | N36: =L36*M36 -> 0 | V36: =SUM(O36:T36) -> 0
A37: AYTE DE ELECTR. -A | E37: hr | F37: 0 | G37: 63.21 | H37: =F37*G37 -> 0 | I37: =W37 -> 0 | J37: =G37*1.5 -> 94.815 | K37: =I37*J37 -> 0 | L37: =X37 -> 0 | M37: =G37*2.25 -> 142.2225 | N37: =L37*M37 -> 0 | O37: 8 | P37: 8 | Q37: 8 | R37: 8 | S37: 8 | V37: =SUM(O37:T37) -> 40
A38: AYTE GENERAL | E38: hr | F38: 0 | G38: 50.77 | H38: =F38*G38 -> 0 | I38: =W38 -> 0 | J38: =G38*1.5 -> 76.155 | K38: =I38*J38 -> 0 | L38: =X38 -> 0 | M38: =G38*2.25 -> 114.2325 | N38: =L38*M38 -> 0
A39: INGENIERO DE SUBESTACIONES | E39: hr | F39: 0 | G39: 186 | H39: =F39*G39 -> 0 | I39: =W39 -> 0 | J39: 186 | K39: =I39*J39 -> 0 | L39: =X39 -> 0 | M39: 186 | N39: =L39*M39 -> 0 | V39: =SUM(O39:T39) -> 0
A40: INGENIERO DE PRUEBAS ELECTRICAS | E40: hr | F40: 0 | G40: 186 | H40: =F40*G40 -> 0 | I40: =W40 -> 0 | J40: 186 | K40: =I40*J40 -> 0 | L40: =X40 -> 0 | M40: 186 | N40: =L40*M40 -> 0 | V40: =SUM(O40:T40) -> 0
A41: ING. ESPECIALISTA EN PROTECCIONES | E41: hr | F41: 0 | G41: 230.47 | H41: =F41*G41 -> 0 | I41: =W41 -> 0 | J41: 294 | K41: =I41*J41 -> 0 | L41: =X41 -> 0 | M41: 294 | N41: =L41*M41 -> 0 | V41: =SUM(O41:T41) -> 0
A42: SUPERINTENDENTE | E42: hr | F42: =V42 -> 0 | G42: 279.53 | H42: =F42*G42 -> 0 | I42: =W42 -> 0 | J42: 372.71 | K42: =I42*J42 -> 0 | L42: =X42 -> 0 | M42: 559.07 | N42: =L42*M42 -> 0 | V42: =SUM(O42:T42) -> 0
F43: =V43 -> 287 | G43: SUBT 2 | H43: =SUM(H21:H42) -> 7339.52 | J43: SUBT. | K43: =SUM(K22:K41) -> 3595.23 | M43: SUBT. | N43: =SUM(N22:N41) -> 0 | V43: =SUM(V21:V42) -> 287 | W43: 45
G44: SUMA M.O. | H44: =H43+K43+N43 -> 10934.75
A45: HERRAMIENTA MENOR | G45: 1 a 10% | H45: =+H44*0.06 -> 656.085
A47: VEHICULOS
A48: DESCRIPCION | E48: UNIDAD | F48: CANT. | G48: P.U. | H48: IMPORTE | J48: HR IDA | K48: HR RETORNO | L48: HR SITIO | M48: SUMA
A49: camioneta RANGER sin operador sin combustible | E49: HR | G49: 102.29 | H49: =F49*G49 -> 0 | J49: 0 | K49: 0 | L49: 0 | M49: =J49+K49+L49 -> 0
A50: camioneta NISSAN sin operador sin combustible | E50: HR | F50: 0 | G50: 68.7 | H50: =F50*G50 -> 0 | J50: 0 | K50: 0 | M50: =J50+K50+L50 -> 0
A51: camioneta TORNADO Tornado sin operador sin combustible | E51: HR | F51: 0 | G51: 54.43 | H51: =F51*G51 -> 0 | J51: 0.45 | K51: 0.45 | M51: =J51+K51+L51 -> 0.9
A52: Camion con grua sin operador sin conbustible. | E52: HR | F52: 0 | G52: 203.19 | H52: =F52*G52 -> 0 | M52: =J52+K52+L52 -> 0
A53: Camion con grua con operador con conbustible. | E53: HR | F53: 0 | G53: 407.62 | H53: =F53*G53 -> 0
A54: autobus | E54: pza | F54: 0 | G54: 5000 | H54: =F54*G54 -> 0
A55: Km. Recorrido (incluye conbustible y depresiación de Vehiculo | E55: KM | F55: 0 | G55: 2.5 | H55: =F55*G55 -> 0
G56: SUBT 4 | H56: =SUM(H49:H55) -> 0
A57: COMBUSTIBLE
A58: DESCRIPCION | E58: UNIDAD | F58: CANT. | G58: P.U. | H58: IMPORTE | J58: KM IDA | K58: KM RETORNO | L58: KM SITIO | M58: SUMA
A59: GASOLINA MAGNA | E59: LT | F59: 0 | G59: 19 | H59: =F59*G59 -> 0 | J59: 22 | K59: 22 | M59: =J59+K59+L59 -> 44
A60: DIESEL | E60: LT | F60: =M60/4.5 -> 0 | G60: 0 | H60: =F60*G60 -> 0 | M60: =J60+K60+L60 -> 0
G61: SUBT 5 | H61: =SUM(H59:H60) -> 0
A62: CASETAS
A63: DESCRIPCION | E63: UNIDAD | F63: CANT. | G63: P.U. | H63: IMPORTE
A64: camioneta pick up | E64: CASETA | F64: 0 | G64: 100 | H64: =F64*G64 -> 0
A65: camioneta pick up | E65: CASETA | F65: 0 | G65: 65 | H65: =F65*G65 -> 0
G66: SUBT 6 | H66: =SUM(H64:H65) -> 0
A67: VIATICOS
A68: ALIMENTOS
A69: DESCRIPCION | E69: UNIDAD | F69: CANT. | G69: P.U. | H69: IMPORTE
A70: CONSUMO DE ALIMENTOS | E70: Pza | F70: 0 | G70: 450 | H70: =F70*G70 -> 0
H71: =SUM(H70) -> 0
A72: HOSPEDAJE
A73: DESCRIPCION | E73: UNIDAD | F73: CANT. | G73: P.U. | H73: IMPORTE
A74: HOTEL | E74: NOCHES | F74: 0 | G74: 900 | H74: =F74*G74 -> 0
G75: SUBT 8 | H75: =SUM(H74) -> 0
G76: SUMA: | H76: =H56+H61+H66+H71+H75+H45+H44+H17 -> 11590.835
A77: EQUIPO DE PRUEBA
A78: DESCRIPCION | E78: UNIDAD | F78: CANT. | G78: P.U. | H78: IMPORTE | I78: TR | K78: S.E
A79: Megger | E79: jr | F79: 0.5 | G79: 2200 | H79: =(F79*G79) -> 1100
A80: TTR | E80: jr | F80: 0.5 | G80: 2000 | H80: =(F80*G80) -> 1000
A81: Factor de Potencia de 2.5 KV | E81: jr | F81: 0 | G81: 7000 | H81: =(F81*G81) -> 0
A82: Factor de Potencia de 10.5 KV | E82: jr | F82: 0.3 | G82: 15200 | H82: =(F82*G82) -> 4560
A83: Ducter | E83: jr | F83: 0.3 | G83: 2200 | H83: =(F83*G83) -> 660
A84: resistencia óhmica | E84: jr | F84: 0.3 | G84: 2000 | H84: =(F84*G84) -> 600
A85: hipot de 80 KV vcd | E85: jr | G85: 2500 | H85: =(F85*G85) -> 0
A86: Rigidez dieléctrica al aceite 60 kv | E86: jr | G86: 1600 | H86: =(F86*G86) -> 0
A87: Terrómetro | E87: jr | G87: 1100 | H87: =(F87*G87) -> 0
A88: Analizador de tiempos de interruptor | E88: jr | G88: 2700 | H88: =(F88*G88) -> 0
A89: Fuente de corriente para calibrador de relevadores | E89: jr | F89: 0.3 | G89: 2500 | H89: =(F89*G89) -> 750
A90: Probador de relevador de Protecciones | E90: jr | G90: 13373 | H90: =(F90*G90) -> 0
A91: Fuente trifasica de voltaje | E91: jr | G91: 800 | H91: =(F91*G91) -> 0
A92: Analizador de energía trifásica | E92: jr | G92: 1900 | H92: =(F92*G92) -> 0
A93: Medidor de presión y llenado de gas SF6 | E93: jr | G93: 2000 | H93: =(F93*G93) -> 0
A94: Medidor de secuencia de fases | E94: jr | G94: 200 | H94: =(F94*G94) -> 0
A95: Unidad de Pba y config. Para relevadores de Int. ABB | E95: jr | G95: 1100 | H95: =(F95*G95) -> 0
A96: Máquina centrifugadora de aceite | E96: jr | G96: 2200 | H96: =(F96*G96) -> 0
A97: Luxómetro | E97: jr | G97: 1420 | H97: =(F97*G97) -> 0
A98: Generador de Luz con combustible | E98: jr | F98: 1 | G98: 383.5 | H98: =(F98*G98) -> 383.5
G99: SUBT 9 | H99: =SUM(H79:H98) -> 9053.5
E101: 0 | H101: =+E101 -> 0 | I101: % DE IMP. | J101: INDIRECTO DISPONIBLE
G102: COSTO DIRECTO | H102: =H76+H99 -> 20644.335
F103: Indirectos | G103: 0.1 | H103: =H102*G103 -> 2064.4335 | I103: =(M109*100)/H103 -> 1.5594579 | J103: =H103-M109 -> 2032.2395
F104: Subtotal 1 | H104: =H102+H103 -> 22708.768
...

Sheet PROTECCIONES MAT.
A1: I M M E E S. A. D E C. V.
A2: A N A L I S I S D E P R E C I O U N I T A R I O
A3: COTIZACION:
A4: FECHA:
A5: PARTIDA 1
A7: MATERIALES.
A8: DESCRIPCION | E8: UNIDAD | F8: CANT. | G8: P.U. | H8: IMPORTE
A9: Gasolina | E9: L | F9: 1 | G9: 25 | H9: =G9*F9 -> 25 | J9: HR NORMAL
E10: Pza | F10: 1 | H10: =G10*F10 -> 0 | J10: HR DOBLE
E11: Pza | F11: 1 | H11: =G11*F11 -> 0 | J11: HR TRIPLE
E12: Pza | F12: 1 | H12: =G12*F12 -> 0
E13: Pza | F13: 1 | H13: =G13*F13 -> 0
E14: Pza | F14: 1 | H14: =G14*F14 -> 0
E15: Pza | F15: 1 | H15: =G15*F15 -> 0
E16: Pza | F16: 1 | H16: =G16*F16 -> 0
G17: SUBT 1 | H17: =SUM(H9:H16) -> 25
A19: MANO DE OBRA SIN INDIRECTOS | O19: HORARIOS DE TRABAJO | V19: HORAS RESULTANTES
A20: PERSONAL. | E20: UNIDAD | F20: CANT. | G20: P.U. | H20: IMPORTE | I20: CANT. | J20: Hr. Extra | K20: IMPORTE | L20: CANT. | M20: Dom, ó Fest. | N20: IMPORTE | O20: L | P20: M | Q20: MI | R20: J | S20: V | T20: S | U20: D | V20: N | W20: D | X20: T
A21: COORDINADOR DE OPERACIONES | E21: hr | F21: =V21 -> 0 | G21: 185.69 | H21: =F21*G21 -> 0 | I21: =W21 -> 0 | J21: =G21*1.5 -> 278.535 | K21: =I21*J21 -> 0 | L21: =X21 -> 0 | M21: =G21*2.25 -> 417.8025 | N21: =L21*M21 -> 0 | V21: =SUM(O21:T21) -> 0
A22: INGENIERIA Y SOPORTE TEC. | E22: hr | F22: =V22 -> 0 | G22: 177.79 | H22: =F22*G22 -> 0 | I22: =W22 -> 0 | J22: =G22*1.5 -> 266.685 | K22: =I22*J22 -> 0 | L22: =X22 -> 0 | M22: =G22*2.25 -> 400.0275 | N22: =L22*M22 -> 0 | V22: =SUM(O22:T22) -> 0
A23: SUPERVISOR DE SEGURIDAD CERTIFICADO | E23: hr | F23: =V23 -> 0 | G23: 185.69 | H23: =F23*G23 -> 0 | I23: =W23 -> 0 | J23: =G23*1.5 -> 278.535 | K23: =I23*J23 -> 0 | L23: =X23 -> 0 | M23: =G23*2.25 -> 417.8025 | N23: =L23*M23 -> 0 | V23: =SUM(O23:T23) -> 0
A24: SUPERVISOR ELECTRICO | E24: hr | F24: 0 | G24: 148.16 | H24: =F24*G24 -> 0 | I24: =W24 -> 0 | J24: =G24*1.5 -> 222.24 | K24: =I24*J24 -> 0 | L24: =X24 -> 0 | M24: =G24*2.25 -> 333.36 | N24: =L24*M24 -> 0 | O24: 8 | P24: 8 | Q24: 8 | R24: 8 | S24: 8 | V24: =SUM(O24:T24) -> 40
A25: TECNICO DE PRUEBAS ELECTRICAS | E25: hr | F25: 0 | G25: 136.31 | H25: =F25*G25 -> 0 | I25: =W25 -> 0 | J25: =G25*1.5 -> 204.465 | K25: =I25*J25 -> 0 | L25: =X25 -> 0 | M25: =G25*2.25 -> 306.6975 | N25: =L25*M25 -> 0 | V25: =SUM(O25:T25) -> 0
A26: CABO OBRA ELECTRICA | E26: hr | F26: =V26 -> 0 | G26: 136.31 | H26: =F26*G26 -> 0 | I26: =W26 -> 0 | J26: =G26*1.5 -> 204.465 | K26: =I26*J26 -> 0 | L26: =X26 -> 0 | M26: =G26*2.25 -> 306.6975 | N26: =L26*M26 -> 0 | V26: =SUM(O26:T26) -> 0
A27: LINIERO | E27: hr | F27: 0 | G27: 126.43 | H27: =F27*G27 -> 0 | I27: =W27 -> 0 | J27: =G27*1.5 -> 189.645 | K27: =I27*J27 -> 0 | L27: =X27 -> 0 | M27: =G27*2.25 -> 284.4675 | N27: =L27*M27 -> 0 | O27: 16 | P27: 16 | Q27: 16 | R27: 8 | S27: 8 | T27: 5 | V27: =SUM(O27:T27) -> 69
A28: LINIERO | E28: hr | F28: 0 | G28: 126.43 | H28: =F28*G28 -> 0 | I28: =W28 -> 0 | J28: =G28*1.5 -> 189.645 | K28: =I28*J28 -> 0 | L28: =X28 -> 0 | M28: =G28*2.25 -> 284.4675 | N28: =L28*M28 -> 0 | O28: 16 | P28: 16 | Q28: 16 | R28: 8 | S28: 8 | T28: 5 | V28: =SUM(O28:T28) -> 69
A29: ESPECIALISTA ELECTRICO | E29: hr | F29: 0 | G29: 110.63 | H29: =F29*G29 -> 0 | I29: =W29 -> 0 | J29: =G29*1.5 -> 165.945 | K29: =I29*J29 -> 0 | L29: =X29 -> 0 | M29: =G29*2.25 -> 248.9175 | N29: =L29*M29 -> 0 | V29: =SUM(O29:T29) -> 0
A30: TECNICO EN INSTRUMENTACION | E30: hr | F30: =V30 -> 0 | G30: 104.36 | H30: =F30*G30 -> 0 | I30: =W30 -> 0 | J30: =G30*1.5 -> 156.54 | K30: =I30*J30 -> 0 | L30: =X30 -> 0 | M30: =G30*2.25 -> 234.81 | N30: =L30*M30 -> 0 | V30: =SUM(O30:T30) -> 0
A31: OFICIAL ELECTRICO | E31: hr | F31: 0 | G31: 104.36 | H31: =F31*G31 -> 0 | I31: =W31 -> 0 | J31: =G31*1.5 -> 156.54 | K31: =I31*J31 -> 0 | L31: =X31 -> 0 | M31: =G31*2.25 -> 234.81 | N31: =L31*M31 -> 0 | V31: =SUM(O31:T31) -> 0
A32: ASISTENTE DE DISEÑO | E32: hr | F32: 0 | G32: 104.36 | H32: =F32*G32 -> 0 | I32: =W32 -> 0 | J32: =G32*1.5 -> 156.54 | K32: =I32*J32 -> 0 | L32: =X32 -> 0 | M32: =G32*2.25 -> 234.81 | N32: =L32*M32 -> 0 | V32: =SUM(O32:T32) -> 0
A33: ELECTRICISTA -B | E33: hr | F33: 8 | G33: 90.87 | H33: =F33*G33 -> 726.96 | I33: =W33 -> 0 | J33: =G33*1.5 -> 136.305 | K33: =I33*J33 -> 0 | L33: =X33 -> 0 | M33: =G33*2.25 -> 204.4575 | N33: =L33*M33 -> 0 | O33: 16 | P33: 16 | Q33: 16 | R33: 8 | S33: 8 | T33: 5 | V33: =SUM(O33:T33) -> 69
A34: ELECTRICISTA -A | E34: hr | F34: =V34 -> 0 | G34: 82.97 | H34: =F34*G34 -> 0 | I34: =W34 -> 0 | J34: =G34*1.5 -> 124.455 | K34: =I34*J34 -> 0 | L34: =X34 -> 0 | M34: =G34*2.25 -> 186.6825 | N34: =L34*M34 -> 0 | V34: =SUM(O34:T34) -> 0
A35: AUXILIAR TECNICO | E35: hr | F35: 4 | G35: 75.07 | H35: =F35*G35 -> 300.28 | I35: =W35 -> 0 | J35: =G35*1.5 -> 112.605 | K35: =I35*J35 -> 0 | L35: =X35 -> 0 | M35: =G35*2.25 -> 168.9075 | N35: =L35*M35 -> 0 | V35: =SUM(O35:T35) -> 0
A36: AYTE ELECTRICO - B | E36: hr | F36: 0 | G36: 75.07 | H36: =F36*G36 -> 0 | I36: =W36 -> 0 | J36: =G36*1.5 -> 112.605 | K36: =I36*J36 -> 0 | L36: =X36 -> 0 | M36: =G36*2.25 -> 168.9075 | N36: =L36*M36 -> 0 | V36: =SUM(O36:T36) -> 0
A37: AYTE DE ELECTR. -A | E37: hr | F37: 0 | G37: 63.21 | H37: =F37*G37 -> 0 | I37: =W37 -> 0 | J37: =G37*1.5 -> 94.815 | K37: =I37*J37 -> 0 | L37: =X37 -> 0 | M37: =G37*2.25 -> 142.2225 | N37: =L37*M37 -> 0 | O37: 8 | P37: 8 | Q37: 8 | R37: 8 | S37: 8 | V37: =SUM(O37:T37) -> 40
A38: AYTE GENERAL | E38: hr | F38: =V38 -> 0 | G38: 50.77 | H38: =F38*G38 -> 0 | I38: =W38 -> 0 | J38: =G38*1.5 -> 76.155 | K38: =I38*J38 -> 0 | L38: =X38 -> 0 | M38: =G38*2.25 -> 114.2325 | N38: =L38*M38 -> 0
A39: INGENIERO DE SUBESTACIONES | E39: hr | F39: =V39 -> 0 | G39: 186 | H39: =F39*G39 -> 0 | I39: =W39 -> 0 | J39: 186 | K39: =I39*J39 -> 0 | L39: =X39 -> 0 | M39: 186 | N39: =L39*M39 -> 0 | V39: =SUM(O39:T39) -> 0
A40: INGENIERO DE PRUEBAS ELECTRICAS | E40: hr | F40: =V40 -> 0 | G40: 186 | H40: =F40*G40 -> 0 | I40: =W40 -> 0 | J40: 186 | K40: =I40*J40 -> 0 | L40: =X40 -> 0 | M40: 186 | N40: =L40*M40 -> 0 | V40: =SUM(O40:T40) -> 0
A41: ING. ESPECIALISTA EN PROTECCIONES | E41: hr | F41: =V41 -> 0 | G41: 230.47 | H41: =F41*G41 -> 0 | I41: =W41 -> 0 | J41: 294 | K41: =I41*J41 -> 0 | L41: =X41 -> 0 | M41: 294 | N41: =L41*M41 -> 0 | V41: =SUM(O41:T41) -> 0
A42: SUPERINTENDENTE | E42: hr | F42: =V42 -> 0 | G42: 279.53 | H42: =F42*G42 -> 0 | I42: =W42 -> 0 | J42: 372.71 | K42: =I42*J42 -> 0 | L42: =X42 -> 0 | M42: 559.07 | N42: =L42*M42 -> 0 | V42: =SUM(O42:T42) -> 0
F43: =V43 -> 287 | G43: SUBT 2 | H43: =SUM(H21:H42) -> 1027.24 | J43: SUBT. | K43: =SUM(K22:K41) -> 0 | M43: SUBT. | N43: =SUM(N22:N41) -> 0 | V43: =SUM(V21:V42) -> 287 | W43: 45
G44: SUMA M.O. | H44: =H43+K43+N43 -> 1027.24
A45: HERRAMIENTA MENOR | G45: 1 a 10% | H45: =+H44*0.06 -> 61.6344
A47: VEHICULOS
A48: DESCRIPCION | E48: UNIDAD | F48: CANT. | G48: P.U. | H48: IMPORTE | J48: HR IDA | K48: HR RETORNO | L48: HR SITIO | M48: SUMA
A49: camioneta RANGER sin operador sin combustible | E49: HR | F49: 0 | G49: 102.29 | H49: =F49*G49 -> 0 | J49: 0 | K49: 0 | L49: 0 | M49: =J49+K49+L49 -> 0
A50: camioneta NISSAN sin operador sin combustible | E50: HR | F50: 0 | G50: 68.7 | H50: =F50*G50 -> 0 | J50: 0 | K50: 0 | M50: =J50+K50+L50 -> 0
A51: camioneta TORNADO Tornado sin operador sin combustible | E51: HR | F51: 8 | G51: 54.43 | H51: =F51*G51 -> 435.44 | J51: 0.45 | K51: 0.45 | M51: =J51+K51+L51 -> 0.9
A52: Camion con grua sin operador sin conbustible. | E52: HR | F52: =M52 -> 0 | G52: 203.19 | H52: =F52*G52 -> 0 | M52: =J52+K52+L52 -> 0
A53: Camion con grua con operador con conbustible. | E53: HR | G53: 407.62 | H53: =F53*G53 -> 0
A54: autobus | E54: pza | G54: 5000 | H54: =F54*G54 -> 0
A55: Km. Recorrido (incluye conbustible y depresiación de Vehiculo | E55: KM | G55: 2.5 | H55: =F55*G55 -> 0
G56: SUBT 4 | H56: =SUM(H49:H55) -> 435.44
A57: COMBUSTIBLE
A58: DESCRIPCION | E58: UNIDAD | F58: CANT. | G58: P.U. | H58: IMPORTE | J58: KM IDA | K58: KM RETORNO | L58: KM SITIO | M58: SUMA
A59: GASOLINA MAGNA | E59: LT | F59: 30 | G59: 16.48 | H59: =F59*G59 -> 494.4 | J59: 22 | K59: 22 | M59: =J59+K59+L59 -> 44
A60: DIESEL | E60: LT | F60: =M60/4.5 -> 0 | G60: 0 | H60: =F60*G60 -> 0 | M60: =J60+K60+L60 -> 0
G61: SUBT 5 | H61: =SUM(H59:H60) -> 494.4
A62: CASETAS
A63: DESCRIPCION | E63: UNIDAD | F63: CANT. | G63: P.U. | H63: IMPORTE
A64: camioneta pick up | E64: CASETA | F64: 2 | G64: 180 | H64: =F64*G64 -> 360
A65: camioneta pick up | E65: CASETA | G65: 65 | H65: =F65*G65 -> 0
G66: SUBT 6 | H66: =SUM(H64:H65) -> 360
A67: VIATICOS
A68: ALIMENTOS
A69: DESCRIPCION | E69: UNIDAD | F69: CANT. | G69: P.U. | H69: IMPORTE
A70: CONSUMO DE ALIMENTOS | E70: Pza | F70: 0.5 | G70: 450 | H70: =F70*G70 -> 225
H71: =SUM(H70) -> 225
A72: HOSPEDAJE
A73: DESCRIPCION | E73: UNIDAD | F73: CANT. | G73: P.U. | H73: IMPORTE
A74: HOTEL | E74: NOCHES | F74: 0 | G74: 900 | H74: =F74*G74 -> 0
G75: SUBT 8 | H75: =SUM(H74) -> 0
G76: SUMA: | H76: =H56+H61+H66+H71+H75+H45+H44+H17 -> 2628.7144
A77: EQUIPO DE PRUEBA
A78: DESCRIPCION | E78: UNIDAD | F78: CANT. | G78: P.U. | H78: IMPORTE | I78: TR | K78: S.E
A79: Megger | E79: jr | G79: 2200 | H79: =(F79*G79) -> 0
A80: TTR | E80: jr | G80: 2000 | H80: =(F80*G80) -> 0
A81: Factor de Potencia de 2.5 KV | E81: jr | G81: 7000 | H81: =(F81*G81) -> 0
A82: Factor de Potencia de 10.5 KV | E82: jr | G82: 15200 | H82: =(F82*G82) -> 0
A83: Ducter | E83: jr | G83: 2200 | H83: =(F83*G83) -> 0
A84: resistencia óhmica | E84: jr | G84: 2000 | H84: =(F84*G84) -> 0
A85: hipot de 80 KV vcd | E85: jr | G85: 2500 | H85: =(F85*G85) -> 0
A86: Rigidez dieléctrica al aceite 60 kv | E86: jr | G86: 1600 | H86: =(F86*G86) -> 0
A87: Terrómetro | E87: jr | G87: 1100 | H87: =(F87*G87) -> 0
A88: Analizador de tiempos de interruptor | E88: jr | G88: 2700 | H88: =(F88*G88) -> 0
A89: Fuente de corriente para calibrador de relevadores | E89: jr | G89: 2500 | H89: =(F89*G89) -> 0
A90: Probador de relevador de Protecciones | E90: jr | G90: 13373 | H90: =(F90*G90) -> 0
... A98: Generador de Luz con combustible | E98: jr | G98: 383.5 | H98: =(F98*G98) -> 0
G99: SUBT 9 | H99: =SUM(H79:H98) -> 0
E101: 0 | H101: =+E101 -> 0 | I101: % DE IMP. | J101: INDIRECTO DISPONIBLE
G102: COSTO DIRECTO | H102: =H76+H99 -> 2628.7144
F103: Indirectos | G103: 0.1 | H103: =H102*G103 -> 262.87144 | I103: =(M109*100)/H103 -> -47.884612 | J103: =H103-M109 -> 388.74641
F104: Subtotal 1 | H104: =H102+H103 -> 2891.5858
K105: BASE IMPUESTO
F106: Financ. | G106: 0.05 | H106: =H104*G106 -> 144.57929 | I106: =H106+[1]Part.2!H84+[1]Part.3!H84+[1]Part.4!H84+[1]part.5!H84+[1]traslado!H66 -> 354.79134 | J106: COMPRAS | K106: =+H17 -> 25
F107: Subtotal 2 | H107: =H104+H106 -> 3036.1651 | J107: M.O | K107: =H44 -> 1027.24
F108: Utilidad | G108: 0.2 | H108: =H107*G108 -> 607.23303 | J108: GASTOS FACTURADOS | K108: =H76-H56 -> 2193.2744 | M108: IMP. 32%
F109: Importe | H109: =H107+H108 -> 3643.3982 | J109: SUMA | K109: =SUM(K106:K108) -> 3245.5144 | L109: =H109-H108-(H103*0.7)-K109 -> -393.35928 | M109: =0.32*L109 -> -125.87497
I110: FACTOR | J110: =H109/H102 -> 1.386

Sheet PROTECCIONES MO
A1: I M M E E S. A. D E C. V.
A2: A N A L I S I S D E P R E C I O U N I T A R I O
A3: COTIZACION:
A4: FECHA:
A5: PARTIDA 1
A7: MATERIALES.
A8: DESCRIPCION | E8: UNIDAD | F8: CANT. | G8: P.U. | H8: IMPORTE
E9: Pza | F9: 1 | G9: 0 | H9: =G9 -> 0 | J9: HR NORMAL
E10: Pza | J10: HR DOBLE
E11: Pza | J11: HR TRIPLE
E12: Pza
E13: Pza
E14: Pza
E15: Pza
E16: Pza | I16: =H16*1.455 -> 0
G17: SUBT 1 | H17: =SUM(H9:H16) -> 0
A19: MANO DE OBRA SIN INDIRECTOS | O19: HORARIOS DE TRABAJO | V19: HORAS RESULTANTES
A20: PERSONAL. | E20: UNIDAD | F20: CANT. | G20: P.U. | H20: IMPORTE | I20: CANT. | J20: Hr. Extra | K20: IMPORTE | L20: CANT. | M20: Dom, ó Fest. | N20: IMPORTE | O20: L | P20: M | Q20: MI | R20: J | S20: V | T20: S | U20: D | V20: N | W20: D | X20: T
A21: COORDINADOR DE OPERACIONES | E21: hr | F21: =V21 -> 0 | G21: 185.69 | H21: =F21*G21 -> 0 | I21: =W21 -> 0 | J21: =G21*1.5 -> 278.535 | K21: =I21*J21 -> 0 | L21: =X21 -> 0 | M21: =G21*2.25 -> 417.8025 | N21: =L21*M21 -> 0 | V21: =SUM(O21:T21) -> 0
A22: INGENIERIA Y SOPORTE TEC. | E22: hr | F22: =V22 -> 0 | G22: 177.79 | H22: =F22*G22 -> 0 | I22: =W22 -> 0 | J22: =G22*1.5 -> 266.685 | K22: =I22*J22 -> 0 | L22: =X22 -> 0 | M22: =G22*2.25 -> 400.0275 | N22: =L22*M22 -> 0 | V22: =SUM(O22:T22) -> 0
A23: SUPERVISOR DE SEGURIDAD CERTIFICADO | E23: hr | F23: =V23 -> 0 | G23: 185.69 | H23: =F23*G23 -> 0 | I23: =W23 -> 0 | J23: =G23*1.5 -> 278.535 | K23: =I23*J23 -> 0 | L23: =X23 -> 0 | M23: =G23*2.25 -> 417.8025 | N23: =L23*M23 -> 0 | V23: =SUM(O23:T23) -> 0
A24: SUPERVISOR ELECTRICO | E24: hr | F24: 4 | G24: 237 | H24: =F24*G24 -> 948 | I24: =W24 -> 0 | J24: =G24*1.5 -> 355.5 | K24: =I24*J24 -> 0 | L24: =X24 -> 0 | M24: =G24*2.25 -> 533.25 | N24: =L24*M24 -> 0 | O24: 8 | P24: 8 | Q24: 8 | R24: 8 | S24: 8 | V24: =SUM(O24:T24) -> 40
A25: TECNICO DE PRUEBAS ELECTRICAS | E25: hr | F25: 16 | G25: 209.25 | H25: =F25*G25 -> 3348 | I25: 6 | J25: =G25*1.5 -> 313.875 | K25: =I25*J25 -> 1883.25 | L25: =X25 -> 0 | M25: =G25*2.25 -> 470.8125 | N25: =L25*M25 -> 0 | V25: =SUM(O25:T25) -> 0
A26: CABO OBRA ELECTRICA | E26: hr | F26: =V26 -> 0 | G26: 136.31 | H26: =F26*G26 -> 0 | I26: =W26 -> 0 | J26: =G26*1.5 -> 204.465 | K26: =I26*J26 -> 0 | L26: =X26 -> 0 | M26: =G26*2.25 -> 306.6975 | N26: =L26*M26 -> 0 | V26: =SUM(O26:T26) -> 0
A27: LINIERO | E27: hr | F27: 16 | G27: 190.22 | H27: =F27*G27 -> 3043.52 | I27: 6 | J27: =G27*1.5 -> 285.33 | K27: =I27*J27 -> 1711.98 | L27: =X27 -> 0 | M27: =G27*2.25 -> 427.995 | N27: =L27*M27 -> 0 | O27: 16 | P27: 16 | Q27: 16 | R27: 8 | S27: 8 | T27: 5 | V27: =SUM(O27:T27) -> 69
A28: LINIERO | E28: hr | F28: 0 | G28: 126.43 | H28: =F28*G28 -> 0 | I28: =W28 -> 0 | J28: =G28*1.5 -> 189.645 | K28: =I28*J28 -> 0 | L28: =X28 -> 0 | M28: =G28*2.25 -> 284.4675 | N28: =L28*M28 -> 0 | O28: 16 | P28: 16 | Q28: 16 | R28: 8 | S28: 8 | T28: 5 | V28: =SUM(O28:T28) -> 69
A29: ESPECIALISTA ELECTRICO | E29: hr | F29: 0 | G29: 110.63 | H29: =F29*G29 -> 0 | I29: =W29 -> 0 | J29: =G29*1.5 -> 165.945 | K29: =I29*J29 -> 0 | L29: =X29 -> 0 | M29: =G29*2.25 -> 248.9175 | N29: =L29*M29 -> 0 | V29: =SUM(O29:T29) -> 0
A30: TECNICO EN INSTRUMENTACION | E30: hr | F30: =V30 -> 0 | G30: 104.36 | H30: =F30*G30 -> 0 | I30: =W30 -> 0 | J30: =G30*1.5 -> 156.54 | K30: =I30*J30 -> 0 | L30: =X30 -> 0 | M30: =G30*2.25 -> 234.81 | N30: =L30*M30 -> 0 | V30: =SUM(O30:T30) -> 0
A31: OFICIAL ELECTRICO | E31: hr | F31: 0 | G31: 104.36 | H31: =F31*G31 -> 0 | I31: =W31 -> 0 | J31: =G31*1.5 -> 156.54 | K31: =I31*J31 -> 0 | L31: =X31 -> 0 | M31: =G31*2.25 -> 234.81 | N31: =L31*M31 -> 0 | V31: =SUM(O31:T31) -> 0
A32: ASISTENTE DE DISEÑO | E32: hr | F32: =V32 -> 0 | G32: 104.36 | H32: =F32*G32 -> 0 | I32: =W32 -> 0 | J32: =G32*1.5 -> 156.54 | K32: =I32*J32 -> 0 | L32: =X32 -> 0 | M32: =G32*2.25 -> 234.81 | N32: =L32*M32 -> 0 | V32: =SUM(O32:T32) -> 0
A33: ELECTRICISTA -B | E33: hr | F33: 0 | G33: 90.87 | H33: =F33*G33 -> 0 | I33: =W33 -> 0 | J33: =G33*1.5 -> 136.305 | K33: =I33*J33 -> 0 | L33: =X33 -> 0 | M33: =G33*2.25 -> 204.4575 | N33: =L33*M33 -> 0 | O33: 16 | P33: 16 | Q33: 16 | R33: 8 | S33: 8 | T33: 5 | V33: =SUM(O33:T33) -> 69
A34: ELECTRICISTA -A | E34: hr | F34: 0 | G34: 82.97 | H34: =F34*G34 -> 0 | I34: =W34 -> 0 | J34: =G34*1.5 -> 124.455 | K34: =I34*J34 -> 0 | L34: =X34 -> 0 | M34: =G34*2.25 -> 186.6825 | N34: =L34*M34 -> 0 | V34: =SUM(O34:T34) -> 0
A35: AUXILIAR TECNICO | E35: hr | F35: 0 | G35: 75.07 | H35: =F35*G35 -> 0 | I35: =W35 -> 0 | J35: =G35*1.5 -> 112.605 | K35: =I35*J35 -> 0 | L35: =X35 -> 0 | M35: =G35*2.25 -> 168.9075 | N35: =L35*M35 -> 0 | V35: =SUM(O35:T35) -> 0
A36: AYTE ELECTRICO - B | E36: hr | F36: 0 | G36: 75.07 | H36: =F36*G36 -> 0 | I36: =W36 -> 0 | J36: =G36*1.5 -> 112.605 | K36: =I36*J36 -> 0 | L36: =X36 -> 0 | M36: =G36*2.25 -> 168.9075 | N36: =L36*M36 -> 0 | V36: =SUM(O36:T36) -> 0
A37: AYTE DE ELECTR. -A | E37: hr | F37: 0 | G37: 63.21 | H37: =F37*G37 -> 0 | I37: =W37 -> 0 | J37: =G37*1.5 -> 94.815 | K37: =I37*J37 -> 0 | L37: =X37 -> 0 | M37: =G37*2.25 -> 142.2225 | N37: =L37*M37 -> 0 | O37: 8 | P37: 8 | Q37: 8 | R37: 8 | S37: 8 | V37: =SUM(O37:T37) -> 40
A38: AYTE GENERAL | E38: hr | F38: 0 | G38: 50.77 | H38: =F38*G38 -> 0 | I38: =W38 -> 0 | J38: =G38*1.5 -> 76.155 | K38: =I38*J38 -> 0 | L38: =X38 -> 0 | M38: =G38*2.25 -> 114.2325 | N38: =L38*M38 -> 0
A39: INGENIERO DE SUBESTACIONES | E39: hr | F39: 0 | G39: 186 | H39: =F39*G39 -> 0 | I39: =W39 -> 0 | J39: 186 | K39: =I39*J39 -> 0 | L39: =X39 -> 0 | M39: 186 | N39: =L39*M39 -> 0 | V39: =SUM(O39:T39) -> 0
A40: INGENIERO DE PRUEBAS ELECTRICAS | E40: hr | F40: 0 | G40: 186 | H40: =F40*G40 -> 0 | I40: =W40 -> 0 | J40: 186 | K40: =I40*J40 -> 0 | L40: =X40 -> 0 | M40: 186 | N40: =L40*M40 -> 0 | V40: =SUM(O40:T40) -> 0
A41: ING. ESPECIALISTA EN PROTECCIONES | E41: hr | F41: 0 | G41: 230.47 | H41: =F41*G41 -> 0 | I41: =W41 -> 0 | J41: 294 | K41: =I41*J41 -> 0 | L41: =X41 -> 0 | M41: 294 | N41: =L41*M41 -> 0 | V41: =SUM(O41:T41) -> 0
A42: SUPERINTENDENTE | E42: hr | F42: =V42 -> 0 | G42: 279.53 | H42: =F42*G42 -> 0 | I42: =W42 -> 0 | J42: 372.71 | K42: =I42*J42 -> 0 | L42: =X42 -> 0 | M42: 559.07 | N42: =L42*M42 -> 0 | V42: =SUM(O42:T42) -> 0
F43: =V43 -> 287 | G43: SUBT 2 | H43: =SUM(H21:H42) -> 7339.52 | J43: SUBT. | K43: =SUM(K22:K41) -> 3595.23 | M43: SUBT. | N43: =SUM(N22:N41) -> 0 | V43: =SUM(V21:V42) -> 287 | W43: 45
G44: SUMA M.O. | H44: =H43+K43+N43 -> 10934.75
A45: HERRAMIENTA MENOR | G45: 1 a 10% | H45: =+H44*0.06 -> 656.085
A47: VEHICULOS
A48: DESCRIPCION | E48: UNIDAD | F48: CANT. | G48: P.U. | H48: IMPORTE | J48: HR IDA | K48: HR RETORNO | L48: HR SITIO | M48: SUMA
A49: camioneta RANGER sin operador sin combustible | E49: HR | G49: 102.29 | H49: =F49*G49 -> 0 | J49: 0 | K49: 0 | L49: 0 | M49: =J49+K49+L49 -> 0
A50: camioneta NISSAN sin operador sin combustible | E50: HR | F50: 0 | G50: 68.7 | H50: =F50*G50 -> 0 | J50: 0 | K50: 0 | M50: =J50+K50+L50 -> 0
A51: camioneta TORNADO Tornado sin operador sin combustible | E51: HR | F51: 0 | G51: 54.43 | H51: =F51*G51 -> 0 | J51: 0.45 | K51: 0.45 | M51: =J51+K51+L51 -> 0.9
A52: Camion con grua sin operador sin conbustible. | E52: HR | F52: 0 | G52: 203.19 | H52: =F52*G52 -> 0 | M52: =J52+K52+L52 -> 0
A53: Camion con grua con operador con conbustible. | E53: HR | F53: 0 | G53: 407.62 | H53: =F53*G53 -> 0
A54: autobus | E54: pza | F54: 0 | G54: 5000 | H54: =F54*G54 -> 0
A55: Km. Recorrido (incluye conbustible y depresiación de Vehiculo | E55: KM | F55: 0 | G55: 2.5 | H55: =F55*G55 -> 0
G56: SUBT 4 | H56: =SUM(H49:H55) -> 0
A57: COMBUSTIBLE
A58: DESCRIPCION | E58: UNIDAD | F58: CANT. | G58: P.U. | H58: IMPORTE | J58: KM IDA | K58: KM RETORNO | L58: KM SITIO | M58: SUMA
A59: GASOLINA MAGNA | E59: LT | F59: 0 | G59: 19 | H59: =F59*G59 -> 0 | J59: 22 | K59: 22 | M59: =J59+K59+L59 -> 44
A60: DIESEL | E60: LT | F60: =M60/4.5 -> 0 | G60: 0 | H60: =F60*G60 -> 0 | M60: =J60+K60+L60 -> 0
G61: SUBT 5 | H61: =SUM(H59:H60) -> 0
A62: CASETAS
A63: DESCRIPCION | E63: UNIDAD | F63: CANT. | G63: P.U. | H63: IMPORTE
A64: camioneta pick up | E64: CASETA | F64: 0 | G64: 100 | H64: =F64*G64 -> 0
A65: camioneta pick up | E65: CASETA | F65: 0 | G65: 65 | H65: =F65*G65 -> 0
G66: SUBT 6 | H66: =SUM(H64:H65) -> 0
A67: VIATICOS
A68: ALIMENTOS
A69: DESCRIPCION | E69: UNIDAD | F69: CANT. | G69: P.U. | H69: IMPORTE
A70: CONSUMO DE ALIMENTOS | E70: Pza | F70: 0 | G70: 450 | H70: =F70*G70 -> 0
H71: =SUM(H70) -> 0
A72: HOSPEDAJE
A73: DESCRIPCION | E73: UNIDAD | F73: CANT. | G73: P.U. | H73: IMPORTE
A74: HOTEL | E74: NOCHES | F74: 0 | G74: 900 | H74: =F74*G74 -> 0
G75: SUBT 8 | H75: =SUM(H74) -> 0
G76: SUMA: | H76: =H56+H61+H66+H71+H75+H45+H44+H17 -> 11590.835
A77: EQUIPO DE PRUEBA
A78: DESCRIPCION | E78: UNIDAD | F78: CANT. | G78: P.U. | H78: IMPORTE | I78: TR | K78: S.E
A79: Megger | E79: jr | F79: 0.5 | G79: 2200 | H79: =(F79*G79) -> 1100
A80: TTR | E80: jr | F80: 0.5 | G80: 2000 | H80: =(F80*G80) -> 1000
A81: Factor de Potencia de 2.5 KV | E81: jr | F81: 0 | G81: 7000 | H81: =(F81*G81) -> 0
A82: Factor de Potencia de 10.5 KV | E82: jr | F82: 0.3 | G82: 15200 | H82: =(F82*G82) -> 4560
A83: Ducter | E83: jr | F83: 0.3 | G83: 2200 | H83: =(F83*G83) -> 660
A84: resistencia óhmica | E84: jr | F84: 0.3 | G84: 2000 | H84: =(F84*G84) -> 600
A85: hipot de 80 KV vcd | E85: jr | G85: 2500 | H85: =(F85*G85) -> 0
A86: Rigidez dieléctrica al aceite 60 kv | E86: jr | G86: 1600 | H86: =(F86*G86) -> 0
A87: Terrómetro | E87: jr | G87: 1100 | H87: =(F87*G87) -> 0
A88: Analizador de tiempos de interruptor | E88: jr | G88: 2700 | H88: =(F88*G88) -> 0
A89: Fuente de corriente para calibrador de relevadores | E89: jr | F89: 0.3 | G89: 2500 | H89: =(F89*G89) -> 750
A90: Probador de relevador de Protecciones | E90: jr | G90: 13373 | H90: =(F90*G90) -> 0
A91: Fuente trifasica de voltaje | E91: jr | G91: 800 | H91: =(F91*G91) -> 0
A92: Analizador de energía trifásica | E92: jr | G92: 1900 | H92: =(F92*G92) -> 0
A93: Medidor de presión y llenado de gas SF6 | E93: jr | G93: 2000 | H93: =(F93*G93) -> 0
A94: Medidor de secuencia de fases | E94: jr | G94: 200 | H94: =(F94*G94) -> 0
A95: Unidad de Pba y config. Para relevadores de Int. ABB | E95: jr | G95: 1100 | H95: =(F95*G95) -> 0
A96: Máquina centrifugadora de aceite | E96: jr | G96: 2200 | H96: =(F96*G96) -> 0
A97: Luxómetro | E97: jr | G97: 1420 | H97: =(F97*G97) -> 0
A98: Generador de Luz con combustible | E98: jr | F98: 1 | G98: 383.5 | H98: =(F98*G98) -> 383.5
G99: SUBT 9 | H99: =SUM(H79:H98) -> 9053.5
E101: 0 | H101: =+E101 -> 0 | I101: % DE IMP. | J101: INDIRECTO DISPONIBLE
G102: COSTO DIRECTO | H102: =H76+H99 -> 20644.335
F103: Indirectos | G103: 0.1 | H103: =H102*G103 -> 2064.4335 | I103: =(M109*100)/H103 -> 1.5594579 | J103: =H103-M109 -> 2032.2395
F104: Subtotal 1 | H104: =H102+H103 -> 22708.768
...

Sheet TERMOGRAFIA MAT.
A1: I M M E E S. A. D E C. V.
A2: A N A L I S I S D E P R E C I O U N I T A R I O
A3: COTIZACION:
A4: FECHA:
A5: PARTIDA 1
A7: MATERIALES.
A8: DESCRIPCION | E8: UNIDAD | F8: CANT. | G8: P.U. | H8: IMPORTE
A9: Servicio de termografia | E9: serv | F9: 2 | G9: 40000 | H9: =G9*F9 -> 80000 | J9: HR NORMAL
E10: Pza | F10: 0 | H10: =G10*F10 -> 0 | J10: HR DOBLE
E11: Pza | F11: 1 | H11: =G11*F11 -> 0 | J11: HR TRIPLE
E12: Pza | F12: 1 | H12: =G12*F12 -> 0
E13: Pza | F13: 1 | H13: =G13*F13 -> 0
E14: Pza | F14: 1 | H14: =G14*F14 -> 0
E15: Pza | F15: 1 | H15: =G15*F15 -> 0
E16: Pza | F16: 1 | H16: =G16*F16 -> 0
G17: SUBT 1 | H17: =SUM(H9:H16) -> 80000
A19: MANO DE OBRA SIN INDIRECTOS | O19: HORARIOS DE TRABAJO | V19: HORAS RESULTANTES
A20: PERSONAL. | E20: UNIDAD | F20: CANT. | G20: P.U. | H20: IMPORTE | I20: CANT. | J20: Hr. Extra | K20: IMPORTE | L20: CANT. | M20: Dom, ó Fest. | N20: IMPORTE | O20: L | P20: M | Q20: MI | R20: J | S20: V | T20: S | U20: D | V20: N | W20: D | X20: T
A21: COORDINADOR DE OPERACIONES | E21: hr | F21: =V21 -> 0 | G21: 185.69 | H21: =F21*G21 -> 0 | I21: =W21 -> 0 | J21: =G21*1.5 -> 278.535 | K21: =I21*J21 -> 0 | L21: =X21 -> 0 | M21: =G21*2.25 -> 417.8025 | N21: =L21*M21 -> 0 | V21: =SUM(O21:T21) -> 0
A22: INGENIERIA Y SOPORTE TEC. | E22: hr | F22: =V22 -> 0 | G22: 177.79 | H22: =F22*G22 -> 0 | I22: =W22 -> 0 | J22: =G22*1.5 -> 266.685 | K22: =I22*J22 -> 0 | L22: =X22 -> 0 | M22: =G22*2.25 -> 400.0275 | N22: =L22*M22 -> 0 | V22: =SUM(O22:T22) -> 0
A23: SUPERVISOR DE SEGURIDAD CERTIFICADO | E23: hr | F23: =V23 -> 0 | G23: 185.69 | H23: =F23*G23 -> 0 | I23: =W23 -> 0 | J23: =G23*1.5 -> 278.535 | K23: =I23*J23 -> 0 | L23: =X23 -> 0 | M23: =G23*2.25 -> 417.8025 | N23: =L23*M23 -> 0 | V23: =SUM(O23:T23) -> 0
A24: SUPERVISOR ELECTRICO | E24: hr | F24: 0 | G24: 148.16 | H24: =F24*G24 -> 0 | I24: =W24 -> 0 | J24: =G24*1.5 -> 222.24 | K24: =I24*J24 -> 0 | L24: =X24 -> 0 | M24: =G24*2.25 -> 333.36 | N24: =L24*M24 -> 0 | O24: 8 | P24: 8 | Q24: 8 | R24: 8 | S24: 8 | V24: =SUM(O24:T24) -> 40
A25: TECNICO DE PRUEBAS ELECTRICAS | E25: hr | F25: 0 | G25: 136.31 | H25: =F25*G25 -> 0 | I25: =W25 -> 0 | J25: =G25*1.5 -> 204.465 | K25: =I25*J25 -> 0 | L25: =X25 -> 0 | M25: =G25*2.25 -> 306.6975 | N25: =L25*M25 -> 0 | V25: =SUM(O25:T25) -> 0
A26: CABO OBRA ELECTRICA | E26: hr | F26: =V26 -> 0 | G26: 136.31 | H26: =F26*G26 -> 0 | I26: =W26 -> 0 | J26: =G26*1.5 -> 204.465 | K26: =I26*J26 -> 0 | L26: =X26 -> 0 | M26: =G26*2.25 -> 306.6975 | N26: =L26*M26 -> 0 | V26: =SUM(O26:T26) -> 0
A27: LINIERO | E27: hr | F27: 0 | G27: 126.43 | H27: =F27*G27 -> 0 | I27: =W27 -> 0 | J27: =G27*1.5 -> 189.645 | K27: =I27*J27 -> 0 | L27: =X27 -> 0 | M27: =G27*2.25 -> 284.4675 | N27: =L27*M27 -> 0 | O27: 16 | P27: 16 | Q27: 16 | R27: 8 | S27: 8 | T27: 5 | V27: =SUM(O27:T27) -> 69
A28: LINIERO | E28: hr | F28: 0 | G28: 126.43 | H28: =F28*G28 -> 0 | I28: =W28 -> 0 | J28: =G28*1.5 -> 189.645 | K28: =I28*J28 -> 0 | L28: =X28 -> 0 | M28: =G28*2.25 -> 284.4675 | N28: =L28*M28 -> 0 | O28: 16 | P28: 16 | Q28: 16 | R28: 8 | S28: 8 | T28: 5 | V28: =SUM(O28:T28) -> 69
A29: ESPECIALISTA ELECTRICO | E29: hr | F29: 0 | G29: 110.63 | H29: =F29*G29 -> 0 | I29: =W29 -> 0 | J29: =G29*1.5 -> 165.945 | K29: =I29*J29 -> 0 | L29: =X29 -> 0 | M29: =G29*2.25 -> 248.9175 | N29: =L29*M29 -> 0 | V29: =SUM(O29:T29) -> 0
A30: TECNICO EN INSTRUMENTACION | E30: hr | F30: =V30 -> 0 | G30: 104.36 | H30: =F30*G30 -> 0 | I30: =W30 -> 0 | J30: =G30*1.5 -> 156.54 | K30: =I30*J30 -> 0 | L30: =X30 -> 0 | M30: =G30*2.25 -> 234.81 | N30: =L30*M30 -> 0 | V30: =SUM(O30:T30) -> 0
A31: OFICIAL ELECTRICO | E31: hr | F31: 0 | G31: 104.36 | H31: =F31*G31 -> 0 | I31: =W31 -> 0 | J31: =G31*1.5 -> 156.54 | K31: =I31*J31 -> 0 | L31: =X31 -> 0 | M31: =G31*2.25 -> 234.81 | N31: =L31*M31 -> 0 | V31: =SUM(O31:T31) -> 0
A32: ASISTENTE DE DISEÑO | E32: hr | F32: 0 | G32: 104.36 | H32: =F32*G32 -> 0 | I32: =W32 -> 0 | J32: =G32*1.5 -> 156.54 | K32: =I32*J32 -> 0 | L32: =X32 -> 0 | M32: =G32*2.25 -> 234.81 | N32: =L32*M32 -> 0 | V32: =SUM(O32:T32) -> 0
A33: ELECTRICISTA -B | E33: hr | F33: 8 | G33: 90.87 | H33: =F33*G33 -> 726.96 | I33: =W33 -> 0 | J33: =G33*1.5 -> 136.305 | K33: =I33*J33 -> 0 | L33: =X33 -> 0 | M33: =G33*2.25 -> 204.4575 | N33: =L33*M33 -> 0 | O33: 16 | P33: 16 | Q33: 16 | R33: 8 | S33: 8 | T33: 5 | V33: =SUM(O33:T33) -> 69
A34: ELECTRICISTA -A | E34: hr | F34: =V34 -> 0 | G34: 82.97 | H34: =F34*G34 -> 0 | I34: =W34 -> 0 | J34: =G34*1.5 -> 124.455 | K34: =I34*J34 -> 0 | L34: =X34 -> 0 | M34: =G34*2.25 -> 186.6825 | N34: =L34*M34 -> 0 | V34: =SUM(O34:T34) -> 0
A35: AUXILIAR TECNICO | E35: hr | F35: 4 | G35: 75.07 | H35: =F35*G35 -> 300.28 | I35: =W35 -> 0 | J35: =G35*1.5 -> 112.605 | K35: =I35*J35 -> 0 | L35: =X35 -> 0 | M35: =G35*2.25 -> 168.9075 | N35: =L35*M35 -> 0 | V35: =SUM(O35:T35) -> 0
A36: AYTE ELECTRICO - B | E36: hr | F36: 0 | G36: 75.07 | H36: =F36*G36 -> 0 | I36: =W36 -> 0 | J36: =G36*1.5 -> 112.605 | K36: =I36*J36 -> 0 | L36: =X36 -> 0 | M36: =G36*2.25 -> 168.9075 | N36: =L36*M36 -> 0 | V36: =SUM(O36:T36) -> 0
A37: AYTE DE ELECTR. -A | E37: hr | F37: 0 | G37: 63.21 | H37: =F37*G37 -> 0 | I37: =W37 -> 0 | J37: =G37*1.5 -> 94.815 | K37: =I37*J37 -> 0 | L37: =X37 -> 0 | M37: =G37*2.25 -> 142.2225 | N37: =L37*M37 -> 0 | O37: 8 | P37: 8 | Q37: 8 | R37: 8 | S37: 8 | V37: =SUM(O37:T37) -> 40
A38: AYTE GENERAL | E38: hr | F38: =V38 -> 0 | G38: 50.77 | H38: =F38*G38 -> 0 | I38: =W38 -> 0 | J38: =G38*1.5 -> 76.155 | K38: =I38*J38 -> 0 | L38: =X38 -> 0 | M38: =G38*2.25 -> 114.2325 | N38: =L38*M38 -> 0
A39: INGENIERO DE SUBESTACIONES | E39: hr | F39: =V39 -> 0 | G39: 186 | H39: =F39*G39 -> 0 | I39: =W39 -> 0 | J39: 186 | K39: =I39*J39 -> 0 | L39: =X39 -> 0 | M39: 186 | N39: =L39*M39 -> 0 | V39: =SUM(O39:T39) -> 0
A40: INGENIERO DE PRUEBAS ELECTRICAS | E40: hr | F40: =V40 -> 0 | G40: 186 | H40: =F40*G40 -> 0 | I40: =W40 -> 0 | J40: 186 | K40: =I40*J40 -> 0 | L40: =X40 -> 0 | M40: 186 | N40: =L40*M40 -> 0 | V40: =SUM(O40:T40) -> 0
A41: ING. ESPECIALISTA EN PROTECCIONES | E41: hr | F41: =V41 -> 0 | G41: 230.47 | H41: =F41*G41 -> 0 | I41: =W41 -> 0 | J41: 294 | K41: =I41*J41 -> 0 | L41: =X41 -> 0 | M41: 294 | N41: =L41*M41 -> 0 | V41: =SUM(O41:T41) -> 0
A42: SUPERINTENDENTE | E42: hr | F42: =V42 -> 0 | G42: 279.53 | H42: =F42*G42 -> 0 | I42: =W42 -> 0 | J42: 372.71 | K42: =I42*J42 -> 0 | L42: =X42 -> 0 | M42: 559.07 | N42: =L42*M42 -> 0 | V42: =SUM(O42:T42) -> 0
F43: =V43 -> 287 | G43: SUBT 2 | H43: =SUM(H21:H42) -> 1027.24 | J43: SUBT. | K43: =SUM(K22:K41) -> 0 | M43: SUBT. | N43: =SUM(N22:N41) -> 0 | V43: =SUM(V21:V42) -> 287 | W43: 45
G44: SUMA M.O. | H44: =H43+K43+N43 -> 1027.24
A45: HERRAMIENTA MENOR | G45: 1 a 10% | H45: =+H44*0.06 -> 61.6344
A47: VEHICULOS
A48: DESCRIPCION | E48: UNIDAD | F48: CANT. | G48: P.U. | H48: IMPORTE | J48: HR IDA | K48: HR RETORNO | L48: HR SITIO | M48: SUMA
A49: camioneta RANGER sin operador sin combustible | E49: HR | F49: 0 | G49: 102.29 | H49: =F49*G49 -> 0 | J49: 0 | K49: 0 | L49: 0 | M49: =J49+K49+L49 -> 0
A50: camioneta NISSAN sin operador sin combustible | E50: HR | F50: 0 | G50: 68.7 | H50: =F50*G50 -> 0 | J50: 0 | K50: 0 | M50: =J50+K50+L50 -> 0
A51: camioneta TORNADO Tornado sin operador sin combustible | E51: HR | F51: 8 | G51: 54.43 | H51: =F51*G51 -> 435.44 | J51: 0.45 | K51: 0.45 | M51: =J51+K51+L51 -> 0.9
A52: Camion con grua sin operador sin conbustible. | E52: HR | F52: =M52 -> 0 | G52: 203.19 | H52: =F52*G52 -> 0 | M52: =J52+K52+L52 -> 0
A53: Camion con grua con operador con conbustible. | E53: HR | G53: 407.62 | H53: =F53*G53 -> 0
A54: autobus | E54: pza | G54: 5000 | H54: =F54*G54 -> 0
A55: Km. Recorrido (incluye conbustible y depresiación de Vehiculo | E55: KM | G55: 2.5 | H55: =F55*G55 -> 0
G56: SUBT 4 | H56: =SUM(H49:H55) -> 435.44
A57: COMBUSTIBLE
A58: DESCRIPCION | E58: UNIDAD | F58: CANT. | G58: P.U. | H58: IMPORTE | J58: KM IDA | K58: KM RETORNO | L58: KM SITIO | M58: SUMA
A59: GASOLINA MAGNA | E59: LT | F59: 30 | G59: 16.48 | H59: =F59*G59 -> 494.4 | J59: 22 | K59: 22 | M59: =J59+K59+L59 -> 44
A60: DIESEL | E60: LT | F60: =M60/4.5 -> 0 | G60: 0 | H60: =F60*G60 -> 0 | M60: =J60+K60+L60 -> 0
G61: SUBT 5 | H61: =SUM(H59:H60) -> 494.4
A62: CASETAS
A63: DESCRIPCION | E63: UNIDAD | F63: CANT. | G63: P.U. | H63: IMPORTE
A64: camioneta pick up | E64: CASETA | F64: 2 | G64: 180 | H64: =F64*G64 -> 360
A65: camioneta pick up | E65: CASETA | G65: 65 | H65: =F65*G65 -> 0
G66: SUBT 6 | H66: =SUM(H64:H65) -> 360
A67: VIATICOS
A68: ALIMENTOS
A69: DESCRIPCION | E69: UNIDAD | F69: CANT. | G69: P.U. | H69: IMPORTE
A70: CONSUMO DE ALIMENTOS | E70: Pza | F70: 0.5 | G70: 450 | H70: =F70*G70 -> 225
H71: =SUM(H70) -> 225
A72: HOSPEDAJE
A73: DESCRIPCION | E73: UNIDAD | F73: CANT. | G73: P.U. | H73: IMPORTE
A74: HOTEL | E74: NOCHES | F74: 0 | G74: 900 | H74: =F74*G74 -> 0
G75: SUBT 8 | H75: =SUM(H74) -> 0
G76: SUMA: | H76: =H56+H61+H66+H71+H75+H45+H44+H17 -> 82603.714
A77: EQUIPO DE PRUEBA
A78: DESCRIPCION | E78: UNIDAD | F78: CANT. | G78: P.U. | H78: IMPORTE | I78: TR | K78: S.E
A79: Megger | E79: jr | G79: 2200 | H79: =(F79*G79) -> 0
A80: TTR | E80: jr | G80: 2000 | H80: =(F80*G80) -> 0
A81: Factor de Potencia de 2.5 KV | E81: jr | G81: 7000 | H81: =(F81*G81) -> 0
A82: Factor de Potencia de 10.5 KV | E82: jr | G82: 15200 | H82: =(F82*G82) -> 0
A83: Ducter | E83: jr | G83: 2200 | H83: =(F83*G83) -> 0
A84: resistencia óhmica | E84: jr | G84: 2000 | H84: =(F84*G84) -> 0
A85: hipot de 80 KV vcd | E85: jr | G85: 2500 | H85: =(F85*G85) -> 0
A86: Rigidez dieléctrica al aceite 60 kv | E86: jr | G86: 1600 | H86: =(F86*G86) -> 0
A87: Terrómetro | E87: jr | G87: 1100 | H87: =(F87*G87) -> 0
A88: Analizador de tiempos de interruptor | E88: jr | G88: 2700 | H88: =(F88*G88) -> 0
A89: Fuente de corriente para calibrador de relevadores | E89: jr | G89: 2500 | H89: =(F89*G89) -> 0
A90: Probador de relevador de Protecciones | E90: jr | G90: 13373 | H90: =(F90*G90) -> 0
... A99: Camara Termografica | E99: jr | G99: 383.5 | H99: =(F99*G99) -> 0
G100: SUBT 9 | H100: =SUM(H79:H98) -> 0
E102: 0 | H102: =+E102 -> 0 | I102: % DE IMP. | J102: INDIRECTO DISPONIBLE
G103: COSTO DIRECTO | H103: =H76+H100 -> 82603.714
F104: Indirectos | G104: 0.1 | H104: =H103*G104 -> 8260.3714 | I104: =(M110*100)/H104 -> -281.48601 | J104: =H104-M110 -> 31512.161
F105: Subtotal 1 | H105: =H103+H104 -> 90864.086
K106: BASE IMPUESTO
F107: Financ. | G107: 0.06 | H107: =H105*G107 -> 5451.8452 | I107: =H107+[1]Part.2!H84+[1]Part.3!H84+[1]Part.4!H84+[1]part.5!H84+[1]traslado!H66 -> 5662.0572 | J107: COMPRAS | K107: =+H17 -> 80000
F108: Subtotal 2 | H108: =H105+H107 -> 96315.931 | J108: M.O | K108: =H44 -> 1027.24
F109: Utilidad | G109: 0.1 | H109: =H108*G109 -> 9631.5931 | J109: GASTOS FACTURADOS | K109: =H76-H56 -> 82168.274 | M109: IMP. 32%
F110: Importe | H110: =H108+H109 -> 105947.52 | J110: SUMA | K110: =SUM(K107:K109) -> 163195.51 | L110: =H110-H109-(H104*0.7)-K110 -> -72661.843 | M110: =0.32*L110 -> -23251.79
I111: FACTOR | J111: =H110/H103 -> 1.2826

Sheet TERMOGRAFIAS MO
A1: I M M E E S. A. D E C. V.
A2: A N A L I S I S D E P R E C I O U N I T A R I O
A3: COTIZACION:
A4: FECHA:
A5: PARTIDA 1
A7: MATERIALES.
A8: DESCRIPCION | E8: UNIDAD | F8: CANT. | G8: P.U. | H8: IMPORTE
E9: Pza | F9: 1 | G9: 0 | H9: =G9 -> 0 | J9: HR NORMAL
E10: Pza | J10: HR DOBLE
E11: Pza | J11: HR TRIPLE
E12: Pza
E13: Pza
E14: Pza
E15: Pza
E16: Pza | I16: =H16*1.455 -> 0
G17: SUBT 1 | H17: =SUM(H9:H16) -> 0
A19: MANO DE OBRA SIN INDIRECTOS | O19: HORARIOS DE TRABAJO | V19: HORAS RESULTANTES
A20: PERSONAL. | E20: UNIDAD | F20: CANT. | G20: P.U. | H20: IMPORTE | I20: CANT. | J20: Hr. Extra | K20: IMPORTE | L20: CANT. | M20: Dom, ó Fest. | N20: IMPORTE | O20: L | P20: M | Q20: MI | R20: J | S20: V | T20: S | U20: D | V20: N | W20: D | X20: T
A21: COORDINADOR DE OPERACIONES | E21: hr | F21: =V21 -> 0 | G21: 185.69 | H21: =F21*G21 -> 0 | I21: =W21 -> 0 | J21: =G21*1.5 -> 278.535 | K21: =I21*J21 -> 0 | L21: =X21 -> 0 | M21: =G21*2.25 -> 417.8025 | N21: =L21*M21 -> 0 | V21: =SUM(O21:T21) -> 0
A22: INGENIERIA Y SOPORTE TEC. | E22: hr | F22: =V22 -> 0 | G22: 177.79 | H22: =F22*G22 -> 0 | I22: =W22 -> 0 | J22: =G22*1.5 -> 266.685 | K22: =I22*J22 -> 0 | L22: =X22 -> 0 | M22: =G22*2.25 -> 400.0275 | N22: =L22*M22 -> 0 | V22: =SUM(O22:T22) -> 0
A23: SUPERVISOR DE SEGURIDAD CERTIFICADO | E23: hr | F23: =V23 -> 0 | G23: 185.69 | H23: =F23*G23 -> 0 | I23: =W23 -> 0 | J23: =G23*1.5 -> 278.535 | K23: =I23*J23 -> 0 | L23: =X23 -> 0 | M23: =G23*2.25 -> 417.8025 | N23: =L23*M23 -> 0 | V23: =SUM(O23:T23) -> 0
A24: SUPERVISOR ELECTRICO | E24: hr | F24: 0 | G24: 237 | H24: =F24*G24 -> 0 | I24: =W24 -> 0 | J24: =G24*1.5 -> 355.5 | K24: =I24*J24 -> 0 | L24: =X24 -> 0 | M24: =G24*2.25 -> 533.25 | N24: =L24*M24 -> 0 | O24: 8 | P24: 8 | Q24: 8 | R24: 8 | S24: 8 | V24: =SUM(O24:T24) -> 40
A25: TECNICO DE PRUEBAS ELECTRICAS | E25: hr | F25: 0 | G25: 209.25 | H25: =F25*G25 -> 0 | I25: 0 | J25: =G25*1.5 -> 313.875 | K25: =I25*J25 -> 0 | L25: =X25 -> 0 | M25: =G25*2.25 -> 470.8125 | N25: =L25*M25 -> 0 | V25: =SUM(O25:T25) -> 0
A26: CABO OBRA ELECTRICA | E26: hr | F26: =V26 -> 0 | G26: 136.31 | H26: =F26*G26 -> 0 | I26: =W26 -> 0 | J26: =G26*1.5 -> 204.465 | K26: =I26*J26 -> 0 | L26: =X26 -> 0 | M26: =G26*2.25 -> 306.6975 | N26: =L26*M26 -> 0 | V26: =SUM(O26:T26) -> 0
A27: LINIERO | E27: hr | F27: 0 | G27: 190.22 | H27: =F27*G27 -> 0 | I27: 0 | J27: =G27*1.5 -> 285.33 | K27: =I27*J27 -> 0 | L27: =X27 -> 0 | M27: =G27*2.25 -> 427.995 | N27: =L27*M27 -> 0 | O27: 16 | P27: 16 | Q27: 16 | R27: 8 | S27: 8 | T27: 5 | V27: =SUM(O27:T27) -> 69
A28: LINIERO | E28: hr | F28: 0 | G28: 126.43 | H28: =F28*G28 -> 0 | I28: =W28 -> 0 | J28: =G28*1.5 -> 189.645 | K28: =I28*J28 -> 0 | L28: =X28 -> 0 | M28: =G28*2.25 -> 284.4675 | N28: =L28*M28 -> 0 | O28: 16 | P28: 16 | Q28: 16 | R28: 8 | S28: 8 | T28: 5 | V28: =SUM(O28:T28) -> 69
A29: ESPECIALISTA ELECTRICO | E29: hr | F29: 0 | G29: 110.63 | H29: =F29*G29 -> 0 | I29: =W29 -> 0 | J29: =G29*1.5 -> 165.945 | K29: =I29*J29 -> 0 | L29: =X29 -> 0 | M29: =G29*2.25 -> 248.9175 | N29: =L29*M29 -> 0 | V29: =SUM(O29:T29) -> 0
A30: TECNICO EN INSTRUMENTACION | E30: hr | F30: =V30 -> 0 | G30: 104.36 | H30: =F30*G30 -> 0 | I30: =W30 -> 0 | J30: =G30*1.5 -> 156.54 | K30: =I30*J30 -> 0 | L30: =X30 -> 0 | M30: =G30*2.25 -> 234.81 | N30: =L30*M30 -> 0 | V30: =SUM(O30:T30) -> 0
A31: OFICIAL ELECTRICO | E31: hr | F31: 0 | G31: 104.36 | H31: =F31*G31 -> 0 | I31: =W31 -> 0 | J31: =G31*1.5 -> 156.54 | K31: =I31*J31 -> 0 | L31: =X31 -> 0 | M31: =G31*2.25 -> 234.81 | N31: =L31*M31 -> 0 | V31: =SUM(O31:T31) -> 0
A32: ASISTENTE DE DISEÑO | E32: hr | F32: =V32 -> 0 | G32: 104.36 | H32: =F32*G32 -> 0 | I32: =W32 -> 0 | J32: =G32*1.5 -> 156.54 | K32: =I32*J32 -> 0 | L32: =X32 -> 0 | M32: =G32*2.25 -> 234.81 | N32: =L32*M32 -> 0 | V32: =SUM(O32:T32) -> 0
A33: ELECTRICISTA -B | E33: hr | F33: 0 | G33: 90.87 | H33: =F33*G33 -> 0 | I33: =W33 -> 0 | J33: =G33*1.5 -> 136.305 | K33: =I33*J33 -> 0 | L33: =X33 -> 0 | M33: =G33*2.25 -> 204.4575 | N33: =L33*M33 -> 0 | O33: 16 | P33: 16 | Q33: 16 | R33: 8 | S33: 8 | T33: 5 | V33: =SUM(O33:T33) -> 69
A34: ELECTRICISTA -A | E34: hr | F34: 0 | G34: 82.97 | H34: =F34*G34 -> 0 | I34: =W34 -> 0 | J34: =G34*1.5 -> 124.455 | K34: =I34*J34 -> 0 | L34: =X34 -> 0 | M34: =G34*2.25 -> 186.6825 | N34: =L34*M34 -> 0 | V34: =SUM(O34:T34) -> 0
A35: AUXILIAR TECNICO | E35: hr | F35: 0 | G35: 75.07 | H35: =F35*G35 -> 0 | I35: =W35 -> 0 | J35: =G35*1.5 -> 112.605 | K35: =I35*J35 -> 0 | L35: =X35 -> 0 | M35: =G35*2.25 -> 168.9075 | N35: =L35*M35 -> 0 | V35: =SUM(O35:T35) -> 0
A36: AYTE ELECTRICO - B | E36: hr | F36: 0 | G36: 75.07 | H36: =F36*G36 -> 0 | I36: =W36 -> 0 | J36: =G36*1.5 -> 112.605 | K36: =I36*J36 -> 0 | L36: =X36 -> 0 | M36: =G36*2.25 -> 168.9075 | N36: =L36*M36 -> 0 | V36: =SUM(O36:T36) -> 0
A37: AYTE DE ELECTR. -A | E37: hr | F37: 0 | G37: 63.21 | H37: =F37*G37 -> 0 | I37: =W37 -> 0 | J37: =G37*1.5 -> 94.815 | K37: =I37*J37 -> 0 | L37: =X37 -> 0 | M37: =G37*2.25 -> 142.2225 | N37: =L37*M37 -> 0 | O37: 8 | P37: 8 | Q37: 8 | R37: 8 | S37: 8 | V37: =SUM(O37:T37) -> 40
A38: AYTE GENERAL | E38: hr | F38: 0 | G38: 50.77 | H38: =F38*G38 -> 0 | I38: =W38 -> 0 | J38: =G38*1.5 -> 76.155 | K38: =I38*J38 -> 0 | L38: =X38 -> 0 | M38: =G38*2.25 -> 114.2325 | N38: =L38*M38 -> 0
A39: INGENIERO DE SUBESTACIONES | E39: hr | F39: 0 | G39: 186 | H39: =F39*G39 -> 0 | I39: =W39 -> 0 | J39: 186 | K39: =I39*J39 -> 0 | L39: =X39 -> 0 | M39: 186 | N39: =L39*M39 -> 0 | V39: =SUM(O39:T39) -> 0
A40: INGENIERO DE PRUEBAS ELECTRICAS | E40: hr | F40: 0 | G40: 186 | H40: =F40*G40 -> 0 | I40: =W40 -> 0 | J40: 186 | K40: =I40*J40 -> 0 | L40: =X40 -> 0 | M40: 186 | N40: =L40*M40 -> 0 | V40: =SUM(O40:T40) -> 0
A41: ING. ESPECIALISTA EN PROTECCIONES | E41: hr | F41: 0 | G41: 230.47 | H41: =F41*G41 -> 0 | I41: =W41 -> 0 | J41: 294 | K41: =I41*J41 -> 0 | L41: =X41 -> 0 | M41: 294 | N41: =L41*M41 -> 0 | V41: =SUM(O41:T41) -> 0
A42: SUPERINTENDENTE | E42: hr | F42: =V42 -> 0 | G42: 279.53 | H42: =F42*G42 -> 0 | I42: =W42 -> 0 | J42: 372.71 | K42: =I42*J42 -> 0 | L42: =X42 -> 0 | M42: 559.07 | N42: =L42*M42 -> 0 | V42: =SUM(O42:T42) -> 0
F43: =V43 -> 287 | G43: SUBT 2 | H43: =SUM(H21:H42) -> 0 | J43: SUBT. | K43: =SUM(K22:K41) -> 0 | M43: SUBT. | N43: =SUM(N22:N41) -> 0 | V43: =SUM(V21:V42) -> 287 | W43: 45
G44: SUMA M.O. | H44: =H43+K43+N43 -> 0
A45: HERRAMIENTA MENOR | G45: 1 a 10% | H45: =+H44*0.06 -> 0
A47: VEHICULOS
A48: DESCRIPCION | E48: UNIDAD | F48: CANT. | G48: P.U. | H48: IMPORTE | J48: HR IDA | K48: HR RETORNO | L48: HR SITIO | M48: SUMA
A49: camioneta RANGER sin operador sin combustible | E49: HR | G49: 102.29 | H49: =F49*G49 -> 0 | J49: 0 | K49: 0 | L49: 0 | M49: =J49+K49+L49 -> 0
A50: camioneta NISSAN sin operador sin combustible | E50: HR | F50: 0 | G50: 68.7 | H50: =F50*G50 -> 0 | J50: 0 | K50: 0 | M50: =J50+K50+L50 -> 0
